Workbook
Name \103: #REF!
Name \107: #REF!
Name \108: #REF!
Name \109: #REF!
Name \112: #REF!
Name \114: #REF!
Name \115: #REF!
Name \117: #REF!
Name \118: #REF!
Name \119: #REF!
Name \120: #REF!
Name \121: #REF!
Name \123: #REF!
Name \124: #REF!
Name \125: #REF!
Name \126: #REF!
Name \128: #REF!
Name \139: #REF!
Name \140: #REF!
Name \150: #REF!
Name \154: #REF!
Name \156: #REF!
Name \157: #REF!
Name \158: #REF!
Name \160: #REF!
Name \305: #REF!
Name \323: #REF!
Name \325: #REF!
Name \326: #REF!
Name \327: #REF!
Name \328: #REF!
Name \342: #REF!
Name \346: #REF!
Name \347: #REF!
Name \348: #REF!
Name \349: #REF!
Name \353: #REF!
Name \357: #REF!
Name \358: #REF!
Name \359: #REF!
Name \4055: #REF!
Name \4057: #REF!
Name \4059: #REF!
Name \4062: #REF!
Name \4063: #REF!
Name \4064: #REF!
Name \4065: #REF!
Name \4066: #REF!
Name \4069: #REF!
Name \A: #REF!
Name \B: #REF!
Name \D: #REF!
Name \G: #REF!
Name \H: #REF!
Name \J: #REF!
Name \m: #REF!
Name \P: #REF!
Name \Q: #REF!
Name \R: #REF!
Name \S: #REF!

Sheet Nov Inv Recon
A1: Nov Vendor Inv Detail | B1: Nov Vendor Inv Detail | C1: Nov Vendor Inv Detail | D1: Nov Vendor Inv Detail | E1: Nov Vendor Inv Detail | F1: Nov Vendor Inv Detail | G1: Calculated | H1: Cognos - Nov Billing CDK | I1: Cognos - Nov Billing CDK | J1: Cognos - CDK Contract Detail | K1: Cognos - CDK Contract Detail | L1: Cognos - CDK Contract Detail | M1: Cognos - CDK Contract Detail | N1: Cognos - CDK Contract Detail | O1: Cognos - Nov Billing CDK | P1: Cognos - Nov Billing CDK | Q1: Calculated | R1: Calculated | S1: Calculated | T1: Manual | U1: Cognos - Inv Detail Packages | V1: Cognos - Inv Detail Packages | W1: Cognos - Inv Detail Packages | X1: ? | Y1: ? | Z1: ?
A2: Account | B2: Customer_ID | C2: External Billing ID | D2: Total minutes | E2: Overages | F2: Billing_amount | G2: CarWars Excl Overage | H2: CMF | I2: Ship to Name | J2: ANS Date | K2: Install Date | L2: LSS Date | M2: Catalog Number | N2: Catalog Description | O2: CDK Billing | P2: CDK Overages | Q2: CDK total Billing | R2: Margin Excl Overage | S2: Margin % Excl Overage | T2: Comment Group | U2: CDK Package 1 | V2: CDK Package 2 | W2: CDK Package 3 | X2: CallRevu Package 1 | Y2: CallRevu Package 2 | Z2: CallRevu Package 3
A3: Baker - Buick GMC Cadillac | B3: 76195 | C3: 17223 | D3: 8351.73 | E3: 0 | F3: 1571.65 | G3: =+F3-E3 -> 1571.65 | H3: 76143222 | I3: BAKER BUICK GMC CADILLAC | K3: 44707 | L3: 45808 | M3: 4570060 | N3: CRM OUTBOUND TELEPHONY TRACKING (NEW AND CONVERSION) | O3: =VLOOKUP(H3,'Billing CDK pivot'!A:C,3,FALSE) -> #N/A | P3: =IFERROR(VLOOKUP(H3,'Billing CDK pivot (overages)'!A:F,6,FALSE),0) -> 0 | Q3: =+O3+P3 -> #N/A | R3: =+O3-G3 -> #N/A | S3: =+R3/O3 -> #N/A | T3: ANS/Loss | U3: #N/A | V3: #N/A | W3: #N/A | X3: Secondary Package: Carrier Registration - Monthly ($10.00)
A4: Bob Bell Hyundai | B4: 92128 | C4: 18596 | D4: 9740.35 | E4: 0 | F4: 1581.65 | G4: =+F4-E4 -> 1581.65 | H4: 76217678 | I4: BOB BELL HYUNDAI | K4: 45566 | L4: 45914 | M4: 4570062 | N4: CARWARS PREMIUM SALES | O4: =VLOOKUP(H4,'Billing CDK pivot'!A:C,3,FALSE) -> #N/A | P4: =IFERROR(VLOOKUP(H4,'Billing CDK pivot (overages)'!A:F,6,FALSE),0) -> 0 | Q4: =+O4+P4 -> #N/A | R4: =+O4-G4 -> #N/A | S4: =+R4/O4 -> #N/A | T4: ANS/Loss | U4: #N/A | V4: #N/A | W4: #N/A | X4: Secondary Package: Carrier Registration - Monthly ($10.00) | Y4: Elead CW Unlimited v2 ($1,571.65)
A5: Cella Ford | B5: 90338 | C5: 8230 | D5: 2477.75 | E5: 0 | F5: 264.15 | G5: =+F5-E5 -> 264.15 | H5: 08320047 | I5: CELLA FORD | K5: 44053 | L5: 45961 | M5: 4570009 | N5: CARWARS STARTER 3500 | O5: =VLOOKUP(H5,'Billing CDK pivot'!A:C,3,FALSE) -> #N/A | P5: =IFERROR(VLOOKUP(H5,'Billing CDK pivot (overages)'!A:F,6,FALSE),0) -> 0 | Q5: =+O5+P5 -> #N/A | R5: =+O5-G5 -> #N/A | S5: =+R5/O5 -> #N/A | T5: ANS/Loss | U5: #N/A | V5: #N/A | W5: #N/A | X5: Secondary Package: Carrier Registration - Monthly ($10.00) | Y5: Elead CW Starter 4000 v2 ($254.15)
A6: Fair Oaks CDJR | B6: 93471 | C6: 10445 | D6: 0 | E6: 0 | F6: 1793.3 | G6: =+F6-E6 -> 1793.3 | H6: 76003426 | I6: FAIR OAKS CHANTILLY CHRYSLER DODGE JEEP RAM | K6: 44053 | L6: 45961 | M6: 4570009 | N6: CARWARS STARTER 3500 | O6: =VLOOKUP(H6,'Billing CDK pivot'!A:C,3,FALSE) -> #N/A | P6: =IFERROR(VLOOKUP(H6,'Billing CDK pivot (overages)'!A:F,6,FALSE),0) -> 0 | Q6: =+O6+P6 -> #N/A | R6: =+O6-G6 -> #N/A | S6: =+R6/O6 -> #N/A | T6: ANS/Loss | U6: #N/A | V6: #N/A | W6: #N/A | X6: eLead - CW Starter - 7500 mins v2 ($424.15) | Y6: eLead - CW Premium - Sales 50k v2 ($1,571.65) | Z6: Secondary Package: eLead - Car Wars Texting v2 ($211.65)
A7: Fredy KIA | B7: 116892 | C7: 6397 | D7: 52.02 | E7: 0 | F7: 1581.65 | G7: =+F7-E7 -> 1581.65 | H7: 76062949 | I7: FREDY KIA | K7: 43862 | L7: 45869 | M7: =VLOOKUP(H7,'Billing CDK pivot'!A:C,3,FALSE) -> #N/A | N7: =VLOOKUP(I7,'Billing CDK pivot'!B:D,3,FALSE) -> #N/A | O7: =VLOOKUP(H7,'Billing CDK pivot'!A:C,3,FALSE) -> #N/A | P7: =IFERROR(VLOOKUP(H7,'Billing CDK pivot (overages)'!A:F,6,FALSE),0) -> 0 | Q7: =+O7+P7 -> #N/A | R7: =+O7-G7 -> #N/A | S7: =+R7/O7 -> #N/A | T7: ANS/Loss | U7: #N/A | V7: #N/A | W7: #N/A | X7: eLead - CW Starter - 3500 mins v2 ($254.15) | Y7: eLead - CW Premium - Sales 50k v2 ($1,571.65)
A8: King KIA | B8: 86863 | C8: 18077 | D8: 4423.02 | E8: 29.19 | F8: 293.34 | G8: =+F8-E8 -> 264.15 | H8: 76049589 | I8: KING KIA | K8: 44013 | L8: 45777 | M8: 4570009 | N8: CARWARS STARTER 3500 | O8: =VLOOKUP(H8,'Billing CDK pivot'!A:C,3,FALSE) -> #N/A | P8: =IFERROR(VLOOKUP(H8,'Billing CDK pivot (overages)'!A:F,6,FALSE),0) -> 0 | Q8: =+O8+P8 -> #N/A | R8: =+O8-G8 -> #N/A | S8: =+R8/O8 -> #N/A | T8: ANS/Loss | U8: #N/A | V8: #N/A | W8: #N/A | X8: Secondary Package: Carrier Registration - Monthly ($10.00) | Y8: Elead CW Starter 4000 v2 ($254.15)
A9: King Kia of Laurel | B9: 150401 | C9: 27069 | D9: 9933.82 | E9: 443.93 | F9: 708.08 | G9: =+F9-E9 -> 264.15 | H9: 76230032 | I9: KING KIA OF LAUREL | K9: 44663 | L9: 45777 | M9: 4570009 | N9: CARWARS STARTER 3500 | O9: =VLOOKUP(H9,'Billing CDK pivot'!A:C,3,FALSE) -> #N/A | P9: =IFERROR(VLOOKUP(H9,'Billing CDK pivot (overages)'!A:F,6,FALSE),0) -> 0 | Q9: =+O9+P9 -> #N/A | R9: =+O9-G9 -> #N/A | S9: =+R9/O9 -> #N/A | T9: ANS/Loss | U9: #N/A | V9: #N/A | W9: #N/A | X9: Secondary Package: Carrier Registration - Monthly ($10.00) | Y9: eLead - CW Starter - 3500 mins v2 ($254.15)
A10: King Volkswagen | B10: 86862 | C10: 18076 | D10: 4425.79 | E10: 29.38 | F10: 293.53 | G10: =+F10-E10 -> 264.15 | H10: 76049571 | I10: KING VOLKSWAGEN | K10: 44013 | L10: 45777 | M10: 4570009 | N10: CARWARS STARTER 3500 | O10: =VLOOKUP(H10,'Billing CDK pivot'!A:C,3,FALSE) -> #N/A | P10: =IFERROR(VLOOKUP(H10,'Billing CDK pivot (overages)'!A:F,6,FALSE),0) -> 0 | Q10: =+O10+P10 -> #N/A | R10: =+O10-G10 -> #N/A | S10: =+R10/O10 -> #N/A | T10: ANS/Loss | U10: #N/A | V10: #N/A | W10: #N/A | X10: Secondary Package: Carrier Registration - Monthly ($10.00) | Y10: Elead CW Starter 4000 v2 ($254.15)
A11: Lokey Nissan | B11: 148843 | C11: 10786 | D11: 0 | E11: 0 | F11: 0 | G11: =+F11-E11 -> 0 | H11: 76211594 | I11: LOKEY NISSAN | K11: 45545 | L11: 45961 | M11: 4571030 | N11: CARWARS STARTER 5000 | O11: =VLOOKUP(H11,'Billing CDK pivot'!A:C,3,FALSE) -> #N/A | P11: =IFERROR(VLOOKUP(H11,'Billing CDK pivot (overages)'!A:F,6,FALSE),0) -> 0 | Q11: =+O11+P11 -> #N/A | R11: =+O11-G11 -> #N/A | S11: =+R11/O11 -> #N/A | T11: ANS/Loss | U11: #N/A | V11: #N/A | W11: #N/A | X11: eLead - Elite Small v2 ($1,274.15)
A12: Mel Hambelton Ford | B12: 116785 | C12: 19638 | D12: 43 | E12: 0 | F12: 1571.65 | G12: =+F12-E12 -> 1571.65 | H12: 76049550 | I12: MEL HAMBELTON FORD | K12: 44657 | L12: 45777 | M12: 4570062 | N12: CARWARS PREMIUM SALES | O12: =VLOOKUP(H12,'Billing CDK pivot'!A:C,3,FALSE) -> #N/A | P12: =IFERROR(VLOOKUP(H12,'Billing CDK pivot (overages)'!A:F,6,FALSE),0) -> 0 | Q12: =+O12+P12 -> #N/A | R12: =+O12-G12 -> #N/A | S12: =+R12/O12 -> #N/A | T12: ANS/Loss | U12: #N/A | V12: #N/A | W12: #N/A | X12: Secondary Package: Carrier Registration - Monthly ($10.00)
A13: Midlands Toyota | B13: 46377 | C13: 8725 | D13: 36 | E13: 0 | F13: 0 | G13: =+F13-E13 -> 0 | H13: 76228629 | I13: MIDLANDS TOYOTA | K13: 44568 | L13: 45716 | M13: 4570058 | N13: CARWARS STARTER 7500 | O13: =VLOOKUP(H13,'Billing CDK pivot'!A:C,3,FALSE) -> #N/A | P13: =IFERROR(VLOOKUP(H13,'Billing CDK pivot (overages)'!A:F,6,FALSE),0) -> 0 | Q13: =+O13+P13 -> #N/A | R13: =+O13-G13 -> #N/A | S13: =+R13/O13 -> #N/A | T13: ANS/Loss | U13: #N/A | V13: #N/A | W13: #N/A | X13: Secondary Package: Carrier Registration - Monthly ($10.00)
A14: Mobile Bay Harley Davidson | B14: 99628 | C14: 17155 | D14: 1264.34 | E14: 0 | F14: 264.15 | G14: =+F14-E14 -> 264.15 | H14: 76211956 | I14: MOBILE BAY HARLEY DAVIDSON | K14: 43862 | L14: 45777 | M14: 4570060 | N14: CRM OUTBOUND TELEPHONY TRACKING (NEW AND CONVERSION) | O14: =VLOOKUP(H14,'Billing CDK pivot'!A:C,3,FALSE) -> #N/A | P14: =IFERROR(VLOOKUP(H14,'Billing CDK pivot (overages)'!A:F,6,FALSE),0) -> 0 | Q14: =+O14+P14 -> #N/A | R14: =+O14-G14 -> #N/A | S14: =+R14/O14 -> #N/A | T14: ANS/Loss | U14: #N/A | V14: #N/A | W14: #N/A | X14: Secondary Package: Carrier Registration - Monthly ($10.00) | Y14: eLead - CW Starter - 3500 mins v2 ($254.15)
A15: New Orleans Harley Davidson | B15: 99624 | C15: 4548 | D15: 42.65 | E15: 0 | F15: 139 | G15: =+F15-E15 -> 139 | H15: 76211900 | I15: NEW ORLEANS HARLEY-DAVIDSON | K15: 43862 | L15: 45777 | M15: 4570060 | N15: CRM OUTBOUND TELEPHONY TRACKING (NEW AND CONVERSION) | O15: =VLOOKUP(H15,'Billing CDK pivot'!A:C,3,FALSE) -> #N/A | P15: =IFERROR(VLOOKUP(H15,'Billing CDK pivot (overages)'!A:F,6,FALSE),0) -> 0 | Q15: =+O15+P15 -> #N/A | R15: =+O15-G15 -> #N/A | S15: =+R15/O15 -> #N/A | T15: ANS/Loss | U15: #N/A | V15: #N/A | W15: #N/A | X15: Elead Outbound 4000 v2 ($129.00) | Y15: Elead Outbound 4000 v2 ($129.00)
A16: Piazza Nissan of Ardmore | B16: 142901 | C16: 23308 | D16: 0 | E16: 0 | F16: 254.15 | G16: =+F16-E16 -> 254.15 | H16: 76215011 | I16: PIAZZA NISSAN OF ARDMORE | K16: 44118 | L16: 45900 | M16: 4570009 | N16: CARWARS STARTER 3500 | O16: =VLOOKUP(H16,'Billing CDK pivot'!A:C,3,FALSE) -> #N/A | P16: =IFERROR(VLOOKUP(H16,'Billing CDK pivot (overages)'!A:F,6,FALSE),0) -> 0 | Q16: =+O16+P16 -> #N/A | R16: =+O16-G16 -> #N/A | S16: =+R16/O16 -> #N/A | T16: ANS/Loss | U16: #N/A | V16: #N/A | W16: #N/A | X16: Secondary Package: Carrier Registration - Monthly ($10.00)
A17: Renaldo Kia | B17: 154381 | C17: 9560 | D17: 2 | E17: 0 | F17: 434.15 | G17: =+F17-E17 -> 434.15 | H17: 76171765 | I17: RENALDO KIA | K17: 44958 | L17: 45930 | M17: 4570058 | N17: CARWARS STARTER 7500 | O17: =VLOOKUP(H17,'Billing CDK pivot'!A:C,3,FALSE) -> #N/A | P17: =IFERROR(VLOOKUP(H17,'Billing CDK pivot (overages)'!A:F,6,FALSE),0) -> 0 | Q17: =+O17+P17 -> #N/A | R17: =+O17-G17 -> #N/A | S17: =+R17/O17 -> #N/A | T17: ANS/Loss | U17: #N/A | V17: #N/A | W17: #N/A | X17: Secondary Package: Carrier Registration - Monthly ($10.00) | Y17: eLead - CW Starter - 7500 mins v2 ($424.15)
A18: Rosedale Chevrolet | B18: 59676 | C18: 11619 | D18: 11274.29 | E18: 449.14 | F18: 1298.14 | G18: =+F18-E18 -> 849 | H18: 76055608 | I18: ROSEDALE CHEVROLET | K18: 43965 | L18: 45930 | M18: 4570383 | N18: EL1OUTCALLTRACK (GM IMR) | O18: =VLOOKUP(H18,'Billing CDK pivot'!A:C,3,FALSE) -> #N/A | P18: =IFERROR(VLOOKUP(H18,'Billing CDK pivot (overages)'!A:F,6,FALSE),0) -> 0 | Q18: =+O18+P18 -> #N/A | R18: =+O18-G18 -> #N/A | S18: =+R18/O18 -> #N/A | T18: ANS/Loss | U18: #N/A | V18: #N/A | W18: #N/A | X18: Secondary Package: Carrier Registration - Monthly ($10.00) | Y18: Elead - 24' CW Elite Small ($839.00)
A19: Union Auto Grupo Usados | B19: 145682 | C19: 25433 | D19: 0 | E19: 0 | F19: 254.15 | G19: =+F19-E19 -> 254.15 | H19: 76224283 | I19: UNION AUTO GRUPO USADOS | K19: 44305 | L19: 45869 | M19: 4570009 | N19: CARWARS STARTER 3500 | O19: =VLOOKUP(H19,'Billing CDK pivot'!A:C,3,FALSE) -> #N/A | P19: =IFERROR(VLOOKUP(H19,'Billing CDK pivot (overages)'!A:F,6,FALSE),0) -> 0 | Q19: =+O19+P19 -> #N/A | R19: =+O19-G19 -> #N/A | S19: =+R19/O19 -> #N/A | T19: ANS/Loss | U19: #N/A | V19: #N/A | W19: #N/A | X19: eLead - CW Starter - 3500 mins v2 ($254.15)
A20: Stanley Ford Sweetwater | B20: 97584 | C20: 18849 | D20: 8390.85 | E20: 61.47 | F20: 495.62 | G20: =+F20-E20 -> 434.15 | H20: 76166962 | I20: STANLEY FORD SWEETWATER | K20: 43862 | L20: 43878 | M20: 4570060 | N20: CRM OUTBOUND TELEPHONY TRACKING (NEW AND CONVERSION) | O20: =VLOOKUP(H20,'Billing CDK pivot'!A:C,3,FALSE) -> #N/A | P20: =IFERROR(VLOOKUP(H20,'Billing CDK pivot (overages)'!A:F,6,FALSE),0) -> 0 | Q20: =+O20+P20 -> #N/A | R20: =+O20-G20 -> #N/A | S20: =+R20/O20 -> #N/A | T20: ANS/Loss - Click to all active and reason on CLM of billing line is that this is downgrading to Carwars starter 7500 from carwars advanced sales - no billing though | U20: #N/A | V20: #N/A | W20: #N/A | X20: Secondary Package: Carrier Registration - Monthly ($10.00) | Y20: eLead - CW Starter - 7500 mins v2 ($424.15)
A21: McSweeney Auto Group Clanton LLC | B21: 187780 | C21: 76201662 | D21: 4406.98 | E21: 0 | F21: 1653 | G21: =+F21-E21 -> 1653 | H21: 76201662 | I21: MCSWEENEY CHRYSLER DODGE JEEP RAM | K21: 45390 | L21: 45595 | M21: 4570289 | N21: CARWARS ELITE 12,500 PACKAGE | O21: =VLOOKUP(H21,'Billing CDK pivot'!A:C,3,FALSE) -> #N/A | P21: =IFERROR(VLOOKUP(H21,'Billing CDK pivot (overages)'!A:F,6,FALSE),0) -> 0 | Q21: =+O21+P21 -> #N/A | R21: =+O21-G21 -> #N/A | S21: =+R21/O21 -> #N/A | T21: ANS/Loss - Deactivated Apr - Reactive as of Sept | U21: #N/A | V21: #N/A | W21: #N/A | X21: eLead - CW Starter - 3500 mins v2 ($254.15) | Y21: Elead - 24' CW Elite Medium ($1,294.00) | Z21: Secondary Package: Elead - 24' CW Elite Medium Service ($349.00)
A22: Modern Nissan of Lake Norman | B22: 131763 | C22: 21795 | D22: 3176.66 | E22: 0 | F22: 264.15 | G22: =+F22-E22 -> 264.15 | H22: 76165887 | I22: MODERN NISSAN OF LAKE NORMAN | K22: 43862 | L22: 45322 | M22: 4570060 | N22: CRM OUTBOUND TELEPHONY TRACKING (NEW AND CONVERSION) | O22: =VLOOKUP(H22,'Billing CDK pivot'!A:C,3,FALSE) -> #N/A | P22: =IFERROR(VLOOKUP(H22,'Billing CDK pivot (overages)'!A:F,6,FALSE),0) -> 0 | Q22: =+O22+P22 -> #N/A | R22: =+O22-G22 -> #N/A | S22: =+R22/O22 -> #N/A | T22: ANS/Loss - sent form but Carwars said dealer wanted to keep it but no billing - sent email to sales | U22: #N/A | V22: #N/A | W22: #N/A | X22: Secondary Package: Carrier Registration - Monthly ($10.00) | Y22: eLead - CW Starter - 3500 mins v2 ($254.15)
A23: Zimbrick Acura of Brookfield | B23: 141131 | C23: 15952 | D23: 1584.05 | E23: 0 | F23: 434.15 | G23: =+F23-E23 -> 434.15 | H23: 76066612 | I23: ZIMBRICK ACURA OF BROOKFIELD | K23: 44082 | L23: 45412 | M23: 4570058 | N23: CARWARS STARTER 7500 | O23: =VLOOKUP(H23,'Billing CDK pivot'!A:C,3,FALSE) -> #N/A | P23: =IFERROR(VLOOKUP(H23,'Billing CDK pivot (overages)'!A:F,6,FALSE),0) -> 0 | Q23: =+O23+P23 -> #N/A | R23: =+O23-G23 -> #N/A | S23: =+R23/O23 -> #N/A | T23: ANS/Loss - sent to carwars 8/12/25 | U23: #N/A | V23: #N/A | W23: #N/A | X23: eLead - Elite Small ($1,019.00) | Y23: eLead - CW Starter - 7500 mins v2 ($424.15)
A24: Bob Bell Ford | B24: 59246 | C24: 18577 | D24: 13420.63 | E24: 0 | F24: 1581.65 | G24: =+F24-E24 -> 1581.65 | H24: 25181201 | I24: BOB BELL FORD | J24: 45526 | M24: 4570062 | N24: CARWARS PREMIUM SALES | O24: =VLOOKUP(H24,'Billing CDK pivot'!A:C,3,FALSE) -> #N/A | P24: =IFERROR(VLOOKUP(H24,'Billing CDK pivot (overages)'!A:F,6,FALSE),0) -> 0 | Q24: =+O24+P24 -> #N/A | R24: =+O24-G24 -> #N/A | S24: =+R24/O24 -> #N/A | T24: ANS/Loss - Sent to carwars 8/8/25 | U24: #N/A | V24: #N/A | W24: #N/A | X24: Secondary Package: Carrier Registration - Monthly ($10.00) | Y24: eLead - CW Premium - Sales 50k v2 ($1,571.65)
A25: Moonshine Harley Davidson | B25: 119133 | C25: 4545 | D25: 6999.72 | E25: 0 | F25: 499 | G25: =+F25-E25 -> 499 | H25: 76253988 | I25: MOONSHINE HARLEY-DAVIDSON | M25: 4570060 | N25: CARWARS LEISURE SMALL (SALES ONLY) | O25: =VLOOKUP(H25,'Billing CDK pivot'!A:C,3,FALSE) -> #N/A | P25: =IFERROR(VLOOKUP(H25,'Billing CDK pivot (overages)'!A:F,6,FALSE),0) -> 0 | Q25: =+O25+P25 -> #N/A | R25: =+O25-G25 -> #N/A | S25: =+R25/O25 -> #N/A | T25: Margin >30% | U25: #N/A | V25: #N/A | W25: #N/A | X25: Secondary Package: Carrier Registration - Monthly ($10.00) | Y25: eLead - CW Leisure Small (Sales Only) ($489.00)
A26: HAN - Audi Jacksonville | B26: 94617 | C26: 17989 | D26: 0.99 | E26: 0 | F26: 139 | G26: =+F26-E26 -> 139 | H26: 76200288 | I26: AUDI JACKSONVILLE | K26: 43862 | L26: 45688 | M26: 4570060 | N26: CRM OUTBOUND TELEPHONY TRACKING (NEW AND CONVERSION) | O26: =VLOOKUP(H26,'Billing CDK pivot'!A:C,3,FALSE) -> #N/A | P26: =IFERROR(VLOOKUP(H26,'Billing CDK pivot (overages)'!A:F,6,FALSE),0) -> 0 | Q26: =+O26+P26 -> #N/A | R26: =+O26-G26 -> #N/A | S26: =+R26/O26 -> #N/A | T26: Moved to call Revu | U26: #N/A | V26: #N/A | W26: #N/A | X26: Secondary Package: Carrier Registration - Monthly ($10.00) | Y26: Elead Outbound 4000 v2 ($129.00)
A27: HAN - Coconut Point Honda | B27: 146561 | C27: 15230 | D27: 0 | E27: 0 | F27: 1284.15 | G27: =+F27-E27 -> 1284.15 | H27: 76177675 | I27: COCONUT POINT HONDA | K27: 44461 | L27: 45713 | M27: 4570289 | N27: CARWARS ELITE 12,500 PACKAGE | O27: =VLOOKUP(H27,'Billing CDK pivot'!A:C,3,FALSE) -> #N/A | P27: =IFERROR(VLOOKUP(H27,'Billing CDK pivot (overages)'!A:F,6,FALSE),0) -> 0 | Q27: =+O27+P27 -> #N/A | R27: =+O27-G27 -> #N/A | S27: =+R27/O27 -> #N/A | T27: Moved to call Revu | U27: #N/A | V27: #N/A | W27: #N/A | X27: Secondary Package: Carrier Registration - Monthly ($10.00) | Y27: eLead - Elite Small v2 ($1,274.15)
A28: Infiniti of Tallahassee | B28: 115609 | C28: 19515 | D28: 243.17 | E28: 0 | F28: 264.15 | G28: =+F28-E28 -> 264.15 | H28: 76208041 | I28: KRAFT INFINITI | K28: 43862 | L28: 45273 | M28: 4570060 | N28: CRM OUTBOUND TELEPHONY TRACKING (NEW AND CONVERSION) | O28: =VLOOKUP(H28,'Billing CDK pivot'!A:C,3,FALSE) -> #N/A | P28: =IFERROR(VLOOKUP(H28,'Billing CDK pivot (overages)'!A:F,6,FALSE),0) -> 0 | Q28: =+O28+P28 -> #N/A | R28: =+O28-G28 -> #N/A | S28: =+R28/O28 -> #N/A | T28: Moved to call Revu | U28: #N/A | V28: #N/A | W28: #N/A | X28: Secondary Package: Carrier Registration - Monthly ($10.00) | Y28: eLead - CW Starter - 3500 mins v2 ($254.15)
A29: Keyser and Miller Ford | B29: 117484 | C29: 19910 | D29: 0 | E29: 0 | F29: 254.15 | G29: =+F29-E29 -> 254.15 | H29: 76067593 | I29: KEYSER & MILLER FORD | K29: 43862 | L29: 45273 | M29: 4570060 | N29: CRM OUTBOUND TELEPHONY TRACKING (NEW AND CONVERSION) | O29: =VLOOKUP(H29,'Billing CDK pivot'!A:C,3,FALSE) -> #N/A | P29: =IFERROR(VLOOKUP(H29,'Billing CDK pivot (overages)'!A:F,6,FALSE),0) -> 0 | Q29: =+O29+P29 -> #N/A | R29: =+O29-G29 -> #N/A | S29: =+R29/O29 -> #N/A | T29: Moved to call Revu | U29: #N/A | V29: #N/A | W29: #N/A | X29: Secondary Package: Carrier Registration - Monthly ($10.00)
A30: Murray Chrysler Dodge Jeep Ram | B30: 90442 | C30: 18231 | D30: 0 | E30: 0 | F30: 424.15 | G30: =+F30-E30 -> 424.15 | H30: 76167994 | I30: MURRAY CHRYSLER DODGE JEEP | K30: 43862 | L30: 44500 | M30: 4570060 | N30: CRM OUTBOUND TELEPHONY TRACKING (NEW AND CONVERSION) | O30: =VLOOKUP(H30,'Billing CDK pivot'!A:C,3,FALSE) -> #N/A | P30: =IFERROR(VLOOKUP(H30,'Billing CDK pivot (overages)'!A:F,6,FALSE),0) -> 0 | Q30: =+O30+P30 -> #N/A | R30: =+O30-G30 -> #N/A | S30: =+R30/O30 -> #N/A | T30: Moved to Call Revu in 2021 | U30: #N/A | V30: #N/A | W30: #N/A | X30: Secondary Package: Carrier Registration - Monthly ($10.00)
A31: North Point CJDR | B31: 81644 | C31: 17721 | D31: 16020.29 | E31: 0 | F31: 1581.65 | G31: =+F31-E31 -> 1581.65 | H31: 01326364 | I31: NORTH POINT CHRYSLER DODGE JEEP RAM | M31: =VLOOKUP(H31,'Billing CDK pivot (by package)'!A:D,3,FALSE) -> 4570060 | N31: =VLOOKUP(H31,'Billing CDK pivot (by package)'!A:D,4,FALSE) -> CRM OUTBOUND TELEPHONY TRACKING (NEW AND CONVERSION) | O31: =VLOOKUP(H31,'Billing CDK pivot'!A:C,3,FALSE) -> #N/A | P31: =IFERROR(VLOOKUP(H31,'Billing CDK pivot (overages)'!A:F,6,FALSE),0) -> 0 | Q31: =+O31+P31 -> #N/A | R31: =+O31-G31 -> #N/A | S31: =+R31/O31 -> #N/A | T31: Negative Margin | U31: CRM OUTBOUND TELEPHONY TRACKING (NEW AND CONVERSION) ($131.04) | X31: Secondary Package: Carrier Registration - Monthly ($10.00) | Y31: Elead CW Unlimited v2 ($1,571.65)
A32: Holman NC - Leith Autopark Wendell | B32: 61226 | C32: 16386 | D32: 13441.24 | E32: 426.58 | F32: 1295.73 | G32: =+F32-E32 -> 869.15 | H32: 71039289 | I32: LEITH AUTO PARK KIA | M32: =VLOOKUP(H32,'Billing CDK pivot (by package)'!A:D,3,FALSE) -> #N/A | N32: =VLOOKUP(H32,'Billing CDK pivot (by package)'!A:D,4,FALSE) -> #N/A | O32: =VLOOKUP(H32,'Billing CDK pivot'!A:C,3,FALSE) -> #N/A | P32: =IFERROR(VLOOKUP(H32,'Billing CDK pivot (overages)'!A:F,6,FALSE),0) -> 0 | Q32: =+O32+P32 -> #N/A | R32: =+O32-G32 -> #N/A | S32: =+R32/O32 -> #N/A | T32: Negative Margin | U32: CRM OUTBOUND TELEPHONY TRACKING (NEW AND CONVERSION) ($199.00) | V32: CARWARS INDEFINITE CALL RECORDINGS ($10.00) | X32: Secondary Package: Carrier Registration - Monthly ($10.00) | Y32: eLead - CW Advanced - Sales - 7500 mins v2 ($849.15) | Z32: Secondary Package: Long Term Audio Storage - $10 ($10.00)
A33: Bruce Bennett Nissan of Danbury | B33: 154578 | C33: 27016 | D33: 14366.1 | E33: 0 | F33: 1581.65 | G33: =+F33-E33 -> 1581.65 | H33: 76225899 | I33: DANBURY NISSAN INFINITI | M33: =VLOOKUP(H33,'Billing CDK pivot (by package)'!A:D,3,FALSE) -> #N/A | N33: =VLOOKUP(H33,'Billing CDK pivot (by package)'!A:D,4,FALSE) -> #N/A | O33: =VLOOKUP(H33,'Billing CDK pivot'!A:C,3,FALSE) -> #N/A | P33: =IFERROR(VLOOKUP(H33,'Billing CDK pivot (overages)'!A:F,6,FALSE),0) -> 0 | Q33: =+O33+P33 -> #N/A | R33: =+O33-G33 -> #N/A | S33: =+R33/O33 -> #N/A | T33: Negative Margin | U33: CARWARS STARTER 7500 ($499.00) | X33: Elead Launch Phase-0 ($0.00) | Y33: eLead - CW Premium - Sales 50k v2 ($1,571.65)
A34: Zimbrick BMW | B34: 56397 | C34: 15949 | D34: 9173.52 | E34: 80.97 | F34: 525.12 | G34: =+F34-E34 -> 444.15 | H34: 76066617 | I34: ZIMBRICK BMW | M34: =VLOOKUP(H34,'Billing CDK pivot (by package)'!A:D,3,FALSE) -> #N/A | N34: =VLOOKUP(H34,'Billing CDK pivot (by package)'!A:D,4,FALSE) -> #N/A | O34: =VLOOKUP(H34,'Billing CDK pivot'!A:C,3,FALSE) -> #N/A | P34: =IFERROR(VLOOKUP(H34,'Billing CDK pivot (overages)'!A:F,6,FALSE),0) -> 0 | Q34: =+O34+P34 -> #N/A | R34: =+O34-G34 -> #N/A | S34: =+R34/O34 -> #N/A | T34: Negative Margin | U34: CRM OUTBOUND TELEPHONY TRACKING (NEW AND CONVERSION) ($142.17) | X34: Secondary Package: Carrier Registration - Monthly ($10.00) | Y34: Elead CW Starter 8000 v2 ($424.15) | Z34: Secondary Package: Long Term Audio Storage - $10 ($10.00)
A35: Zimbrick Chevrolet | B35: 56395 | C35: 15949 | D35: 1040.22 | E35: 0 | F35: 434.15 | G35: =+F35-E35 -> 434.15 | H35: 76161145 | I35: ZIMBRICK CHEVROLET | M35: =VLOOKUP(H35,'Billing CDK pivot (by package)'!A:D,3,FALSE) -> #N/A | N35: =VLOOKUP(H35,'Billing CDK pivot (by package)'!A:D,4,FALSE) -> #N/A | O35: =VLOOKUP(H35,'Billing CDK pivot'!A:C,3,FALSE) -> #N/A | P35: =IFERROR(VLOOKUP(H35,'Billing CDK pivot (overages)'!A:F,6,FALSE),0) -> 0 | Q35: =+O35+P35 -> #N/A | R35: =+O35-G35 -> #N/A | S35: =+R35/O35 -> #N/A | T35: Negative Margin | U35: CRM OUTBOUND TELEPHONY TRACKING (NEW AND CONVERSION) ($142.17) | X35: Secondary Package: Carrier Registration - Monthly ($10.00) | Y35: Elead CW Starter 8000 v2 ($424.15)
A36: Zimbrick Mini | B36: 56403 | C36: 15949 | D36: 1760.72 | E36: 0 | F36: 434.15 | G36: =+F36-E36 -> 434.15 | H36: 76069427 | I36: ZIMBRICK MINI | M36: =VLOOKUP(H36,'Billing CDK pivot (by package)'!A:D,3,FALSE) -> #N/A | N36: =VLOOKUP(H36,'Billing CDK pivot (by package)'!A:D,4,FALSE) -> #N/A | O36: =VLOOKUP(H36,'Billing CDK pivot'!A:C,3,FALSE) -> #N/A | P36: =IFERROR(VLOOKUP(H36,'Billing CDK pivot (overages)'!A:F,6,FALSE),0) -> 0 | Q36: =+O36+P36 -> #N/A | R36: =+O36-G36 -> #N/A | S36: =+R36/O36 -> #N/A | T36: Negative Margin | U36: CRM OUTBOUND TELEPHONY TRACKING (NEW AND CONVERSION) ($142.17) | X36: eLead - Elite Small ($1,019.00) | Y36: Elead CW Starter 8000 v2 ($424.15)
A37: Holman NC - Leith Porsche Cary | B37: 61225 | C37: 16380 | D37: 8772.33 | E37: 0 | F37: 1581.65 | G37: =+F37-E37 -> 1581.65 | H37: 01021838 | I37: LEITH PORSCHE | M37: =VLOOKUP(H37,'Billing CDK pivot (by package)'!A:D,3,FALSE) -> 4571030 | N37: =VLOOKUP(H37,'Billing CDK pivot (by package)'!A:D,4,FALSE) -> CARWARS STARTER 5000 | O37: =VLOOKUP(H37,'Billing CDK pivot'!A:C,3,FALSE) -> #N/A | P37: =IFERROR(VLOOKUP(H37,'Billing CDK pivot (overages)'!A:F,6,FALSE),0) -> 0 | Q37: =+O37+P37 -> #N/A | R37: =+O37-G37 -> #N/A | S37: =+R37/O37 -> #N/A | T37: Negative Margin | U37: CARWARS STARTER 5000 ($599.00) | X37: Secondary Package: Carrier Registration - Monthly ($10.00) | Y37: eLead - CW Premium - Sales 50k v2 ($1,571.65)
A38: Holman NC - Leith Maserati of Raleigh | B38: 61222 | C38: 16370 | D38: 3014.34 | E38: 0 | F38: 1581.65 | G38: =+F38-E38 -> 1581.65 | H38: 76025122 | I38: MASERATI OF RALEIGH | M38: =VLOOKUP(H38,'Billing CDK pivot (by package)'!A:D,3,FALSE) -> #N/A | N38: =VLOOKUP(H38,'Billing CDK pivot (by package)'!A:D,4,FALSE) -> #N/A | O38: =VLOOKUP(H38,'Billing CDK pivot'!A:C,3,FALSE) -> #N/A | P38: =IFERROR(VLOOKUP(H38,'Billing CDK pivot (overages)'!A:F,6,FALSE),0) -> 0 | Q38: =+O38+P38 -> #N/A | R38: =+O38-G38 -> #N/A | S38: =+R38/O38 -> #N/A | T38: Negative Margin | U38: CARWARS INDEFINITE CALL RECORDINGS ($20.00) | V38: CARWARS STARTER 5000 ($599.00) | X38: Secondary Package: Carrier Registration - Monthly ($10.00) | Y38: eLead - CW Premium - Sales 50k v2 ($1,571.65)
A39: Modern Subaru of Boone | B39: 131769 | C39: 21831 | D39: 1393.76 | E39: 0 | F39: 434.15 | G39: =+F39-E39 -> 434.15 | H39: 76162431 | I39: MODERN SUBARU OF BOONE | M39: =VLOOKUP(H39,'Billing CDK pivot (by package)'!A:D,3,FALSE) -> #N/A | N39: =VLOOKUP(H39,'Billing CDK pivot (by package)'!A:D,4,FALSE) -> #N/A | O39: =VLOOKUP(H39,'Billing CDK pivot'!A:C,3,FALSE) -> #N/A | P39: =IFERROR(VLOOKUP(H39,'Billing CDK pivot (overages)'!A:F,6,FALSE),0) -> 0 | Q39: =+O39+P39 -> #N/A | R39: =+O39-G39 -> #N/A | S39: =+R39/O39 -> #N/A | T39: Negative Margin | U39: CARWARS STARTER 3500 ($200.93) | X39: Secondary Package: Carrier Registration - Monthly ($10.00) | Y39: eLead - CW Starter - 7500 mins v2 ($424.15)
A40: Holman NC - Leith Audi Raleigh | B40: 61230 | C40: 16397 | D40: 2412.18 | E40: 0 | F40: 1581.65 | G40: =+F40-E40 -> 1581.65 | H40: 76072454 | I40: AUDI RALEIGH | M40: =VLOOKUP(H40,'Billing CDK pivot (by package)'!A:D,3,FALSE) -> #N/A | N40: =VLOOKUP(H40,'Billing CDK pivot (by package)'!A:D,4,FALSE) -> #N/A | O40: =VLOOKUP(H40,'Billing CDK pivot'!A:C,3,FALSE) -> #N/A | P40: =IFERROR(VLOOKUP(H40,'Billing CDK pivot (overages)'!A:F,6,FALSE),0) -> 0 | Q40: =+O40+P40 -> #N/A | R40: =+O40-G40 -> #N/A | S40: =+R40/O40 -> #N/A | T40: Negative Margin | U40: CARWARS INDEFINITE CALL RECORDINGS ($20.00) | V40: CARWARS STARTER UNLIMITED (FOR PHONE SYSTEMS) ($799.00) | X40: Secondary Package: Carrier Registration - Monthly ($10.00) | Y40: eLead - CW Premium - Sales 50k v2 ($1,571.65)
A41: Zimbrick Volkswagen of Madison | B41: 84497 | C41: 15961 | D41: 518.33 | E41: 0 | F41: 264.15 | G41: =+F41-E41 -> 264.15 | H41: 76066648 | I41: ZIMBRICK VOLKSWAGEN EAST | M41: =VLOOKUP(H41,'Billing CDK pivot (by package)'!A:D,3,FALSE) -> #N/A | N41: =VLOOKUP(H41,'Billing CDK pivot (by package)'!A:D,4,FALSE) -> #N/A | O41: =VLOOKUP(H41,'Billing CDK pivot'!A:C,3,FALSE) -> #N/A | P41: =IFERROR(VLOOKUP(H41,'Billing CDK pivot (overages)'!A:F,6,FALSE),0) -> 0 | Q41: =+O41+P41 -> #N/A | R41: =+O41-G41 -> #N/A | S41: =+R41/O41 -> #N/A | T41: Negative Margin | U41: CRM OUTBOUND TELEPHONY TRACKING (NEW AND CONVERSION) ($145.08) | X41: eLead - Elite Small ($1,019.00) | Y41: eLead - CW Starter - 3500 mins v2 ($254.15)
A42: Greenway - Greenway Kia of Rivergate | B42: 79241 | C42: 17536 | D42: 9824.7 | E42: 0 | F42: 1581.65 | G42: =+F42-E42 -> 1581.65 | H42: 76212425 | I42: GREENWAY KIA RIVERGATE | M42: =VLOOKUP(H42,'Billing CDK pivot (by package)'!A:D,3,FALSE) -> #N/A | N42: =VLOOKUP(H42,'Billing CDK pivot (by package)'!A:D,4,FALSE) -> #N/A | O42: =VLOOKUP(H42,'Billing CDK pivot'!A:C,3,FALSE) -> #N/A | P42: =IFERROR(VLOOKUP(H42,'Billing CDK pivot (overages)'!A:F,6,FALSE),0) -> 0 | Q42: =+O42+P42 -> #N/A | R42: =+O42-G42 -> #N/A | S42: =+R42/O42 -> #N/A | T42: Negative Margin | U42: CRM OUTBOUND TELEPHONY TRACKING (NEW AND CONVERSION) ($995.00) | X42: Secondary Package: Carrier Registration - Monthly ($10.00) | Y42: eLead - CW Premium - Sales 50k v2 ($1,571.65)
A43: Holman NC - Leith Jaguar Land Rover of Raleigh | B43: 115628 | C43: 19523 | D43: 6368.57 | E43: 0 | F43: 1581.65 | G43: =+F43-E43 -> 1581.65 | H43: 76208075 | I43: JAGUAR LAND ROVER RALEIGH | M43: =VLOOKUP(H43,'Billing CDK pivot (by package)'!A:D,3,FALSE) -> #N/A | N43: =VLOOKUP(H43,'Billing CDK pivot (by package)'!A:D,4,FALSE) -> #N/A | O43: =VLOOKUP(H43,'Billing CDK pivot'!A:C,3,FALSE) -> #N/A | P43: =IFERROR(VLOOKUP(H43,'Billing CDK pivot (overages)'!A:F,6,FALSE),0) -> 0 | Q43: =+O43+P43 -> #N/A | R43: =+O43-G43 -> #N/A | S43: =+R43/O43 -> #N/A | T43: Negative Margin | U43: CARWARS ADVANCED SALES ($999.00) | X43: Secondary Package: Carrier Registration - Monthly ($10.00) | Y43: eLead - CW Premium - Sales 50k v2 ($1,571.65)
A44: Holman NC - Leith Autopark Chrysler Jeep | B44: 58253 | C44: 16166 | D44: 4579.92 | E44: 0 | F44: 1581.65 | G44: =+F44-E44 -> 1581.65 | H44: 01327379 | I44: AUTO PARK CHRYSLER JEEP | M44: =VLOOKUP(H44,'Billing CDK pivot (by package)'!A:D,3,FALSE) -> 4570122 | N44: =VLOOKUP(H44,'Billing CDK pivot (by package)'!A:D,4,FALSE) -> CARWARS ADVANCED SALES | O44: =VLOOKUP(H44,'Billing CDK pivot'!A:C,3,FALSE) -> #N/A | P44: =IFERROR(VLOOKUP(H44,'Billing CDK pivot (overages)'!A:F,6,FALSE),0) -> 0 | Q44: =+O44+P44 -> #N/A | R44: =+O44-G44 -> #N/A | S44: =+R44/O44 -> #N/A | T44: Negative Margin | U44: CARWARS ADVANCED SALES ($999.00) | V44: CARWARS INDEFINITE CALL RECORDINGS ($20.00) | X44: Secondary Package: Carrier Registration - Monthly ($10.00) | Y44: eLead - CW Premium - Sales 50k v2 ($1,571.65)
A45: Holman NC - Leith BMW | B45: 58245 | C45: 16167 | D45: 16121.39 | E45: 0 | F45: 1581.65 | G45: =+F45-E45 -> 1581.65 | H45: 01021824 | I45: LEITH BMW | M45: =VLOOKUP(H45,'Billing CDK pivot (by package)'!A:D,3,FALSE) -> 4570122 | N45: =VLOOKUP(H45,'Billing CDK pivot (by package)'!A:D,4,FALSE) -> CARWARS ADVANCED SALES | O45: =VLOOKUP(H45,'Billing CDK pivot'!A:C,3,FALSE) -> #N/A | P45: =IFERROR(VLOOKUP(H45,'Billing CDK pivot (overages)'!A:F,6,FALSE),0) -> 0 | Q45: =+O45+P45 -> #N/A | R45: =+O45-G45 -> #N/A | S45: =+R45/O45 -> #N/A | T45: Negative Margin | U45: CARWARS ADVANCED SALES ($999.00) | V45: CARWARS INDEFINITE CALL RECORDINGS ($20.00) | X45: Secondary Package: Carrier Registration - Monthly ($10.00) | Y45: eLead - CW Premium - Sales 50k v2 ($1,571.65)
A46: Holman NC - Leith Land Rover Cary | B46: 61223 | C46: 16372 | D46: 9131.46 | E46: 0 | F46: 1581.65 | G46: =+F46-E46 -> 1581.65 | H46: 09700157 | I46: LAND ROVER CARY | M46: =VLOOKUP(H46,'Billing CDK pivot (by package)'!A:D,3,FALSE) -> 4570122 | N46: =VLOOKUP(H46,'Billing CDK pivot (by package)'!A:D,4,FALSE) -> CARWARS ADVANCED SALES | O46: =VLOOKUP(H46,'Billing CDK pivot'!A:C,3,FALSE) -> #N/A | P46: =IFERROR(VLOOKUP(H46,'Billing CDK pivot (overages)'!A:F,6,FALSE),0) -> 0 | Q46: =+O46+P46 -> #N/A | R46: =+O46-G46 -> #N/A | S46: =+R46/O46 -> #N/A | T46: Negative Margin | U46: CARWARS ADVANCED SALES ($999.00) | V46: CARWARS INDEFINITE CALL RECORDINGS ($20.00) | X46: Secondary Package: Carrier Registration - Monthly ($10.00) | Y46: eLead - CW Premium - Sales 50k v2 ($1,571.65)
A47: Holman NC - Leith Mercedes-Benz of Raleigh | B47: 150508 | C47: 16169 | D47: 15069.56 | E47: 0 | F47: 1581.65 | G47: =+F47-E47 -> 1581.65 | H47: 01021828 | I47: LEITH MERCEDES BENZ OF RALEIGH | M47: =VLOOKUP(H47,'Billing CDK pivot (by package)'!A:D,3,FALSE) -> 4570122 | N47: =VLOOKUP(H47,'Billing CDK pivot (by package)'!A:D,4,FALSE) -> CARWARS ADVANCED SALES | O47: =VLOOKUP(H47,'Billing CDK pivot'!A:C,3,FALSE) -> #N/A | P47: =IFERROR(VLOOKUP(H47,'Billing CDK pivot (overages)'!A:F,6,FALSE),0) -> 0 | Q47: =+O47+P47 -> #N/A | R47: =+O47-G47 -> #N/A | S47: =+R47/O47 -> #N/A | T47: Negative Margin | U47: CARWARS ADVANCED SALES ($999.00) | V47: CARWARS INDEFINITE CALL RECORDINGS ($20.00) | X47: Secondary Package: Carrier Registration - Monthly ($10.00) | Y47: eLead - CW Premium - Sales 50k v2 ($1,571.65)
A48: Toyota of Wichita Falls | B48: 145647 | C48: 24702 | D48: 624.96 | E48: 0 | F48: 434.15 | G48: =+F48-E48 -> 434.15 | H48: 76214101 | I48: BRADLEY/WILSON W.F., LLLP DBA TOYOTA WICHITA FALLS | M48: =VLOOKUP(H48,'Billing CDK pivot (by package)'!A:D,3,FALSE) -> #N/A | N48: =VLOOKUP(H48,'Billing CDK pivot (by package)'!A:D,4,FALSE) -> #N/A | O48: =VLOOKUP(H48,'Billing CDK pivot'!A:C,3,FALSE) -> #N/A | P48: =IFERROR(VLOOKUP(H48,'Billing CDK pivot (overages)'!A:F,6,FALSE),0) -> 0 | Q48: =+O48+P48 -> #N/A | R48: =+O48-G48 -> #N/A | S48: =+R48/O48 -> #N/A | T48: Negative Margin | U48: CARWARS STARTER 7500 ($294.41) | X48: Secondary Package: Carrier Registration - Monthly ($10.00) | Y48: eLead - CW Starter - 7500 mins v2 ($424.15)
A49: Kia of Abilene | B49: 144285 | C49: 24706 | D49: 11163.04 | E49: 0 | F49: 1581.65 | G49: =+F49-E49 -> 1581.65 | H49: 76152812 | I49: KIA OF ABILENE | M49: =VLOOKUP(H49,'Billing CDK pivot (by package)'!A:D,3,FALSE) -> #N/A | N49: =VLOOKUP(H49,'Billing CDK pivot (by package)'!A:D,4,FALSE) -> #N/A | O49: =VLOOKUP(H49,'Billing CDK pivot'!A:C,3,FALSE) -> #N/A | P49: =IFERROR(VLOOKUP(H49,'Billing CDK pivot (overages)'!A:F,6,FALSE),0) -> 0 | Q49: =+O49+P49 -> #N/A | R49: =+O49-G49 -> #N/A | S49: =+R49/O49 -> #N/A | T49: Negative Margin | U49: CARWARS PREMIUM SALES ($1,090.91) | X49: Elead CW Starter 4000 v2 ($254.15) | Y49: eLead - CW Premium - Sales 50k v2 ($1,571.65)
A50: TMC - Manchester Harley-Davidson | B50: 138624 | C50: 18505 | D50: 12758.72 | E50: 0 | F50: 2005.65 | G50: =+F50-E50 -> 2005.65 | H50: 76044726 | I50: MANCHESTER HARLEY DAVIDSON | M50: =VLOOKUP(H50,'Billing CDK pivot (by package)'!A:D,3,FALSE) -> #N/A | N50: =VLOOKUP(H50,'Billing CDK pivot (by package)'!A:D,4,FALSE) -> #N/A | O50: =VLOOKUP(H50,'Billing CDK pivot'!A:C,3,FALSE) -> #N/A | P50: =IFERROR(VLOOKUP(H50,'Billing CDK pivot (overages)'!A:F,6,FALSE),0) -> 0 | Q50: =+O50+P50 -> #N/A | R50: =+O50-G50 -> #N/A | S50: =+R50/O50 -> #N/A | T50: Negative Margin | U50: CARWARS PREMIUM SALES ($1,386.75) | X50: Secondary Package: Carrier Registration - Monthly ($10.00) | Y50: eLead - CW Premium - Sales 50k v2 ($1,571.65) | Z50: Secondary Package: Reseller - Voice Recongnition v2 ($424.00)
A51: Evergreen Kia | B51: 156791 | C51: 28946 | D51: 1905.45 | E51: 0 | F51: 424.15 | G51: =+F51-E51 -> 424.15 | H51: 76002263 | I51: EVERGREEN MOTORS INC | M51: =VLOOKUP(H51,'Billing CDK pivot (by package)'!A:D,3,FALSE) -> #N/A | N51: =VLOOKUP(H51,'Billing CDK pivot (by package)'!A:D,4,FALSE) -> #N/A | O51: =VLOOKUP(H51,'Billing CDK pivot'!A:C,3,FALSE) -> #N/A | P51: =IFERROR(VLOOKUP(H51,'Billing CDK pivot (overages)'!A:F,6,FALSE),0) -> 0 | Q51: =+O51+P51 -> #N/A | R51: =+O51-G51 -> #N/A | S51: =+R51/O51 -> #N/A | T51: Negative Margin | U51: CARWARS STARTER 3500 ($319.00) | X51: Secondary Package: Carrier Registration - Monthly ($10.00)
A52: Modern Nissan of Hickory | B52: 140643 | C52: 23116 | D52: 5305.43 | E52: 124.57 | F52: 388.72 | G52: =+F52-E52 -> 264.15 | H52: 76179995 | I52: MODERN NISSAN OF HICKORY | M52: =VLOOKUP(H52,'Billing CDK pivot (by package)'!A:D,3,FALSE) -> #N/A | N52: =VLOOKUP(H52,'Billing CDK pivot (by package)'!A:D,4,FALSE) -> #N/A | O52: =VLOOKUP(H52,'Billing CDK pivot'!A:C,3,FALSE) -> #N/A | P52: =IFERROR(VLOOKUP(H52,'Billing CDK pivot (overages)'!A:F,6,FALSE),0) -> 0 | Q52: =+O52+P52 -> #N/A | R52: =+O52-G52 -> #N/A | S52: =+R52/O52 -> #N/A | T52: Negative Margin | U52: CARWARS STARTER 3500 ($200.93) | X52: Secondary Package: Carrier Registration - Monthly ($10.00) | Y52: eLead - CW Starter - 3500 mins v2 ($254.15)
A53: Modern Chevrolet Cadillac of Burlington | B53: 139748 | C53: 9273 | D53: 2041.07 | E53: 0 | F53: 264.15 | G53: =+F53-E53 -> 264.15 | H53: 76203742 | I53: MODERN CHEVROLET CADILLAC OF BURLINGTON | M53: =VLOOKUP(H53,'Billing CDK pivot (by package)'!A:D,3,FALSE) -> #N/A | N53: =VLOOKUP(H53,'Billing CDK pivot (by package)'!A:D,4,FALSE) -> #N/A | O53: =VLOOKUP(H53,'Billing CDK pivot'!A:C,3,FALSE) -> #N/A | P53: =IFERROR(VLOOKUP(H53,'Billing CDK pivot (overages)'!A:F,6,FALSE),0) -> 0 | Q53: =+O53+P53 -> #N/A | R53: =+O53-G53 -> #N/A | S53: =+R53/O53 -> #N/A | T53: Negative Margin | U53: CARWARS STARTER 3500 ($200.93) | X53: Secondary Package: Carrier Registration - Monthly ($10.00) | Y53: eLead - CW Starter - 3500 mins v2 ($254.15)
A54: Modern Ford of Boone | B54: 144122 | C54: 19202 | D54: 733.39 | E54: 0 | F54: 264.15 | G54: =+F54-E54 -> 264.15 | H54: 76190193 | I54: MODERN FORD OF BOONE, LLC | M54: =VLOOKUP(H54,'Billing CDK pivot (by package)'!A:D,3,FALSE) -> #N/A | N54: =VLOOKUP(H54,'Billing CDK pivot (by package)'!A:D,4,FALSE) -> #N/A | O54: =VLOOKUP(H54,'Billing CDK pivot'!A:C,3,FALSE) -> #N/A | P54: =IFERROR(VLOOKUP(H54,'Billing CDK pivot (overages)'!A:F,6,FALSE),0) -> 0 | Q54: =+O54+P54 -> #N/A | R54: =+O54-G54 -> #N/A | S54: =+R54/O54 -> #N/A | T54: Negative Margin | U54: CARWARS STARTER 3500 ($200.93) | X54: Secondary Package: Carrier Registration - Monthly ($10.00) | Y54: eLead - CW Starter - 3500 mins v2 ($254.15)
A55: Modern Hyundai of Concord | B55: 138603 | C55: 22232 | D55: 5949.05 | E55: 168.98 | F55: 433.13 | G55: =+F55-E55 -> 264.15 | H55: 76043216 | I55: MODERN HYUNDAI OF CONCORD | M55: =VLOOKUP(H55,'Billing CDK pivot (by package)'!A:D,3,FALSE) -> #N/A | N55: =VLOOKUP(H55,'Billing CDK pivot (by package)'!A:D,4,FALSE) -> #N/A | O55: =VLOOKUP(H55,'Billing CDK pivot'!A:C,3,FALSE) -> #N/A | P55: =IFERROR(VLOOKUP(H55,'Billing CDK pivot (overages)'!A:F,6,FALSE),0) -> 0 | Q55: =+O55+P55 -> #N/A | R55: =+O55-G55 -> #N/A | S55: =+R55/O55 -> #N/A | T55: Negative Margin | U55: CARWARS STARTER 3500 ($200.93) | X55: eLead - CW Starter - 5000 mins v2 ($509.15) | Y55: eLead - CW Starter - 3500 mins v2 ($254.15)
A56: Modern Infiniti of Greensboro | B56: 131694 | C56: 21728 | D56: 2550.33 | E56: 0 | F56: 264.15 | G56: =+F56-E56 -> 264.15 | H56: 71043922 | I56: MODERN INFINITI OF GREENSBORO | M56: =VLOOKUP(H56,'Billing CDK pivot (by package)'!A:D,3,FALSE) -> #N/A | N56: =VLOOKUP(H56,'Billing CDK pivot (by package)'!A:D,4,FALSE) -> #N/A | O56: =VLOOKUP(H56,'Billing CDK pivot'!A:C,3,FALSE) -> #N/A | P56: =IFERROR(VLOOKUP(H56,'Billing CDK pivot (overages)'!A:F,6,FALSE),0) -> 0 | Q56: =+O56+P56 -> #N/A | R56: =+O56-G56 -> #N/A | S56: =+R56/O56 -> #N/A | T56: Negative Margin | U56: CARWARS STARTER 3500 ($200.93) | X56: Secondary Package: Carrier Registration - Monthly ($10.00) | Y56: eLead - CW Starter - 3500 mins v2 ($254.15)
A57: Modern Infiniti of Winston Salem | B57: 131695 | C57: 21729 | D57: 1726.19 | E57: 0 | F57: 264.15 | G57: =+F57-E57 -> 264.15 | H57: 76162462 | I57: MODERN INFINITI OF WINSTON-SALEM | M57: =VLOOKUP(H57,'Billing CDK pivot (by package)'!A:D,3,FALSE) -> #N/A | N57: =VLOOKUP(H57,'Billing CDK pivot (by package)'!A:D,4,FALSE) -> #N/A | O57: =VLOOKUP(H57,'Billing CDK pivot'!A:C,3,FALSE) -> #N/A | P57: =IFERROR(VLOOKUP(H57,'Billing CDK pivot (overages)'!A:F,6,FALSE),0) -> 0 | Q57: =+O57+P57 -> #N/A | R57: =+O57-G57 -> #N/A | S57: =+R57/O57 -> #N/A | T57: Negative Margin | U57: CARWARS STARTER 3500 ($200.93) | X57: Secondary Package: Carrier Registration - Monthly ($10.00) | Y57: eLead - CW Starter - 3500 mins v2 ($254.15)
A58: Modern Mazda of Burlington | B58: 143944 | C58: 21588 | D58: 894.45 | E58: 0 | F58: 264.15 | G58: =+F58-E58 -> 264.15 | H58: 76203700 | I58: MODERN MAZDA OF BURLINGTON | M58: =VLOOKUP(H58,'Billing CDK pivot (by package)'!A:D,3,FALSE) -> #N/A | N58: =VLOOKUP(H58,'Billing CDK pivot (by package)'!A:D,4,FALSE) -> #N/A | O58: =VLOOKUP(H58,'Billing CDK pivot'!A:C,3,FALSE) -> #N/A | P58: =IFERROR(VLOOKUP(H58,'Billing CDK pivot (overages)'!A:F,6,FALSE),0) -> 0 | Q58: =+O58+P58 -> #N/A | R58: =+O58-G58 -> #N/A | S58: =+R58/O58 -> #N/A | T58: Negative Margin | U58: CARWARS STARTER 3500 ($200.93) | X58: Secondary Package: Carrier Registration - Monthly ($10.00) | Y58: eLead - CW Starter - 3500 mins v2 ($254.15)
A59: Modern Nissan of Concord | B59: 138480 | C59: 22230 | D59: 12233.14 | E59: 602.59 | F59: 866.74 | G59: =+F59-E59 -> 264.15 | H59: 76162428 | I59: MODERN NISSAN OF CONCORD | M59: =VLOOKUP(H59,'Billing CDK pivot (by package)'!A:D,3,FALSE) -> #N/A | N59: =VLOOKUP(H59,'Billing CDK pivot (by package)'!A:D,4,FALSE) -> #N/A | O59: =VLOOKUP(H59,'Billing CDK pivot'!A:C,3,FALSE) -> #N/A | P59: =IFERROR(VLOOKUP(H59,'Billing CDK pivot (overages)'!A:F,6,FALSE),0) -> 0 | Q59: =+O59+P59 -> #N/A | R59: =+O59-G59 -> #N/A | S59: =+R59/O59 -> #N/A | T59: Negative Margin | U59: CARWARS STARTER 3500 ($200.93) | X59: Secondary Package: Carrier Registration - Monthly ($10.00) | Y59: eLead - CW Starter - 3500 mins v2 ($254.15)
A60: Modern Toyota of Boone | B60: 131770 | C60: 21830 | D60: 4028.11 | E60: 36.44 | F60: 300.59 | G60: =+F60-E60 -> 264.15 | H60: 71064573 | I60: MODERN TOYOTA OF BOONE | M60: =VLOOKUP(H60,'Billing CDK pivot (by package)'!A:D,3,FALSE) -> #N/A | N60: =VLOOKUP(H60,'Billing CDK pivot (by package)'!A:D,4,FALSE) -> #N/A | O60: =VLOOKUP(H60,'Billing CDK pivot'!A:C,3,FALSE) -> #N/A | P60: =IFERROR(VLOOKUP(H60,'Billing CDK pivot (overages)'!A:F,6,FALSE),0) -> 0 | Q60: =+O60+P60 -> #N/A | R60: =+O60-G60 -> #N/A | S60: =+R60/O60 -> #N/A | T60: Negative Margin | U60: CARWARS STARTER 3500 ($200.93) | X60: Secondary Package: Carrier Registration - Monthly ($10.00) | Y60: eLead - CW Starter - 3500 mins v2 ($254.15)
A61: Modern Nissan of Winston Salem | B61: 140642 | C61: 23115 | D61: 12096.9 | E61: 317.19 | F61: 751.34 | G61: =+F61-E61 -> 434.15 | H61: 71043920 | I61: MODERN NISSAN | M61: =VLOOKUP(H61,'Billing CDK pivot (by package)'!A:D,3,FALSE) -> #N/A | N61: =VLOOKUP(H61,'Billing CDK pivot (by package)'!A:D,4,FALSE) -> #N/A | O61: =VLOOKUP(H61,'Billing CDK pivot'!A:C,3,FALSE) -> #N/A | P61: =IFERROR(VLOOKUP(H61,'Billing CDK pivot (overages)'!A:F,6,FALSE),0) -> 0 | Q61: =+O61+P61 -> #N/A | R61: =+O61-G61 -> #N/A | S61: =+R61/O61 -> #N/A | T61: Negative Margin | U61: CARWARS STARTER 7500 ($335.33) | X61: Secondary Package: Carrier Registration - Monthly ($10.00) | Y61: eLead - CW Starter - 7500 mins v2 ($424.15)
A62: Independence Harley Davidson | B62: 120186 | C62: 21332 | D62: 1346.42 | E62: 0 | F62: 434.15 | G62: =+F62-E62 -> 434.15 | H62: 76210935 | I62: INDEPENDENCE HARLEY | M62: =VLOOKUP(H62,'Billing CDK pivot (by package)'!A:D,3,FALSE) -> #N/A | N62: =VLOOKUP(H62,'Billing CDK pivot (by package)'!A:D,4,FALSE) -> #N/A | O62: =VLOOKUP(H62,'Billing CDK pivot'!A:C,3,FALSE) -> #N/A | P62: =IFERROR(VLOOKUP(H62,'Billing CDK pivot (overages)'!A:F,6,FALSE),0) -> 0 | Q62: =+O62+P62 -> #N/A | R62: =+O62-G62 -> #N/A | S62: =+R62/O62 -> #N/A | T62: Negative Margin | U62: CRM OUTBOUND TELEPHONY TRACKING (NEW AND CONVERSION) ($338.20) | X62: Secondary Package: Carrier Registration - Monthly ($10.00) | Y62: eLead - CW Starter - 7500 mins v2 ($424.15)
A63: Modern Chevrolet - Winston | B63: 136865 | C63: 22158 | D63: 14083.53 | E63: 0 | F63: 1581.65 | G63: =+F63-E63 -> 1581.65 | H63: 71047244 | I63: MODERN CHEVROLET - WINSTON | M63: =VLOOKUP(H63,'Billing CDK pivot (by package)'!A:D,3,FALSE) -> #N/A | N63: =VLOOKUP(H63,'Billing CDK pivot (by package)'!A:D,4,FALSE) -> #N/A | O63: =VLOOKUP(H63,'Billing CDK pivot'!A:C,3,FALSE) -> #N/A | P63: =IFERROR(VLOOKUP(H63,'Billing CDK pivot (overages)'!A:F,6,FALSE),0) -> 0 | Q63: =+O63+P63 -> #N/A | R63: =+O63-G63 -> #N/A | S63: =+R63/O63 -> #N/A | T63: Negative Margin | U63: CARWARS PREMIUM SALES ($1,242.53) | X63: Secondary Package: Carrier Registration - Monthly ($10.00) | Y63: eLead - CW Premium - Sales 50k v2 ($1,571.65)
... A66: Modern Toyota of Asheboro | B66: 147129 | C66: 9504 | D66: 2219.78 | E66: 0 | F66: 264.15 | G66: =+F66-E66 -> 264.15 | H66: 76227241 | I66: MODERN TOYOTA OF ASHEBORO | M66: =VLOOKUP(H66,'Billing CDK pivot (by package)'!A:D,3,FALSE) -> #N/A | N66: =VLOOKUP(H66,'Billing CDK pivot (by package)'!A:D,4,FALSE) -> #N/A | O66: =VLOOKUP(H66,'Billing CDK pivot'!A:C,3,FALSE) -> #N/A | P66: =IFERROR(VLOOKUP(H66,'Billing CDK pivot (overages)'!A:F,6,FALSE),0) -> 0 | Q66: =+O66+P66 -> #N/A | R66: =+O66-G66 -> #N/A | S66: =+R66/O66 -> #N/A | T66: Negative Margin | U66: CARWARS STARTER 3500 ($213.49) | X66: Secondary Package: Carrier Registration - Monthly ($10.00) | Y66: eLead - CW Starter - 3500 mins v2 ($254.15)
A67: Grainger Honda | B67: 79044 | C67: 15653 | D67: 8188.13 | E67: 0 | F67: 1591.65 | G67: =+F67-E67 -> 1591.65 | H67: 08300018 | I67: GRAINGER HONDA | M67: =VLOOKUP(H67,'Billing CDK pivot (by package)'!A:D,3,FALSE) -> 4570062 | N67: =VLOOKUP(H67,'Billing CDK pivot (by package)'!A:D,4,FALSE) -> CARWARS PREMIUM SALES | O67: =VLOOKUP(H67,'Billing CDK pivot'!A:C,3,FALSE) -> #N/A | P67: =IFERROR(VLOOKUP(H67,'Billing CDK pivot (overages)'!A:F,6,FALSE),0) -> 0 | Q67: =+O67+P67 -> #N/A | R67: =+O67-G67 -> #N/A | S67: =+R67/O67 -> #N/A | T67: Negative Margin | U67: CARWARS PREMIUM SALES ($1,294.30) | X67: Secondary Package: Carrier Registration - Monthly ($10.00) | Y67: Elead CW Unlimited v2 ($1,571.65) | Z67: Secondary Package: Long Term Audio Storage - $10 ($10.00)
A68: Circle - Volkswagen of Garden Grove | B68: 143783 | C68: 20698 | D68: 2158.05 | E68: 0 | F68: 264.15 | G68: =+F68-E68 -> 264.15 | H68: 76039334 | I68: VW OF GARDEN GROVE | M68: =VLOOKUP(H68,'Billing CDK pivot (by package)'!A:D,3,FALSE) -> #N/A | N68: =VLOOKUP(H68,'Billing CDK pivot (by package)'!A:D,4,FALSE) -> #N/A | O68: =VLOOKUP(H68,'Billing CDK pivot'!A:C,3,FALSE) -> #N/A | P68: =IFERROR(VLOOKUP(H68,'Billing CDK pivot (overages)'!A:F,6,FALSE),0) -> 0 | Q68: =+O68+P68 -> #N/A | R68: =+O68-G68 -> #N/A | S68: =+R68/O68 -> #N/A | T68: Negative Margin | U68: CARWARS STARTER 3500 ($217.23) | X68: Elead Launch Phase-0 ($0.00) | Y68: eLead - CW Starter - 3500 mins v2 ($254.15)
A69: Hughes Subaru | B69: 125150 | C69: 18058 | D69: 3808.83 | E69: 0 | F69: 424.15 | G69: =+F69-E69 -> 424.15 | H69: 76140120 | I69: HUGHES SUBARU | M69: =VLOOKUP(H69,'Billing CDK pivot (by package)'!A:D,3,FALSE) -> #N/A | N69: =VLOOKUP(H69,'Billing CDK pivot (by package)'!A:D,4,FALSE) -> #N/A | O69: =VLOOKUP(H69,'Billing CDK pivot'!A:C,3,FALSE) -> #N/A | P69: =IFERROR(VLOOKUP(H69,'Billing CDK pivot (overages)'!A:F,6,FALSE),0) -> 0 | Q69: =+O69+P69 -> #N/A | R69: =+O69-G69 -> #N/A | S69: =+R69/O69 -> #N/A | T69: Negative Margin | U69: CARWARS STARTER 7500 ($350.30) | X69: Elead CW Unlimited v2 ($1,571.65)
A70: Greenway - Riverchase Kia | B70: 118912 | C70: 19810 | D70: 4486.81 | E70: 0 | F70: 598 | G70: =+F70-E70 -> 598 | H70: 76209497 | I70: GREENWAY KIA OF RIVERCHASE | M70: =VLOOKUP(H70,'Billing CDK pivot (by package)'!A:D,3,FALSE) -> #N/A | N70: =VLOOKUP(H70,'Billing CDK pivot (by package)'!A:D,4,FALSE) -> #N/A | O70: =VLOOKUP(H70,'Billing CDK pivot'!A:C,3,FALSE) -> #N/A | P70: =IFERROR(VLOOKUP(H70,'Billing CDK pivot (overages)'!A:F,6,FALSE),0) -> 0 | Q70: =+O70+P70 -> #N/A | R70: =+O70-G70 -> #N/A | S70: =+R70/O70 -> #N/A | T70: Negative Margin | U70: CRM OUTBOUND TELEPHONY TRACKING (NEW AND CONVERSION) ($499.00) | X70: Secondary Package: Carrier Registration - Monthly ($10.00) | Y70: eLead - Starter 7500 + Starter 7500 ($588.00)
A71: Zimbrick Hyundai East | B71: 87080 | C71: 15963 | D71: 244.35 | E71: 0 | F71: 254.15 | G71: =+F71-E71 -> 254.15 | H71: 76066624 | I71: ZIMBRICK HYUNDAI EAST | M71: =VLOOKUP(H71,'Billing CDK pivot (by package)'!A:D,3,FALSE) -> #N/A | N71: =VLOOKUP(H71,'Billing CDK pivot (by package)'!A:D,4,FALSE) -> #N/A | O71: =VLOOKUP(H71,'Billing CDK pivot'!A:C,3,FALSE) -> #N/A | P71: =IFERROR(VLOOKUP(H71,'Billing CDK pivot (overages)'!A:F,6,FALSE),0) -> 0 | Q71: =+O71+P71 -> #N/A | R71: =+O71-G71 -> #N/A | S71: =+R71/O71 -> #N/A | T71: Negative Margin | U71: CRM OUTBOUND TELEPHONY TRACKING (NEW AND CONVERSION) ($217.99) | X71: eLead - Elite Small ($1,019.00)
A72: Zimbrick Nissan | B72: 87079 | C72: 15962 | D72: 326.63 | E72: 0 | F72: 254.15 | G72: =+F72-E72 -> 254.15 | H72: 76066621 | I72: ZIMBRICK EASTSIDE NISSAN | M72: =VLOOKUP(H72,'Billing CDK pivot (by package)'!A:D,3,FALSE) -> #N/A | N72: =VLOOKUP(H72,'Billing CDK pivot (by package)'!A:D,4,FALSE) -> #N/A | O72: =VLOOKUP(H72,'Billing CDK pivot'!A:C,3,FALSE) -> #N/A | P72: =IFERROR(VLOOKUP(H72,'Billing CDK pivot (overages)'!A:F,6,FALSE),0) -> 0 | Q72: =+O72+P72 -> #N/A | R72: =+O72-G72 -> #N/A | S72: =+R72/O72 -> #N/A | T72: Negative Margin | U72: CRM OUTBOUND TELEPHONY TRACKING (NEW AND CONVERSION) ($217.99) | X72: Secondary Package: Carrier Registration - Monthly ($10.00)
A73: TMC - Harley-Davidson of The Woodlands | B73: 156700 | C73: 28612 | D73: 29704.12 | E73: 0 | F73: 1601.65 | G73: =+F73-E73 -> 1601.65 | H73: 76250870 | I73: HARLEY-DAVIDSON OF THE WOODLANDS | M73: =VLOOKUP(H73,'Billing CDK pivot (by package)'!A:D,3,FALSE) -> #N/A | N73: =VLOOKUP(H73,'Billing CDK pivot (by package)'!A:D,4,FALSE) -> #N/A | O73: =VLOOKUP(H73,'Billing CDK pivot'!A:C,3,FALSE) -> #N/A | P73: =IFERROR(VLOOKUP(H73,'Billing CDK pivot (overages)'!A:F,6,FALSE),0) -> 0 | Q73: =+O73+P73 -> #N/A | R73: =+O73-G73 -> #N/A | S73: =+R73/O73 -> #N/A | T73: Negative Margin | U73: CARWARS PREMIUM SALES ($1,386.75) | X73: Secondary Package: Carrier Registration - Monthly ($10.00) | Y73: eLead - CW Premium - Sales 50k v2 ($1,571.65) | Z73: Secondary Package: Long Term Audio Storage ($20.00)
A74: TMC - Rockstar Powersports of Brandon | B74: 155859 | C74: 27874 | D74: 10395.36 | E74: 0 | F74: 1601.65 | G74: =+F74-E74 -> 1601.65 | H74: 76250877 | I74: ROCKSTAR POWERSPORTS OF BRANDON | M74: =VLOOKUP(H74,'Billing CDK pivot (by package)'!A:D,3,FALSE) -> #N/A | N74: =VLOOKUP(H74,'Billing CDK pivot (by package)'!A:D,4,FALSE) -> #N/A | O74: =VLOOKUP(H74,'Billing CDK pivot'!A:C,3,FALSE) -> #N/A | P74: =IFERROR(VLOOKUP(H74,'Billing CDK pivot (overages)'!A:F,6,FALSE),0) -> 0 | Q74: =+O74+P74 -> #N/A | R74: =+O74-G74 -> #N/A | S74: =+R74/O74 -> #N/A | T74: Negative Margin | U74: CARWARS PREMIUM SALES ($1,386.75) | X74: Secondary Package: Carrier Registration - Monthly ($10.00) | Y74: eLead - CW Premium - Sales 50k v2 ($1,571.65) | Z74: Secondary Package: Long Term Audio Storage ($20.00)
A75: TMC - Rockstar Powersports of Brooksville | B75: 155855 | C75: 27872 | D75: 9723.67 | E75: 0 | F75: 1601.65 | G75: =+F75-E75 -> 1601.65 | H75: 76250879 | I75: ROCKSTAR POWERSPORTS OF BROOKSVILLE | M75: =VLOOKUP(H75,'Billing CDK pivot (by package)'!A:D,3,FALSE) -> #N/A | N75: =VLOOKUP(H75,'Billing CDK pivot (by package)'!A:D,4,FALSE) -> #N/A | O75: =VLOOKUP(H75,'Billing CDK pivot'!A:C,3,FALSE) -> #N/A | P75: =IFERROR(VLOOKUP(H75,'Billing CDK pivot (overages)'!A:F,6,FALSE),0) -> 0 | Q75: =+O75+P75 -> #N/A | R75: =+O75-G75 -> #N/A | S75: =+R75/O75 -> #N/A | T75: Negative Margin | U75: CARWARS PREMIUM SALES ($1,386.75) | X75: Secondary Package: Carrier Registration - Monthly ($10.00) | Y75: eLead - CW Premium - Sales 50k v2 ($1,571.65) | Z75: Secondary Package: Long Term Audio Storage ($20.00)
A76: TMC - Rockstar Powersports of St Pete | B76: 155857 | C76: 27873 | D76: 8614.89 | E76: 0 | F76: 1601.65 | G76: =+F76-E76 -> 1601.65 | H76: 76250884 | I76: ROCKSTAR POWERSPORTS OF ST PETE | M76: =VLOOKUP(H76,'Billing CDK pivot (by package)'!A:D,3,FALSE) -> #N/A | N76: =VLOOKUP(H76,'Billing CDK pivot (by package)'!A:D,4,FALSE) -> #N/A | O76: =VLOOKUP(H76,'Billing CDK pivot'!A:C,3,FALSE) -> #N/A | P76: =IFERROR(VLOOKUP(H76,'Billing CDK pivot (overages)'!A:F,6,FALSE),0) -> 0 | Q76: =+O76+P76 -> #N/A | R76: =+O76-G76 -> #N/A | S76: =+R76/O76 -> #N/A | T76: Negative Margin | U76: CARWARS PREMIUM SALES ($1,386.75) | X76: Secondary Package: Carrier Registration - Monthly ($10.00) | Y76: eLead - CW Premium - Sales 50k v2 ($1,571.65) | Z76: Secondary Package: Long Term Audio Storage ($20.00)
A77: TMC - Alligator Alley Harley-Davidson | B77: 138485 | C77: 22454 | D77: 18267.36 | E77: 0 | F77: 1581.65 | G77: =+F77-E77 -> 1581.65 | H77: 76192405 | I77: ALLIGATOR ALLEY HARELY DAVIDSON | M77: =VLOOKUP(H77,'Billing CDK pivot (by package)'!A:D,3,FALSE) -> #N/A | N77: =VLOOKUP(H77,'Billing CDK pivot (by package)'!A:D,4,FALSE) -> #N/A | O77: =VLOOKUP(H77,'Billing CDK pivot'!A:C,3,FALSE) -> #N/A | P77: =IFERROR(VLOOKUP(H77,'Billing CDK pivot (overages)'!A:F,6,FALSE),0) -> 0 | Q77: =+O77+P77 -> #N/A | R77: =+O77-G77 -> #N/A | S77: =+R77/O77 -> #N/A | T77: Negative Margin | U77: CARWARS PREMIUM SALES ($1,386.75) | X77: Secondary Package: Carrier Registration - Monthly ($10.00) | Y77: eLead - CW Premium - Sales 50k v2 ($1,571.65)
A78: TMC - Atlanta Harley-Davidson | B78: 153774 | C78: 27795 | D78: 17073.86 | E78: 0 | F78: 1581.65 | G78: =+F78-E78 -> 1581.65 | H78: 76250876 | I78: ATLANTA HARLEY-DAVIDSON | M78: =VLOOKUP(H78,'Billing CDK pivot (by package)'!A:D,3,FALSE) -> #N/A | N78: =VLOOKUP(H78,'Billing CDK pivot (by package)'!A:D,4,FALSE) -> #N/A | O78: =VLOOKUP(H78,'Billing CDK pivot'!A:C,3,FALSE) -> #N/A | P78: =IFERROR(VLOOKUP(H78,'Billing CDK pivot (overages)'!A:F,6,FALSE),0) -> 0 | Q78: =+O78+P78 -> #N/A | R78: =+O78-G78 -> #N/A | S78: =+R78/O78 -> #N/A | T78: Negative Margin | U78: CARWARS PREMIUM SALES ($1,386.75) | X78: Secondary Package: Carrier Registration - Monthly ($10.00) | Y78: eLead - CW Premium - Sales 50k v2 ($1,571.65)
A79: TMC - Avalanche Harley-Davidson | B79: 76163 | C79: 6660 | D79: 14663.07 | E79: 0 | F79: 1581.65 | G79: =+F79-E79 -> 1581.65 | H79: 76237651 | I79: AVALANCHE HARLEY DAVIDSON | M79: =VLOOKUP(H79,'Billing CDK pivot (by package)'!A:D,3,FALSE) -> #N/A | N79: =VLOOKUP(H79,'Billing CDK pivot (by package)'!A:D,4,FALSE) -> #N/A | O79: =VLOOKUP(H79,'Billing CDK pivot'!A:C,3,FALSE) -> #N/A | P79: =IFERROR(VLOOKUP(H79,'Billing CDK pivot (overages)'!A:F,6,FALSE),0) -> 0 | Q79: =+O79+P79 -> #N/A | R79: =+O79-G79 -> #N/A | S79: =+R79/O79 -> #N/A | T79: Negative Margin | U79: CARWARS PREMIUM SALES ($1,386.75) | X79: Secondary Package: Carrier Registration - Monthly ($10.00) | Y79: eLead - CW Premium - Sales 50k v2 ($1,571.65)
A80: TMC - Desert Wind Harley-Davidson | B80: 118740 | C80: 19659 | D80: 19836.94 | E80: 0 | F80: 1581.65 | G80: =+F80-E80 -> 1581.65 | H80: 76208273 | I80: DESERT WIND HARLEY - DAVIDSON | M80: =VLOOKUP(H80,'Billing CDK pivot (by package)'!A:D,3,FALSE) -> #N/A | N80: =VLOOKUP(H80,'Billing CDK pivot (by package)'!A:D,4,FALSE) -> #N/A | O80: =VLOOKUP(H80,'Billing CDK pivot'!A:C,3,FALSE) -> #N/A | P80: =IFERROR(VLOOKUP(H80,'Billing CDK pivot (overages)'!A:F,6,FALSE),0) -> 0 | Q80: =+O80+P80 -> #N/A | R80: =+O80-G80 -> #N/A | S80: =+R80/O80 -> #N/A | T80: Negative Margin | U80: CARWARS PREMIUM SALES ($1,386.75) | X80: Secondary Package: Carrier Registration - Monthly ($10.00) | Y80: eLead - CW Premium - Sales 50k v2 ($1,571.65)
A81: TMC - High Octane Harley-Davidson | B81: 72226 | C81: 6605 | D81: 10838.75 | E81: 0 | F81: 1581.65 | G81: =+F81-E81 -> 1581.65 | H81: 76237653 | I81: HIGH OCTANE HARLEY DAVIDSON | M81: =VLOOKUP(H81,'Billing CDK pivot (by package)'!A:D,3,FALSE) -> #N/A | N81: =VLOOKUP(H81,'Billing CDK pivot (by package)'!A:D,4,FALSE) -> #N/A | O81: =VLOOKUP(H81,'Billing CDK pivot'!A:C,3,FALSE) -> #N/A | P81: =IFERROR(VLOOKUP(H81,'Billing CDK pivot (overages)'!A:F,6,FALSE),0) -> 0 | Q81: =+O81+P81 -> #N/A | R81: =+O81-G81 -> #N/A | S81: =+R81/O81 -> #N/A | T81: Negative Margin | U81: CARWARS PREMIUM SALES ($1,386.75) | X81: Secondary Package: Carrier Registration - Monthly ($10.00) | Y81: eLead - CW Premium - Sales 50k v2 ($1,571.65)
A82: TMC - Jet City Harley-Davidson | B82: 99533 | C82: 19252 | D82: 8504.56 | E82: 0 | F82: 1581.65 | G82: =+F82-E82 -> 1581.65 | H82: 76215888 | I82: JET CITY HARLEY-DAVIDSON | M82: =VLOOKUP(H82,'Billing CDK pivot (by package)'!A:D,3,FALSE) -> #N/A | N82: =VLOOKUP(H82,'Billing CDK pivot (by package)'!A:D,4,FALSE) -> #N/A | O82: =VLOOKUP(H82,'Billing CDK pivot'!A:C,3,FALSE) -> #N/A | P82: =IFERROR(VLOOKUP(H82,'Billing CDK pivot (overages)'!A:F,6,FALSE),0) -> 0 | Q82: =+O82+P82 -> #N/A | R82: =+O82-G82 -> #N/A | S82: =+R82/O82 -> #N/A | T82: Negative Margin | U82: CARWARS PREMIUM SALES ($1,386.75) | X82: Secondary Package: Carrier Registration - Monthly ($10.00) | Y82: eLead - CW Premium - Sales 50k v2 ($1,571.65)
A83: TMC - Motor City Harley-Davidson | B83: 146893 | C83: 17936 | D83: 17120.67 | E83: 0 | F83: 1581.65 | G83: =+F83-E83 -> 1581.65 | H83: 76225896 | I83: MOTORCITY HARLEY-DAVIDSON | M83: =VLOOKUP(H83,'Billing CDK pivot (by package)'!A:D,3,FALSE) -> #N/A | N83: =VLOOKUP(H83,'Billing CDK pivot (by package)'!A:D,4,FALSE) -> #N/A | O83: =VLOOKUP(H83,'Billing CDK pivot'!A:C,3,FALSE) -> #N/A | P83: =IFERROR(VLOOKUP(H83,'Billing CDK pivot (overages)'!A:F,6,FALSE),0) -> 0 | Q83: =+O83+P83 -> #N/A | R83: =+O83-G83 -> #N/A | S83: =+R83/O83 -> #N/A | T83: Negative Margin | U83: CARWARS PREMIUM SALES ($1,386.75) | X83: Secondary Package: Carrier Registration - Monthly ($10.00) | Y83: eLead - CW Premium - Sales 50k v2 ($1,571.65)
A84: TMC - Palm Beach Harley-Davidson | B84: 72659 | C84: 16266 | D84: 10870.28 | E84: 0 | F84: 1581.65 | G84: =+F84-E84 -> 1581.65 | H84: 76212401 | I84: HARLEY-DAVIDSON OF PALM BEACH | M84: =VLOOKUP(H84,'Billing CDK pivot (by package)'!A:D,3,FALSE) -> #N/A | N84: =VLOOKUP(H84,'Billing CDK pivot (by package)'!A:D,4,FALSE) -> #N/A | O84: =VLOOKUP(H84,'Billing CDK pivot'!A:C,3,FALSE) -> #N/A | P84: =IFERROR(VLOOKUP(H84,'Billing CDK pivot (overages)'!A:F,6,FALSE),0) -> 0 | Q84: =+O84+P84 -> #N/A | R84: =+O84-G84 -> #N/A | S84: =+R84/O84 -> #N/A | T84: Negative Margin | U84: CARWARS PREMIUM SALES ($1,386.75) | X84: Secondary Package: Carrier Registration - Monthly ($10.00) | Y84: eLead - CW Premium - Sales 50k v2 ($1,571.65)
A85: TMC - Patriot Harley Davidson | B85: 155386 | C85: 17456 | D85: 10322.96 | E85: 0 | F85: 1581.65 | G85: =+F85-E85 -> 1581.65 | H85: 76236368 | I85: PATRIOT HARLEY DAVIDSON | M85: =VLOOKUP(H85,'Billing CDK pivot (by package)'!A:D,3,FALSE) -> #N/A | N85: =VLOOKUP(H85,'Billing CDK pivot (by package)'!A:D,4,FALSE) -> #N/A | O85: =VLOOKUP(H85,'Billing CDK pivot'!A:C,3,FALSE) -> #N/A | P85: =IFERROR(VLOOKUP(H85,'Billing CDK pivot (overages)'!A:F,6,FALSE),0) -> 0 | Q85: =+O85+P85 -> #N/A | R85: =+O85-G85 -> #N/A | S85: =+R85/O85 -> #N/A | T85: Negative Margin | U85: CARWARS PREMIUM SALES ($1,386.75) | X85: Secondary Package: Carrier Registration - Monthly ($10.00) | Y85: eLead - CW Premium - Sales 50k v2 ($1,571.65)
A86: TMC - Rockstar Harley-Davidson | B86: 92413 | C86: 9591 | D86: 14694.23 | E86: 0 | F86: 1581.65 | G86: =+F86-E86 -> 1581.65 | H86: 76237654 | I86: ROCKSTAR HARLEY-DAVIDSON | M86: =VLOOKUP(H86,'Billing CDK pivot (by package)'!A:D,3,FALSE) -> #N/A | N86: =VLOOKUP(H86,'Billing CDK pivot (by package)'!A:D,4,FALSE) -> #N/A | O86: =VLOOKUP(H86,'Billing CDK pivot'!A:C,3,FALSE) -> #N/A | P86: =IFERROR(VLOOKUP(H86,'Billing CDK pivot (overages)'!A:F,6,FALSE),0) -> 0 | Q86: =+O86+P86 -> #N/A | R86: =+O86-G86 -> #N/A | S86: =+R86/O86 -> #N/A | T86: Negative Margin | U86: CARWARS PREMIUM SALES ($1,386.75) | X86: Secondary Package: Carrier Registration - Monthly ($10.00) | Y86: eLead - CW Premium - Sales 50k v2 ($1,571.65)
A87: TMC - Stars and Stripes Harley-Davidson | B87: 144005 | C87: 24621 | D87: 15677.9 | E87: 0 | F87: 1581.65 | G87: =+F87-E87 -> 1581.65 | H87: 76250874 | I87: STARS AND STRIPES HARLEY-DAVIDSON | M87: =VLOOKUP(H87,'Billing CDK pivot (by package)'!A:D,3,FALSE) -> #N/A | N87: =VLOOKUP(H87,'Billing CDK pivot (by package)'!A:D,4,FALSE) -> #N/A | O87: =VLOOKUP(H87,'Billing CDK pivot'!A:C,3,FALSE) -> #N/A | P87: =IFERROR(VLOOKUP(H87,'Billing CDK pivot (overages)'!A:F,6,FALSE),0) -> 0 | Q87: =+O87+P87 -> #N/A | R87: =+O87-G87 -> #N/A | S87: =+R87/O87 -> #N/A | T87: Negative Margin | U87: CARWARS PREMIUM SALES ($1,386.75) | X87: Secondary Package: Carrier Registration - Monthly ($10.00) | Y87: eLead - CW Premium - Sales 50k v2 ($1,571.65)
A88: TMC - Summit Harley Davidson | B88: 154997 | C88: 28220 | D88: 8108.46 | E88: 0 | F88: 1581.65 | G88: =+F88-E88 -> 1581.65 | H88: 76250872 | I88: SUMMIT HARLEY-DAVIDSON | M88: =VLOOKUP(H88,'Billing CDK pivot (by package)'!A:D,3,FALSE) -> #N/A | N88: =VLOOKUP(H88,'Billing CDK pivot (by package)'!A:D,4,FALSE) -> #N/A | O88: =VLOOKUP(H88,'Billing CDK pivot'!A:C,3,FALSE) -> #N/A | P88: =IFERROR(VLOOKUP(H88,'Billing CDK pivot (overages)'!A:F,6,FALSE),0) -> 0 | Q88: =+O88+P88 -> #N/A | R88: =+O88-G88 -> #N/A | S88: =+R88/O88 -> #N/A | T88: Negative Margin | U88: CARWARS PREMIUM SALES ($1,386.75) | X88: Secondary Package: Carrier Registration - Monthly ($10.00) | Y88: eLead - CW Premium - Sales 50k v2 ($1,571.65)
A89: TMC - Volcano Harley-Davidson | B89: 146894 | C89: 25647 | D89: 9778.37 | E89: 0 | F89: 1581.65 | G89: =+F89-E89 -> 1581.65 | H89: 76250875 | I89: VOLCANO HARLEY-DAVIDSON | M89: =VLOOKUP(H89,'Billing CDK pivot (by package)'!A:D,3,FALSE) -> #N/A | N89: =VLOOKUP(H89,'Billing CDK pivot (by package)'!A:D,4,FALSE) -> #N/A | O89: =VLOOKUP(H89,'Billing CDK pivot'!A:C,3,FALSE) -> #N/A | P89: =IFERROR(VLOOKUP(H89,'Billing CDK pivot (overages)'!A:F,6,FALSE),0) -> 0 | Q89: =+O89+P89 -> #N/A | R89: =+O89-G89 -> #N/A | S89: =+R89/O89 -> #N/A | T89: Negative Margin | U89: CARWARS PREMIUM SALES ($1,386.75) | X89: Secondary Package: Carrier Registration - Monthly ($10.00) | Y89: eLead - CW Premium - Sales 50k v2 ($1,571.65)
A90: HUD - Rock Hill Nissan | B90: 90212 | C90: (blank) | D90: 0 | E90: 0 | F90: 1571.65 | G90: =+F90-E90 -> 1571.65 | H90: 76212138 | I90: ROCK HILL NISSAN | M90: =VLOOKUP(H90,'Billing CDK pivot (by package)'!A:D,3,FALSE) -> #N/A | N90: =VLOOKUP(H90,'Billing CDK pivot (by package)'!A:D,4,FALSE) -> #N/A | O90: =VLOOKUP(H90,'Billing CDK pivot'!A:C,3,FALSE) -> #N/A | P90: =IFERROR(VLOOKUP(H90,'Billing CDK pivot (overages)'!A:F,6,FALSE),0) -> 0 | Q90: =+O90+P90 -> #N/A | R90: =+O90-G90 -> #N/A | S90: =+R90/O90 -> #N/A | T90: Negative Margin | U90: CARWARS PREMIUM SALES ($1,386.75) | X90: Secondary Package: Carrier Registration - Monthly ($10.00)
A91: Koeppel Hyundai | B91: 150176 | C91: 26261 | D91: 4850.02 | E91: 0 | F91: 1698 | G91: =+F91-E91 -> 1698 | H91: 76226286 | I91: KOEPPEL HYUNDAI | M91: =VLOOKUP(H91,'Billing CDK pivot (by package)'!A:D,3,FALSE) -> #N/A | N91: =VLOOKUP(H91,'Billing CDK pivot (by package)'!A:D,4,FALSE) -> #N/A | O91: =VLOOKUP(H91,'Billing CDK pivot'!A:C,3,FALSE) -> #N/A | P91: =IFERROR(VLOOKUP(H91,'Billing CDK pivot (overages)'!A:F,6,FALSE),0) -> 0 | Q91: =+O91+P91 -> #N/A | R91: =+O91-G91 -> #N/A | S91: =+R91/O91 -> #N/A | T91: Negative Margin | U91: CARWARS ELITE 12,500 PACKAGE ($1,499.00) | X91: Secondary Package: Carrier Registration - Monthly ($10.00) | Y91: Elead - CW Elite Small + Advanced Service ($1,688.00)
A92: Pine Belt Nissan of Keyport | B92: 140778 | C92: 23379 | D92: 8860.55 | E92: 0 | F92: 1581.65 | G92: =+F92-E92 -> 1581.65 | H92: 25298851 | I92: PINE BELT NISSAN OF KEYPORT | M92: =VLOOKUP(H92,'Billing CDK pivot (by package)'!A:D,3,FALSE) -> #N/A | N92: =VLOOKUP(H92,'Billing CDK pivot (by package)'!A:D,4,FALSE) -> #N/A | O92: =VLOOKUP(H92,'Billing CDK pivot'!A:C,3,FALSE) -> #N/A | P92: =IFERROR(VLOOKUP(H92,'Billing CDK pivot (overages)'!A:F,6,FALSE),0) -> 0 | Q92: =+O92+P92 -> #N/A | R92: =+O92-G92 -> #N/A | S92: =+R92/O92 -> #N/A | T92: Negative Margin | U92: CARWARS PREMIUM SALES ($1,408.33) | X92: Void / $0 ($0.00) | Y92: eLead - CW Premium - Sales 50k v2 ($1,571.65)
A93: Pine Belt Nissan of Toms River | B93: 140777 | C93: 23370 | D93: 5850.92 | E93: 0 | F93: 1581.65 | G93: =+F93-E93 -> 1581.65 | H93: 25298808 | I93: PINE BELT NISSAN OF TOMS RIVER | M93: =VLOOKUP(H93,'Billing CDK pivot (by package)'!A:D,3,FALSE) -> #N/A | N93: =VLOOKUP(H93,'Billing CDK pivot (by package)'!A:D,4,FALSE) -> #N/A | O93: =VLOOKUP(H93,'Billing CDK pivot'!A:C,3,FALSE) -> #N/A | P93: =IFERROR(VLOOKUP(H93,'Billing CDK pivot (overages)'!A:F,6,FALSE),0) -> 0 | Q93: =+O93+P93 -> #N/A | R93: =+O93-G93 -> #N/A | S93: =+R93/O93 -> #N/A | T93: Negative Margin | U93: CARWARS PREMIUM SALES ($1,408.33) | X93: Secondary Package: Carrier Registration - Monthly ($10.00) | Y93: eLead - CW Premium - Sales 50k v2 ($1,571.65)
A94: TMC - Old Glory Harley-Davidson | B94: 143252 | C94: 17362 | D94: 17349.19 | E94: 0 | F94: 1581.65 | G94: =+F94-E94 -> 1581.65 | H94: 76220875 | I94: OLD GLORY HARLEY-DAVIDSON | M94: =VLOOKUP(H94,'Billing CDK pivot (by package)'!A:D,3,FALSE) -> #N/A | N94: =VLOOKUP(H94,'Billing CDK pivot (by package)'!A:D,4,FALSE) -> #N/A | O94: =VLOOKUP(H94,'Billing CDK pivot'!A:C,3,FALSE) -> #N/A | P94: =IFERROR(VLOOKUP(H94,'Billing CDK pivot (overages)'!A:F,6,FALSE),0) -> 0 | Q94: =+O94+P94 -> #N/A | R94: =+O94-G94 -> #N/A | S94: =+R94/O94 -> #N/A | T94: Negative Margin | U94: CARWARS PREMIUM SALES ($1,469.12) | X94: Secondary Package: Carrier Registration - Monthly ($10.00) | Y94: eLead - CW Premium - Sales 50k v2 ($1,571.65)
A95: Haldeman Ford East Windsor | B95: 90532 | C95: 9100 | D95: 4733.6 | E95: 0 | F95: 1284.15 | G95: =+F95-E95 -> 1284.15 | H95: 71061710 | I95: HALDEMAN FORD EAST WINDSOR | M95: =VLOOKUP(H95,'Billing CDK pivot (by package)'!A:D,3,FALSE) -> #N/A | N95: =VLOOKUP(H95,'Billing CDK pivot (by package)'!A:D,4,FALSE) -> #N/A | O95: =VLOOKUP(H95,'Billing CDK pivot'!A:C,3,FALSE) -> #N/A | P95: =IFERROR(VLOOKUP(H95,'Billing CDK pivot (overages)'!A:F,6,FALSE),0) -> 0 | Q95: =+O95+P95 -> #N/A | R95: =+O95-G95 -> #N/A | S95: =+R95/O95 -> #N/A | T95: Negative Margin | U95: CARWARS ELITE SMALL ($1,199.00) | X95: Secondary Package: Carrier Registration - Monthly ($10.00) | Y95: eLead - Elite Small v2 ($1,274.15)
A96: Haldeman Lexus of Princeton | B96: 75178 | C96: 9104 | D96: 6648.22 | E96: 0 | F96: 1284.15 | G96: =+F96-E96 -> 1284.15 | H96: 71061708 | I96: HALDEMAN LEXUS OF PRINCETON | M96: =VLOOKUP(H96,'Billing CDK pivot (by package)'!A:D,3,FALSE) -> #N/A | N96: =VLOOKUP(H96,'Billing CDK pivot (by package)'!A:D,4,FALSE) -> #N/A | O96: =VLOOKUP(H96,'Billing CDK pivot'!A:C,3,FALSE) -> #N/A | P96: =IFERROR(VLOOKUP(H96,'Billing CDK pivot (overages)'!A:F,6,FALSE),0) -> 0 | Q96: =+O96+P96 -> #N/A | R96: =+O96-G96 -> #N/A | S96: =+R96/O96 -> #N/A | T96: Negative Margin | U96: CARWARS ELITE SMALL ($1,199.00) | X96: Secondary Package: Carrier Registration - Monthly ($10.00) | Y96: eLead - Elite Small v2 ($1,274.15)
A97: Haldeman Subaru | B97: 186357 | C97: 29183 | D97: 5175.25 | E97: 0 | F97: 1284.15 | G97: =+F97-E97 -> 1284.15 | H97: 76231359 | I97: HALDEMAN SUBARU | M97: =VLOOKUP(H97,'Billing CDK pivot (by package)'!A:D,3,FALSE) -> #N/A | N97: =VLOOKUP(H97,'Billing CDK pivot (by package)'!A:D,4,FALSE) -> #N/A | O97: =VLOOKUP(H97,'Billing CDK pivot'!A:C,3,FALSE) -> #N/A | P97: =IFERROR(VLOOKUP(H97,'Billing CDK pivot (overages)'!A:F,6,FALSE),0) -> 0 | Q97: =+O97+P97 -> #N/A | R97: =+O97-G97 -> #N/A | S97: =+R97/O97 -> #N/A | T97: Negative Margin | U97: CARWARS ELITE SMALL ($1,199.00) | X97: Secondary Package: Carrier Registration - Monthly ($10.00) | Y97: eLead - Elite Small v2 ($1,274.15)
A98: TMC - Huntington Beach Harley-Davidson | B98: 94337 | C98: 11739 | D98: 27424.03 | E98: 0 | F98: 1581.65 | G98: =+F98-E98 -> 1581.65 | H98: 76212334 | I98: HUNTINGTON BEACH HARLEY-DAVIDSON | M98: =VLOOKUP(H98,'Billing CDK pivot (by package)'!A:D,3,FALSE) -> #N/A | N98: =VLOOKUP(H98,'Billing CDK pivot (by package)'!A:D,4,FALSE) -> #N/A | O98: =VLOOKUP(H98,'Billing CDK pivot'!A:C,3,FALSE) -> #N/A | P98: =IFERROR(VLOOKUP(H98,'Billing CDK pivot (overages)'!A:F,6,FALSE),0) -> 0 | Q98: =+O98+P98 -> #N/A | R98: =+O98-G98 -> #N/A | S98: =+R98/O98 -> #N/A | T98: Negative Margin | U98: CARWARS PREMIUM SALES ($1,386.75) | V98: CRM TELEPHONY TRACKING ($100.00) | X98: Secondary Package: Carrier Registration - Monthly ($10.00) | Y98: eLead - CW Premium - Sales 50k v2 ($1,571.65)
A99: TMC - Rawhide Harley-Davidson | B99: 98156 | C99: 5641 | D99: 18371.22 | E99: 0 | F99: 1581.65 | G99: =+F99-E99 -> 1581.65 | H99: 76072668 | I99: RAWHIDE HARLEY-DAVIDSON | M99: =VLOOKUP(H99,'Billing CDK pivot (by package)'!A:D,3,FALSE) -> #N/A | N99: =VLOOKUP(H99,'Billing CDK pivot (by package)'!A:D,4,FALSE) -> #N/A | O99: =VLOOKUP(H99,'Billing CDK pivot'!A:C,3,FALSE) -> #N/A | P99: =IFERROR(VLOOKUP(H99,'Billing CDK pivot (overages)'!A:F,6,FALSE),0) -> 0 | Q99: =+O99+P99 -> #N/A | R99: =+O99-G99 -> #N/A | S99: =+R99/O99 -> #N/A | T99: Negative Margin | U99: CARWARS PREMIUM SALES ($1,386.75) | V99: CRM TELEPHONY TRACKING ($100.00) | X99: Secondary Package: Carrier Registration - Monthly ($10.00) | Y99: eLead - CW Premium - Sales 50k v2 ($1,571.65)
A100: TMC - Riverside Harley-Davidson | B100: 84176 | C100: 9141 | D100: 26264.33 | E100: 0 | F100: 1581.65 | G100: =+F100-E100 -> 1581.65 | H100: 76161776 | I100: RIVERSIDE HARLEY-DAVIDSON | M100: =VLOOKUP(H100,'Billing CDK pivot (by package)'!A:D,3,FALSE) -> #N/A | N100: =VLOOKUP(H100,'Billing CDK pivot (by package)'!A:D,4,FALSE) -> #N/A | O100: =VLOOKUP(H100,'Billing CDK pivot'!A:C,3,FALSE) -> #N/A | P100: =IFERROR(VLOOKUP(H100,'Billing CDK pivot (overages)'!A:F,6,FALSE),0) -> 0 | Q100: =+O100+P100 -> #N/A | R100: =+O100-G100 -> #N/A | S100: =+R100/O100 -> #N/A | T100: Negative Margin | U100: CARWARS PREMIUM SALES ($1,386.75) | V100: CRM TELEPHONY TRACKING ($100.00) | X100: Secondary Package: Carrier Registration - Monthly ($10.00) | Y100: eLead - CW Premium - Sales 50k v2 ($1,571.65)
A101: Phil Hughes Honda | B101: 92188 | C101: 18515 | D101: 11449.4 | E101: 272.51 | F101: 938.31 | G101: =+F101-E101 -> 665.8 | H101: 76025871 | I101: PHIL HUGHES HONDA | M101: =VLOOKUP(H101,'Billing CDK pivot (by package)'!A:D,3,FALSE) -> #N/A | N101: =VLOOKUP(H101,'Billing CDK pivot (by package)'!A:D,4,FALSE) -> #N/A | O101: =VLOOKUP(H101,'Billing CDK pivot'!A:C,3,FALSE) -> #N/A | P101: =IFERROR(VLOOKUP(H101,'Billing CDK pivot (overages)'!A:F,6,FALSE),0) -> 0 | Q101: =+O101+P101 -> #N/A | R101: =+O101-G101 -> #N/A | S101: =+R101/O101 -> #N/A | T101: Negative Margin | U101: CARWARS STARTER 7500 ($350.30) | V101: CARWARS INDEFINITE CALL RECORDINGS ($14.04) | W101: CARWARS VOICE RECOGNITION (STARTER/ADV) ($268.92) | X101: Secondary Package: Carrier Registration - Monthly ($10.00) | Y101: eLead - CW Starter - 7500 mins v2 ($424.15) | Z101: Secondary Package: eLead - Car Wars Texting v2 ($211.65)
A102: Koeppel Mazda | B102: 145665 | C102: 25374 | D102: 12246.32 | E102: 0 | F102: 1698 | G102: =+F102-E102 -> 1698 | H102: 76075892 | I102: KOEPPEL MAZDA | M102: =VLOOKUP(H102,'Billing CDK pivot (by package)'!A:D,3,FALSE) -> #N/A | N102: =VLOOKUP(H102,'Billing CDK pivot (by package)'!A:D,4,FALSE) -> #N/A | O102: =VLOOKUP(H102,'Billing CDK pivot'!A:C,3,FALSE) -> #N/A | P102: =IFERROR(VLOOKUP(H102,'Billing CDK pivot (overages)'!A:F,6,FALSE),0) -> 0 | Q102: =+O102+P102 -> #N/A | R102: =+O102-G102 -> #N/A | S102: =+R102/O102 -> #N/A | T102: Negative Margin | U102: CARWARS ELITE 12,500 PACKAGE ($1,618.92) | X102: Secondary Package: Carrier Registration - Monthly ($10.00) | Y102: Elead - CW Elite Small + Advanced Service ($1,688.00)
...

Sheet VictoryHeitrich
A1: Vendor Invoice Detail | D1: CDK Invoice Detail | I1: NOV Billing CDK | J1: ? | K1: ? | L1: Manual
A2: Account | B2: Customer_ID | C2: External Billing ID | D2: CMF | E2: Name | F2: Install Date | G2: LSS Date | H2: Catalog Number | I2: Nov Recurring | J2: Nov Overages | K2: Nov Bill | L2: Comments/updated eleadID
A3: VA - Ocean Honda Milford | B3: 188878 | C3: 32166 | D3: 76257348 | E3: OCEAN HONDA MILFORD | F3: 45978 | H3: CAR WARS CUSTOM PACKAGE--VICTORY AUTO | I3: =VLOOKUP(D3,'Billing CDK pivot'!A:C,3,FALSE) -> #N/A | K3: 731.91273 | L3: Dec Billing
A4: VA - Ocean Honda of Ventura | B4: 143170 | C4: 9448 | D4: 76217400 | E4: OCEAN HONDA OF VENTURA | F4: 44230 | G4: 45810 | H4: CAR WARS CUSTOM PACKAGE--VICTORY AUTO | I4: =VLOOKUP(D4,'Billing CDK pivot'!A:C,3,FALSE) -> #N/A | K4: 731.91273 | L4: LSS
A5: VA - Victory Chrysler Dodge Jeep Ram | B5: 187886 | C5: 30697 | D5: 76188954 | E5: VICTORY CHRYSLER DODGE JEEP RAM | F5: 44230 | G5: 45169 | H5: CAR WARS CUSTOM PACKAGE--VICTORY AUTO | I5: =VLOOKUP(D5,'Billing CDK pivot'!A:C,3,FALSE) -> #N/A | K5: 731.91273 | L5: LSS
A6: Crossroads Hyundai of Loveland at Centerra | B6: 59103 | C6: 16318 | D6: 76243306 | E6: CROSSROADS HYUNDAI | H6: =VLOOKUP(D6,'Billing CDK pivot (by package)'!A:D,4,FALSE) -> #N/A | I6: =VLOOKUP(D6,'Billing CDK pivot'!A:C,3,FALSE) -> #N/A | K6: 185 | L6: No Call Tracking Catalog
A7: VA - Albany Subaru | B7: 136870 | D7: 76228429 | E7: ALBANY SUBARU | H7: =VLOOKUP(D7,'Billing CDK pivot (by package)'!A:D,4,FALSE) -> CAR WARS CUSTOM PACKAGE--VICTORY AUTO | I7: =VLOOKUP(D7,'Billing CDK pivot'!A:C,3,FALSE) -> #N/A | K7: 731.91273 | L7: OK
A8: VA - Auburn Honda | B8: 143054 | C8: 7314 | D8: 76202512 | E8: AUBURN HONDA | H8: =VLOOKUP(D8,'Billing CDK pivot (by package)'!A:D,4,FALSE) -> CAR WARS CUSTOM PACKAGE--VICTORY AUTO | I8: =VLOOKUP(D8,'Billing CDK pivot'!A:C,3,FALSE) -> #N/A | K8: 731.91273 | L8: OK
A9: VA - BMW of Humboldt Bay | B9: 177594 | C9: 29917 | D9: 76245927 | E9: BMW OF HUMBOLDT BAY | H9: =VLOOKUP(D9,'Billing CDK pivot (by package)'!A:D,4,FALSE) -> CAR WARS CUSTOM PACKAGE--VICTORY AUTO | I9: =VLOOKUP(D9,'Billing CDK pivot'!A:C,3,FALSE) -> #N/A | K9: 731.91273 | L9: OK
A10: VA - Chevrolet Milan | B10: 143053 | C10: 24233 | D10: 76202505 | E10: VICTORY CHEVROLET BUICK | H10: =VLOOKUP(D10,'Billing CDK pivot (by package)'!A:D,4,FALSE) -> CAR WARS CUSTOM PACKAGE--VICTORY AUTO | I10: =VLOOKUP(D10,'Billing CDK pivot'!A:C,3,FALSE) -> #N/A | K10: 731.91273 | L10: OK
A11: VA - Cookevillle Honda | B11: 143165 | C11: 2590 | D11: 76202499 | E11: COOKEVILLE HONDA | H11: =VLOOKUP(D11,'Billing CDK pivot (by package)'!A:D,4,FALSE) -> CAR WARS CUSTOM PACKAGE--VICTORY AUTO | I11: =VLOOKUP(D11,'Billing CDK pivot'!A:C,3,FALSE) -> #N/A | K11: 731.91273 | L11: OK
A12: VA - Dave Kirk Chevrolet GMC | B12: 154889 | C12: 22473 | D12: 76235670 | E12: DAVE KIRK AUTOMOTIVE | H12: =VLOOKUP(D12,'Billing CDK pivot (by package)'!A:D,4,FALSE) -> CAR WARS CUSTOM PACKAGE--VICTORY AUTO | I12: =VLOOKUP(D12,'Billing CDK pivot'!A:C,3,FALSE) -> #N/A | K12: 731.91273 | L12: OK
A13: VA - East Tennessee Dodge | B13: 143046 | C13: 2217 | D13: 76202568 | E13: EAST TENNESSEE DODGE CHRYSLER JEEP | H13: =VLOOKUP(D13,'Billing CDK pivot (by package)'!A:D,4,FALSE) -> CAR WARS CUSTOM PACKAGE--VICTORY AUTO | I13: =VLOOKUP(D13,'Billing CDK pivot'!A:C,3,FALSE) -> #N/A | K13: 731.91273 | L13: OK
A14: VA - East Tennessee Ford | B14: 143071 | C14: 9917 | D14: 76202498 | E14: EAST TENNESSEE FORD | H14: =VLOOKUP(D14,'Billing CDK pivot (by package)'!A:D,4,FALSE) -> CAR WARS CUSTOM PACKAGE--VICTORY AUTO | I14: =VLOOKUP(D14,'Billing CDK pivot'!A:C,3,FALSE) -> #N/A | K14: 731.91273 | L14: OK
A15: VA - Freeway Toyota | B15: 143062 | C15: 11370 | D15: 76179964 | E15: FREEWAY TOYOTA OF HANFORD | H15: =VLOOKUP(D15,'Billing CDK pivot (by package)'!A:D,4,FALSE) -> CAR WARS CUSTOM PACKAGE--VICTORY AUTO | I15: =VLOOKUP(D15,'Billing CDK pivot'!A:C,3,FALSE) -> #N/A | K15: 731.91273 | L15: OK
A16: VA - Freeway Toyota of Gilroy | B16: 153483 | D16: 76228607 | E16: FREEWAY TOYOTA OF GILROY | H16: =VLOOKUP(D16,'Billing CDK pivot (by package)'!A:D,4,FALSE) -> CAR WARS CUSTOM PACKAGE--VICTORY AUTO | I16: =VLOOKUP(D16,'Billing CDK pivot'!A:C,3,FALSE) -> #N/A | K16: 731.91273 | L16: OK
A17: VA - Honda of Jackson | B17: 143173 | C17: 3334 | D17: 76202492 | E17: VICTORY HONDA OF JACKSON | H17: =VLOOKUP(D17,'Billing CDK pivot (by package)'!A:D,4,FALSE) -> CAR WARS CUSTOM PACKAGE--VICTORY AUTO | I17: =VLOOKUP(D17,'Billing CDK pivot'!A:C,3,FALSE) -> #N/A | K17: 731.91273 | L17: OK
A18: VA - Honda of Monroe | B18: 143060 | C18: 2631 | D18: 76202491 | E18: VICTORY HONDA OF MONROE | H18: =VLOOKUP(D18,'Billing CDK pivot (by package)'!A:D,4,FALSE) -> CAR WARS CUSTOM PACKAGE--VICTORY AUTO | I18: =VLOOKUP(D18,'Billing CDK pivot'!A:C,3,FALSE) -> #N/A | K18: 731.91273 | L18: OK
A19: VA - Honda of Morgan Hill | B19: 143174 | C19: 19709 | D19: 76214531 | E19: VICTORY HONDA OF MORGAN HILL | H19: =VLOOKUP(D19,'Billing CDK pivot (by package)'!A:D,4,FALSE) -> CAR WARS CUSTOM PACKAGE--VICTORY AUTO | I19: =VLOOKUP(D19,'Billing CDK pivot'!A:C,3,FALSE) -> #N/A | K19: 731.91273 | L19: OK
A20: VA - Honda of Muncie | B20: 143175 | C20: 2229 | D20: 76202355 | E20: VICTORY HONDA OF MUNCIE | H20: =VLOOKUP(D20,'Billing CDK pivot (by package)'!A:D,4,FALSE) -> CAR WARS CUSTOM PACKAGE--VICTORY AUTO | I20: =VLOOKUP(D20,'Billing CDK pivot'!A:C,3,FALSE) -> #N/A | K20: 731.91273 | L20: OK
A21: VA - Honda of Plymouth | B21: 143178 | C21: 2226 | D21: 76202360 | E21: VICTORY HONDA OF PLYMOUTH | H21: =VLOOKUP(D21,'Billing CDK pivot (by package)'!A:D,4,FALSE) -> CAR WARS CUSTOM PACKAGE--VICTORY AUTO | I21: =VLOOKUP(D21,'Billing CDK pivot'!A:C,3,FALSE) -> #N/A | K21: 731.91273 | L21: OK
A22: VA - Kastner Honda | B22: 153318 | D22: 76232648 | E22: KASTNER HONDA | H22: =VLOOKUP(D22,'Billing CDK pivot (by package)'!A:D,4,FALSE) -> CAR WARS CUSTOM PACKAGE--VICTORY AUTO | I22: =VLOOKUP(D22,'Billing CDK pivot'!A:C,3,FALSE) -> #N/A | K22: 731.91273 | L22: OK
A23: VA - Lexus Monterey Peninsula | B23: 143063 | C23: 17614 | D23: 76211755 | E23: LEXUS MONTEREY PENINSULA | H23: =VLOOKUP(D23,'Billing CDK pivot (by package)'!A:D,4,FALSE) -> CAR WARS CUSTOM PACKAGE--VICTORY AUTO | I23: =VLOOKUP(D23,'Billing CDK pivot'!A:C,3,FALSE) -> #N/A | K23: 731.91273 | L23: OK
A24: VA - Marin County Ford | B24: 143073 | C24: 9982 | D24: 76169916 | E24: MARIN COUNTY FORD | H24: =VLOOKUP(D24,'Billing CDK pivot (by package)'!A:D,4,FALSE) -> CAR WARS CUSTOM PACKAGE--VICTORY AUTO | I24: =VLOOKUP(D24,'Billing CDK pivot'!A:C,3,FALSE) -> #N/A | K24: 731.91273 | L24: OK
A25: VA - Melody Toyota | B25: 143064 | C25: 1032 | D25: 76202911 | E25: VICTORY TOYOTA OF SAN BRUNO | H25: =VLOOKUP(D25,'Billing CDK pivot (by package)'!A:D,4,FALSE) -> CAR WARS CUSTOM PACKAGE--VICTORY AUTO | I25: =VLOOKUP(D25,'Billing CDK pivot'!A:C,3,FALSE) -> #N/A | K25: 731.91273 | L25: OK
A26: VA - Nissan West Dickson | B26: 143181 | C26: 2739 | D26: 76202353 | E26: VICTORY NISSAN WEST | H26: =VLOOKUP(D26,'Billing CDK pivot (by package)'!A:D,4,FALSE) -> CAR WARS CUSTOM PACKAGE--VICTORY AUTO | I26: =VLOOKUP(D26,'Billing CDK pivot'!A:C,3,FALSE) -> #N/A | K26: 731.91273 | L26: OK
A27: VA - Ocean Honda | B27: 143167 | C27: 5331 | D27: 76202509 | E27: OCEAN HONDA | H27: =VLOOKUP(D27,'Billing CDK pivot (by package)'!A:D,4,FALSE) -> CAR WARS CUSTOM PACKAGE--VICTORY AUTO | I27: =VLOOKUP(D27,'Billing CDK pivot'!A:C,3,FALSE) -> #N/A | K27: 731.91273 | L27: OK
A28: VA - Ocean Honda Groton | B28: 188256 | C28: 31836 | D28: 76255144 | E28: OCEAN HONDA GROTON | H28: =VLOOKUP(D28,'Billing CDK pivot (by package)'!A:D,4,FALSE) -> CAR WARS CUSTOM PACKAGE--VICTORY AUTO | I28: =VLOOKUP(D28,'Billing CDK pivot'!A:C,3,FALSE) -> #N/A | K28: 731.91273 | L28: OK
A29: VA - Ocean Honda of Brockton | B29: 143055 | C29: 16820 | D29: 76216792 | E29: OCEAN HONDA OF BROCKTON | H29: CAR WARS CUSTOM PACKAGE--VICTORY AUTO | I29: =VLOOKUP(D29,'Billing CDK pivot'!A:C,3,FALSE) -> #N/A | K29: 731.91273 | L29: OK
A30: VA - Ocean Honda of Burlingame | B30: 143168 | C30: 17105 | D30: 76212419 | E30: OCEAN HONDA OF BURLINGAME | H30: CAR WARS CUSTOM PACKAGE--VICTORY AUTO | I30: =VLOOKUP(D30,'Billing CDK pivot'!A:C,3,FALSE) -> #N/A | K30: 731.91273 | L30: OK
A31: VA - Ocean Honda of Weymouth | B31: 143057 | C31: 13780 | D31: 76211538 | E31: OCEAN HONDA OF HANOVER | H31: CAR WARS CUSTOM PACKAGE--VICTORY AUTO | I31: =VLOOKUP(D31,'Billing CDK pivot'!A:C,3,FALSE) -> #N/A | K31: 731.91273 | L31: OK
A32: VA - Ocean Honda of Whittier | B32: 143171 | C32: 16461 | D32: 76202508 | E32: OCEAN HONDA OF WHITTIER | H32: CAR WARS CUSTOM PACKAGE--VICTORY AUTO | I32: =VLOOKUP(D32,'Billing CDK pivot'!A:C,3,FALSE) -> #N/A | K32: 731.91273 | L32: OK
A33: VA - Ocean Subaru of Fullerton | B33: 143182 | C33: 24244 | D33: 76217403 | E33: OCEAN SUBARU | H33: CAR WARS CUSTOM PACKAGE--VICTORY AUTO | I33: =VLOOKUP(D33,'Billing CDK pivot'!A:C,3,FALSE) -> #N/A | K33: 731.91273 | L33: OK
A34: VA - San Francisco Honda | B34: 143059 | C34: 15809 | D34: 76204566 | E34: SAN FRANCISCO HONDA ACURA | H34: CAR WARS CUSTOM PACKAGE--VICTORY AUTO | I34: =VLOOKUP(D34,'Billing CDK pivot'!A:C,3,FALSE) -> #N/A | K34: 731.91273 | L34: OK
A35: VA - Tower Honda | B35: 143172 | C35: 15136 | D35: 76202671 | E35: TOWER HONDA OF LONGVIEW | H35: CAR WARS CUSTOM PACKAGE--VICTORY AUTO | I35: =VLOOKUP(D35,'Billing CDK pivot'!A:C,3,FALSE) -> #N/A | K35: 731.91273 | L35: OK
A36: VA - Toyota of Canton | B36: 143185 | C36: 2221 | D36: 76125298 | E36: VICTORY TOYOTA OF CANTON | H36: CAR WARS CUSTOM PACKAGE--VICTORY AUTO | I36: =VLOOKUP(D36,'Billing CDK pivot'!A:C,3,FALSE) -> #N/A | K36: 731.91273 | L36: OK
A37: VA - Toyota of Midtown | B37: 143611 | C37: 24390 | D37: 76221153 | E37: VICTORY TOYOTA OF MIDTOWN | H37: CAR WARS CUSTOM PACKAGE--VICTORY AUTO | I37: =VLOOKUP(D37,'Billing CDK pivot'!A:C,3,FALSE) -> #N/A | K37: 731.91273 | L37: OK
A38: VA - Toyota of Seaside | B38: 143186 | C38: 17613 | D38: 76164812 | E38: VICTORY TOYOTA | H38: CAR WARS CUSTOM PACKAGE--VICTORY AUTO | I38: =VLOOKUP(D38,'Billing CDK pivot'!A:C,3,FALSE) -> #N/A | K38: 731.91273 | L38: OK
A39: VA - Tri Cities Chrysler Dodge Jeep Ram | B39: 143049 | C39: 8335 | D39: 76202493 | E39: TRI-CITIES CHRYSLER DODGE JEEP RAM | H39: CAR WARS CUSTOM PACKAGE--VICTORY AUTO | I39: =VLOOKUP(D39,'Billing CDK pivot'!A:C,3,FALSE) -> #N/A | K39: 731.91273 | L39: OK
A40: VA - Victory Chevrolet GMC Highlands | B40: 159095 | C40: 29415 | D40: 76242001 | E40: VICTORY CHEVROLET GMC HIGHLANDS | H40: CAR WARS CUSTOM PACKAGE--VICTORY AUTO | I40: =VLOOKUP(D40,'Billing CDK pivot'!A:C,3,FALSE) -> #N/A | K40: 731.91273 | L40: OK
A41: VA - Victory Honda Austinburg | B41: 150749 | D41: 76232504 | E41: VICTORY HONDA | H41: =VLOOKUP(D41,'Billing CDK pivot (by package)'!A:D,4,FALSE) -> CAR WARS CUSTOM PACKAGE--VICTORY AUTO | I41: =VLOOKUP(D41,'Billing CDK pivot'!A:C,3,FALSE) -> #N/A | K41: 731.91273 | L41: OK
A42: VA - Victory Honda Chicago-Northside | B42: 188574 | C42: 32012 | D42: 76256438 | E42: VICTORY HONDA CHICAGO-NORTHSIDE | H42: =VLOOKUP(D42,'Billing CDK pivot (by package)'!A:D,4,FALSE) -> CAR WARS CUSTOM PACKAGE--VICTORY AUTO | I42: =VLOOKUP(D42,'Billing CDK pivot'!A:C,3,FALSE) -> #N/A | K42: 731.91273 | L42: OK
A43: VA - Victory Honda Highland | B43: 187887 | C43: 30696 | D43: 76254200 | E43: VICTORY HONDA HIGHLAND | H43: =VLOOKUP(D43,'Billing CDK pivot (by package)'!A:D,4,FALSE) -> CAR WARS CUSTOM PACKAGE--VICTORY AUTO | I43: =VLOOKUP(D43,'Billing CDK pivot'!A:C,3,FALSE) -> #N/A | K43: 731.91273 | L43: OK
A44: VA - Victory Honda Michigan City | B44: 187884 | C44: 30698 | D44: 76254199 | E44: VICTORY HONDA MICHIGAN CITY | H44: =VLOOKUP(D44,'Billing CDK pivot (by package)'!A:D,4,FALSE) -> CAR WARS CUSTOM PACKAGE--VICTORY AUTO | I44: =VLOOKUP(D44,'Billing CDK pivot'!A:C,3,FALSE) -> #N/A | K44: 731.91273 | L44: OK
A45: VA - Victory Honda of San Bruno | B45: 143177 | C45: 7807 | D45: 76202358 | E45: VICTORY HONDA OF SAN BRUNO | H45: =VLOOKUP(D45,'Billing CDK pivot (by package)'!A:D,4,FALSE) -> CAR WARS CUSTOM PACKAGE--VICTORY AUTO | I45: =VLOOKUP(D45,'Billing CDK pivot'!A:C,3,FALSE) -> #N/A | K45: 731.91273 | L45: OK
A46: VA - Victory Hyundai Jefferson | B46: 177565 | C46: 29857 | D46: 76245508 | E46: VICTORY HYUNDAI | H46: =VLOOKUP(D46,'Billing CDK pivot (by package)'!A:D,4,FALSE) -> CAR WARS CUSTOM PACKAGE--VICTORY AUTO | I46: =VLOOKUP(D46,'Billing CDK pivot'!A:C,3,FALSE) -> #N/A | K46: 731.91273 | L46: OK
A47: VA - Victory Mazda San Leandro | B47: 186347 | C47: 30226 | D47: 76251847 | E47: VICTORY MAZDA SAN LEANDRO | H47: =VLOOKUP(D47,'Billing CDK pivot (by package)'!A:D,4,FALSE) -> CAR WARS CUSTOM PACKAGE--VICTORY AUTO | I47: =VLOOKUP(D47,'Billing CDK pivot'!A:C,3,FALSE) -> #N/A | K47: 731.91273 | L47: OK
A48: VA - Victory Nissan Chesterton | B48: 187885 | C48: 30699 | D48: 76254201 | E48: VICTORY NISSAN CHESTERTON | H48: =VLOOKUP(D48,'Billing CDK pivot (by package)'!A:D,4,FALSE) -> CAR WARS CUSTOM PACKAGE--VICTORY AUTO | I48: =VLOOKUP(D48,'Billing CDK pivot'!A:C,3,FALSE) -> #N/A | K48: 731.91273 | L48: OK
A49: VA - Victory Nissan of Mechanicsville | B49: 177593 | C49: 8833 | D49: 76245758 | E49: VICTORY NISSAN OF MECHANICSVILLE | H49: =VLOOKUP(D49,'Billing CDK pivot (by package)'!A:D,4,FALSE) -> CAR WARS CUSTOM PACKAGE--VICTORY AUTO | I49: =VLOOKUP(D49,'Billing CDK pivot'!A:C,3,FALSE) -> #N/A | K49: 731.91273 | L49: OK
A50: VA - Victory Nissan of Nashville | B50: 177592 | C50: 29898 | D50: 76245787 | E50: VICTORY NISSAN OF NASHVILLE | H50: =VLOOKUP(D50,'Billing CDK pivot (by package)'!A:D,4,FALSE) -> CAR WARS CUSTOM PACKAGE--VICTORY AUTO | I50: =VLOOKUP(D50,'Billing CDK pivot'!A:C,3,FALSE) -> #N/A | K50: 731.91273 | L50: OK
A51: VA - Victory Toyota Barboursville | B51: 186505 | C51: 30363 | D51: 76252209 | E51: VICTORY TOYOTA BARBOURSVILLE | H51: =VLOOKUP(D51,'Billing CDK pivot (by package)'!A:D,4,FALSE) -> CAR WARS CUSTOM PACKAGE--VICTORY AUTO | I51: =VLOOKUP(D51,'Billing CDK pivot'!A:C,3,FALSE) -> #N/A | K51: 731.91273 | L51: OK
A52: VA - Victory Toyota CDJR | B52: 156789 | C52: 28983 | D52: 76238017 | E52: VICTORY TOYOTA CDJR MARIETTA | H52: =VLOOKUP(D52,'Billing CDK pivot (by package)'!A:D,4,FALSE) -> CAR WARS CUSTOM PACKAGE--VICTORY AUTO | I52: =VLOOKUP(D52,'Billing CDK pivot'!A:C,3,FALSE) -> #N/A | K52: 731.91273 | L52: OK
A53: VA - Victory Toyota Charleston | B53: 186504 | C53: 30362 | D53: 76252216 | E53: VICTORY TOYOTA CHARLESTON | H53: =VLOOKUP(D53,'Billing CDK pivot (by package)'!A:D,4,FALSE) -> CAR WARS CUSTOM PACKAGE--VICTORY AUTO | I53: =VLOOKUP(D53,'Billing CDK pivot'!A:C,3,FALSE) -> #N/A | K53: 731.91273 | L53: OK
... A55: VA - Victory Toyota Highlands | B55: 159094 | C55: 29414 | D55: 76242002 | E55: VICTORY TOYOTA HIGHLANDS | H55: =VLOOKUP(D55,'Billing CDK pivot (by package)'!A:D,4,FALSE) -> CAR WARS CUSTOM PACKAGE--VICTORY AUTO | I55: =VLOOKUP(D55,'Billing CDK pivot'!A:C,3,FALSE) -> #N/A | K55: 731.91273 | L55: OK
A56: VA - Victory Toyota of Ashtabula County | B56: 150750 | D56: 76232503 | E56: VICTORY TOYOTA OF ASHTABULA COUNTY | H56: =VLOOKUP(D56,'Billing CDK pivot (by package)'!A:D,4,FALSE) -> CAR WARS CUSTOM PACKAGE--VICTORY AUTO | I56: =VLOOKUP(D56,'Billing CDK pivot'!A:C,3,FALSE) -> #N/A | K56: 731.91273 | L56: OK
A57: VA - Victory Toyota of Brook Park | B57: 177327 | C57: 29759 | D57: 76244926 | E57: VICTORY TOYOTA OF BROOK PARK | H57: =VLOOKUP(D57,'Billing CDK pivot (by package)'!A:D,4,FALSE) -> CAR WARS CUSTOM PACKAGE--VICTORY AUTO | I57: =VLOOKUP(D57,'Billing CDK pivot'!A:C,3,FALSE) -> #N/A | K57: 731.91273 | L57: OK
A58: VA - Victory Toyota of St. Louis | B58: 186083 | C58: 30123 | D58: 76250786 | E58: VICTORY TOYOTA OF ST LOUIS | H58: =VLOOKUP(D58,'Billing CDK pivot (by package)'!A:D,4,FALSE) -> CAR WARS CUSTOM PACKAGE--VICTORY AUTO | I58: =VLOOKUP(D58,'Billing CDK pivot'!A:C,3,FALSE) -> #N/A | K58: 731.91273 | L58: OK
A59: Hertrich Acura of New Castle | B59: 59112 | C59: 16310 | D59: 76211581 | E59: HERTRICH ACURA OF NEW CASTLE | H59: =VLOOKUP(D59,'Billing CDK pivot (by package)'!A:D,4,FALSE) -> CRM OUTBOUND TELEPHONY TRACKING (NEW AND CONVERSION) | I59: =VLOOKUP(D59,'Billing CDK pivot'!A:C,3,FALSE) -> #N/A | K59: 185 | L59: OK
A60: Hertrich All American Chevrolet | B60: 59102 | C60: 16317 | D60: 76217649 | E60: HERTRICH CHEVROLET | H60: =VLOOKUP(D60,'Billing CDK pivot (by package)'!A:D,4,FALSE) -> CRM OUTBOUND TELEPHONY TRACKING (NEW AND CONVERSION) | I60: =VLOOKUP(D60,'Billing CDK pivot'!A:C,3,FALSE) -> #N/A | K60: 185 | L60: OK
A61: Hertrich Buick GMC of Salisbury | B61: 72916 | C61: 9218A | D61: 76211548 | E61: HERTRICH BUICK GMC OF SALISBURY | H61: =VLOOKUP(D61,'Billing CDK pivot (by package)'!A:D,4,FALSE) -> CRM OUTBOUND TELEPHONY TRACKING (NEW AND CONVERSION) | I61: =VLOOKUP(D61,'Billing CDK pivot'!A:C,3,FALSE) -> #N/A | K61: 185 | L61: OK
A62: Hertrich Buick GMC of Seaford | B62: 59095 | C62: 16307 | D62: 76211510 | E62: HERTRICH CHEVROLET GMC OF EASTON | H62: =VLOOKUP(D62,'Billing CDK pivot (by package)'!A:D,4,FALSE) -> CRM OUTBOUND TELEPHONY TRACKING (NEW AND CONVERSION) | I62: =VLOOKUP(D62,'Billing CDK pivot'!A:C,3,FALSE) -> #N/A | K62: 185 | L62: OK
A63: Hertrich CDJR and Ford of Pocomoke | B63: 59101 | C63: 16316 | D63: 76214817 | E63: HERTRICH CHRYSLER DODGE FORD OF POCOMOKE | H63: =VLOOKUP(D63,'Billing CDK pivot (by package)'!A:D,4,FALSE) -> CRM OUTBOUND TELEPHONY TRACKING (NEW AND CONVERSION) | I63: =VLOOKUP(D63,'Billing CDK pivot'!A:C,3,FALSE) -> #N/A | K63: 185 | L63: OK
A64: Hertrich Chevrolet | B64: 59097 | C64: 16312 | D64: 76217649 | E64: HERTRICH CHEVROLET | H64: =VLOOKUP(D64,'Billing CDK pivot (by package)'!A:D,4,FALSE) -> CRM OUTBOUND TELEPHONY TRACKING (NEW AND CONVERSION) | I64: =VLOOKUP(D64,'Billing CDK pivot'!A:C,3,FALSE) -> #N/A | K64: 185 | L64: OK
A65: Hertrich Chevrolet Buick GMC | B65: 59098 | C65: 16313 | D65: 76211989 | E65: HERTRICH BUICK GMC | H65: =VLOOKUP(D65,'Billing CDK pivot (by package)'!A:D,4,FALSE) -> CRM OUTBOUND TELEPHONY TRACKING (NEW AND CONVERSION) | I65: =VLOOKUP(D65,'Billing CDK pivot'!A:C,3,FALSE) -> #N/A | K65: 185 | L65: OK
A66: Hertrich Chevrolet Cadillac Salisbury | B66: 92363 | C66: 18572 | D66: 76219122 | E66: HERTRICH CHEVROLET CADILLAC OF SALISBURY | H66: =VLOOKUP(D66,'Billing CDK pivot (by package)'!A:D,4,FALSE) -> CRM OUTBOUND TELEPHONY TRACKING (NEW AND CONVERSION) | I66: =VLOOKUP(D66,'Billing CDK pivot'!A:C,3,FALSE) -> #N/A | K66: 185 | L66: OK
A67: Hertrich Chevrolet of Dover | B67: 139187 | D67: 76195594 | E67: HERTRICH CHEVROLET OF DOVER | H67: =VLOOKUP(D67,'Billing CDK pivot (by package)'!A:D,4,FALSE) -> CRM OUTBOUND TELEPHONY TRACKING (NEW AND CONVERSION) | I67: =VLOOKUP(D67,'Billing CDK pivot'!A:C,3,FALSE) -> #N/A | K67: 185 | L67: OK
A68: Hertrich Chrysler Dodge Jeep Ram of Elkton | B68: 59111 | C68: 16311 | D68: 76217603 | E68: HERTRICH CHRYSLER DODGE JEEP RAM OF ELKTON | H68: =VLOOKUP(D68,'Billing CDK pivot (by package)'!A:D,4,FALSE) -> CRM OUTBOUND TELEPHONY TRACKING (NEW AND CONVERSION) | I68: =VLOOKUP(D68,'Billing CDK pivot'!A:C,3,FALSE) -> #N/A | K68: 185 | L68: OK
A69: Hertrich Ford - Lincoln of Milford | B69: 59093 | C69: 16306 | D69: 76149019 | E69: HERTRICH FORD LINCOLN | H69: =VLOOKUP(D69,'Billing CDK pivot (by package)'!A:D,4,FALSE) -> CRM OUTBOUND TELEPHONY TRACKING (NEW AND CONVERSION) | I69: =VLOOKUP(D69,'Billing CDK pivot'!A:C,3,FALSE) -> #N/A | K69: 185 | L69: OK
A70: Hertrich Ford of Easton | B70: 59099 | C70: 16314 | D70: 76212090 | E70: HERTRICH FORD OF EASTON | H70: =VLOOKUP(D70,'Billing CDK pivot (by package)'!A:D,4,FALSE) -> CRM OUTBOUND TELEPHONY TRACKING (NEW AND CONVERSION) | I70: =VLOOKUP(D70,'Billing CDK pivot'!A:C,3,FALSE) -> #N/A | K70: 185 | L70: OK
A71: Hertrich Ford of Elkton | B71: 140696 | D71: 76218332 | E71: HERTRICH FORD OF ELKTON | H71: =VLOOKUP(D71,'Billing CDK pivot (by package)'!A:D,4,FALSE) -> CRM OUTBOUND TELEPHONY TRACKING (NEW AND CONVERSION) | I71: =VLOOKUP(D71,'Billing CDK pivot'!A:C,3,FALSE) -> #N/A | K71: 185 | L71: OK
A72: Hertrich Frederick Ford | B72: 59096 | C72: 16308 | D72: 76211981 | E72: HERTRICH FREDERICK FORD | H72: =VLOOKUP(D72,'Billing CDK pivot (by package)'!A:D,4,FALSE) -> CRM OUTBOUND TELEPHONY TRACKING (NEW AND CONVERSION) | I72: =VLOOKUP(D72,'Billing CDK pivot'!A:C,3,FALSE) -> #N/A | K72: 185 | L72: OK
A73: Hertrich Honda KIA | B73: 59100 | C73: 16315 | D73: 76212075 | E73: HERTRICH HONDA KIA OF EASTON | H73: =VLOOKUP(D73,'Billing CDK pivot (by package)'!A:D,4,FALSE) -> CRM OUTBOUND TELEPHONY TRACKING (NEW AND CONVERSION) | I73: =VLOOKUP(D73,'Billing CDK pivot'!A:C,3,FALSE) -> #N/A | K73: 185 | L73: OK
A74: Hertrich Hyundai of New Castle | B74: 59094 | C74: 16309 | D74: 76211580 | E74: HERTRICH HYUNDAI OF NEW CASTLE | H74: =VLOOKUP(D74,'Billing CDK pivot (by package)'!A:D,4,FALSE) -> CRM OUTBOUND TELEPHONY TRACKING (NEW AND CONVERSION) | I74: =VLOOKUP(D74,'Billing CDK pivot'!A:C,3,FALSE) -> #N/A | K74: 185 | L74: OK
A75: Hertrich Toyota Chevrolet Buick Cadillac | B75: 92394 | C75: 18571 | D75: 76215188 | E75: HERTRICH TOYOTA CHEVROLET | H75: =VLOOKUP(D75,'Billing CDK pivot (by package)'!A:D,4,FALSE) -> CRM OUTBOUND TELEPHONY TRACKING (NEW AND CONVERSION) | I75: =VLOOKUP(D75,'Billing CDK pivot'!A:C,3,FALSE) -> #N/A | K75: 185 | L75: OK
A76: Hertrich Toyota of Milford | B76: 59092 | C76: 16305 | D76: 76212307 | E76: HERTRICH TOYOTA SCION OF MILFORD | H76: =VLOOKUP(D76,'Billing CDK pivot (by package)'!A:D,4,FALSE) -> CRM OUTBOUND TELEPHONY TRACKING (NEW AND CONVERSION) | I76: =VLOOKUP(D76,'Billing CDK pivot'!A:C,3,FALSE) -> #N/A | K76: 185 | L76: OK
A77: Hertrich's Capitol | B77: 59091 | C77: 16304 | D77: 76212369 | E77: HERTRICH'S CAPITAL | H77: =VLOOKUP(D77,'Billing CDK pivot (by package)'!A:D,4,FALSE) -> CRM OUTBOUND TELEPHONY TRACKING (NEW AND CONVERSION) | I77: =VLOOKUP(D77,'Billing CDK pivot'!A:C,3,FALSE) -> #N/A | K77: 185 | L77: OK

Sheet Detail1
A1: Details for Count of Account - Comment Group: CDK no Charge
A3: Account | B3: Customer_ID | C3: External Billing ID | D3: Total minutes | E3: Overages | F3: Billing_amount | G3: CarWars Excl Overage | H3: CMF | I3: Ship to Name | J3: ANS Date | K3: Install Date | L3: LSS Date | M3: Catalog Number | N3: Catalog Description | O3: CDK Billing | P3: CDK Overages | Q3: CDK total Billing | R3: Margin Excl Overage | S3: Margin % Excl Overage | T3: Comment Group | U3: CDK Package 1 | V3: CDK Package 2 | W3: CDK Package 3 | X3: CallRevu Package 1 | Y3: CallRevu Package 2 | Z3: CallRevu Package 3
A4: Staunton Chrysler Dodge Jeep RAM | B4: 79668 | C4: 17662 | D4: 2844.43 | E4: 0 | F4: 254.15 | G4: 254.15 | H4: 76212445 | I4: STAUNTON CHRYSLER, DODGE,JEEP,RAM | M4: 4570060 | N4: CRM OUTBOUND TELEPHONY TRACKING (NEW AND CONVERSION) | O4: 0 | P4: 0 | Q4: 0 | R4: -254.15 | S4: #DIV/0! | T4: CDK no Charge | U4: CRM OUTBOUND TELEPHONY TRACKING (NEW AND CONVERSION) ($0.00) | X4: Secondary Package: Carrier Registration - Monthly ($10.00)

Sheet Nov Inv Recon Pivot
A3: Row Labels | B3: Count of Account | C3: Sum of Billing_amount | D3: CM Comments on process:
A4: ANS/Loss | B4: 17 | C4: 12302.74 | D4: Looked in contract detail and pulled all contract lines associated to the CMF number for the call tracking catalogs in scope. Based on manual review, determined that the most recent contract line was either in ANS or Loss status which means CDK is not billing the customer but the vendor is still billing CDK
A5: ANS/Loss - Click to all active and reason on CLM of billing line is that this is downgrading to Carwars starter 7500 from carwars advanced sales - no billing though | B5: 1 | C5: 495.62 | D5: Same comment as in row 4 but we worked with contract team to get more information.
A6: ANS/Loss - Deactivated Apr - Reactive as of Sept | B6: 1 | C6: 1653 | D6: same comment as in row 4 but received more information from Leigh Broomberg on the cancellation. She works with the vendor to cancel the lines if needed.
A7: ANS/Loss - sent form but Carwars said dealer wanted to keep it but no billing - sent email to sales | B7: 1 | C7: 264.15 | D7: same comment as in row 4 but received more information from Leigh Broomberg on the cancellation. She works with the vendor to cancel the lines if needed.
A8: ANS/Loss - sent to carwars 8/12/25 | B8: 1 | C8: 434.15 | D8: same comment as in row 4 but received more information from Leigh Broomberg on the cancellation. She works with the vendor to cancel the lines if needed. This was the date Leigh sent the cancellation to car wars but it doesn't appear the cancellation happened as we were still billed.
A9: ANS/Loss - Sent to carwars 8/8/25 | B9: 1 | C9: 1581.65 | D9: same comment as in row 4 but received more information from Leigh Broomberg on the cancellation. She works with the vendor to cancel the lines if needed. This was the date Leigh sent the cancellation to car wars but it doesn't appear the cancellation happened as we were still billed.
A10: Moved to call Revu | B10: 4 | C10: 1941.45 | D10: When I pulled contract detail I pulled all catalogs for call tracking and not just Car wars so I noticed the customer had an active call revu contract line
A11: Moved to Call Revu in 2021 | B11: 1 | C11: 424.15 | D11: When I pulled contract detail I pulled all catalogs for call tracking and not just Car wars so I noticed the customer had an active call revu contract line
A12: Negative Margin | B12: 73 | C12: 84888.83 | D12: This is just math - flagged anything with a negative margin
A13: Negative Margin - Should have been Deactivated in Sep | B13: 1 | C13: 429 | D13: This is just math - flagged anything with a negative margin. However information from Leigh Broomberg said see sent cancellation in sep but it was never cancelled on car wars side
A14: No Charge from Car wars | B14: 1 | C14: 0 | D14: Billing amount from carwars was $0 so didn't investigate these lines further
A15: No charge from Carwars | B15: 14 | C15: 0 | D15: Billing amount from carwars was $0 so didn't investigate these lines further
... A21: Margin >30% | B21: 1 | C21: 499 | D21: Bad grouping. Should have used the same grouping as row 20
A22: (blank)
A23: CDK no Charge | B23: 1 | C23: 254.15 | D23: Should have probably been included in negative margin group
A24: Grand Total | B24: 382 | C24: 308366.21

Sheet Nov Vendor Inv Detail
A1: Account | B1: Customer_ID | C1: External Billing ID | D1: Tracking_lines | E1: Dynamic_website_tracking | F1: Total Minutes | G1: Overages | H1: Minutes_Inbound | I1: Minutes_Outbound | J1: Minutes_Humanatic | K1: Price_plan | L1: Billing_amount | M1: Excl Overages
A2: Jordan Ford | B2: 61934 | C2: 16480 | D2: 16 | E2: 0 | F2: 82.34 | H2: 82.34 | I2: 0 | J2: 0 | K2: Elead CW Starter 4000 v2 | L2: 254.15 | M2: =+L2-G2 -> 254.15
A3: ELEAD1ONE CRM | B3: 8012 | D3: 2 | E3: 0 | F3: 4.67 | H3: 4.67 | I3: 0 | J3: 0 | K3: Elead Launch Phase-0 | L3: 0 | M3: =+L3-G3 -> 0
A4: ALBRECHT - INFINITI OF NORWOOD | B4: 62658 | C4: 16613 | D4: 21 | E4: 0 | F4: 1890.85 | H4: 1890.85 | I4: 0 | J4: 0 | K4: eLead - CW Starter - 3500 mins v2 | L4: 254.15 | M4: =+L4-G4 -> 254.15
A5: ALBRECHT - NASHUA INFINITI | B5: 62657 | C5: 16614 | D5: 19 | E5: 0 | F5: 37.67 | H5: 37.67 | I5: 0 | J5: 0 | K5: eLead - CW Starter - 3500 mins v2 | L5: 254.15 | M5: =+L5-G5 -> 254.15
A6: ALBRECHT - NASHUA INFINITI | B6: 62657 | C6: 16614 | D6: - | E6: - | F6: - | H6: - | I6: - | J6: - | K6: Secondary Package: Carrier Registration - Monthly | L6: 10 | M6: =+L6-G6 -> 10
A7: Allan Vigil Ford Lincoln | B7: 154247 | C7: 468 | D7: 84 | E7: 0 | F7: 18325.19 | H7: 1395.62 | I7: 16929.57 | J7: 14001.79 | K7: eLead CW Elite (Sales Service AI) v2 | L7: 2533.85 | M7: =+L7-G7 -> 2533.85
A8: Allan Vigil Ford Lincoln | B8: 154247 | C8: 468 | D8: - | E8: - | F8: - | H8: - | I8: - | J8: - | K8: Secondary Package: Carrier Registration - Monthly | L8: 10 | M8: =+L8-G8 -> 10
A9: Alpha One Motors | B9: 149876 | C9: 27280 | D9: 11 | E9: 0 | F9: 13.35 | H9: 13.35 | I9: 0 | J9: 0 | K9: eLead - CW Starter - 3500 mins v2 | L9: 254.15 | M9: =+L9-G9 -> 254.15
A10: Alpha One Motors | B10: 149876 | C10: 27280 | D10: - | E10: - | F10: - | H10: - | I10: - | J10: - | K10: Secondary Package: Carrier Registration - Monthly | L10: 10 | M10: =+L10-G10 -> 10
A11: Anderson Crystal Lake BMW / Mazda | B11: 84602 | C11: 4613a | D11: 34 | E11: 0 | F11: 1140.56 | H11: 102.95 | I11: 1037.61 | J11: 0 | K11: Elead CW Starter 4000 v2 | L11: 254.15 | M11: =+L11-G11 -> 254.15
A12: Anderson Crystal Lake BMW / Mazda | B12: 84602 | C12: 4613a | D12: - | E12: - | F12: - | H12: - | I12: - | J12: - | K12: Secondary Package: Carrier Registration - Monthly | L12: 10 | M12: =+L12-G12 -> 10
A13: Apple Honda | B13: 188955 | C13: 32347 | D13: 0 | E13: 0 | F13: 0 | H13: 0 | I13: 0 | J13: 0 | K13: Elead Launch Phase-0 | L13: 0 | M13: =+L13-G13 -> 0
A14: Apple Honda MD | B14: 97941 | D14: 50 | E14: 0 | F14: 79.33 | H14: 16.66 | I14: 62.67 | J14: 72.02 | K14: Elead - 24' CW Elite Medium | L14: 1294 | M14: =+L14-G14 -> 1294
A15: Apple Honda MD | B15: 97941 | D15: - | E15: - | F15: - | H15: - | I15: - | J15: - | K15: Secondary Package: Carrier Registration - Monthly | L15: 10 | M15: =+L15-G15 -> 10
A16: Apple Tree Superstore | B16: 99534 | C16: 19240 | D16: 3 | E16: 0 | F16: 6415.46 | G16: 48.31 | H16: 523.99 | I16: 5891.47 | J16: 0 | K16: Elead Outbound 4000 v2 | L16: 177.31 | M16: =+L16-G16 -> 129
A17: Apple Tree Superstore | B17: 99534 | C17: 19240 | D17: - | E17: - | F17: - | H17: - | I17: - | J17: - | K17: Secondary Package: Carrier Registration - Monthly | L17: 10 | M17: =+L17-G17 -> 10
A18: Arrive n Drive | B18: 187858 | C18: 30006 | D18: 12 | E18: 0 | F18: 3126.83 | H18: 626.69 | I18: 2500.14 | J18: 0 | K18: eLead - CW Starter - 5000 mins v2 | L18: 509.15 | M18: =+L18-G18 -> 509.15
A19: Athens BMW | B19: 84739 | C19: 18059 | D19: 10 | E19: 0 | F19: 1292.64 | H19: 278.72 | I19: 1013.92 | J19: 0 | K19: eLead - CW Starter - 7500 mins v2 | L19: 424.15 | M19: =+L19-G19 -> 424.15
A20: Athens BMW | B20: 84739 | C20: 18059 | D20: - | E20: - | F20: - | H20: - | I20: - | J20: - | K20: Secondary Package: Carrier Registration - Monthly | L20: 10 | M20: =+L20-G20 -> 10
A21: Audi Miami South | B21: 185463 | C21: 29715 | D21: 53 | E21: 0 | F21: 3608.44 | H21: 2979.4 | I21: 629.04 | J21: 2283.28 | K21: Elead - CW Elite Small + Advanced Service | L21: 1688 | M21: =+L21-G21 -> 1688
A22: Audi Miami South | B22: 185463 | C22: 29715 | D22: - | E22: - | F22: - | H22: - | I22: - | J22: - | K22: Secondary Package: Carrier Registration - Monthly | L22: 10 | M22: =+L22-G22 -> 10
A23: Baker - Buick GMC Cadillac | B23: 76195 | C23: 17223 | D23: 82 | E23: 0 | F23: 8351.73 | H23: 8351.73 | I23: 0 | J23: 1596.02 | K23: Elead CW Unlimited v2 | L23: 1571.65 | M23: =+L23-G23 -> 1571.65
A24: Berglund Toyota | B24: 96547 | C24: 7862 | D24: 37 | E24: 0 | F24: 2965.1 | H24: 2894.11 | I24: 70.99 | J24: 645.7 | K24: Elead CW Unlimited v2 | L24: 1571.65 | M24: =+L24-G24 -> 1571.65
A25: Bill Black Chevrolet Cadillac | B25: 142323 | C25: 22425 | D25: 14 | E25: 0 | F25: 679.89 | H25: 77.33 | I25: 602.56 | J25: 0 | K25: eLead - CW Starter - 7500 mins v2 | L25: 424.15 | M25: =+L25-G25 -> 424.15
A26: Bill Black Chevrolet Cadillac | B26: 142323 | C26: 22425 | D26: - | E26: - | F26: - | H26: - | I26: - | J26: - | K26: Secondary Package: Carrier Registration - Monthly | L26: 10 | M26: =+L26-G26 -> 10
A27: BMW/MINI of the Main Line | B27: 74464 | C27: 16765 | D27: 129 | E27: 0 | F27: 24179.12 | H27: 18067.14 | I27: 6111.98 | J27: 6130.54 | K27: eLead - CW Premium - Sales 50k v2 | L27: 1571.65 | M27: =+L27-G27 -> 1571.65
A28: BMW/MINI of the Main Line | B28: 74464 | C28: 16765 | D28: - | E28: - | F28: - | H28: - | I28: - | J28: - | K28: Secondary Package: Carrier Registration - Monthly | L28: 10 | M28: =+L28-G28 -> 10
A29: Bob Bell Ford | B29: 59246 | C29: 18577 | D29: 17 | E29: 0 | F29: 13420.63 | H29: 7548.65 | I29: 5871.98 | J29: 5617.04 | K29: eLead - CW Premium - Sales 50k v2 | L29: 1571.65 | M29: =+L29-G29 -> 1571.65
A30: Bob Bell Ford | B30: 59246 | C30: 18577 | D30: - | E30: - | F30: - | H30: - | I30: - | J30: - | K30: Secondary Package: Carrier Registration - Monthly | L30: 10 | M30: =+L30-G30 -> 10
A31: Bob Bell Hyundai | B31: 92128 | C31: 18596 | D31: 76 | E31: 0 | F31: 9740.35 | H31: 5682.62 | I31: 4057.73 | J31: 8870.65 | K31: Elead CW Unlimited v2 | L31: 1571.65 | M31: =+L31-G31 -> 1571.65
A32: Bob Bell Hyundai | B32: 92128 | C32: 18596 | D32: - | E32: - | F32: - | H32: - | I32: - | J32: - | K32: Secondary Package: Carrier Registration - Monthly | L32: 10 | M32: =+L32-G32 -> 10
A33: Bob Bell Nissan | B33: 90311 | C33: 18246 | D33: 45 | E33: 0 | F33: 5375.75 | G33: 33.82 | H33: 255.14 | I33: 5120.61 | J33: 0 | K33: eLead - CW Starter - 5000 mins v2 | L33: 542.97 | M33: =+L33-G33 -> 509.15
A34: Bob Brown Chevrolet | B34: 138653 | C34: 22237 | D34: 73 | E34: 0 | F34: 4.32 | H34: 0.67 | I34: 3.65 | J34: 0 | K34: eLead CW Elite (Sales Service AI) v2 | L34: 2533.85 | M34: =+L34-G34 -> 2533.85
A35: Bob Brown Chevrolet | B35: 138653 | C35: 22237 | D35: - | E35: - | F35: - | H35: - | I35: - | J35: - | K35: Secondary Package: Carrier Registration - Monthly | L35: 10 | M35: =+L35-G35 -> 10
A36: Bob Robinson Chevrolet Buick GMC | B36: 159842 | C36: 29415 | D36: 0 | E36: 0 | F36: 0 | H36: 0 | I36: 0 | J36: 0 | K36: Elead Launch Phase-0 | L36: 0 | M36: =+L36-G36 -> 0
A37: Bruce Bennett Nissan of Danbury | B37: 154578 | C37: 27016 | D37: 54 | E37: 0 | F37: 14366.1 | H37: 4792.49 | I37: 9573.61 | J37: 12831.22 | K37: eLead - CW Premium - Sales 50k v2 | L37: 1571.65 | M37: =+L37-G37 -> 1571.65
A38: Bruce Bennett Nissan of Danbury | B38: 154578 | C38: 27016 | D38: - | E38: - | F38: - | H38: - | I38: - | J38: - | K38: Secondary Package: Carrier Registration - Monthly | L38: 10 | M38: =+L38-G38 -> 10
A39: Buchanan Auto Park | B39: 61123 | C39: 7279 | D39: 30 | E39: 0 | F39: 5108.68 | G39: 76.5 | H39: 3173.73 | I39: 1934.95 | J39: 0 | K39: Elead CW Starter 4000 v2 | L39: 330.65 | M39: =+L39-G39 -> 254.15
A40: Buchanan Auto Park | B40: 61123 | C40: 7279 | D40: - | E40: - | F40: - | H40: - | I40: - | J40: - | K40: Secondary Package: Carrier Registration - Monthly | L40: 10 | M40: =+L40-G40 -> 10
A41: Buchanan Chevrolet Buick GMC Cadillac of Waynesboro | B41: 61125 | C41: 16270 | D41: 24 | E41: 0 | F41: 2834.74 | H41: 1272.55 | I41: 1562.19 | J41: 0 | K41: Elead CW Starter 4000 v2 | L41: 254.15 | M41: =+L41-G41 -> 254.15
A42: Buchanan Chevrolet Buick GMC Cadillac of Waynesboro | B42: 61125 | C42: 16270 | D42: - | E42: - | F42: - | H42: - | I42: - | J42: - | K42: Secondary Package: Carrier Registration - Monthly | L42: 10 | M42: =+L42-G42 -> 10
A43: Buchanan KIA | B43: 61126 | C43: 16271 | D43: 25 | E43: 0 | F43: 266.63 | H43: 125.99 | I43: 140.64 | J43: 0 | K43: Elead CW Starter 4000 v2 | L43: 254.15 | M43: =+L43-G43 -> 254.15
A44: Call Box test | B44: 143336 | C44: 123456 | D44: 2 | E44: 0 | F44: 0 | H44: 0 | I44: 0 | J44: 0 | K44: Elead Launch Phase-0 | L44: 0 | M44: =+L44-G44 -> 0
A45: Capital - Hyundai of Jacksonville | B45: 36446 | C45: 10556 | D45: 15 | E45: 0 | F45: 41.02 | H45: 41.02 | I45: 0 | J45: 40.69 | K45: Elead CW 8000 | L45: 710 | M45: =+L45-G45 -> 710
A46: Car Town Hyundai | B46: 144287 | C46: 24709 | D46: 15 | E46: 0 | F46: 746.64 | H46: 746.31 | I46: 0.33 | J46: 0 | K46: eLead - CW Starter - 5000 mins v2 | L46: 509.15 | M46: =+L46-G46 -> 509.15
A47: CarHeroes USA | B47: 141461 | C47: 22159 | D47: 11 | E47: 0 | F47: 6171.14 | G47: 184.31 | H47: 1777.18 | I47: 4393.96 | J47: 0 | K47: eLead - CW Starter - 3500 mins v2 | L47: 438.46 | M47: =+L47-G47 -> 254.15
A48: CarHeroes USA | B48: 141461 | C48: 22159 | D48: - | E48: - | F48: - | H48: - | I48: - | J48: - | K48: Secondary Package: Carrier Registration - Monthly | L48: 10 | M48: =+L48-G48 -> 10
A49: CarHeroes USA Tampa | B49: 156703 | C49: 29023 | D49: 10 | E49: 0 | F49: 4685.86 | G49: 81.82 | H49: 777.91 | I49: 3907.95 | J49: 0 | K49: eLead - CW Starter - 3500 mins v2 | L49: 335.97 | M49: =+L49-G49 -> 254.15
A50: CarHeroes USA Tampa | B50: 156703 | C50: 29023 | D50: - | E50: - | F50: - | H50: - | I50: - | J50: - | K50: Secondary Package: Carrier Registration - Monthly | L50: 10 | M50: =+L50-G50 -> 10
A51: Cavalier Ford at Chesapeake Square | B51: 74078 | C51: 5068 | D51: 14 | E51: 0 | F51: 4458.19 | G51: 31.62 | H51: 2637.44 | I51: 1820.75 | J51: 0 | K51: Elead CW Starter 4000 v2 | L51: 285.77 | M51: =+L51-G51 -> 254.15
A52: Cavalier Ford at Chesapeake Square | B52: 74078 | C52: 5068 | D52: - | E52: - | F52: - | H52: - | I52: - | J52: - | K52: Secondary Package: Carrier Registration - Monthly | L52: 10 | M52: =+L52-G52 -> 10
A53: Cavalier Mazda | B53: 50391 | C53: 15178 | D53: 2 | E53: 0 | F53: 4384.01 | G53: 7.68 | H53: 323.89 | I53: 4060.12 | J53: 0 | K53: Elead Outbound 4000 v2 | L53: 136.68 | M53: =+L53-G53 -> 129
A54: Cavalier Mazda | B54: 50391 | C54: 15178 | D54: - | E54: - | F54: - | H54: - | I54: - | J54: - | K54: Secondary Package: Carrier Registration - Monthly | L54: 10 | M54: =+L54-G54 -> 10
A55: Cella Ford | B55: 90338 | C55: 8230 | D55: 19 | E55: 0 | F55: 2477.75 | H55: 267.36 | I55: 2210.39 | J55: 0 | K55: Elead CW Starter 4000 v2 | L55: 254.15 | M55: =+L55-G55 -> 254.15
A56: Cella Ford | B56: 90338 | C56: 8230 | D56: - | E56: - | F56: - | H56: - | I56: - | J56: - | K56: Secondary Package: Carrier Registration - Monthly | L56: 10 | M56: =+L56-G56 -> 10
A57: Central Ford | B57: 79776 | C57: 17654 | D57: 53 | E57: 0 | F57: 18972.27 | H57: 13251.63 | I57: 5720.64 | J57: 6623.52 | K57: eLead CW Elite (Sales Service AI) v2 | L57: 2533.85 | M57: =+L57-G57 -> 2533.85
A58: CENTURY BUICK GMC | B58: 46371 | C58: 11519 | D58: 2 | E58: 0 | F58: 3112.69 | H58: 0 | I58: 3112.69 | J58: 0 | K58: Elead Outbound 4000 v2 | L58: 129 | M58: =+L58-G58 -> 129
A59: CENTURY BUICK GMC | B59: 46371 | C59: 11519 | D59: - | E59: - | F59: - | H59: - | I59: - | J59: - | K59: Secondary Package: Carrier Registration - Monthly | L59: 10 | M59: =+L59-G59 -> 10
A60: Century Kia of Tampa | B60: 46376 | C60: 15064 | D60: 2 | E60: 0 | F60: 4038.14 | G60: 0.76 | H60: 296.84 | I60: 3741.3 | J60: 0 | K60: Elead Outbound 4000 v2 | L60: 129.76 | M60: =+L60-G60 -> 129
A61: Charlie Clark Nissan Harlingen | B61: 84596 | C61: 17024 | D61: 4 | E61: 0 | F61: 23.66 | H61: 22.66 | I61: 1 | J61: 0 | K61: Elead CW Starter 4000 v2 | L61: 254.15 | M61: =+L61-G61 -> 254.15
A62: Cherry Hill Nissan | B62: 147556 | C62: 26427 | D62: 14 | E62: 0 | F62: 5634.21 | G62: 147.26 | H62: 26.05 | I62: 5608.16 | J62: 0 | K62: eLead - CW Starter - 3500 mins v2 | L62: 401.41 | M62: =+L62-G62 -> 254.15
A63: Cherry Hill Nissan | B63: 147556 | C63: 26427 | D63: - | E63: - | F63: - | H63: - | I63: - | J63: - | K63: Secondary Package: Carrier Registration - Monthly | L63: 10 | M63: =+L63-G63 -> 10
A64: Chi Town Harley-Davidson | B64: 149326 | C64: 26939 | D64: 5 | E64: 0 | F64: 460.01 | H64: 35.68 | I64: 424.33 | J64: 0 | K64: eLead - CW Starter - 7500 mins v2 | L64: 424.15 | M64: =+L64-G64 -> 424.15
A65: Chi Town Harley-Davidson | B65: 149326 | C65: 26939 | D65: - | E65: - | F65: - | H65: - | I65: - | J65: - | K65: Secondary Package: Carrier Registration - Monthly | L65: 10 | M65: =+L65-G65 -> 10
A66: Chrysler Dodge Jeep Ram of Franklin | B66: 187147 | C66: 4352 | D66: 0 | E66: 0 | F66: 0 | H66: 0 | I66: 0 | J66: 0 | K66: Elead Launch Phase-0 | L66: 0 | M66: =+L66-G66 -> 0
A67: Circle - Volkswagen of Garden Grove | B67: 143783 | C67: 20698 | D67: 12 | E67: 0 | F67: 2158.05 | H67: 1700.68 | I67: 457.37 | J67: 0 | K67: eLead - CW Starter - 3500 mins v2 | L67: 254.15 | M67: =+L67-G67 -> 254.15
A68: Circle - Volkswagen of Garden Grove | B68: 143783 | C68: 20698 | D68: - | E68: - | F68: - | H68: - | I68: - | J68: - | K68: Secondary Package: Carrier Registration - Monthly | L68: 10 | M68: =+L68-G68 -> 10
A69: Cloninger Ford of Hickory | B69: 108920 | C69: 19322 | D69: 86 | E69: 0 | F69: 8650.13 | H69: 891.16 | I69: 7758.97 | J69: 7087.85 | K69: eLead CW Elite (Sales Service AI) v2 | L69: 2533.85 | M69: =+L69-G69 -> 2533.85
A70: Cloninger Ford of Hickory | B70: 108920 | C70: 19322 | D70: - | E70: - | F70: - | H70: - | I70: - | J70: - | K70: Secondary Package: Carrier Registration - Monthly | L70: 10 | M70: =+L70-G70 -> 10
A71: Cloninger Ford of Morganton | B71: 108919 | C71: 19326 | D71: 32 | E71: 0 | F71: 1352.5 | H71: 236.6 | I71: 1115.9 | J71: 1287.2 | K71: eLead - Elite Small v2 | L71: 1274.15 | M71: =+L71-G71 -> 1274.15
A72: Cloninger Ford of Morganton | B72: 108919 | C72: 19326 | D72: - | E72: - | F72: - | H72: - | I72: - | J72: - | K72: Secondary Package: Carrier Registration - Monthly | L72: 10 | M72: =+L72-G72 -> 10
A73: Cloninger Ford of Salisbury | B73: 108921 | C73: 19319 | D73: 15 | E73: 0 | F73: 0 | H73: 0 | I73: 0 | J73: 0 | K73: Elead CW Starter 4000 v2 | L73: 254.15 | M73: =+L73-G73 -> 254.15
A74: Cloninger Ford of Salisbury | B74: 108921 | C74: 19319 | D74: - | E74: - | F74: - | H74: - | I74: - | J74: - | K74: Secondary Package: Carrier Registration - Monthly | L74: 10 | M74: =+L74-G74 -> 10
A75: Cloninger Toyota | B75: 108918 | C75: 19295 | D75: 14 | E75: 0 | F75: 0 | H75: 0 | I75: 0 | J75: 0 | K75: Elead CW Starter 4000 v2 | L75: 254.15 | M75: =+L75-G75 -> 254.15
A76: Cloninger Toyota | B76: 108918 | C76: 19295 | D76: - | E76: - | F76: - | H76: - | I76: - | J76: - | K76: Secondary Package: Carrier Registration - Monthly | L76: 10 | M76: =+L76-G76 -> 10
A77: Coastal Kia | B77: 36440 | C77: 10557A | D77: 248 | E77: 0 | F77: 16135.7 | H77: 955.16 | I77: 15180.54 | J77: 13083.84 | K77: eLead - CW Premium - Sales 50k v2 | L77: 1571.65 | M77: =+L77-G77 -> 1571.65
A78: Coastal Kia | B78: 36440 | C78: 10557A | D78: - | E78: - | F78: - | H78: - | I78: - | J78: - | K78: Secondary Package: Carrier Registration - Monthly | L78: 10 | M78: =+L78-G78 -> 10
A79: Coconut Point Ford | B79: 156745 | C79: 3869 | D79: 10 | E79: 0 | F79: 3911.88 | H79: 287.2 | I79: 3624.68 | J79: 0 | K79: eLead - CW Starter - 7500 mins v2 | L79: 424.15 | M79: =+L79-G79 -> 424.15
A80: Coconut Point Ford | B80: 156745 | C80: 3869 | D80: - | E80: - | F80: - | H80: - | I80: - | J80: - | K80: Secondary Package: Carrier Registration - Monthly | L80: 10 | M80: =+L80-G80 -> 10
A81: Commonwealth Chevrolet | B81: 84459 | C81: 18079 | D81: 42 | E81: 1 | F81: 2455.53 | H81: 1590.05 | I81: 865.48 | J81: 1747.53 | K81: Elead CW Unlimited v2 | L81: 1571.65 | M81: =+L81-G81 -> 1571.65
A82: Commonwealth Chevrolet | B82: 84459 | C82: 18079 | D82: - | E82: - | F82: - | H82: - | I82: - | J82: - | K82: Secondary Package: Carrier Registration - Monthly | L82: 10 | M82: =+L82-G82 -> 10
A83: Commonwealth Honda | B83: 84504 | C83: 18080 | D83: 33 | E83: 2 | F83: 1571.65 | H83: 215.29 | I83: 1356.36 | J83: 0 | K83: eLead - CW Starter - 3500 mins v2 | L83: 254.15 | M83: =+L83-G83 -> 254.15
A84: Commonwealth Honda | B84: 84504 | C84: 18080 | D84: - | E84: - | F84: - | H84: - | I84: - | J84: - | K84: Secondary Package: Carrier Registration - Monthly | L84: 10 | M84: =+L84-G84 -> 10
A85: Commonwealth Kia | B85: 84503 | C85: 18081 | D85: 50 | E85: 1 | F85: 1525.89 | H85: 573.36 | I85: 952.53 | J85: 0 | K85: eLead - CW Starter - 3500 mins v2 | L85: 254.15 | M85: =+L85-G85 -> 254.15
A86: Commonwealth Kia | B86: 84503 | C86: 18081 | D86: - | E86: - | F86: - | H86: - | I86: - | J86: - | K86: Secondary Package: Carrier Registration - Monthly | L86: 10 | M86: =+L86-G86 -> 10
A87: Commonwealth Nissan | B87: 84465 | C87: 18082 | D87: 72 | E87: 1 | F87: 1418.84 | H87: 617.18 | I87: 801.66 | J87: 0 | K87: eLead - CW Starter - 3500 mins v2 | L87: 254.15 | M87: =+L87-G87 -> 254.15
A88: Commonwealth Nissan | B88: 84465 | C88: 18082 | D88: - | E88: - | F88: - | H88: - | I88: - | J88: - | K88: Secondary Package: Carrier Registration - Monthly | L88: 10 | M88: =+L88-G88 -> 10
A89: Commonwealth Volkswagen | B89: 84506 | C89: 18083 | D89: 28 | E89: 1 | F89: 2205.35 | H89: 1569.59 | I89: 635.76 | J89: 0 | K89: eLead - CW Starter - 3500 mins v2 | L89: 254.15 | M89: =+L89-G89 -> 254.15
A90: Commonwealth Volkswagen | B90: 84506 | C90: 18083 | D90: - | E90: - | F90: - | H90: - | I90: - | J90: - | K90: Secondary Package: Carrier Registration - Monthly | L90: 10 | M90: =+L90-G90 -> 10
A91: Commuter Cars | B91: 150041 | C91: 17995 | D91: 3 | E91: 0 | F91: 138.12 | H91: 2.32 | I91: 135.8 | J91: 0 | K91: eLead - CW Starter - 3500 mins v2 | L91: 254.15 | M91: =+L91-G91 -> 254.15
A92: Commuter Cars | B92: 150041 | C92: 17995 | D92: - | E92: - | F92: - | H92: - | I92: - | J92: - | K92: Secondary Package: Carrier Registration - Monthly | L92: 10 | M92: =+L92-G92 -> 10
A93: Crescent Ford | B93: 146876 | C93: 8209 | D93: 23 | E93: 0 | F93: 7719.1 | H93: 4159.09 | I93: 3560.01 | J93: 7140.73 | K93: eLead - Elite Small | L93: 1019 | M93: =+L93-G93 -> 1019
A94: Crescent Ford | B94: 146876 | C94: 8209 | D94: - | E94: - | F94: - | H94: - | I94: - | J94: - | K94: Secondary Package: Carrier Registration - Monthly | L94: 10 | M94: =+L94-G94 -> 10
A95: DARCARS Chrysler Jeep Dodge RAM of Rockville | B95: 59903 | C95: 5252 | D95: 2 | E95: 0 | F95: 0.33 | H95: 0 | I95: 0.33 | J95: 0 | K95: Elead Outbound 4000 v2 | L95: 129 | M95: =+L95-G95 -> 129
A96: DARCARS Honda | B96: 58680 | C96: 9472 | D96: 2 | E96: 0 | F96: 0 | H96: 0 | I96: 0 | J96: 0 | K96: Elead Outbound 4000 v2 | L96: 129 | M96: =+L96-G96 -> 129
A97: DARCARS Lexus of Silver Spring | B97: 58685 | C97: 2432 | D97: 2 | E97: 0 | F97: 0 | H97: 0 | I97: 0 | J97: 0 | K97: Elead Outbound 4000 v2 | L97: 129 | M97: =+L97-G97 -> 129
A98: David Taylor Michigan City CDJR IN | B98: 121132 | C98: 21229 | D98: 8 | E98: 0 | F98: 20.98 | H98: 19.33 | I98: 1.65 | J98: 0 | K98: eLead - CW Starter - 3500 mins v2 | L98: 254.15 | M98: =+L98-G98 -> 254.15
A99: Dayton Andrews St Petersburg | B99: 99695 | C99: 17450 | D99: 45 | E99: 0 | F99: 3170.77 | H99: 260.47 | I99: 2910.3 | J99: 2820.42 | K99: eLead - Elite Small | L99: 1019 | M99: =+L99-G99 -> 1019
A100: Deacon Jones BMW of Kinston | B100: 177336 | C100: 29810 | D100: 12 | E100: 0 | F100: 1878.39 | H100: 1741.07 | I100: 137.32 | J100: 0 | K100: eLead - CW Starter - 3500 mins v2 | L100: 254.15 | M100: =+L100-G100 -> 254.15
...

Sheet Vendor Inv Pivot
A3: Account | B3: Customer_ID | C3: External Billing ID | D3: Sum of Total Minutes | E3: Sum of Overages | F3: Sum of Billing_amount
A4: Jordan Ford | B4: 61934 | C4: 16480 | D4: 82.34 | E4: 0 | F4: 254.15
A5: ELEAD1ONE CRM | B5: 8012 | C5: (blank) | D5: 4.67 | E5: 0 | F5: 0
A6: ALBRECHT - INFINITI OF NORWOOD | B6: 62658 | C6: 16613 | D6: 1890.85 | E6: 0 | F6: 254.15
A7: ALBRECHT - NASHUA INFINITI | B7: 62657 | C7: 16614 | D7: 37.67 | E7: 0 | F7: 264.15
A8: Allan Vigil Ford Lincoln | B8: 154247 | C8: 468 | D8: 18325.19 | E8: 0 | F8: 2543.85
A9: Alpha One Motors | B9: 149876 | C9: 27280 | D9: 13.35 | E9: 0 | F9: 264.15
A10: Anderson Crystal Lake BMW / Mazda | B10: 84602 | C10: 4613a | D10: 1140.56 | E10: 0 | F10: 264.15
A11: Apple Honda | B11: 188955 | C11: 32347 | D11: 0 | E11: 0 | F11: 0
A12: Apple Honda MD | B12: 97941 | C12: (blank) | D12: 79.33 | E12: 0 | F12: 1304
A13: Apple Tree Superstore | B13: 99534 | C13: 19240 | D13: 6415.46 | E13: 48.31 | F13: 187.31
A14: Arrive n Drive | B14: 187858 | C14: 30006 | D14: 3126.83 | E14: 0 | F14: 509.15
A15: Athens BMW | B15: 84739 | C15: 18059 | D15: 1292.64 | E15: 0 | F15: 434.15
A16: Audi Miami South | B16: 185463 | C16: 29715 | D16: 3608.44 | E16: 0 | F16: 1698
A17: Baker - Buick GMC Cadillac | B17: 76195 | C17: 17223 | D17: 8351.73 | E17: 0 | F17: 1571.65
A18: Berglund Toyota | B18: 96547 | C18: 7862 | D18: 2965.1 | E18: 0 | F18: 1571.65
A19: Bill Black Chevrolet Cadillac | B19: 142323 | C19: 22425 | D19: 679.89 | E19: 0 | F19: 434.15
A20: BMW/MINI of the Main Line | B20: 74464 | C20: 16765 | D20: 24179.12 | E20: 0 | F20: 1581.65
A21: Bob Bell Ford | B21: 59246 | C21: 18577 | D21: 13420.63 | E21: 0 | F21: 1581.65
A22: Bob Bell Hyundai | B22: 92128 | C22: 18596 | D22: 9740.35 | E22: 0 | F22: 1581.65
A23: Bob Bell Nissan | B23: 90311 | C23: 18246 | D23: 5375.75 | E23: 33.82 | F23: 542.97
A24: Bob Brown Chevrolet | B24: 138653 | C24: 22237 | D24: 4.32 | E24: 0 | F24: 2543.85
... A49: Cloninger Toyota | B49: 108918 | C49: 19295 | D49: 0 | E49: 0 | F49: 264.15
A50: Coastal Kia | B50: 36440 | C50: 10557A | D50: 16135.7 | E50: 0 | F50: 1581.65
A51: Coconut Point Ford | B51: 156745 | C51: 3869 | D51: 3911.88 | E51: 0 | F51: 434.15
A52: Commonwealth Chevrolet | B52: 84459 | C52: 18079 | D52: 2455.53 | E52: 0 | F52: 1581.65
A53: Commonwealth Honda | B53: 84504 | C53: 18080 | D53: 1571.65 | E53: 0 | F53: 264.15
A54: Commonwealth Kia | B54: 84503 | C54: 18081 | D54: 1525.89 | E54: 0 | F54: 264.15
A55: Commonwealth Nissan | B55: 84465 | C55: 18082 | D55: 1418.84 | E55: 0 | F55: 264.15
A56: Commonwealth Volkswagen | B56: 84506 | C56: 18083 | D56: 2205.35 | E56: 0 | F56: 264.15
A57: Commuter Cars | B57: 150041 | C57: 17995 | D57: 138.12 | E57: 0 | F57: 264.15
A58: Crescent Ford | B58: 146876 | C58: 8209 | D58: 7719.1 | E58: 0 | F58: 1029
A59: DARCARS Chrysler Jeep Dodge RAM of Rockville | B59: 59903 | C59: 5252 | D59: 0.33 | E59: 0 | F59: 129
A60: DARCARS Honda | B60: 58680 | C60: 9472 | D60: 0 | E60: 0 | F60: 129
A61: DARCARS Lexus of Silver Spring | B61: 58685 | C61: 2432 | D61: 0 | E61: 0 | F61: 129
A62: David Taylor Michigan City CDJR IN | B62: 121132 | C62: 21229 | D62: 20.98 | E62: 0 | F62: 254.15
... A104: Greenway - Greenway FIAT of East Orlando | B104: 82486 | C104: 17715 | D104: 17.64 | E104: 0 | F104: 264.15
A105: Greenway - Greenway Hyundai Orlando | B105: 84240 | C105: (blank) | D105: 21950.17 | E105: 0 | F105: 2543.85
A106: Greenway - Greenway Kia of Franklin | B106: 117573 | C106: 17302 | D106: 2554.66 | E106: 0 | F106: 434.15
A107: Greenway - Greenway Kia of Hickory Hollow | B107: 79117 | C107: 17537 | D107: 12216.95 | E107: 329.34 | F107: 1069.34
A108: Greenway - Greenway Kia of Rivergate | B108: 79241 | C108: 17536 | D108: 9824.7 | E108: 0 | F108: 1581.65
A109: Greenway - Greenway Mazda | B109: 118922 | C109: 19750 | D109: 11938.02 | E109: 0 | F109: 1284.15
A110: Greenway - Kia at the Avenues | B110: 156783 | C110: 28998 | D110: 8005.94 | E110: 0 | F110: 1304.15
A111: Greenway - Laredo DCJR | B111: 118900 | C111: 19824 | D111: 3104.9 | E111: 0 | F111: 434.15
A112: Greenway - Norristown Chrysler Dodge Jeep Ram | B112: 141757 | C112: 17782 | D112: 3171.09 | E112: 0 | F112: 848
A113: Greenway - Opelika CDJR Ford | B113: 118913 | C113: 19809 | D113: 15565.79 | E113: 239.44 | F113: 1523.59
A114: Greenway - Riverchase Kia | B114: 118912 | C114: 19810 | D114: 4486.81 | E114: 0 | F114: 598
A115: Greenway - San Antonio CDJR | B115: 118924 | C115: 19746 | D115: 41253.04 | E115: 0 | F115: 2563.85
A116: Greenway - Team1One CDJR of Gadsen | B116: 118917 | C116: 19804 | D116: 3775.14 | E116: 0 | F116: 434.15
A117: Greenway - Team1One Chevrolet of Gadsden | B117: 118916 | C117: 19806 | D117: 5573.17 | E117: 0 | F117: 434.15
... A142: HeightsNissan | B142: 188956 | C142: 25376 | D142: 0 | E142: 0 | F142: 0
A143: HERTRICH AUTO GROUP (elead) | B143: 76985 | C143: (blank) | D143: 0 | E143: 0 | F143: 0
A144: Hertrich Infiniti of Newark | B144: 154901 | C144: 28188 | D144: 1211 | E144: 0 | F144: 264.15
A145: Hertrich Nissan of Dover | B145: 59090 | C145: 16303 | D145: 3597.68 | E145: 0 | F145: 1284.15
A146: Hertrich Nissan of Newark | B146: 154900 | C146: 28187 | D146: 7062.71 | E146: 0 | F146: 1284.15
A147: High Country Harley Davidson - Cheyenne | B147: 154756 | C147: 28303 | D147: 5.34 | E147: 0 | F147: 0
A148: High Country Harley Davidson - Frederick | B148: 154755 | C148: 28305 | D148: 4.32 | E148: 0 | F148: 0
A149: Holland Motorsports/Harley Davidson of Dothan | B149: 77178 | C149: 16702 | D149: 522.63 | E149: 0 | F149: 254.15
A150: Holman NC - Leith Acura of Cary | B150: 61229 | C150: 16394 | D150: 2095.71 | E150: 0 | F150: 869.15
A151: Holman NC - Leith Acura of Raleigh | B151: 138752 | C151: (blank) | D151: 1451.06 | E151: 0 | F151: 264.15
A152: Holman NC - Leith Audi Cary | B152: 61224 | C152: 16381 | D152: 4345.61 | E152: 26.99 | F152: 675.99
A153: Holman NC - Leith Audi Raleigh | B153: 61230 | C153: 16397 | D153: 2412.18 | E153: 0 | F153: 1581.65
A154: Holman NC - Leith Autopark Chrysler Jeep | B154: 58253 | C154: 16166 | D154: 4579.92 | E154: 0 | F154: 1581.65
A155: Holman NC - Leith Autopark Honda | B155: 58252 | C155: 16165 | D155: 14578.12 | E155: 0 | F155: 1581.65
A156: Holman NC - Leith Autopark Wendell | B156: 61226 | C156: 16386 | D156: 13441.24 | E156: 426.58 | F156: 1295.73
A157: Holman NC - Leith BMW | B157: 58245 | C157: 16167 | D157: 16121.39 | E157: 0 | F157: 1581.65
A158: Holman NC - Leith Chrysler Jeep | B158: 61221 | C158: 3934 | D158: 2102.37 | E158: 0 | F158: 649
A159: Holman NC - Leith Honda | B159: 58247 | C159: 16164 | D159: 9868.43 | E159: 0 | F159: 1700.65
A160: Holman NC - Leith Honda Chrysler Dodge Jeep RAM Aberdeen | B160: 61232 | C160: 16395 | D160: 3785.22 | E160: 0 | F160: 1581.65
A161: Holman NC - Leith Jaguar Land Rover of Raleigh | B161: 115628 | C161: 19523 | D161: 6368.57 | E161: 0 | F161: 1581.65
A162: Holman NC - Leith Land Rover Cary | B162: 61223 | C162: 16372 | D162: 9131.46 | E162: 0 | F162: 1581.65
A163: Holman NC - Leith Lincoln | B163: 61219 | C163: 16369 | D163: 6213.33 | E163: 0 | F163: 839
... A175: House Ford CDJR | B175: 119044 | C175: 21218 | D175: 10318.92 | E175: 0 | F175: 1284.15
A176: HUD - Rock Hill Nissan | B176: 90212 | C176: (blank) | D176: 0 | E176: 0 | F176: 1571.65
A177: Hughes Subaru | B177: 125150 | C177: 18058 | D177: 3808.83 | E177: 0 | F177: 424.15
A178: Hyman Bros Land Rover Richmond | B178: 142809 | C178: 23503 | D178: 4395.91 | E178: 0 | F178: 434.15
A179: Hyman Bros Nissan Kia | B179: 143527 | C179: 23501 | D179: 14842.95 | E179: 0 | F179: 598
A180: Hyman Bros Subaru | B180: 142811 | C180: 23500 | D180: 505.37 | E180: 0 | F180: 434.15
A181: Independence Harley Davidson | B181: 120186 | C181: 21332 | D181: 1346.42 | E181: 0 | F181: 434.15
A182: Infiniti of Tallahassee | B182: 115609 | C182: 19515 | D182: 243.17 | E182: 0 | F182: 264.15
A183: Iron Steed Harley Davidson | B183: 150665 | C183: 27596 | D183: 2691.58 | E183: 0 | F183: 264.15
A184: Jack Daniels Audi | B184: 122660 | C184: (blank) | D184: 5925.73 | E184: 0 | F184: 1284.15
A185: Jack Daniels Audi of Paramus | B185: 122661 | C185: (blank) | D185: 5176.63 | E185: 0 | F185: 1284.15
A186: Jack Daniels KIA | B186: 122662 | C186: (blank) | D186: 7620.45 | E186: 0 | F186: 1284.15
A187: Jack Daniels Porsche | B187: 122663 | C187: (blank) | D187: 1168.94 | E187: 0 | F187: 1284.15
A188: Jack Daniels Volkswagen | B188: 122664 | C188: (blank) | D188: 6533.87 | E188: 0 | F188: 1284.15
A189: Jack Schmitt Ford Lincoln | B189: 83085 | C189: 17813 | D189: 0 | E189: 0 | F189: 254.15
A190: Jackson Acura of Roswell | B190: 77807 | C190: 7742 | D190: 21.22 | E190: 0 | F190: 254.15
A191: Jaguar Land Rover Coral Gables | B191: 153404 | C191: 27739 | D191: 2190.42 | E191: 0 | F191: 2543.85
A192: JT's AUTOLAND II | B192: 159190 | C192: 28942 | D192: 633.74 | E192: 0 | F192: 859.15
A193: JT's Kia of Columbia II | B193: 159263 | C193: 437779 | D193: 18877.78 | E193: 0 | F193: 1581.65
A194: Keffer - Elevation Chevrolet Buick GMC | B194: 159539 | C194: 29582 | D194: 3026.4 | E194: 0 | F194: 424.15
A195: Keffer - Hyundai of Anderson | B195: 147873 | C195: 26623 | D195: 12309.71 | E195: 345.34 | F195: 1204.49
A196: Keyser and Miller Ford | B196: 117484 | C196: 19910 | D196: 0 | E196: 0 | F196: 254.15
A197: KIA Mall of Georgia | B197: 72057 | C197: 16585 | D197: 2190.39 | E197: 0 | F197: 254.15
A198: Kia of Abilene | B198: 144285 | C198: 24706 | D198: 11163.04 | E198: 0 | F198: 1581.65
A199: Kia of San Angelo | B199: 149893 | C199: 24705 | D199: 8455.44 | E199: 65.93 | F199: 711.73
A200: King KIA | B200: 86863 | C200: 18077 | D200: 4423.02 | E200: 29.19 | F200: 293.34
... A217: Long Hyundai Genesis Volvo | B217: 145823 | C217: 25641 | D217: 183.65 | E217: 0 | F217: 424.15
A218: Lou Sobh Volkswagen of Athens | B218: 177879 | C218: (blank) | D218: 4088.49 | E218: 0 | F218: 1284.15
...

Sheet Detail2
A1: Details for Sum of Recurring Amount (U.S.) - Ship-To Name: STAUNTON CHRYSLER, DODGE,JEEP,RAM, CMF Number: 76212445, Charge Reference: 00200283SW05, Catalog Number: 4570009, Catalog Description: CALLSOURCE (CONVERSION) (+)
A3: Business Unit Code | B3: Product Level 1 Description | C3: Product Level 2 Description | D3: Product Level 3 Description | E3: Line of Business Code | F3: Account Code | G3: Primary (Y/N/NA) | H3: Ship-To/Location State/Province | I3: One Time Amount (U.S.) | J3: Recurring Amount (U.S.) | K3: Quantity | L3: CMF Number | M3: On Carwars Inv | N3: On Heitrich/Victory | O3: Ship-To Name | P3: Transaction Type | Q3: Charge Reference | R3: CDF Id | S3: Catalog Number | T3: Catalog Description | U3: Charge Type | V3: Charge Type Description | W3: Invoice Fiscal Year | X3: Invoice Fiscal Month | Y3: Rollup Level Code | Z3: Invoice Calendar Year | AA3: Invoice Month Name | AB3: Primary / Secondary
A4: 0914 | B4: ELEAD | C4: ELEAD OTHER | D4: CALL TRACKING COUNT AS ONE | E4: 21112 | F4: 4111001 | G4: N | H4: IL | I4: 0 | J4: 0 | K4: 1 | L4: 76212445 | M4: 76212445 | N4: #N/A | O4: STAUNTON CHRYSLER, DODGE,JEEP,RAM | P4: US INVOICE | Q4: 67035312SW04 | R4: 67035312SW04 | S4: 4570060 | T4: CRM OUTBOUND TELEPHONY TRACKING (NEW AND CONVERSION) | U4: SWW | V4: SW ACCESS VIA WEB | W4: 2025 | X4: 11 | Y4: FIN5030 | Z4: 2025 | AA4: November | AB4: Primary

Sheet Billing CDK pivot
A1: Charge Reference | B1: (Multiple Items)
A2: Catalog Number | B2: (All)
A3: Catalog Description | B3: (All)
A5: CMF Number | B5: Ship-To Name | C5: Sum of Recurring Amount (U.S.)
A6: 76212445 | B6: STAUNTON CHRYSLER, DODGE,JEEP,RAM | C6: 0
A7: Grand Total | C7: 0

Sheet Billing CDK pivot (No match)
A1: Charge Reference | B1: (Multiple Items)
A2: On Carwars Inv | B2: #N/A
A4: CMF Number | B4: Ship-To Name | C4: Catalog Number | D4: Catalog Description | E4: Sum of Recurring Amount (U.S.) | F4: Sum of One Time Amount (U.S.)
A5: 01231901 | B5: CECIL CLARK CHEVROLET | C5: 4570358 | D5: OUTBOUND CALL TRACKING PKGS (GM IMR CONVERSION) | E5: 293.02 | F5: 0
A6: 05237634 | B6: SANTA MARGARITA FORD | C6: 4570120 | D6: CRM TELEPHONY TRACKING | E6: 112 | F6: 0
A7: 08300215 | B7: HONDA KINGSTON | C7: 4570120 | D7: CRM TELEPHONY TRACKING | E7: 147.46 | F7: 0
A8: 09700154 | B8: POHANKA HONDA OF FREDERICKSBURG | C8: 4570120 | D8: CRM TELEPHONY TRACKING | E8: 65.46 | F8: 0
A9: 17272601 | B9: DON DAVIS EL CAMPO | C9: 4570060 | D9: CRM OUTBOUND TELEPHONY TRACKING (NEW AND CONVERSION) | E9: 0 | F9: 0
A10: 17272602 | B10: DON DAVIS BUICK,PONT.,GMC | C10: 4570060 | D10: CRM OUTBOUND TELEPHONY TRACKING (NEW AND CONVERSION) | E10: 0 | F10: 0
A11: 25149301 | B11: WESTBROOK HONDA | C11: 4570060 | D11: CRM OUTBOUND TELEPHONY TRACKING (NEW AND CONVERSION) | E11: 476.05 | F11: 0
A12: 25149302 | B12: HONDA OF WATERTOWN | C12: 4570060 | D12: CRM OUTBOUND TELEPHONY TRACKING (NEW AND CONVERSION) | E12: 476.05 | F12: 0
A13: 25149303 | B13: ACURA OF AVON | C13: 4570060 | D13: CRM OUTBOUND TELEPHONY TRACKING (NEW AND CONVERSION) | E13: 476.05 | F13: 0
A14: 25149304 | B14: ACURA OF MILFORD | C14: 4570060 | D14: CRM OUTBOUND TELEPHONY TRACKING (NEW AND CONVERSION) | E14: 476.05 | F14: 0
A15: 25149306 | B15: TOYOTA OF WESTBROOK | C15: 4570060 | D15: CRM OUTBOUND TELEPHONY TRACKING (NEW AND CONVERSION) | E15: 476.05 | F15: 0
A16: 25152901 | B16: BRANDFON HONDA | C16: 4570120 | D16: CRM TELEPHONY TRACKING | E16: 105 | F16: 0
... A69: 76215859 | B69: DAVE HALLMAN CHEVROLET | C69: 4570383 | D69: EL1OUTCALLTRACK (GM IMR) | E69: 1469.02 | F69: 0
C70: 4570648 | D70: SERVICE VISION PACKAGE 300 CALLS WINTEL (FOPS CMONITORING WPERFANALYTICS) | E70: 734.49 | F70: 0
A71: 76216996 | B71: SOUTHWEST INFINITI- | C71: 4570062 | D71: CARWARS PREMIUM SALES | E71: 1904.47 | F71: 0
A72: 76222492 | B72: PENSKE VOLVO PUENTE HILLS | C72: 4570120 | D72: CRM TELEPHONY TRACKING | E72: 104 | F72: 0
A73: 76222495 | B73: LAND ROVER PUENTE HILLS | C73: 4570120 | D73: CRM TELEPHONY TRACKING | E73: 104 | F73: 0
A74: 76223605 | B74: AUTOMALL AUTOMOTIVE LLC DBA TOWBIN DODGE RAM AND F | C74: 4570120 | D74: CRM TELEPHONY TRACKING | E74: 82.95 | F74: 0
A75: 76223993 | B75: GUNTERSVILLE CHEVROLET | C75: 4570120 | D75: CRM TELEPHONY TRACKING | E75: 123.81 | F75: 0
A76: 76224292 | B76: NEWTON CHEVROLET BUICK GMC | C76: 4570120 | D76: CRM TELEPHONY TRACKING | E76: 124.14 | F76: 0
A77: 76224293 | B77: NEWTON NISSAN OF GALLATIN | C77: 4570120 | D77: CRM TELEPHONY TRACKING | E77: 124.14 | F77: 0
A78: 76224320 | B78: NEWTON FORD SOUTH | C78: 4570120 | D78: CRM TELEPHONY TRACKING | E78: 105.94 | F78: 0
A79: 76225979 | B79: BERT SMITH BMW | C79: 4570104 | D79: CALLSOURCE EL ATTRIBUTED SMALL | E79: 87.59 | F79: 0
A80: 76225980 | B80: PORSCHE CLEARWATER | C80: 4570104 | D80: CALLSOURCE EL ATTRIBUTED SMALL | E80: 87.59 | F80: 0
A81: 76226123 | B81: BACHMAN BERNARD CHEVROLET GMC CADILLAC | C81: 4570120 | D81: CRM TELEPHONY TRACKING | E81: 0 | F81: 0
A82: 76227862 | B82: MATT BOWERS HYUNDAI - GULFPORT | C82: 4570009 | D82: CARWARS STARTER 3500 | E82: 322.92 | F82: 0
... A90: 76238766 | B90: FRED ANDERSON TOYOTA OF GREER | C90: 4570062 | D90: CARWARS PREMIUM SALES | E90: 1849 | F90: 0
C91: 4570124 | D91: CARWARS CARI AI | E91: 995 | F91: 0
A92: 76239770 | B92: FRED ANDERSON HYUNDAI | C92: 4570009 | D92: CARWARS STARTER 3500 | E92: 319 | F92: 0
A93: 76240559 | B93: ROBERTS CHEVROLET GMC | C93: 4570383 | D93: EL1OUTCALLTRACK (GM IMR) | E93: 1066.24 | F93: 0
C94: 4570522 | D94: SERVICE VISION PACKAGE 100 CALLS WINTEL (FOPS CMONITORING WPERFANALYTICS) | E94: 366.45 | F94: 0
A95: 76240828 | B95: MCSWEENEY AUTO GROUP CLANTON, LLC | C95: 4570129 | D95: CARWARS INDEFINITE CALL RECORDINGS | E95: 20 | F95: 0
A96: 76245381 | B96: NORTHWEST HYUNDAI | C96: 4571030 | D96: CARWARS STARTER 5000 | E96: 599 | F96: 0
A97: 76250570 | B97: ESCUDE NISSAN OF GREER | C97: 4571030 | D97: CARWARS STARTER 5000 | E97: 599 | F97: 0
A98: 76253984 | B98: MOBILE BAY HARLEY DAVIDSON | C98: 4570060 | D98: CRM OUTBOUND TELEPHONY TRACKING (NEW AND CONVERSION) | E98: 320.08 | F98: 0
A99: 76253986 | B99: SMOKIN HARLEY DAVIDSON | C99: 4570120 | D99: CRM TELEPHONY TRACKING | E99: 74.94 | F99: 0
A100: 76253994 | B100: NEW ORLEANS HARLEY-DAVIDSON | C100: 4570060 | D100: CRM OUTBOUND TELEPHONY TRACKING (NEW AND CONVERSION) | E100: 213.03 | F100: 0
A101: 76253995 | B101: PENSACOLA HARLEY-DAVIDSON | C101: 4570120 | D101: CRM TELEPHONY TRACKING | E101: 74.94 | F101: 0
A102: 76255362 | B102: OCEAN HONDA OF VENTURA | C102: 4570548 | D102: CAR WARS CUSTOM PACKAGE--VICTORY AUTO | E102: 1053.45 | F102: 0
A103: 76257172 | B103: CDJR OF FORT MYERS | C103: 4570289 | D103: CARWARS ELITE 12,500 PACKAGE | E103: 1499 | F103: 0
C104: 4571029 | D104: CARWARS ADDITIONAL BLOCK MINUTES | E104: 999 | F104: 0
A105: 76257174 | B105: KIA OF FORT MYERS | C105: 4570289 | D105: CARWARS ELITE 12,500 PACKAGE | E105: 1499 | F105: 0
C106: 4571029 | D106: CARWARS ADDITIONAL BLOCK MINUTES | E106: 999 | F106: 0
A107: Grand Total | E107: 31711.17 | F107: 0

Sheet Cognos - CDK Contract Detail
A1: CDF ID | B1: CNV CDF Catalog Number | C1: CNV Catalog Number Description | D1: Consolidated Location Type Rollup | E1: Active Automobile Party Count Tier | F1: Consolidated Location Type Tier | G1: Location Type/General Classification | H1: Term | I1: Ship-To CMF | J1: Recurring Charge Ship-to CMF | K1: Is Ford Direct (Y/N) | L1: Is Ford Direct Sister Store (Y/N) | M1: CMF Number | N1: ELEAD Id | O1: Ship-To Name | P1: CDF Status (w/ATN) | Q1: CDF Sale Type | R1: Conversion To CDF ID | S1: CNV CDF ID | T1: Installed DMS Vendor & System | U1: Consolidation Id | V1: Consolidation Name | W1: Consolidated Party Number | X1: Consolidated Party Name | Y1: Consolidated Location Type | Z1: Default Bill-To CMF Number | AA1: Default Bill-To Name | AB1: Bill-To Designation CMF | AC1: Bill-To Name | AD1: Business Unit Code | AE1: Region Code | AF1: Market Code | AG1: Ship-To/Location Address | AH1: Ship-To City | AI1: Ship-To State/Province | AJ1: Ship-To Country | AK1: Catalog Number | AL1: Catalog Description | AM1: Rollup Level Description | AN1: Product Level 1 Description | AO1: Product Level 2 Description | AP1: Product Level 3 Consolidator Description | AQ1: Product Tier | AR1: Primary (Y/N/NA) | AS1: Quantity | AT1: Front-End List (U.S.) | AU1: Front-End Sale (U.S.) | AV1: Install List (U.S.) | AW1: Install Sale (U.S.) | AX1: Monthly List (U.S.) | AY1: Monthly Sale (U.S.) | AZ1: Total QC | BA1: Free Months | BB1: Status Change Date | BC1: Roll Call Date | BD1: Roll Call Fiscal Year | BE1: Roll Call Fiscal Month | BF1: ANS Date | BG1: ANS Fiscal Year | BH1: ANS Fiscal Month | BI1: Protected From ATN (Y/N) | BJ1: Auto ANS (Y/N) | BK1: Auto ANS Date | BL1: Auto ANS Fiscal Year | BM1: Auto ANS Fiscal Month | BN1: Auto ANS Reverse Date | BO1: Auto ANS Reverse Fiscal Year | BP1: Auto ANS Reverse Fiscal Month | BQ1: Actual Install Date | BR1: Install Fiscal Year | BS1: Install Fiscal Month | BT1: Current Invoice Fiscal Year (based on Billing Cycle) | BU1: Install Fiscal Month (based on Billing Cycle) | BV1: Estimated Install Date | BW1: Estimated Install Fiscal Year | BX1: Estimated Install Fiscal Month | BY1: Estimated Install Fiscal Year (based on Billing Cycle) | BZ1: Estimated Install Fiscal Month (based on Billing Cycle) | CA1: Loss Date | CB1: Loss Fiscal Year | CC1: Loss Fiscal Month | CD1: Reason Code | CE1: Reason Code Description | CF1: Rekey (Y/N) | CG1: Reason Group Code | CH1: Reason Group Description | CI1: Reason Category Code | CJ1: Reason Category Description | CK1: Scenario Code | CL1: Scenario Description | CM1: Chosen Alternative Description | CN1: Replacement Vendor Name | CO1: Hold Code | CP1: Hold Code Description
A2: 68168332SW04 | D2: AUTOMOBILE | E2: 1-2 | F2: NEW AUTO | G2: AUTO | H2: 12 | K2: N | L2: N | M2: 76215681 | N2: 23551 | O2: TRENT CADILLAC BUICK GMC | P2: LSS | Q2: N | R2: 68188401SW10 | U2: 0014000000JW2YAAAR | V2: TRENT CADILLAC BUICK GMC | W2: 40016 | X2: TRENT CADILLAC BUICK GMC | Y2: AUTO | Z2: 76215681 | AA2: TRENT CADILLAC BUICK GMC | AC2: TRENT CADILLAC BUICK GMC | AD2: 0127 | AE2: 127 | AF2: 120 | AG2: 1707 HWY 70 E | AH2: NEW BERN | AI2: NC | AJ2: UNITED STATES | AK2: 4570058 | AL2: CARWARS STARTER 7500 | AM2: FRONT OFFICE | AN2: ELEAD | AO2: ELEAD OTHER | AP2: CALL TRACKING | AR2: N | AS2: 1 | AT2: 0 | AU2: 0 | AV2: 0 | AW2: 0 | AX2: 499 | AY2: 499 | AZ2: 5988 | BA2: 0 | BB2: 44726 | BC2: 43916 | BD2: 2020 | BE2: 9 | BI2: N | BQ2: 43955 | BR2: 2020 | BS2: 11 | BT2: 2026 | BU2: 11 | BV2: 43955 | BW2: 2020 | BX2: 10 | BY2: 2020 | BZ2: 11 | CA2: 44724 | CB2: 2022 | CC2: 12 | CD2: 221 | CE2: CDK CONVERSION - SYS GENERATED | CF2: N | CG2: C | CH2: CDK Conversion | CI2: CV | CJ2: Conversion | CK2: G | CL2: SYS GEN | CM2: CDK | CN2: ADP
A3: 68186645SW01 | B3: 4570062 | C3: CARWARS PREMIUM SALES | D3: AUTOMOBILE | E3: 1-2 | F3: NEW AUTO | G3: AUTO | H3: 3 | K3: N | L3: N | M3: 76003426 | N3: 10445 | O3: FAIR OAKS CHANTILLY CHRYSLER DODGE JEEP RAM | P3: LSS | Q3: C | R3: 68216748SW01 | S3: 68175496SW10 | U3: 0014000000JW3Q3AAJ | V3: FAIR OAKS CHANTILLY CHRYSLER JEEP DODGE RAM | W3: 25108 | X3: FAIR OAKS CHANTILLY CHRYSLER JEEP DODGE RAM | Y3: AUTO | Z3: 76003426 | AA3: FAIR OAKS CHANTILLY CHRYSLER DODGE JEEP RAM | AC3: FAIR OAKS CHANTILLY CHRYSLER DODGE JEEP RAM | AD3: 0127 | AE3: 127 | AF3: 120 | AG3: 4170 AUTO PARK CIRCLE | AH3: CHANTILLY | AI3: VA | AJ3: UNITED STATES | AK3: 4570602 | AL3: INTERACTIVETEL TOTAL TRACK 200+ | AM3: FRONT OFFICE | AN3: ELEAD | AO3: ELEAD OTHER | AP3: CALL TRACKING | AR3: N | AS3: 1 | AT3: 0 | AU3: 0 | AV3: 0 | AW3: 0 | AX3: 1995 | AY3: 1995 | AZ3: 4426.08 | BA3: 0 | BB3: 45279 | BC3: 44472 | BD3: 2022 | BE3: 3 | BI3: N | BQ3: 44501 | BR3: 2022 | BS3: 5 | BT3: 2026 | BU3: 5 | BV3: 44523 | BW3: 2022 | BX3: 5 | BY3: 2022 | BZ3: 6 | CA3: 45278 | CB3: 2023 | CC3: 12 | CD3: 221 | CE3: CDK CONVERSION - SYS GENERATED | CF3: N | CG3: C | CH3: CDK Conversion | CI3: CV | CJ3: Conversion | CK3: G | CL3: SYS GEN | CM3: CDK | CN3: ADP
A4: 68163968SW01 | D4: AUTOMOBILE | E4: 1-2 | F4: NEW AUTO | G4: AUTO | H4: 1 | K4: Y | L4: N | M4: 08320047 | N4: 8230 | O4: CELLA FORD | P4: LSS | Q4: N | R4: 68172588SW01 | U4: 0014000000JW305AAB | V4: CELLA FORD | W4: 10123709 | X4: CELLA FORD | Y4: AUTO | Z4: 08320047 | AA4: CELLA FORD | AC4: CELLA FORD | AD4: 0127 | AE4: 127 | AF4: 120 | AG4: 3210 DR M L KING JR BLVD | AH4: NEW BERN | AI4: NC | AJ4: UNITED STATES | AK4: 4570060 | AL4: CRM OUTBOUND TELEPHONY TRACKING (NEW AND CONVERSION) | AM4: FRONT OFFICE | AN4: ELEAD | AO4: ELEAD OTHER | AP4: CALL TRACKING | AR4: N | AS4: 1 | AT4: 0 | AU4: 0 | AV4: 0 | AW4: 0 | AX4: 195 | AY4: 359 | AZ4: 0 | BA4: 0 | BB4: 44054 | BC4: 43849 | BD4: 2020 | BE4: 7 | BI4: N | BQ4: 43862 | BR4: 2020 | BS4: 7 | BT4: 2026 | BU4: 8 | CA4: 44052 | CB4: 2021 | CC4: 2 | CD4: 221 | CE4: CDK CONVERSION - SYS GENERATED | CF4: N | CG4: C | CH4: CDK Conversion | CI4: CV | CJ4: Conversion | CK4: G | CL4: SYS GEN | CM4: CDK | CN4: ADP
A5: 64238223SW12 | B5: 4570089 | C5: CALLREVU 8000 | D5: AUTOMOBILE | E5: 3-5 | F5: NEW AUTO | G5: AUTO | H5: 12 | J5: 76167994 | K5: N | L5: N | M5: 76167994 | N5: 18231 | O5: MURRAY CHRYSLER DODGE JEEP | P5: INS | Q5: C | S5: 64191075SW42 | U5: 00140000011RWX6AAK | V5: MURRAY AUTO GROUP | W5: 187371 | X5: MURRAY CHRYSLER DODGE JEEP | Y5: AUTO | Z5: 76167994 | AA5: MURRAY CHRYSLER DODGE JEEP | AC5: MURRAY CHRYSLER DODGE JEEP | AD5: 0122 | AE5: 122 | AF5: 120 | AG5: 15160 HWY 301 S | AH5: STARKE | AI5: FL | AJ5: UNITED STATES | AK5: 4571047 | AL5: CALLREVU GROWTH 5K | AM5: FRONT OFFICE | AN5: ELEAD | AO5: ELEAD OTHER | AP5: CALL TRACKING | AR5: N | AS5: 1 | AT5: 0 | AU5: 0 | AV5: 0 | AW5: 0 | AX5: 599 | AY5: 599 | AZ5: 0 | BA5: 0 | BB5: 45869 | BC5: 45744 | BD5: 2025 | BE5: 3 | BI5: N | BQ5: 45869 | BR5: 2025 | BS5: 7 | BT5: 2026 | BU5: 8 | BV5: 45869 | BW5: 2025 | BX5: 7 | BY5: 2025 | BZ5: 8
A6: 67046811SW01 | B6: 4570383 | C6: EL1OUTCALLTRACK (GM IMR) | D6: AUTOMOBILE | E6: 3-5 | F6: NEW AUTO | G6: AUTO | H6: 6 | K6: N | L6: N | M6: 76055608 | N6: 11619 | O6: ROSEDALE CHEVROLET | P6: LSS | Q6: C | R6: 64226861SW29 | S6: 67037962SW08 | U6: 0014000000JVWFPAAR | V6: METROCORP | W6: 187885 | X6: ROSEDALE CHEVROLET | Y6: AUTO | Z6: 76210967 | AA6: GM IMR TURNKEY VENDOR PROGRAM | AC6: GM IMR TURNKEY VENDOR PROGRAM | AD6: 0122 | AE6: 122 | AF6: 120 | AG6: 2845 HIGHWAY 35W | AH6: ROSEVILLE | AI6: MN | AJ6: UNITED STATES | AK6: 4570383 | AL6: EL1OUTCALLTRACK (GM IMR) | AM6: FRONT OFFICE | AN6: ELEAD | AO6: ELEAD OTHER | AP6: CALL TRACKING | AR6: N | AS6: 1 | AT6: 0 | AU6: 0 | AV6: 0 | AW6: 0 | AX6: 0 | AY6: 2981 | AZ6: 6792 | BA6: 0 | BB6: 45385 | BC6: 44245 | BD6: 2021 | BE6: 8 | BI6: N | BQ6: 44251 | BR6: 2021 | BS6: 8 | BT6: 2026 | BU6: 9 | CA6: 45384 | CB6: 2024 | CC6: 4 | CD6: 221 | CE6: CDK CONVERSION - SYS GENERATED | CF6: N | CG6: C | CH6: CDK Conversion | CI6: CV | CJ6: Conversion | CK6: G | CL6: SYS GEN | CM6: CDK | CN6: ADP
A7: 38109204SW01 | D7: RECREATION | E7: Non-Auto | F7: RECREATION | G7: MOTORCYCLE | H7: 1 | K7: N | L7: N | M7: 76212580 | N7: 9973 | O7: EMERALD COAST HARLEY-DAVIDSON | P7: LSS | Q7: N | R7: 64238640SW16 | U7: 0010B00002DHZOWAA1 | V7: EMERALD COAST HARLEY-DAVIDSON | W7: 1733397 | X7: EMERALD COAST HARLEY-DAVIDSON | Y7: MOTORCYCLE | Z7: 76212580 | AA7: EMERALD COAST HARLEY-DAVIDSON | AC7: EMERALD COAST HARLEY-DAVIDSON | AD7: 0122 | AE7: 122 | AF7: 120 | AG7: 788 BEAL PKWY NW | AH7: FORT WALTON BEACH | AI7: FL | AJ7: UNITED STATES | AK7: 4570009 | AL7: CARWARS STARTER 3500 | AM7: FRONT OFFICE | AN7: ELEAD | AO7: ELEAD OTHER | AP7: CALL TRACKING | AR7: N | AS7: 1 | AT7: 0 | AU7: 0 | AV7: 0 | AW7: 0 | AX7: 299 | AY7: 299 | AZ7: 1794 | BA7: 0 | BB7: 45778 | BC7: 44343 | BD7: 2021 | BE7: 11 | BI7: N | BQ7: 44363 | BR7: 2021 | BS7: 12 | BT7: 2026 | BU7: 1 | CA7: 45777 | CB7: 2025 | CC7: 4 | CD7: 221 | CE7: CDK CONVERSION - SYS GENERATED | CF7: N | CG7: C | CH7: CDK Conversion | CI7: CV | CJ7: Conversion | CK7: G | CL7: SYS GEN | CM7: CDK | CN7: ADP
A8: 68219682SW09 | D8: AUTOMOBILE | E8: 1-2 | F8: NEW AUTO | G8: AUTO | H8: 1 | K8: N | L8: N | M8: 76003426 | N8: 10445 | O8: FAIR OAKS CHANTILLY CHRYSLER DODGE JEEP RAM | P8: LSS | Q8: N | R8: 68220056SW01 | U8: 0014000000JW3Q3AAJ | V8: FAIR OAKS CHANTILLY CHRYSLER JEEP DODGE RAM | W8: 25108 | X8: FAIR OAKS CHANTILLY CHRYSLER JEEP DODGE RAM | Y8: AUTO | Z8: 76003426 | AA8: FAIR OAKS CHANTILLY CHRYSLER DODGE JEEP RAM | AC8: FAIR OAKS CHANTILLY CHRYSLER DODGE JEEP RAM | AD8: 0127 | AE8: 127 | AF8: 120 | AG8: 4170 AUTO PARK CIRCLE | AH8: CHANTILLY | AI8: VA | AJ8: UNITED STATES | AK8: 4570602 | AL8: INTERACTIVETEL TOTAL TRACK 200+ | AM8: FRONT OFFICE | AN8: ELEAD | AO8: ELEAD OTHER | AP8: CALL TRACKING | AR8: N | AS8: 1 | AT8: 0 | AU8: 0 | AV8: 0 | AW8: 0 | AX8: 1995 | AY8: 2267.36 | AZ8: 13604.16 | BA8: 0 | BB8: 45352 | BC8: 45316 | BD8: 2024 | BE8: 1 | BI8: N | BQ8: 45299 | BR8: 2024 | BS8: 1 | BT8: 2026 | BU8: 1 | CA8: 45347 | CB8: 2024 | CC8: 2 | CD8: 221 | CE8: CDK CONVERSION - SYS GENERATED | CF8: N | CG8: C | CH8: CDK Conversion | CI8: CV | CJ8: Conversion | CK8: G | CL8: SYS GEN | CM8: CDK | CN8: ADP
A9: 68220056SW01 | B9: 4570602 | C9: INTERACTIVETEL TOTAL TRACK 200+ | D9: AUTOMOBILE | E9: 1-2 | F9: NEW AUTO | G9: AUTO | H9: 1 | J9: 76003426 | K9: N | L9: N | M9: 76003426 | N9: 10445 | O9: FAIR OAKS CHANTILLY CHRYSLER DODGE JEEP RAM | P9: INS | Q9: C | S9: 68219682SW09 | U9: 0014000000JW3Q3AAJ | V9: FAIR OAKS CHANTILLY CHRYSLER JEEP DODGE RAM | W9: 25108 | X9: FAIR OAKS CHANTILLY CHRYSLER JEEP DODGE RAM | Y9: AUTO | Z9: 76003426 | AA9: FAIR OAKS CHANTILLY CHRYSLER DODGE JEEP RAM | AC9: FAIR OAKS CHANTILLY CHRYSLER DODGE JEEP RAM | AD9: 0127 | AE9: 127 | AF9: 120 | AG9: 4170 AUTO PARK CIRCLE | AH9: CHANTILLY | AI9: VA | AJ9: UNITED STATES | AK9: 4570602 | AL9: INTERACTIVETEL TOTAL TRACK 200+ | AM9: FRONT OFFICE | AN9: ELEAD | AO9: ELEAD OTHER | AP9: CALL TRACKING | AR9: N | AS9: 1 | AT9: 0 | AU9: 0 | AV9: 0 | AW9: 0 | AX9: 1995 | AY9: 1995 | AZ9: -1634.16 | BA9: 0 | BB9: 45352 | BC9: 45321 | BD9: 2024 | BE9: 1 | BI9: N | BQ9: 45348 | BR9: 2024 | BS9: 2 | BT9: 2026 | BU9: 3 | BV9: 45348 | BW9: 2024 | BX9: 2 | BY9: 2024 | BZ9: 3
A10: 68163607SW01 | D10: AUTOMOBILE | E10: 1-2 | F10: NEW AUTO | G10: AUTO | H10: 1 | K10: Y | L10: N | M10: 76067593 | N10: 19910 | O10: KEYSER & MILLER FORD | P10: LSS | Q10: N | R10: 68215936SW01 | U10: 0014000000JW296AAB | V10: KEYSER & MILLER FORD | W10: 53354501 | X10: KEYSER & MILLER FORD | Y10: AUTO | Z10: 76067593 | AA10: KEYSER & MILLER FORD | AC10: KEYSER & MILLER FORD | AD10: 0127 | AE10: 127 | AF10: 120 | AG10: 8 E MAIN ST | AH10: COLLEGEVILLE | AI10: PA | AJ10: UNITED STATES | AK10: 4570060 | AL10: CRM OUTBOUND TELEPHONY TRACKING (NEW AND CONVERSION) | AM10: FRONT OFFICE | AN10: ELEAD | AO10: ELEAD OTHER | AP10: CALL TRACKING | AR10: N | AS10: 1 | AT10: 0 | AU10: 0 | AV10: 0 | AW10: 0 | AX10: 195 | AY10: 299 | AZ10: 0 | BA10: 0 | BB10: 45274 | BC10: 43848 | BD10: 2020 | BE10: 7 | BI10: N | BQ10: 43862 | BR10: 2020 | BS10: 7 | BT10: 2026 | BU10: 8 | CA10: 45273 | CB10: 2023 | CC10: 12 | CD10: 221 | CE10: CDK CONVERSION - SYS GENERATED | CF10: N | CG10: C | CH10: CDK Conversion | CI10: CV | CJ10: Conversion | CK10: G | CL10: SYS GEN | CM10: CDK | CN10: ADP
A11: 64169272SW04 | D11: AUTOMOBILE | E11: 1-2 | F11: NEW AUTO | G11: AUTO | H11: 38 | K11: N | L11: N | M11: 76062949 | O11: FREDY KIA | P11: LSS | Q11: N | U11: 0014000000JVXTMAAR | V11: FREDY KIA | W11: 208052 | X11: FREDY KIA | Y11: AUTO | Z11: 76062949 | AA11: FREDY KIA | AC11: FREDY KIA | AD11: 0125 | AE11: 125 | AF11: 120 | AG11: 11711 GULF FREEWAY | AH11: HOUSTON | AI11: TX | AJ11: UNITED STATES | AK11: 4570060 | AL11: CRM OUTBOUND TELEPHONY TRACKING (NEW AND CONVERSION) | AM11: FRONT OFFICE | AN11: ELEAD | AO11: ELEAD OTHER | AP11: CALL TRACKING | AR11: N | AS11: 1 | AT11: 0 | AU11: 0 | AV11: 0 | AW11: 0 | AX11: 195 | AY11: 1849 | AZ11: 0 | BA11: 0 | BB11: 45881 | BC11: 43848 | BD11: 2020 | BE11: 7 | BI11: N | BQ11: 43862 | BR11: 2020 | BS11: 7 | BT11: 2026 | BU11: 8 | CA11: 45869 | CB11: 2025 | CC11: 8 | CD11: 833 | CE11: Ownership Change | CF11: N | CG11: M | CH11: BACK TO MANUAL | CI11: DA | CJ11: Dropped Apps | CK11: P | CL11: PRODUCT | CM11: Manual
A12: 68216748SW01 | B12: 4570602 | C12: INTERACTIVETEL TOTAL TRACK 200+ | D12: AUTOMOBILE | E12: 1-2 | F12: NEW AUTO | G12: AUTO | H12: 1 | K12: N | L12: N | M12: 76003426 | N12: 10445 | O12: FAIR OAKS CHANTILLY CHRYSLER DODGE JEEP RAM | P12: LSS | Q12: R | S12: 68186645SW01 | U12: 0014000000JW3Q3AAJ | V12: FAIR OAKS CHANTILLY CHRYSLER JEEP DODGE RAM | W12: 25108 | X12: FAIR OAKS CHANTILLY CHRYSLER JEEP DODGE RAM | Y12: AUTO | Z12: 76003426 | AA12: FAIR OAKS CHANTILLY CHRYSLER DODGE JEEP RAM | AC12: FAIR OAKS CHANTILLY CHRYSLER DODGE JEEP RAM | AD12: 0127 | AE12: 127 | AF12: 120 | AG12: 4170 AUTO PARK CIRCLE | AH12: CHANTILLY | AI12: VA | AJ12: UNITED STATES | AK12: 4570602 | AL12: INTERACTIVETEL TOTAL TRACK 200+ | AM12: FRONT OFFICE | AN12: ELEAD | AO12: ELEAD OTHER | AP12: CALL TRACKING | AR12: N | AS12: 1 | AT12: 0 | AU12: 0 | AV12: 0 | AW12: 0 | AX12: 1995 | AY12: 1995 | AZ12: 0 | BA12: 0 | BB12: 45414 | BC12: 45274 | BD12: 2023 | BE12: 12 | BI12: N | BQ12: 45279 | BR12: 2023 | BS12: 12 | BT12: 2026 | BU12: 1 | CA12: 45412 | CB12: 2024 | CC12: 5 | CD12: 823 | CE12: Error Correction | CF12: Y | CG12: EC | CH12: ADMINISTRATIVE ADJUSTMENT | CI12: CA | CJ12: CONTRA ADD | CK12: P | CL12: PRODUCT | CM12: N/A
A13: 64226735SW01 | D13: AUTOMOBILE | E13: 1-2 | F13: NEW AUTO | G13: AUTO | H13: 6 | K13: N | L13: N | M13: 76201662 | N13: 17993 | O13: MCSWEENEY CHRYSLER DODGE JEEP RAM | P13: LSS | Q13: N | U13: 0010B00001SWNXUAAG | V13: MCSWEENEY CHRYSLER DODGE JEEP RAM | W13: 1704275 | X13: MCSWEENEY CHRYSLER DODGE JEEP RAM | Y13: AUTO | Z13: 76201662 | AA13: MCSWEENEY CHRYSLER DODGE JEEP RAM | AC13: MCSWEENEY CHRYSLER DODGE JEEP RAM | AD13: 0122 | AE13: 122 | AF13: 120 | AG13: 2605 DR. JOHN HANNES DR. | AH13: PELL CITY | AI13: AL | AJ13: UNITED STATES | AK13: 4570289 | AL13: CARWARS ELITE 12,500 PACKAGE | AM13: FRONT OFFICE | AN13: ELEAD | AO13: ELEAD OTHER | AP13: CALL TRACKING | AR13: N | AS13: 1 | AT13: 0 | AU13: 0 | AV13: 0 | AW13: 0 | AX13: 1499 | AY13: 1499 | AZ13: 8994 | BA13: 0 | BB13: 45595 | BC13: 45371 | BD13: 2024 | BE13: 3 | BI13: N | BQ13: 45390 | BR13: 2024 | BS13: 4 | BT13: 2026 | BU13: 4 | CA13: 45595 | CB13: 2024 | CC13: 10 | CD13: 844 | CE13: Dealership Downsizing | CF13: N | CG13: M | CH13: BACK TO MANUAL | CI13: DA | CJ13: Dropped Apps | CK13: P | CL13: PRODUCT | CM13: N/A
A14: 67037962SW08 | D14: AUTOMOBILE | E14: 3-5 | F14: NEW AUTO | G14: AUTO | H14: 1 | K14: N | L14: N | M14: 76055608 | N14: 11619 | O14: ROSEDALE CHEVROLET | P14: LSS | Q14: N | R14: 67046811SW01 | U14: 0014000000JVWFPAAR | V14: METROCORP | W14: 187885 | X14: ROSEDALE CHEVROLET | Y14: AUTO | Z14: 76210967 | AA14: GM IMR TURNKEY VENDOR PROGRAM | AC14: GM IMR TURNKEY VENDOR PROGRAM | AD14: 0122 | AE14: 122 | AF14: 120 | AG14: 2845 HIGHWAY 35W | AH14: ROSEVILLE | AI14: MN | AJ14: UNITED STATES | AK14: 4570383 | AL14: EL1OUTCALLTRACK (GM IMR) | AM14: FRONT OFFICE | AN14: ELEAD | AO14: ELEAD OTHER | AP14: CALL TRACKING | AR14: N | AS14: 1 | AT14: 0 | AU14: 0 | AV14: 0 | AW14: 0 | AX14: 0 | AY14: 1849 | AZ14: 11094 | BA14: 0 | BB14: 44251 | BC14: 43929 | BD14: 2020 | BE14: 10 | BI14: N | BQ14: 43965 | BR14: 2020 | BS14: 12 | BT14: 2026 | BU14: 12 | CA14: 44250 | CB14: 2021 | CC14: 8 | CD14: 221 | CE14: CDK CONVERSION - SYS GENERATED | CF14: N | CG14: C | CH14: CDK Conversion | CI14: CV | CJ14: Conversion | CK14: G | CL14: SYS GEN | CM14: CDK | CN14: ADP
A15: 68209897SW37 | B15: 4570058 | C15: CARWARS STARTER 7500 | D15: AUTOMOBILE | E15: 11+ | F15: NEW AUTO | G15: AUTO | H15: 60 | K15: N | L15: N | M15: 76228629 | N15: 7459A | O15: MIDLANDS TOYOTA | P15: LSS | Q15: R | S15: 68189336SW40 | U15: 0015A00002TK3GOAA0 | V15: HUDSON AUTOMOTIVE | W15: 196172 | X15: MIDLANDS TOYOTA | Y15: AUTO | Z15: 76228629 | AA15: MIDLANDS TOYOTA | AC15: MIDLANDS TOYOTA | AD15: 0127 | AE15: 127 | AF15: 120 | AG15: 240 KILLIAN COMMON PKWY | AH15: COLUMBIA | AI15: SC | AJ15: UNITED STATES | AK15: 4570058 | AL15: CARWARS STARTER 7500 | AM15: FRONT OFFICE | AN15: ELEAD | AO15: ELEAD OTHER | AP15: CALL TRACKING | AR15: N | AS15: 1 | AT15: 0 | AU15: 0 | AV15: 0 | AW15: 0 | AX15: 499 | AY15: 499 | AZ15: 0 | BA15: 0 | BB15: 45716 | BC15: 45091 | BD15: 2023 | BE15: 6 | BI15: N | BQ15: 45090 | BR15: 2023 | BS15: 6 | BT15: 2026 | BU15: 6 | CA15: 45716 | CB15: 2025 | CC15: 2 | CD15: 836 | CE15: Price/Value Proposition | CF15: N | CG15: M | CH15: BACK TO MANUAL | CI15: DA | CJ15: Dropped Apps | CK15: P | CL15: PRODUCT | CM15: Manual
A16: 68168556SW01 | D16: AUTOMOBILE | E16: 3-5 | F16: NEW AUTO | G16: AUTO | H16: 1 | K16: N | L16: N | M16: 76217678 | N16: 18596 | O16: BOB BELL HYUNDAI | P16: LSS | Q16: N | R16: 68228662SW12 | U16: 0014000000JW2XJAAR | V16: BOB BELL | W16: 1799131 | X16: BOB BELL HYUNDAI | Y16: AUTO | Z16: 76217678 | AA16: BOB BELL HYUNDAI | AC16: BOB BELL HYUNDAI | AD16: 0127 | AE16: 127 | AF16: 120 | AG16: 7117 RITCHIE HWY | AH16: GLEN BURNIE | AI16: MD | AJ16: UNITED STATES | AK16: 4570060 | AL16: CRM OUTBOUND TELEPHONY TRACKING (NEW AND CONVERSION) | AM16: FRONT OFFICE | AN16: ELEAD | AO16: ELEAD OTHER | AP16: CALL TRACKING | AR16: N | AS16: 1 | AT16: 0 | AU16: 0 | AV16: 0 | AW16: 0 | AX16: 195 | AY16: 1849 | AZ16: 0 | BA16: 0 | BB16: 45544 | BC16: 43922 | BD16: 2020 | BE16: 9 | BI16: N | BQ16: 43922 | BR16: 2020 | BS16: 9 | BT16: 2026 | BU16: 10 | CA16: 45535 | CB16: 2024 | CC16: 9 | CD16: 812 | CE16: CDK Conversion | CF16: N | CG16: C | CH16: CDK Conversion | CI16: CV | CJ16: Conversion | CK16: P | CL16: PRODUCT | CM16: CDK | CN16: ADP
A17: 67041955SW02 | D17: AUTOMOBILE | E17: 11+ | F17: NEW AUTO | G17: AUTO | H17: 12 | K17: N | L17: N | M17: 76215011 | N17: 23308 | O17: PIAZZA NISSAN OF ARDMORE | P17: LSS | Q17: N | R17: 68188288SW06 | U17: 0014000000JW0UHAAZ | V17: PIAZZA AUTO GROUP | W17: 71055667 | X17: PIAZZA NISSAN OF ARDMORE | Y17: AUTO | Z17: 76215011 | AA17: PIAZZA NISSAN OF ARDMORE | AC17: PIAZZA NISSAN OF ARDMORE | AD17: 0127 | AE17: 127 | AF17: 120 | AG17: 265 E LANCASTER AVE | AH17: ARDMORE | AI17: PA | AJ17: UNITED STATES | AK17: 4570009 | AL17: CARWARS STARTER 3500 | AM17: FRONT OFFICE | AN17: ELEAD | AO17: ELEAD OTHER | AP17: CALL TRACKING | AR17: N | AS17: 1 | AT17: 0 | AU17: 0 | AV17: 0 | AW17: 0 | AX17: 299 | AY17: 299 | AZ17: 3588 | BA17: 0 | BB17: 44537 | BC17: 44091 | BD17: 2021 | BE17: 3 | BI17: N | BQ17: 44118 | BR17: 2021 | BS17: 4 | BT17: 2026 | BU17: 4 | BV17: 44147 | BW17: 2021 | BX17: 5 | BY17: 2021 | BZ17: 5 | CA17: 44536 | CB17: 2022 | CC17: 6 | CD17: 221 | CE17: CDK CONVERSION - SYS GENERATED | CF17: N | CG17: C | CH17: CDK Conversion | CI17: CV | CJ17: Conversion | CK17: G | CL17: SYS GEN | CM17: CDK | CN17: ADP
A18: 64169219SW03 | D18: RECREATION | E18: Non-Auto | F18: RECREATION | G18: MOTORCYCLE | H18: 1 | K18: N | L18: N | M18: 76211956 | N18: 17155 | O18: MOBILE BAY HARLEY DAVIDSON | P18: LSS | Q18: N | U18: 0014000000MV8QAAA0 | V18: MOBILE BAY HARLEY DAVIDSON | W18: 1447686 | X18: MOBILE BAY HARLEY DAVIDSON | Y18: MOTORCYCLE | Z18: 76211956 | AA18: MOBILE BAY HARLEY DAVIDSON | AC18: MOBILE BAY HARLEY DAVIDSON | AD18: 0122 | AE18: 122 | AF18: 120 | AG18: 3260 PLEASANT VALLEY RD | AH18: MOBILE | AI18: AL | AJ18: UNITED STATES | AK18: 4570120 | AL18: CRM TELEPHONY TRACKING | AM18: FRONT OFFICE | AN18: ELEAD | AO18: ELEAD OTHER | AP18: CALL TRACKING | AR18: N | AS18: 1 | AT18: 0 | AU18: 0 | AV18: 0 | AW18: 0 | AX18: 100 | AY18: 70 | AZ18: 0 | BA18: 0 | BB18: 45036 | BC18: 43848 | BD18: 2020 | BE18: 7 | BI18: N | BQ18: 43862 | BR18: 2020 | BS18: 7 | BT18: 2026 | BU18: 8 | CA18: 45036 | CB18: 2023 | CC18: 4 | CD18: 827 | CE18: Low or No Utilization | CF18: N | CG18: M | CH18: BACK TO MANUAL | CI18: DA | CJ18: Dropped Apps | CK18: P | CL18: PRODUCT | CM18: N/A
A19: 64226735SW02 | D19: AUTOMOBILE | E19: 1-2 | F19: NEW AUTO | G19: AUTO | H19: 6 | K19: N | L19: N | M19: 76201662 | N19: 17993 | O19: MCSWEENEY CHRYSLER DODGE JEEP RAM | P19: LSS | Q19: N | U19: 0010B00001SWNXUAAG | V19: MCSWEENEY CHRYSLER DODGE JEEP RAM | W19: 1704275 | X19: MCSWEENEY CHRYSLER DODGE JEEP RAM | Y19: AUTO | Z19: 76201662 | AA19: MCSWEENEY CHRYSLER DODGE JEEP RAM | AC19: MCSWEENEY CHRYSLER DODGE JEEP RAM | AD19: 0122 | AE19: 122 | AF19: 120 | AG19: 2605 DR. JOHN HANNES DR. | AH19: PELL CITY | AI19: AL | AJ19: UNITED STATES | AK19: 4570123 | AL19: CARWARS ADVANCED SERVICE | AM19: FRONT OFFICE | AN19: ELEAD | AO19: ELEAD OTHER | AP19: CALL TRACKING | AR19: N | AS19: 1 | AT19: 0 | AU19: 0 | AV19: 0 | AW19: 0 | AX19: 999 | AY19: 999 | AZ19: 5994 | BA19: 0 | BB19: 45595 | BC19: 45371 | BD19: 2024 | BE19: 3 | BI19: N | BQ19: 45390 | BR19: 2024 | BS19: 4 | BT19: 2026 | BU19: 4 | CA19: 45595 | CB19: 2024 | CC19: 10 | CD19: 844 | CE19: Dealership Downsizing | CF19: N | CG19: M | CH19: BACK TO MANUAL | CI19: DA | CJ19: Dropped Apps | CK19: P | CL19: PRODUCT | CM19: N/A
A20: 64226787SW02 | D20: AUTOMOBILE | E20: 6-10 | F20: NEW AUTO | G20: AUTO | H20: 12 | K20: N | L20: N | M20: 76220529 | O20: GALEANA CHRYSLER DODGE JEEP RAM OF FORT MYERS | P20: LSS | Q20: N | R20: 64243030SW25 | U20: 0014000000JWA15AAF | V20: GALEANA AUTOMOTIVE GROUP | W20: 1361687 | X20: GALEANA CHRYSLER DODGE JEEP RAM OF FORT MYERS | Y20: AUTO | Z20: 76220529 | AA20: GALEANA CHRYSLER DODGE JEEP RAM OF FORT MYERS | AC20: GALEANA CHRYSLER DODGE JEEP RAM OF FORT MYERS | AD20: 0122 | AE20: 122 | AF20: 120 | AG20: 14375 S TAMIAMI TRAIL | AH20: FORT MYERS | AI20: FL | AJ20: UNITED STATES | AK20: 4571029 | AL20: CARWARS ADDITIONAL BLOCK MINUTES | AM20: FRONT OFFICE | AN20: ELEAD | AO20: ELEAD OTHER | AP20: CALL TRACKING | AR20: N | AS20: 1 | AT20: 0 | AU20: 0 | AV20: 0 | AW20: 0 | AX20: 999 | AY20: 999 | AZ20: 11988 | BA20: 0 | BB20: 45925 | BC20: 45373 | BD20: 2024 | BE20: 3 | BI20: N | BQ20: 45400 | BR20: 2024 | BS20: 4 | BT20: 2026 | BU20: 5 | BV20: 45400 | BW20: 2024 | BX20: 4 | BY20: 2024 | BZ20: 5 | CA20: 45924 | CB20: 2025 | CC20: 9 | CD20: 221 | CE20: CDK CONVERSION - SYS GENERATED | CF20: N | CG20: C | CH20: CDK Conversion | CI20: CV | CJ20: Conversion | CK20: G | CL20: SYS GEN | CM20: CDK | CN20: ADP
A21: 68189336SW40 | B21: 4570058 | C21: CARWARS STARTER 7500 | D21: AUTOMOBILE | E21: 11+ | F21: NEW AUTO | G21: AUTO | H21: 60 | K21: N | L21: N | M21: 76228629 | N21: 7459A | O21: MIDLANDS TOYOTA | P21: LSS | Q21: R | R21: 68209897SW37 | S21: 68187007SW14 | U21: 0015A00002TK3GOAA0 | V21: HUDSON AUTOMOTIVE | W21: 196172 | X21: MIDLANDS TOYOTA | Y21: AUTO | Z21: 76217276 | AA21: WYATT-JOHNSON BUICK GMC | AC21: WYATT-JOHNSON BUICK GMC | AD21: 0127 | AE21: 127 | AF21: 120 | AG21: 240 KILLIAN COMMON PKWY | AH21: COLUMBIA | AI21: SC | AJ21: UNITED STATES | AK21: 4570058 | AL21: CARWARS STARTER 7500 | AM21: FRONT OFFICE | AN21: ELEAD | AO21: ELEAD OTHER | AP21: CALL TRACKING | AR21: N | AS21: 1 | AT21: 0 | AU21: 0 | AV21: 0 | AW21: 0 | AX21: 499 | AY21: 499 | AZ21: 0 | BA21: 0 | BB21: 45098 | BC21: 44566 | BD21: 2022 | BE21: 6 | BI21: N | BQ21: 44586 | BR21: 2022 | BS21: 7 | BT21: 2026 | BU21: 8 | CA21: 45089 | CB21: 2023 | CC21: 6 | CD21: 221 | CE21: CDK CONVERSION - SYS GENERATED | CF21: N | CG21: C | CH21: CDK Conversion | CI21: CV | CJ21: Conversion | CK21: G | CL21: SYS GEN | CM21: CDK | CN21: ADP
A22: 64231666SW01 | B22: 4570062 | C22: CARWARS PREMIUM SALES | D22: AUTOMOBILE | E22: 3-5 | F22: NEW AUTO | G22: AUTO | H22: 12 | K22: N | L22: N | M22: 76211594 | N22: 10786 | O22: LOKEY NISSAN | P22: LSS | Q22: C | S22: 64193165SW01 | U22: 0014000000M6G8KAAB | V22: PAUL LOKEY | W22: 01156105 | X22: LOKEY NISSAN | Y22: AUTO | Z22: 76211594 | AA22: LOKEY NISSAN | AC22: LOKEY NISSAN | AD22: 0122 | AE22: 122 | AF22: 120 | AG22: 27758 US HIGHWAY 19 N | AH22: CLEARWATER | AI22: FL | AJ22: UNITED STATES | AK22: 4571030 | AL22: CARWARS STARTER 5000 | AM22: FRONT OFFICE | AN22: ELEAD | AO22: ELEAD OTHER | AP22: CALL TRACKING | AR22: N | AS22: 1 | AT22: 0 | AU22: 0 | AV22: 0 | AW22: 0 | AX22: 599 | AY22: 599 | AZ22: 0 | BA22: 0 | BB22: 45688 | BC22: 45541 | BD22: 2024 | BE22: 9 | BI22: N | BQ22: 45545 | BR22: 2024 | BS22: 9 | BT22: 2026 | BU22: 9 | CA22: 45688 | CB22: 2025 | CC22: 1 | CD22: 827 | CE22: Low or No Utilization | CF22: N | CG22: M | CH22: BACK TO MANUAL | CI22: DA | CJ22: Dropped Apps | CK22: P | CL22: PRODUCT | CM22: N/A
A23: 64231666SW02 | D23: AUTOMOBILE | E23: 3-5 | F23: NEW AUTO | G23: AUTO | H23: 12 | K23: N | L23: N | M23: 76211594 | N23: 10786 | O23: LOKEY NISSAN | P23: LSS | Q23: N | U23: 0014000000M6G8KAAB | V23: PAUL LOKEY | W23: 01156105 | X23: LOKEY NISSAN | Y23: AUTO | Z23: 76211594 | AA23: LOKEY NISSAN | AC23: LOKEY NISSAN | AD23: 0122 | AE23: 122 | AF23: 120 | AG23: 27758 US HIGHWAY 19 N | AH23: CLEARWATER | AI23: FL | AJ23: UNITED STATES | AK23: 4571030 | AL23: CARWARS STARTER 5000 | AM23: FRONT OFFICE | AN23: ELEAD | AO23: ELEAD OTHER | AP23: CALL TRACKING | AR23: N | AS23: 1 | AT23: 0 | AU23: 0 | AV23: 0 | AW23: 0 | AX23: 599 | AY23: 599 | AZ23: 7188 | BA23: 0 | BB23: 45688 | BC23: 45541 | BD23: 2024 | BE23: 9 | BI23: N | BQ23: 45545 | BR23: 2024 | BS23: 9 | BT23: 2026 | BU23: 9 | CA23: 45688 | CB23: 2025 | CC23: 1 | CD23: 827 | CE23: Low or No Utilization | CF23: N | CG23: M | CH23: BACK TO MANUAL | CI23: DA | CJ23: Dropped Apps | CK23: P | CL23: PRODUCT | CM23: N/A
A24: 64233126SW78 | D24: AUTOMOBILE | E24: 11+ | F24: NEW AUTO | G24: AUTO | H24: 60 | J24: 76200288 | K24: N | L24: N | M24: 76200288 | O24: AUDI JACKSONVILLE | P24: INS | Q24: N | U24: 0014000000JW9X1AAB | V24: JACK HANANIA | W24: 1695755 | X24: AUDI JACKSONVILLE | Y24: AUTO | Z24: 76230871 | AA24: HANANIA AUTO | AC24: HANANIA AUTO | AD24: 0122 | AE24: 122 | AF24: 120 | AG24: 11401 ATLANTIC BLVD | AH24: JACKSONVILLE | AI24: FL | AJ24: UNITED STATES | AK24: 4571049 | AL24: CALLREVU GROWTH 15K | AM24: FRONT OFFICE | AN24: ELEAD | AO24: ELEAD OTHER | AP24: CALL TRACKING | AR24: N | AS24: 1 | AT24: 0 | AU24: 0 | AV24: 0 | AW24: 0 | AX24: 1199 | AY24: 1199 | AZ24: 14388 | BA24: 0 | BB24: 45701 | BC24: 45588 | BD24: 2024 | BE24: 10 | BI24: N | BQ24: 45701 | BR24: 2025 | BS24: 2 | BT24: 2026 | BU24: 3
A25: 64168877SW02 | D25: RECREATION | E25: Non-Auto | F25: RECREATION | G25: MOTORCYCLE | H25: 1 | K25: N | L25: N | M25: 76211939 | N25: 4545 | O25: MOONSHINE HARLEY DAVIDSON | P25: LSS | Q25: N | U25: 0014000000MV3SUAAK | V25: MOONSHINE HARLEY-DAVIDSON | W25: 1443259 | X25: MOONSHINE HARLEY-DAVIDSON | Y25: MOTORCYCLE | Z25: 76211939 | AA25: MOONSHINE HARLEY DAVIDSON | AC25: MOONSHINE HARLEY DAVIDSON | AD25: 0122 | AE25: 122 | AF25: 120 | AG25: 7128 SOUTH SPRINGS DR | AH25: FRANKLIN | AI25: TN | AJ25: UNITED STATES | AK25: 4570060 | AL25: CRM OUTBOUND TELEPHONY TRACKING (NEW AND CONVERSION) | AM25: FRONT OFFICE | AN25: ELEAD | AO25: ELEAD OTHER | AP25: CALL TRACKING | AR25: N | AS25: 1 | AT25: 0 | AU25: 0 | AV25: 0 | AW25: 0 | AX25: 195 | AY25: 499 | AZ25: 0 | BA25: 0 | BB25: 45036 | BC25: 43848 | BD25: 2020 | BE25: 7 | BI25: N | BQ25: 43862 | BR25: 2020 | BS25: 7 | BT25: 2026 | BU25: 8 | CA25: 45036 | CB25: 2023 | CC25: 4 | CD25: 827 | CE25: Low or No Utilization | CF25: N | CG25: M | CH25: BACK TO MANUAL | CI25: DA | CJ25: Dropped Apps | CK25: P | CL25: PRODUCT | CM25: N/A
A26: 68228662SW12 | B26: 4570060 | C26: CRM OUTBOUND TELEPHONY TRACKING (NEW AND CONVERSION) | D26: AUTOMOBILE | E26: 3-5 | F26: NEW AUTO | G26: AUTO | H26: 66 | K26: N | L26: N | M26: 76217678 | N26: 18596 | O26: BOB BELL HYUNDAI | P26: LSS | Q26: C | R26: 68243199SW02 | S26: 68168556SW01 | U26: 0014000000JW2XJAAR | V26: BOB BELL | W26: 1799131 | X26: BOB BELL HYUNDAI | Y26: AUTO | Z26: 76217678 | AA26: BOB BELL HYUNDAI | AC26: BOB BELL HYUNDAI | AD26: 0127 | AE26: 127 | AF26: 120 | AG26: 7117 RITCHIE HWY | AH26: GLEN BURNIE | AI26: MD | AJ26: UNITED STATES | AK26: 4570062 | AL26: CARWARS PREMIUM SALES | AM26: FRONT OFFICE | AN26: ELEAD | AO26: ELEAD OTHER | AP26: CALL TRACKING | AR26: N | AS26: 1 | AT26: 0 | AU26: 0 | AV26: 0 | AW26: 0 | AX26: 1849 | AY26: 1849 | AZ26: -3811.92 | BA26: 0 | BB26: 45915 | BC26: 45530 | BD26: 2024 | BE26: 8 | BI26: N | BQ26: 45566 | BR26: 2024 | BS26: 10 | BT26: 2026 | BU26: 10 | CA26: 45914 | CB26: 2025 | CC26: 9 | CD26: 221 | CE26: CDK CONVERSION - SYS GENERATED | CF26: N | CG26: C | CH26: CDK Conversion | CI26: CV | CJ26: Conversion | CK26: G | CL26: SYS GEN | CM26: CDK | CN26: ADP
A27: 64226788SW02 | D27: AUTOMOBILE | E27: 6-10 | F27: NEW AUTO | G27: AUTO | H27: 12 | K27: N | L27: N | M27: 76220548 | O27: GALEANA KIA OF FORT MYERS | P27: LSS | Q27: N | R27: 64243030SW21 | U27: 0014000000JWA15AAF | V27: GALEANA AUTOMOTIVE GROUP | W27: 186155 | X27: GALEANA KIA OF FORT MYERS | Y27: AUTO | Z27: 76220548 | AA27: GALEANA KIA OF FORT MYERS | AC27: GALEANA KIA OF FORT MYERS | AD27: 0122 | AE27: 122 | AF27: 120 | AG27: 14483 S TAMIAMI TRL | AH27: FORT MYERS | AI27: FL | AJ27: UNITED STATES | AK27: 4571029 | AL27: CARWARS ADDITIONAL BLOCK MINUTES | AM27: FRONT OFFICE | AN27: ELEAD | AO27: ELEAD OTHER | AP27: CALL TRACKING | AR27: N | AS27: 1 | AT27: 0 | AU27: 0 | AV27: 0 | AW27: 0 | AX27: 999 | AY27: 999 | AZ27: 11988 | BA27: 0 | BB27: 45925 | BC27: 45373 | BD27: 2024 | BE27: 3 | BI27: N | BQ27: 45400 | BR27: 2024 | BS27: 4 | BT27: 2026 | BU27: 5 | BV27: 45400 | BW27: 2024 | BX27: 4 | BY27: 2024 | BZ27: 5 | CA27: 45924 | CB27: 2025 | CC27: 9 | CD27: 221 | CE27: CDK CONVERSION - SYS GENERATED | CF27: N | CG27: C | CH27: CDK Conversion | CI27: CV | CJ27: Conversion | CK27: G | CL27: SYS GEN | CM27: CDK | CN27: ADP
A28: 68172164SW40 | D28: AUTOMOBILE | E28: 6-10 | F28: NEW AUTO | G28: AUTO | H28: 60 | K28: N | L28: N | M28: 76049589 | N28: 18076 | O28: KING KIA | P28: LSS | Q28: N | U28: 0015A00003EKE0EAAX | V28: KING AUTO GROUP | W28: 70397813 | X28: KING KIA | Y28: AUTO | Z28: 76049589 | AA28: KING KIA | AC28: KING KIA | AD28: 0127 | AE28: 127 | AF28: 120 | AG28: 953 N FREDERICK AVE | AH28: GAITHERSBURG | AI28: MD | AJ28: UNITED STATES | AK28: 4570009 | AL28: CARWARS STARTER 3500 | AM28: FRONT OFFICE | AN28: ELEAD | AO28: ELEAD OTHER | AP28: CALL TRACKING | AR28: N | AS28: 1 | AT28: 0 | AU28: 0 | AV28: 0 | AW28: 0 | AX28: 299 | AY28: 299 | AZ28: 3588 | BA28: 0 | BB28: 45789 | BC28: 44033 | BD28: 2021 | BE28: 1 | BI28: N | BQ28: 44013 | BR28: 2021 | BS28: 1 | BT28: 2026 | BU28: 1 | CA28: 45777 | CB28: 2025 | CC28: 5 | CD28: 836 | CE28: Price/Value Proposition | CF28: N | CG28: M | CH28: BACK TO MANUAL | CI28: DA | CJ28: Dropped Apps | CK28: P | CL28: PRODUCT | CM28: Manual
A29: 38103593SW02 | B29: 4570120 | C29: CRM TELEPHONY TRACKING | D29: RECREATION | E29: Non-Auto | F29: RECREATION | G29: MOTORCYCLE | H29: 1 | K29: N | L29: N | M29: 76212580 | N29: 9973 | O29: EMERALD COAST HARLEY-DAVIDSON | P29: LSS | Q29: C | S29: 38095572SW02 | U29: 0010B00002DHZOWAA1 | V29: EMERALD COAST HARLEY-DAVIDSON | W29: 1733397 | X29: EMERALD COAST HARLEY-DAVIDSON | Y29: MOTORCYCLE | Z29: 76212580 | AA29: EMERALD COAST HARLEY-DAVIDSON | AC29: EMERALD COAST HARLEY-DAVIDSON | AD29: 0122 | AE29: 122 | AF29: 120 | AG29: 788 BEAL PKWY NW | AH29: FORT WALTON BEACH | AI29: FL | AJ29: UNITED STATES | AK29: 4570009 | AL29: CARWARS STARTER 3500 | AM29: FRONT OFFICE | AN29: ELEAD | AO29: ELEAD OTHER | AP29: CALL TRACKING | AR29: N | AS29: 1 | AT29: 0 | AU29: 0 | AV29: 0 | AW29: 0 | AX29: 299 | AY29: 299 | AZ29: 1374 | BA29: 0 | BB29: 44329 | BC29: 44161 | BD29: 2021 | BE29: 5 | BI29: N | BQ29: 44239 | BR29: 2021 | BS29: 8 | BT29: 2026 | BU29: 9 | CA29: 44316 | CB29: 2021 | CC29: 11 | CD29: 836 | CE29: Price/Value Proposition | CF29: N | CG29: M | CH29: BACK TO MANUAL | CI29: DA | CJ29: Dropped Apps | CK29: P | CL29: PRODUCT | CM29: Manual
A30: 68193749SW02 | B30: 4570060 | C30: CRM OUTBOUND TELEPHONY TRACKING (NEW AND CONVERSION) | D30: AUTOMOBILE | E30: 11+ | F30: NEW AUTO | G30: AUTO | H30: 1 | K30: N | L30: N | M30: 76143222 | N30: 17223 | O30: BAKER BUICK GMC CADILLAC | P30: LSS | Q30: C | S30: 68164176SW02 | U30: 0014000000JW330AAB | V30: TOMMY BAKER | W30: 102187 | X30: BAKER BUICK GMC CADILLAC | Y30: AUTO | Z30: 76143222 | AA30: BAKER BUICK GMC CADILLAC | AC30: BAKER BUICK GMC CADILLAC | AD30: 0127 | AE30: 127 | AF30: 120 | AG30: 1621 SAVANNAH HIGHWAY | AH30: CHARLESTON | AI30: SC | AJ30: UNITED STATES | AK30: 4570060 | AL30: CRM OUTBOUND TELEPHONY TRACKING (NEW AND CONVERSION) | AM30: FRONT OFFICE | AN30: ELEAD | AO30: ELEAD OTHER | AP30: CALL TRACKING | AR30: N | AS30: 1 | AT30: 0 | AU30: 0 | AV30: 0 | AW30: 0 | AX30: 195 | AY30: 1849 | AZ30: 0 | BA30: 0 | BB30: 45810 | BC30: 44705 | BD30: 2022 | BE30: 11 | BI30: N | BQ30: 44707 | BR30: 2022 | BS30: 11 | BT30: 2026 | BU30: 12 | CA30: 45808 | CB30: 2025 | CC30: 5 | CD30: 812 | CE30: CDK Conversion | CF30: N | CG30: C | CH30: CDK Conversion | CI30: CV | CJ30: Conversion | CK30: P | CL30: PRODUCT | CM30: CDK | CN30: ADP
A31: 64226787SW01 | B31: 4570122 | C31: CARWARS ADVANCED SALES | D31: AUTOMOBILE | E31: 6-10 | F31: NEW AUTO | G31: AUTO | H31: 12 | K31: N | L31: N | M31: 76220529 | O31: GALEANA CHRYSLER DODGE JEEP RAM OF FORT MYERS | P31: LSS | Q31: C | R31: 64243030SW24 | S31: 68182618SW01 | U31: 0014000000JWA15AAF | V31: GALEANA AUTOMOTIVE GROUP | W31: 1361687 | X31: GALEANA CHRYSLER DODGE JEEP RAM OF FORT MYERS | Y31: AUTO | Z31: 76220529 | AA31: GALEANA CHRYSLER DODGE JEEP RAM OF FORT MYERS | AC31: GALEANA CHRYSLER DODGE JEEP RAM OF FORT MYERS | AD31: 0122 | AE31: 122 | AF31: 120 | AG31: 14375 S TAMIAMI TRAIL | AH31: FORT MYERS | AI31: FL | AJ31: UNITED STATES | AK31: 4570289 | AL31: CARWARS ELITE 12,500 PACKAGE | AM31: FRONT OFFICE | AN31: ELEAD | AO31: ELEAD OTHER | AP31: CALL TRACKING | AR31: N | AS31: 1 | AT31: 0 | AU31: 0 | AV31: 0 | AW31: 0 | AX31: 1499 | AY31: 1499 | AZ31: 6000 | BA31: 0 | BB31: 45925 | BC31: 45373 | BD31: 2024 | BE31: 3 | BI31: N | BQ31: 45400 | BR31: 2024 | BS31: 4 | BT31: 2026 | BU31: 5 | BV31: 45400 | BW31: 2024 | BX31: 4 | BY31: 2024 | BZ31: 5 | CA31: 45924 | CB31: 2025 | CC31: 9 | CD31: 221 | CE31: CDK CONVERSION - SYS GENERATED | CF31: N | CG31: C | CH31: CDK Conversion | CI31: CV | CJ31: Conversion | CK31: G | CL31: SYS GEN | CM31: CDK | CN31: ADP
A32: 68199331SW01 | D32: AUTOMOBILE | E32: 6-10 | F32: NEW AUTO | G32: AUTO | H32: 12 | K32: N | L32: N | M32: 76171765 | O32: RENALDO KIA | P32: LSS | Q32: N | R32: 68243830SW17 | U32: 0014000000JW9Y1AAB | V32: DONALD AUTOMOTIVE GROUP | W32: 71053228 | X32: RENALDO KIA | Y32: AUTO | Z32: 76171765 | AA32: RENALDO KIA | AC32: RENALDO KIA | AD32: 0127 | AE32: 127 | AF32: 120 | AG32: 4425 E DIXON BLVD | AH32: SHELBY | AI32: NC | AJ32: UNITED STATES | AK32: 4570058 | AL32: CARWARS STARTER 7500 | AM32: FRONT OFFICE | AN32: ELEAD | AO32: ELEAD OTHER | AP32: CALL TRACKING | AR32: N | AS32: 1 | AT32: 0 | AU32: 0 | AV32: 0 | AW32: 0 | AX32: 499 | AY32: 499 | AZ32: 5988 | BA32: 0 | BB32: 45932 | BC32: 44869 | BD32: 2022 | BE32: 17 | BI32: N | BQ32: 44958 | BR32: 2023 | BS32: 2 | BT32: 2026 | BU32: 2 | BV32: 44958 | BW32: 2023 | BX32: 1 | BY32: 2023 | BZ32: 2 | CA32: 45930 | CB32: 2025 | CC32: 10 | CD32: 221 | CE32: CDK CONVERSION - SYS GENERATED | CF32: N | CG32: C | CH32: CDK Conversion | CI32: CV | CJ32: Conversion | CK32: G | CL32: SYS GEN | CM32: CDK | CN32: ADP
A33: 68228477SW22 | D33: AUTOMOBILE | E33: 3-5 | F33: NEW AUTO | G33: AUTO | H33: 66 | K33: Y | L33: N | M33: 25181201 | N33: 18577 | O33: BOB BELL FORD | P33: ANS | Q33: N | U33: 0014000000JW2XJAAR | V33: BOB BELL | W33: 25181201 | X33: BOB BELL FORD | Y33: AUTO | Z33: 25181201 | AA33: BOB BELL FORD | AC33: BOB BELL FORD | AD33: 0127 | AE33: 127 | AF33: 120 | AG33: 7125 RITCHIE HWY | AH33: GLEN BURNIE | AI33: MD | AJ33: UNITED STATES | AK33: 4570062 | AL33: CARWARS PREMIUM SALES | AM33: FRONT OFFICE | AN33: ELEAD | AO33: ELEAD OTHER | AP33: CALL TRACKING | AR33: N | AS33: 1 | AT33: 0 | AU33: 0 | AV33: 0 | AW33: 0 | AX33: 1849 | AY33: 1849 | AZ33: 22188 | BA33: 4 | BB33: 45526.545 | BC33: 45525 | BD33: 2024 | BE33: 8 | BF33: 45526 | BG33: 2024 | BH33: 8 | BI33: N | CD33: 823 | CE33: Error Correction | CF33: Y | CG33: EC | CH33: ADMINISTRATIVE ADJUSTMENT | CI33: CA | CJ33: CONTRA ADD | CK33: S | CL33: SITE | CM33: N/A
A34: 68244081SW18 | B34: 4570009 | C34: CARWARS STARTER 3500 | D34: AUTOMOBILE | E34: 1-2 | F34: NEW AUTO | G34: AUTO | H34: 24 | J34: 08320047 | K34: Y | L34: N | M34: 08320047 | N34: 8230 | O34: CELLA FORD | P34: INS | Q34: C | S34: 68172588SW01 | U34: 0014000000JW305AAB | V34: CELLA FORD | W34: 10123709 | X34: CELLA FORD | Y34: AUTO | Z34: 08320047 | AA34: CELLA FORD | AC34: CELLA FORD | AD34: 0127 | AE34: 127 | AF34: 120 | AG34: 3210 DR M L KING JR BLVD | AH34: NEW BERN | AI34: NC | AJ34: UNITED STATES | AK34: 4571030 | AL34: CARWARS STARTER 5000 | AM34: FRONT OFFICE | AN34: ELEAD | AO34: ELEAD OTHER | AP34: CALL TRACKING | AR34: N | AS34: 1 | AT34: 0 | AU34: 0 | AV34: 0 | AW34: 0 | AX34: 599 | AY34: 599 | AZ34: 4519.2 | BA34: 0 | BB34: 45980 | BC34: 45931 | BD34: 2025 | BE34: 9 | BI34: N | BQ34: 45980 | BR34: 2025 | BS34: 11 | BT34: 2026 | BU34: 12 | BV34: 45980 | BW34: 2025 | BX34: 11 | BY34: 2025 | BZ34: 12
A35: 64169289SW03 | D35: RECREATION | E35: Non-Auto | F35: RECREATION | G35: MOTORCYCLE | H35: 1 | K35: N | L35: N | M35: 76211900 | N35: 4548 | O35: NEW ORLEANS HARLEY-DAVIDSON | P35: LSS | Q35: N | U35: 0014000000MV2TKAA0 | V35: NEW ORLEANS HARLEY-DAVIDSON | W35: 1441908 | X35: NEW ORLEANS HARLEY-DAVIDSON | Y35: MOTORCYCLE | Z35: 76211900 | AA35: NEW ORLEANS HARLEY-DAVIDSON | AC35: NEW ORLEANS HARLEY-DAVIDSON | AD35: 0122 | AE35: 122 | AF35: 120 | AG35: 6015 AIRLINE DRIVE | AH35: METAIRIE | AI35: LA | AJ35: UNITED STATES | AK35: 4570120 | AL35: CRM TELEPHONY TRACKING | AM35: FRONT OFFICE | AN35: ELEAD | AO35: ELEAD OTHER | AP35: CALL TRACKING | AR35: N | AS35: 1 | AT35: 0 | AU35: 0 | AV35: 0 | AW35: 0 | AX35: 100 | AY35: 70 | AZ35: 0 | BA35: 0 | BB35: 45036 | BC35: 43848 | BD35: 2020 | BE35: 7 | BI35: N | BQ35: 43862 | BR35: 2020 | BS35: 7 | BT35: 2026 | BU35: 8 | CA35: 45036 | CB35: 2023 | CC35: 4 | CD35: 827 | CE35: Low or No Utilization | CF35: N | CG35: M | CH35: BACK TO MANUAL | CI35: DA | CJ35: Dropped Apps | CK35: P | CL35: PRODUCT | CM35: N/A
A36: 64188763SW01 | D36: AUTOMOBILE | E36: 11+ | F36: NEW AUTO | G36: AUTO | H36: 12 | K36: N | L36: N | M36: 76177675 | N36: 15230 | O36: COCONUT POINT HONDA | P36: LSS | Q36: N | R36: 64233126SW75 | U36: 0014000000JW9X1AAB | V36: JACK HANANIA | W36: 1581742 | X36: COCONUT POINT HONDA | Y36: AUTO | Z36: 76230871 | AA36: HANANIA AUTO | AC36: COCONUT POINT HONDA | AD36: 0122 | AE36: 122 | AF36: 120 | AG36: 22240 S. TAMIAMI TRAIL | AH36: ESTERO | AI36: FL | AJ36: UNITED STATES | AK36: 4570289 | AL36: CARWARS ELITE 12,500 PACKAGE | AM36: FRONT OFFICE | AN36: ELEAD | AO36: ELEAD OTHER | AP36: CALL TRACKING | AR36: N | AS36: 1 | AT36: 0 | AU36: 0 | AV36: 0 | AW36: 0 | AX36: 1499 | AY36: 1499 | AZ36: 17988 | BA36: 0 | BB36: 45714 | BC36: 44377 | BD36: 2021 | BE36: 12 | BI36: N | BQ36: 44461 | BR36: 2022 | BS36: 3 | BT36: 2026 | BU36: 4 | BV36: 44456 | BW36: 2022 | BX36: 3 | BY36: 2022 | BZ36: 4 | CA36: 45713 | CB36: 2025 | CC36: 2 | CD36: 221 | CE36: CDK CONVERSION - SYS GENERATED | CF36: N | CG36: C | CH36: CDK Conversion | CI36: CV | CJ36: Conversion | CK36: G | CL36: SYS GEN | CM36: CDK | CN36: ADP
A37: 64192511SW08 | B37: 4570009 | C37: CARWARS STARTER 3500 | D37: AUTOMOBILE | E37: 6-10 | F37: USED AUTO | G37: USED VEHICLE | H37: 60 | K37: N | L37: N | M37: 76224283 | N37: 25433 | O37: UNION AUTO GRUPO USADOS | P37: LSS | Q37: R | S37: 64185402SW02 | U37: 0015A00002ZONADAAK | V37: UNION AUTO GROUP | W37: 1839493 | X37: UNION AUTO GROUP | Y37: USED VEHICLE | Z37: 76224283 | AA37: UNION AUTO GRUPO USADOS | AC37: UNION AUTO GRUPO USADOS | AD37: 0122 | AE37: 122 | AF37: 120 | AG37: 867 AVE LUIS MUNOZ RIVERA | AH37: SAN JUAN | AI37: PR | AJ37: UNITED STATES | AK37: 4570009 | AL37: CARWARS STARTER 3500 | AM37: FRONT OFFICE | AN37: ELEAD | AO37: ELEAD OTHER | AP37: CALL TRACKING | AR37: N | AS37: 1 | AT37: 0 | AU37: 0 | AV37: 0 | AW37: 0 | AX37: 299 | AY37: 262 | AZ37: 0 | BA37: 0 | BB37: 45881 | BC37: 44524 | BD37: 2022 | BE37: 5 | BI37: N | BQ37: 44531 | BR37: 2022 | BS37: 5 | BT37: 2026 | BU37: 6 | BV37: 44531 | BW37: 2022 | BX37: 5 | BY37: 2022 | BZ37: 6 | CA37: 45869 | CB37: 2025 | CC37: 8 | CD37: 812 | CE37: CDK Conversion | CF37: N | CG37: C | CH37: CDK Conversion | CI37: CV | CJ37: Conversion | CK37: P | CL37: PRODUCT | CM37: CDK | CN37: ADP
A38: 68164391SW06 | D38: AUTOMOBILE | E38: 3-5 | F38: NEW AUTO | G38: AUTO | H38: 1 | K38: N | L38: N | M38: 76193826 | N38: 17563 | O38: GRAINGER NISSAN OF BEAUFORT | P38: LSS | Q38: N | U38: 0014000000JW3AMAAR | V38: GRAINGER | W38: 1661251 | X38: GRAINGER NISSAN OF BEAUFORT | Y38: AUTO | Z38: 76193826 | AA38: GRAINGER NISSAN OF BEAUFORT | AC38: GRAINGER NISSAN OF BEAUFORT | AD38: 0127 | AE38: 127 | AF38: 120 | AG38: 219 ROBERT SMALLS PARKWAY | AH38: BEAUFORT | AI38: SC | AJ38: UNITED STATES | AK38: 4570060 | AL38: CRM OUTBOUND TELEPHONY TRACKING (NEW AND CONVERSION) | AM38: FRONT OFFICE | AN38: ELEAD | AO38: ELEAD OTHER | AP38: CALL TRACKING | AR38: N | AS38: 1 | AT38: 0 | AU38: 0 | AV38: 0 | AW38: 0 | AX38: 195 | AY38: 995 | AZ38: 0 | BA38: 0 | BB38: 44074 | BC38: 43849 | BD38: 2020 | BE38: 7 | BI38: N | BQ38: 43862 | BR38: 2020 | BS38: 7 | BT38: 2026 | BU38: 8 | CA38: 44074 | CB38: 2021 | CC38: 2 | CD38: 823 | CE38: Error Correction | CF38: Y | CG38: EC | CH38: ADMINISTRATIVE ADJUSTMENT | CI38: CA | CJ38: CONTRA ADD | CK38: P | CL38: PRODUCT | CM38: N/A
A39: 64169289SW04 | D39: RECREATION | E39: Non-Auto | F39: RECREATION | G39: MOTORCYCLE | H39: 1 | K39: N | L39: N | M39: 76211900 | N39: 4548 | O39: NEW ORLEANS HARLEY-DAVIDSON | P39: LSS | Q39: N | R39: 64238640SW03 | U39: 0014000000MV2TKAA0 | V39: NEW ORLEANS HARLEY-DAVIDSON | W39: 1441908 | X39: NEW ORLEANS HARLEY-DAVIDSON | Y39: MOTORCYCLE | Z39: 76211900 | AA39: NEW ORLEANS HARLEY-DAVIDSON | AC39: NEW ORLEANS HARLEY-DAVIDSON | AD39: 0122 | AE39: 122 | AF39: 120 | AG39: 6015 AIRLINE DRIVE | AH39: METAIRIE | AI39: LA | AJ39: UNITED STATES | AK39: 4570060 | AL39: CRM OUTBOUND TELEPHONY TRACKING (NEW AND CONVERSION) | AM39: FRONT OFFICE | AN39: ELEAD | AO39: ELEAD OTHER | AP39: CALL TRACKING | AR39: N | AS39: 1 | AT39: 0 | AU39: 0 | AV39: 0 | AW39: 0 | AX39: 195 | AY39: 199 | AZ39: 0 | BA39: 0 | BB39: 45778 | BC39: 43848 | BD39: 2020 | BE39: 7 | BI39: N | BQ39: 43862 | BR39: 2020 | BS39: 7 | BT39: 2026 | BU39: 8 | CA39: 45777 | CB39: 2025 | CC39: 4 | CD39: 221 | CE39: CDK CONVERSION - SYS GENERATED | CF39: N | CG39: C | CH39: CDK Conversion | CI39: CV | CJ39: Conversion | CK39: G | CL39: SYS GEN | CM39: CDK | CN39: ADP
A40: 67037594SW02 | D40: AUTOMOBILE | E40: 11+ | F40: NEW AUTO | G40: AUTO | H40: 1 | K40: N | L40: N | M40: 76066612 | N40: 15952 | O40: ZIMBRICK ACURA OF BROOKFIELD | P40: LSS | Q40: N | U40: 0014000000JVW6GAAB | V40: ZIMBRICK | W40: 1361883 | X40: ACURA OF BROOKFIELD | Y40: AUTO | Z40: 76066605 | AA40: ZIMBRICK BUICK WEST | AC40: ZIMBRICK BUICK WEST | AD40: 0122 | AE40: 122 | AF40: 120 | AG40: 19180 W BLUEMOUND ROAD | AH40: BROOKFIELD | AI40: WI | AJ40: UNITED STATES | AK40: 4570058 | AL40: CARWARS STARTER 7500 | AM40: FRONT OFFICE | AN40: ELEAD | AO40: ELEAD OTHER | AP40: CALL TRACKING | AR40: N | AS40: 1 | AT40: 0 | AU40: 0 | AV40: 0 | AW40: 0 | AX40: 499 | AY40: 499 | AZ40: 2994 | BA40: 0 | BB40: 45420 | BC40: 43910 | BD40: 2020 | BE40: 9 | BI40: N | BQ40: 44082 | BR40: 2021 | BS40: 4 | BT40: 2026 | BU40: 3 | CA40: 45412 | CB40: 2024 | CC40: 5 | CD40: 827 | CE40: Low or No Utilization | CF40: N | CG40: M | CH40: BACK TO MANUAL | CI40: DA | CJ40: Dropped Apps | CK40: P | CL40: PRODUCT | CM40: N/A
A41: 68175496SW10 | B41: 4570062 | C41: CARWARS PREMIUM SALES | D41: AUTOMOBILE | E41: 1-2 | F41: NEW AUTO | G41: AUTO | H41: 36 | K41: N | L41: N | M41: 76003426 | N41: 10445 | O41: FAIR OAKS CHANTILLY CHRYSLER DODGE JEEP RAM | P41: LSS | Q41: R | R41: 68186645SW01 | S41: 68174966SW11 | U41: 0014000000JW3Q3AAJ | V41: FAIR OAKS CHANTILLY CHRYSLER JEEP DODGE RAM | W41: 25108 | X41: FAIR OAKS CHANTILLY CHRYSLER JEEP DODGE RAM | Y41: AUTO | Z41: 76003426 | AA41: FAIR OAKS CHANTILLY CHRYSLER DODGE JEEP RAM | AC41: FAIR OAKS CHANTILLY CHRYSLER DODGE JEEP RAM | AD41: 0127 | AE41: 127 | AF41: 120 | AG41: 4170 AUTO PARK CIRCLE | AH41: CHANTILLY | AI41: VA | AJ41: UNITED STATES | AK41: 4570062 | AL41: CARWARS PREMIUM SALES | AM41: FRONT OFFICE | AN41: ELEAD | AO41: ELEAD OTHER | AP41: CALL TRACKING | AR41: N | AS41: 1 | AT41: 0 | AU41: 0 | AV41: 0 | AW41: 0 | AX41: 1849 | AY41: 1849 | AZ41: 0 | BA41: 0 | BB41: 44522 | BC41: 44118 | BD41: 2021 | BE41: 4 | BI41: N | BQ41: 44105 | BR41: 2021 | BS41: 4 | BT41: 2026 | BU41: 4 | CA41: 44500 | CB41: 2022 | CC41: 5 | CD41: 221 | CE41: CDK CONVERSION - SYS GENERATED | CF41: N | CG41: C | CH41: CDK Conversion | CI41: CV | CJ41: Conversion | CK41: G | CL41: SYS GEN | CM41: CDK | CN41: ADP
A42: 68181487SW01 | D42: AUTOMOBILE | E42: 1-2 | F42: NEW AUTO | G42: AUTO | H42: 12 | K42: N | L42: N | M42: 76003426 | N42: 10445 | O42: FAIR OAKS CHANTILLY CHRYSLER DODGE JEEP RAM | P42: LSS | Q42: N | U42: 0014000000JW3Q3AAJ | V42: FAIR OAKS CHANTILLY CHRYSLER JEEP DODGE RAM | W42: 25108 | X42: FAIR OAKS CHANTILLY CHRYSLER JEEP DODGE RAM | Y42: AUTO | Z42: 76003426 | AA42: FAIR OAKS CHANTILLY CHRYSLER DODGE JEEP RAM | AC42: FAIR OAKS CHANTILLY CHRYSLER DODGE JEEP RAM | AD42: 0127 | AE42: 127 | AF42: 120 | AG42: 4170 AUTO PARK CIRCLE | AH42: CHANTILLY | AI42: VA | AJ42: UNITED STATES | AK42: 4570288 | AL42: CARWARS TEXTING (PREMIUM) | AM42: FRONT OFFICE | AN42: ELEAD | AO42: ELEAD OTHER | AP42: CALL TRACKING | AR42: N | AS42: 1 | AT42: 0 | AU42: 0 | AV42: 0 | AW42: 0 | AX42: 499 | AY42: 499 | AZ42: 5988 | BA42: 0 | BB42: 44530 | BC42: 44292 | BD42: 2021 | BE42: 10 | BI42: N | BQ42: 44298 | BR42: 2021 | BS42: 10 | BT42: 2026 | BU42: 10 | BV42: 44298 | BW42: 2021 | BX42: 10 | BY42: 2021 | BZ42: 10 | CA42: 44530 | CB42: 2022 | CC42: 5 | CD42: 836 | CE42: Price/Value Proposition | CF42: N | CG42: M | CH42: BACK TO MANUAL | CI42: DA | CJ42: Dropped Apps | CK42: P | CL42: PRODUCT | CM42: Manual
A43: 38095572SW02 | D43: RECREATION | E43: Non-Auto | F43: RECREATION | G43: MOTORCYCLE | H43: 1 | K43: N | L43: N | M43: 76212580 | N43: 9973 | O43: EMERALD COAST HARLEY-DAVIDSON | P43: LSS | Q43: N | R43: 38103593SW02 | U43: 0010B00002DHZOWAA1 | V43: EMERALD COAST HARLEY-DAVIDSON | W43: 1733397 | X43: EMERALD COAST HARLEY-DAVIDSON | Y43: MOTORCYCLE | Z43: 76212580 | AA43: EMERALD COAST HARLEY-DAVIDSON | AC43: EMERALD COAST HARLEY-DAVIDSON | AD43: 0122 | AE43: 122 | AF43: 120 | AG43: 788 BEAL PKWY NW | AH43: FORT WALTON BEACH | AI43: FL | AJ43: UNITED STATES | AK43: 4570120 | AL43: CRM TELEPHONY TRACKING | AM43: FRONT OFFICE | AN43: ELEAD | AO43: ELEAD OTHER | AP43: CALL TRACKING | AR43: N | AS43: 1 | AT43: 0 | AU43: 0 | AV43: 0 | AW43: 0 | AX43: 100 | AY43: 70 | AZ43: 0 | BA43: 0 | BB43: 44239 | BC43: 43848 | BD43: 2020 | BE43: 7 | BI43: N | BQ43: 43862 | BR43: 2020 | BS43: 7 | BT43: 2026 | BU43: 8 | CA43: 44238 | CB43: 2021 | CC43: 8 | CD43: 221 | CE43: CDK CONVERSION - SYS GENERATED | CF43: N | CG43: C | CH43: CDK Conversion | CI43: CV | CJ43: Conversion | CK43: G | CL43: SYS GEN | CM43: CDK | CN43: ADP
A44: 68187007SW14 | D44: AUTOMOBILE | E44: 11+ | F44: NEW AUTO | G44: AUTO | H44: 36 | K44: N | L44: N | M44: 76228629 | O44: MIDLANDS TOYOTA | P44: LSS | Q44: N | R44: 68189336SW40 | U44: 0015A00002TK3GOAA0 | V44: HUDSON AUTOMOTIVE | W44: 196172 | X44: MIDLANDS TOYOTA | Y44: AUTO | Z44: 76217276 | AA44: WYATT-JOHNSON BUICK GMC | AC44: WYATT-JOHNSON BUICK GMC | AD44: 0127 | AE44: 127 | AF44: 120 | AG44: 240 KILLIAN COMMON PKWY | AH44: COLUMBIA | AI44: SC | AJ44: UNITED STATES | AK44: 4570058 | AL44: CARWARS STARTER 7500 | AM44: FRONT OFFICE | AN44: ELEAD | AO44: ELEAD OTHER | AP44: CALL TRACKING | AR44: N | AS44: 1 | AT44: 0 | AU44: 0 | AV44: 0 | AW44: 0 | AX44: 499 | AY44: 499 | AZ44: 5988 | BA44: 0 | BB44: 44586 | BC44: 44484 | BD44: 2022 | BE44: 4 | BI44: N | BQ44: 44568 | BR44: 2022 | BS44: 7 | BT44: 2026 | BU44: 7 | BV44: 44501 | BW44: 2022 | BX44: 4 | BY44: 2022 | BZ44: 5 | CA44: 44585 | CB44: 2022 | CC44: 7 | CD44: 221 | CE44: CDK CONVERSION - SYS GENERATED | CF44: N | CG44: C | CH44: CDK Conversion | CI44: CV | CJ44: Conversion | CK44: G | CL44: SYS GEN | CM44: CDK | CN44: ADP
A45: 68188288SW06 | B45: 4570009 | C45: CARWARS STARTER 3500 | D45: AUTOMOBILE | E45: 11+ | F45: NEW AUTO | G45: AUTO | H45: 45 | K45: N | L45: N | M45: 76215011 | N45: 23308 | O45: PIAZZA NISSAN OF ARDMORE | P45: LSS | Q45: R | S45: 67041955SW02 | U45: 0014000000JW0UHAAZ | V45: PIAZZA AUTO GROUP | W45: 71055667 | X45: PIAZZA NISSAN OF ARDMORE | Y45: AUTO | Z45: 76215011 | AA45: PIAZZA NISSAN OF ARDMORE | AC45: PIAZZA NISSAN OF ARDMORE | AD45: 0127 | AE45: 127 | AF45: 120 | AG45: 265 E LANCASTER AVE | AH45: ARDMORE | AI45: PA | AJ45: UNITED STATES | AK45: 4570009 | AL45: CARWARS STARTER 3500 | AM45: FRONT OFFICE | AN45: ELEAD | AO45: ELEAD OTHER | AP45: CALL TRACKING | AR45: N | AS45: 1 | AT45: 0 | AU45: 0 | AV45: 0 | AW45: 0 | AX45: 299 | AY45: 299 | AZ45: 0 | BA45: 0 | BB45: 45915 | BC45: 44533 | BD45: 2022 | BE45: 5 | BI45: N | BQ45: 44537 | BR45: 2022 | BS45: 6 | BT45: 2026 | BU45: 6 | CA45: 45900 | CB45: 2025 | CC45: 9 | CD45: 818 | CE45: Conversion to Another CDK Division | CF45: N | CG45: C | CH45: CDK Conversion | CI45: CV | CJ45: Conversion | CK45: P | CL45: PRODUCT | CM45: CDK | CN45: ADP
A46: 64193165SW01 | D46: AUTOMOBILE | E46: 3-5 | F46: NEW AUTO | G46: AUTO | H46: 12 | K46: N | L46: N | M46: 76211594 | N46: 10786 | O46: LOKEY NISSAN | P46: LSS | Q46: N | R46: 64231666SW01 | U46: 0014000000M6G8KAAB | V46: PAUL LOKEY | W46: 01156105 | X46: LOKEY NISSAN | Y46: AUTO | Z46: 76211594 | AA46: LOKEY NISSAN | AC46: LOKEY NISSAN | AD46: 0122 | AE46: 122 | AF46: 120 | AG46: 27758 US HIGHWAY 19 N | AH46: CLEARWATER | AI46: FL | AJ46: UNITED STATES | AK46: 4570062 | AL46: CARWARS PREMIUM SALES | AM46: FRONT OFFICE | AN46: ELEAD | AO46: ELEAD OTHER | AP46: CALL TRACKING | AR46: N | AS46: 1 | AT46: 0 | AU46: 0 | AV46: 0 | AW46: 0 | AX46: 1849 | AY46: 1849 | AZ46: 22188 | BA46: 0 | BB46: 45545 | BC46: 44545 | BD46: 2022 | BE46: 6 | BI46: N | BQ46: 44571 | BR46: 2022 | BS46: 7 | BT46: 2026 | BU46: 7 | BV46: 44587 | BW46: 2022 | BX46: 7 | BY46: 2022 | BZ46: 8 | CA46: 45544 | CB46: 2024 | CC46: 9 | CD46: 221 | CE46: CDK CONVERSION - SYS GENERATED | CF46: N | CG46: C | CH46: CDK Conversion | CI46: CV | CJ46: Conversion | CK46: G | CL46: SYS GEN | CM46: CDK | CN46: ADP
A47: 64168996SW05 | D47: AUTOMOBILE | E47: 3-5 | F47: NEW AUTO | G47: AUTO | H47: 1 | K47: N | L47: N | M47: 76167994 | N47: 18231 | O47: MURRAY CHRYSLER DODGE JEEP | P47: LSS | Q47: N | U47: 00140000011RWX6AAK | V47: MURRAY AUTO GROUP | W47: 187371 | X47: MURRAY CHRYSLER DODGE JEEP | Y47: AUTO | Z47: 76167994 | AA47: MURRAY CHRYSLER DODGE JEEP | AC47: MURRAY CHRYSLER DODGE JEEP | AD47: 0122 | AE47: 122 | AF47: 120 | AG47: 15160 HWY 301 S | AH47: STARKE | AI47: FL | AJ47: UNITED STATES | AK47: 4570060 | AL47: CRM OUTBOUND TELEPHONY TRACKING (NEW AND CONVERSION) | AM47: FRONT OFFICE | AN47: ELEAD | AO47: ELEAD OTHER | AP47: CALL TRACKING | AR47: N | AS47: 1 | AT47: 0 | AU47: 0 | AV47: 0 | AW47: 0 | AX47: 195 | AY47: 499 | AZ47: 0 | BA47: 0 | BB47: 44500 | BC47: 43848 | BD47: 2020 | BE47: 7 | BI47: N | BQ47: 43862 | BR47: 2020 | BS47: 7 | BT47: 2026 | BU47: 8 | CA47: 44500 | CB47: 2022 | CC47: 4 | CD47: 812 | CE47: CDK Conversion | CF47: N | CG47: C | CH47: CDK Conversion | CI47: CV | CJ47: Conversion | CK47: P | CL47: PRODUCT | CM47: CDK | CN47: ADP
A48: 68182618SW01 | D48: AUTOMOBILE | E48: 6-10 | F48: NEW AUTO | G48: AUTO | H48: 12 | K48: N | L48: N | M48: 76220529 | O48: GALEANA CHRYSLER DODGE JEEP RAM OF FORT MYERS | P48: LSS | Q48: N | R48: 64226787SW01 | U48: 0014000000JWA15AAF | V48: GALEANA AUTOMOTIVE GROUP | W48: 1361687 | X48: GALEANA CHRYSLER DODGE JEEP RAM OF FORT MYERS | Y48: AUTO | Z48: 76220529 | AA48: GALEANA CHRYSLER DODGE JEEP RAM OF FORT MYERS | AC48: GALEANA CHRYSLER DODGE JEEP RAM OF FORT MYERS | AD48: 0122 | AE48: 122 | AF48: 120 | AG48: 14375 S TAMIAMI TRAIL | AH48: FORT MYERS | AI48: FL | AJ48: UNITED STATES | AK48: 4570122 | AL48: CARWARS ADVANCED SALES | AM48: FRONT OFFICE | AN48: ELEAD | AO48: ELEAD OTHER | AP48: CALL TRACKING | AR48: N | AS48: 1 | AT48: 0 | AU48: 0 | AV48: 0 | AW48: 0 | AX48: 999 | AY48: 999 | AZ48: 11988 | BA48: 0 | BB48: 45401 | BC48: 44329 | BD48: 2021 | BE48: 11 | BI48: N | BQ48: 44356 | BR48: 2021 | BS48: 12 | BT48: 2026 | BU48: 12 | BV48: 44354 | BW48: 2021 | BX48: 12 | BY48: 2021 | BZ48: 12 | CA48: 45399 | CB48: 2024 | CC48: 4 | CD48: 221 | CE48: CDK CONVERSION - SYS GENERATED | CF48: N | CG48: C | CH48: CDK Conversion | CI48: CV | CJ48: Conversion | CK48: G | CL48: SYS GEN | CM48: CDK | CN48: ADP
A49: 64168880SW03 | D49: RECREATION | E49: Non-Auto | F49: RECREATION | G49: MOTORCYCLE | H49: 1 | K49: N | L49: N | M49: 76211939 | N49: 4545 | O49: MOONSHINE HARLEY DAVIDSON | P49: LSS | Q49: N | R49: 64238640SW12 | U49: 0014000000MV3SUAAK | V49: MOONSHINE HARLEY-DAVIDSON | W49: 1443259 | X49: MOONSHINE HARLEY-DAVIDSON | Y49: MOTORCYCLE | Z49: 76211939 | AA49: MOONSHINE HARLEY DAVIDSON | AC49: MOONSHINE HARLEY DAVIDSON | AD49: 0122 | AE49: 122 | AF49: 120 | AG49: 7128 SOUTH SPRINGS DR | AH49: FRANKLIN | AI49: TN | AJ49: UNITED STATES | AK49: 4570120 | AL49: CRM TELEPHONY TRACKING | AM49: FRONT OFFICE | AN49: ELEAD | AO49: ELEAD OTHER | AP49: CALL TRACKING | AR49: N | AS49: 1 | AT49: 0 | AU49: 0 | AV49: 0 | AW49: 0 | AX49: 100 | AY49: 70 | AZ49: 0 | BA49: 0 | BB49: 45778 | BC49: 43848 | BD49: 2020 | BE49: 7 | BI49: N | BQ49: 43862 | BR49: 2020 | BS49: 7 | BT49: 2026 | BU49: 8 | CA49: 45777 | CB49: 2025 | CC49: 4 | CD49: 221 | CE49: CDK CONVERSION - SYS GENERATED | CF49: N | CG49: C | CH49: CDK Conversion | CI49: CV | CJ49: Conversion | CK49: G | CL49: SYS GEN | CM49: CDK | CN49: ADP
A50: 67035426SW10 | D50: AUTOMOBILE | E50: 3-5 | F50: NEW AUTO | G50: AUTO | H50: 1 | K50: N | L50: N | M50: 76055608 | N50: 11619 | O50: ROSEDALE CHEVROLET | P50: LSS | Q50: N | U50: 0014000000JVWFPAAR | V50: METROCORP | W50: 187885 | X50: ROSEDALE CHEVROLET | Y50: AUTO | Z50: 76055608 | AA50: ROSEDALE CHEVROLET | AC50: ROSEDALE CHEVROLET | AD50: 0122 | AE50: 122 | AF50: 120 | AG50: 2845 HIGHWAY 35W | AH50: ROSEVILLE | AI50: MN | AJ50: UNITED STATES | AK50: 4570060 | AL50: CRM OUTBOUND TELEPHONY TRACKING (NEW AND CONVERSION) | AM50: FRONT OFFICE | AN50: ELEAD | AO50: ELEAD OTHER | AP50: CALL TRACKING | AR50: N | AS50: 1 | AT50: 0 | AU50: 0 | AV50: 0 | AW50: 0 | AX50: 195 | AY50: 995 | AZ50: 0 | BA50: 0 | BB50: 43951 | BC50: 43849 | BD50: 2020 | BE50: 7 | BI50: N | BQ50: 43862 | BR50: 2020 | BS50: 7 | BT50: 2026 | BU50: 8 | CA50: 43951 | CB50: 2020 | CC50: 10 | CD50: 836 | CE50: Price/Value Proposition | CF50: N | CG50: M | CH50: BACK TO MANUAL | CI50: DA | CJ50: Dropped Apps | CK50: P | CL50: PRODUCT | CM50: Manual
A51: 64196224SW12 | D51: AUTOMOBILE | E51: 1-2 | F51: NEW AUTO | G51: AUTO | H51: 60 | K51: Y | L51: N | M51: 76049550 | N51: 19638 | O51: MEL HAMBELTON FORD | P51: LSS | Q51: N | U51: 0014000000F2TTXAAI | V51: MEL HAMBELTON | W51: 155779 | X51: MEL HAMBELTON FORD | Y51: AUTO | Z51: 76049550 | AA51: MEL HAMBELTON FORD | AC51: MEL HAMBELTON FORD | AD51: 0122 | AE51: 122 | AF51: 120 | AG51: 11771 W KELLOGG DR | AH51: WICHITA | AI51: KS | AJ51: UNITED STATES | AK51: 4570062 | AL51: CARWARS PREMIUM SALES | AM51: FRONT OFFICE | AN51: ELEAD | AO51: ELEAD OTHER | AP51: CALL TRACKING | AR51: N | AS51: 1 | AT51: 0 | AU51: 0 | AV51: 0 | AW51: 0 | AX51: 1849 | AY51: 1849 | AZ51: 22188 | BA51: 0 | BB51: 45777 | BC51: 44655 | BD51: 2022 | BE51: 9 | BI51: N | BQ51: 44657 | BR51: 2022 | BS51: 10 | BT51: 2026 | BU51: 10 | BV51: 44657 | BW51: 2022 | BX51: 10 | BY51: 2022 | BZ51: 10 | CA51: 45777 | CB51: 2025 | CC51: 4 | CD51: 836 | CE51: Price/Value Proposition | CF51: N | CG51: CL | CH51: COMPETITIVE LOSS | CI51: CM | CJ51: Competitive | CK51: P | CL51: PRODUCT | CM51: Competitor | CN51: Other Vendor
A52: 64169219SW05 | D52: RECREATION | E52: Non-Auto | F52: RECREATION | G52: MOTORCYCLE | H52: 1 | K52: N | L52: N | M52: 76211956 | N52: 17155 | O52: MOBILE BAY HARLEY DAVIDSON | P52: LSS | Q52: N | R52: 64238640SW05 | U52: 0014000000MV8QAAA0 | V52: MOBILE BAY HARLEY DAVIDSON | W52: 1447686 | X52: MOBILE BAY HARLEY DAVIDSON | Y52: MOTORCYCLE | Z52: 76211956 | AA52: MOBILE BAY HARLEY DAVIDSON | AC52: MOBILE BAY HARLEY DAVIDSON | AD52: 0122 | AE52: 122 | AF52: 120 | AG52: 3260 PLEASANT VALLEY RD | AH52: MOBILE | AI52: AL | AJ52: UNITED STATES | AK52: 4570060 | AL52: CRM OUTBOUND TELEPHONY TRACKING (NEW AND CONVERSION) | AM52: FRONT OFFICE | AN52: ELEAD | AO52: ELEAD OTHER | AP52: CALL TRACKING | AR52: N | AS52: 1 | AT52: 0 | AU52: 0 | AV52: 0 | AW52: 0 | AX52: 195 | AY52: 299 | AZ52: 0 | BA52: 0 | BB52: 45778 | BC52: 43848 | BD52: 2020 | BE52: 7 | BI52: N | BQ52: 43862 | BR52: 2020 | BS52: 7 | BT52: 2026 | BU52: 8 | CA52: 45777 | CB52: 2025 | CC52: 4 | CD52: 221 | CE52: CDK CONVERSION - SYS GENERATED | CF52: N | CG52: C | CH52: CDK Conversion | CI52: CV | CJ52: Conversion | CK52: G | CL52: SYS GEN | CM52: CDK | CN52: ADP
A53: 68233896SW13 | B53: 4570058 | C53: CARWARS STARTER 7500 | D53: AUTOMOBILE | E53: 1-2 | F53: NEW AUTO | G53: AUTO | H53: 12 | K53: N | L53: N | M53: 76252487 | O53: PREMIER TOYOTA | P53: LSS | Q53: C | R53: 68234112SW16 | S53: 68207128SW01 | U53: 0014000000JW0PEAAJ | V53: AMHERST AUTOMOTIVE | W53: 2009633 | X53: PREMIER TOYOTA | Y53: AUTO | Z53: 76252487 | AA53: PREMIER TOYOTA | AC53: PREMIER TOYOTA | AD53: 0127 | AE53: 127 | AF53: 120 | AG53: 47190 COOPER FOSTER PARK ROAD | AH53: AMHERST | AI53: OH | AJ53: UNITED STATES | AK53: 4571030 | AL53: CARWARS STARTER 5000 | AM53: FRONT OFFICE | AN53: ELEAD | AO53: ELEAD OTHER | AP53: CALL TRACKING | AR53: N | AS53: 1 | AT53: 0 | AU53: 0 | AV53: 0 | AW53: 0 | AX53: 599 | AY53: 599 | AZ53: 2875.2 | BA53: 0 | BB53: 45742 | BC53: 45639 | BD53: 2024 | BE53: 12 | BI53: N | BQ53: 45642 | BR53: 2024 | BS53: 12 | BT53: 2026 | BU53: 1 | BV53: 45705 | BW53: 2025 | BX53: 2 | BY53: 2025 | BZ53: 3 | CA53: 45740 | CB53: 2025 | CC53: 3 | CD53: 221 | CE53: CDK CONVERSION - SYS GENERATED | CF53: N | CG53: C | CH53: CDK Conversion | CI53: CV | CJ53: Conversion | CK53: G | CL53: SYS GEN | CM53: CDK | CN53: ADP
A54: 64164460SW01 | D54: AUTOMOBILE | E54: 3-5 | F54: NEW AUTO | G54: AUTO | H54: 1 | K54: N | L54: N | M54: 76167994 | N54: 18231 | O54: MURRAY CHRYSLER DODGE JEEP | P54: LSS | Q54: N | R54: 64191075SW42 | U54: 00140000011RWX6AAK | V54: MURRAY AUTO GROUP | W54: 187371 | X54: MURRAY CHRYSLER DODGE JEEP | Y54: AUTO | Z54: 76167994 | AA54: MURRAY CHRYSLER DODGE JEEP | AC54: MURRAY CHRYSLER DODGE JEEP | AD54: 0122 | AE54: 122 | AF54: 120 | AG54: 15160 HWY 301 S | AH54: STARKE | AI54: FL | AJ54: UNITED STATES | AK54: 4570089 | AL54: CALLREVU 8000 | AM54: FRONT OFFICE | AN54: ELEAD | AO54: ELEAD OTHER | AP54: CALL TRACKING | AR54: N | AS54: 1 | AT54: 0 | AU54: 0 | AV54: 0 | AW54: 0 | AX54: 1394 | AY54: 1394 | AZ54: 0 | BA54: 0 | BB54: 44484 | BC54: 43676 | BD54: 2020 | BE54: 1 | BI54: N | BQ54: 43724 | BR54: 2020 | BS54: 4 | BT54: 2026 | BU54: 4 | BV54: 43663 | BW54: 2020 | BX54: 1 | BY54: 2020 | BZ54: 2 | CA54: 44472 | CB54: 2022 | CC54: 4 | CD54: 221 | CE54: CDK CONVERSION - SYS GENERATED | CF54: N | CG54: C | CH54: CDK Conversion | CI54: CV | CJ54: Conversion | CK54: G | CL54: SYS GEN | CM54: CDK | CN54: ADP
A55: 64244482SW01 | D55: AUTOMOBILE | E55: 3-5 | F55: NEW AUTO | G55: AUTO | H55: 12 | J55: 76211594 | K55: N | L55: N | M55: 76211594 | N55: 10786 | O55: LOKEY NISSAN | P55: INS | Q55: N | U55: 0014000000M6G8KAAB | V55: PAUL LOKEY | W55: 01156105 | X55: LOKEY NISSAN | Y55: AUTO | Z55: 76211594 | AA55: LOKEY NISSAN | AC55: LOKEY NISSAN | AD55: 0122 | AE55: 122 | AF55: 120 | AG55: 27758 US HIGHWAY 19 N | AH55: CLEARWATER | AI55: FL | AJ55: UNITED STATES | AK55: 4570084 | AL55: CALLREVU CALL TRACKING PLUS 4000 | AM55: FRONT OFFICE | AN55: ELEAD | AO55: ELEAD OTHER | AP55: CALL TRACKING | AR55: N | AS55: 1 | AT55: 0 | AU55: 0 | AV55: 0 | AW55: 0 | AX55: 299 | AY55: 299 | AZ55: 3588 | BA55: 0 | BB55: 45973 | BC55: 45968 | BD55: 2025 | BE55: 11 | BI55: N | BQ55: 45973 | BR55: 2025 | BS55: 11 | BT55: 2026 | BU55: 11 | BV55: 45973 | BW55: 2025 | BX55: 11 | BY55: 2025 | BZ55: 11
A56: 64185402SW02 | D56: AUTOMOBILE | E56: 6-10 | F56: USED AUTO | G56: USED VEHICLE | H56: 36 | K56: N | L56: N | M56: 76224283 | N56: 25433 | O56: UNION AUTO GRUPO USADOS | P56: LSS | Q56: N | R56: 64192511SW08 | U56: 0015A00002ZONADAAK | V56: UNION AUTO GROUP | W56: 1839493 | X56: UNION AUTO GROUP | Y56: USED VEHICLE | Z56: 76224283 | AA56: UNION AUTO GRUPO USADOS | AC56: UNION AUTO GRUPO USADOS | AD56: 0122 | AE56: 122 | AF56: 120 | AG56: 867 AVE LUIS MUNOZ RIVERA | AH56: SAN JUAN | AI56: PR | AJ56: UNITED STATES | AK56: 4570009 | AL56: CARWARS STARTER 3500 | AM56: FRONT OFFICE | AN56: ELEAD | AO56: ELEAD OTHER | AP56: CALL TRACKING | AR56: N | AS56: 1 | AT56: 0 | AU56: 0 | AV56: 0 | AW56: 0 | AX56: 299 | AY56: 262 | AZ56: 3144 | BA56: 0 | BB56: 44531 | BC56: 44263 | BD56: 2021 | BE56: 9 | BI56: N | BQ56: 44305 | BR56: 2021 | BS56: 10 | BT56: 2026 | BU56: 11 | CA56: 44530 | CB56: 2022 | CC56: 5 | CD56: 221 | CE56: CDK CONVERSION - SYS GENERATED | CF56: N | CG56: C | CH56: CDK Conversion | CI56: CV | CJ56: Conversion | CK56: G | CL56: SYS GEN | CM56: CDK | CN56: ADP
A57: 64226788SW01 | B57: 4570122 | C57: CARWARS ADVANCED SALES | D57: AUTOMOBILE | E57: 6-10 | F57: NEW AUTO | G57: AUTO | H57: 12 | K57: N | L57: N | M57: 76220548 | O57: GALEANA KIA OF FORT MYERS | P57: LSS | Q57: C | R57: 64243030SW20 | S57: 68182618SW02 | U57: 0014000000JWA15AAF | V57: GALEANA AUTOMOTIVE GROUP | W57: 186155 | X57: GALEANA KIA OF FORT MYERS | Y57: AUTO | Z57: 76220548 | AA57: GALEANA KIA OF FORT MYERS | AC57: GALEANA KIA OF FORT MYERS | AD57: 0122 | AE57: 122 | AF57: 120 | AG57: 14483 S TAMIAMI TRL | AH57: FORT MYERS | AI57: FL | AJ57: UNITED STATES | AK57: 4570289 | AL57: CARWARS ELITE 12,500 PACKAGE | AM57: FRONT OFFICE | AN57: ELEAD | AO57: ELEAD OTHER | AP57: CALL TRACKING | AR57: N | AS57: 1 | AT57: 0 | AU57: 0 | AV57: 0 | AW57: 0 | AX57: 1499 | AY57: 1499 | AZ57: 6000 | BA57: 0 | BB57: 45925 | BC57: 45373 | BD57: 2024 | BE57: 3 | BI57: N | BQ57: 45400 | BR57: 2024 | BS57: 4 | BT57: 2026 | BU57: 5 | BV57: 45400 | BW57: 2024 | BX57: 4 | BY57: 2024 | BZ57: 5 | CA57: 45924 | CB57: 2025 | CC57: 9 | CD57: 221 | CE57: CDK CONVERSION - SYS GENERATED | CF57: N | CG57: C | CH57: CDK Conversion | CI57: CV | CJ57: Conversion | CK57: G | CL57: SYS GEN | CM57: CDK | CN57: ADP
A58: 64169292SW02 | D58: AUTOMOBILE | E58: 11+ | F58: NEW AUTO | G58: AUTO | H58: 1 | K58: Y | L58: N | M58: 76166962 | N58: 18849 | O58: STANLEY FORD SWEETWATER | P58: LSS | Q58: N | U58: 0014000000VCZDIAA1 | V58: STANLEY | W58: 71044942 | X58: STANLEY FORD SWEETWATER | Y58: AUTO | Z58: 76166962 | AA58: STANLEY FORD SWEETWATER | AC58: STANLEY FORD SWEETWATER | AD58: 0122 | AE58: 122 | AF58: 120 | AG58: 603 SW GEORGIA AVE | AH58: SWEETWATER | AI58: TX | AJ58: UNITED STATES | AK58: 4570060 | AL58: CRM OUTBOUND TELEPHONY TRACKING (NEW AND CONVERSION) | AM58: FRONT OFFICE | AN58: ELEAD | AO58: ELEAD OTHER | AP58: CALL TRACKING | AR58: N | AS58: 1 | AT58: 0 | AU58: 0 | AV58: 0 | AW58: 0 | AX58: 195 | AY58: 999 | AZ58: 0 | BA58: 0 | BB58: 43878 | BC58: 43848 | BD58: 2020 | BE58: 7 | BI58: N | BQ58: 43862 | BR58: 2020 | BS58: 7 | BT58: 2026 | BU58: 8 | CA58: 43878 | CB58: 2020 | CC58: 8 | CD58: 836 | CE58: Price/Value Proposition | CF58: N | CG58: M | CH58: BACK TO MANUAL | CI58: DA | CJ58: Dropped Apps | CK58: P | CL58: PRODUCT | CM58: Manual
A59: 68189189SW11 | D59: AUTOMOBILE | E59: 6-10 | F59: NEW AUTO | G59: AUTO | H59: 44 | K59: N | L59: N | M59: 76230032 | N59: 27069 | O59: KING KIA OF LAUREL | P59: LSS | Q59: N | U59: 0015A00003EKE0EAAX | V59: KING AUTO GROUP | W59: 71061381 | X59: KING KIA OF LAUREL | Y59: AUTO | Z59: 76230032 | AA59: KING KIA OF LAUREL | AC59: KING KIA OF LAUREL | AD59: 0127 | AE59: 127 | AF59: 120 | AG59: 14921 N BALTIMORE AVE | AH59: LAUREL | AI59: MD | AJ59: UNITED STATES | AK59: 4570009 | AL59: CARWARS STARTER 3500 | AM59: FRONT OFFICE | AN59: ELEAD | AO59: ELEAD OTHER | AP59: CALL TRACKING | AR59: N | AS59: 1 | AT59: 0 | AU59: 0 | AV59: 0 | AW59: 0 | AX59: 299 | AY59: 299 | AZ59: 3588 | BA59: 3 | BB59: 45789 | BC59: 44564 | BD59: 2022 | BE59: 6 | BI59: N | BQ59: 44663 | BR59: 2022 | BS59: 10 | BT59: 2026 | BU59: 10 | BV59: 44676 | BW59: 2022 | BX59: 10 | BY59: 2022 | BZ59: 11 | CA59: 45777 | CB59: 2025 | CC59: 5 | CD59: 836 | CE59: Price/Value Proposition | CF59: N | CG59: M | CH59: BACK TO MANUAL | CI59: DA | CJ59: Dropped Apps | CK59: P | CL59: PRODUCT | CM59: Manual
