Workbook
Name ____gh2: {"'100'!$A$1:$M$83"}
Name ____gh2: {"'100'!$A$1:$M$83"}
Name ____gh2: {"'100'!$A$1:$M$83"}
Name ____hg2: {"'100'!$A$1:$M$83"}
Name ____hg2: {"'100'!$A$1:$M$83"}
Name ____hg2: {"'100'!$A$1:$M$83"}
Name ___gh2: {"'100'!$A$1:$M$83"}
Name ___gh2: {"'100'!$A$1:$M$83"}
Name ___gh2: {"'100'!$A$1:$M$83"}
Name ___hg2: {"'100'!$A$1:$M$83"}
Name ___hg2: {"'100'!$A$1:$M$83"}
Name ___hg2: {"'100'!$A$1:$M$83"}
Name __FDS_HYPERLINK_TOGGLE_STATE__: "ON"
Name __gh2: {"'100'!$A$1:$M$83"}
Name __gh2: {"'100'!$A$1:$M$83"}
Name __gh2: {"'100'!$A$1:$M$83"}
Name __hg2: {"'100'!$A$1:$M$83"}
Name __hg2: {"'100'!$A$1:$M$83"}
Name __hg2: {"'100'!$A$1:$M$83"}
Name _gh2: {"'100'!$A$1:$M$83"}
Name _gh2: {"'100'!$A$1:$M$83"}
Name _gh2: {"'100'!$A$1:$M$83"}
Name _hg2: {"'100'!$A$1:$M$83"}
Name _hg2: {"'100'!$A$1:$M$83"}
Name _hg2: {"'100'!$A$1:$M$83"}
Name _Order1: 0
Name _Order2: 255
Name _Regression_Int: 1
Name a: {"'Hardware Req.'!$A$1:$C$23"}
Name a: {"'Hardware Req.'!$A$1:$C$23"}
Name a: {"'Hardware Req.'!$A$1:$C$23"}
Name activations: {"'Hardware Req.'!$A$1:$C$23"}
Name activations: {"'Hardware Req.'!$A$1:$C$23"}
Name activations: {"'Hardware Req.'!$A$1:$C$23"}
Name anscount: 1
Name April: #REF!
Name AS2DocOpenMode: "AS2DocumentEdit"
Name AS2NamedRange: 6
Name AS2ReportLS: 2
Name AS2SyncStepLS: 0
Name AS2VersionLS: 300
Name Auto: [13]!Table1[[#All],[Column1]]
Name BG_Del: 15
Name BG_Ins: 4
Name BG_Mod: 6
Name Calendar10Month: '[16]NA Finance Calendar'!$D$127
Name Calendar10MonthOption: MATCH(Calendar10Month,'3.10 Cancel List'!Months,0)
Name Calendar10MonthOption: MATCH(Calendar10Month,'TV active sites in March Cancel'!Months,0)
Name Calendar10MonthOption: MATCH(Calendar10Month,Months,0)
Name Calendar10Year: '[16]NA Finance Calendar'!$C$127
Name Calendar11Month: '[16]NA Finance Calendar'!$D$141
Name Calendar11MonthOption: MATCH(Calendar11Month,'3.10 Cancel List'!Months,0)
Name Calendar11MonthOption: MATCH(Calendar11Month,'TV active sites in March Cancel'!Months,0)
Name Calendar11MonthOption: MATCH(Calendar11Month,Months,0)
Name Calendar11Year: '[16]NA Finance Calendar'!$C$141
Name Calendar12Month: '[16]NA Finance Calendar'!$D$155
Name Calendar12MonthOption: MATCH(Calendar12Month,'3.10 Cancel List'!Months,0)
Name Calendar12MonthOption: MATCH(Calendar12Month,'TV active sites in March Cancel'!Months,0)
Name Calendar12MonthOption: MATCH(Calendar12Month,Months,0)
Name Calendar12Year: '[16]NA Finance Calendar'!$C$155

Sheet Summary
C6: Billing Sites | M6: Billing Amount - Gap
D7: TruVideo Billed | E7: CDK INS | F7: CDK BLG | G7: TV Billed vs CDK INS | H7: TV Billed vs CDK INS+BLG | N7: BLG Sites | O7: Non-INS Sites on mass Cancellation list | P7: New Loss Sites since March
C8: April Prorated Billing | D8: 69 | E8: =26 -> 26 | F8: 43 | G8: =D8-E8 -> 43 | H8: =D8-E8-F8 -> 0 | M8: April- Prorated Invoice Sites | N8: =F8 -> 43
C9: May Monthly Billing | D9: 1787 | E9: =1558+22+10 -> 1590 | F9: 117 | G9: =D9-E9 -> 197 | H9: 70 | M9: April- Prorated Invoice Amount | N9: ='April Prorated Invoice-BLG Site'!F89 -> 9100.03
E10: (H+I) | F10: (J+K) | H10: (To Cancel in Invoice GAP sites) | M10: May- Monthly Invoice Sites | N10: =F9 -> 117 | O10: 39 | P10: 31
M11: May- Monthly Invoice Amount | N11: ='May Monthly Invoice- BLG Sites'!I119 -> 58850 | O11: 21300 | P11: 16450
M12: Total Amount | N12: =SUM(N9+N11) -> 67950.03 | O12: =SUM(O9+O11) -> 21300 | P12: =SUM(P9+P11) -> 16450
C14: CDK INS not billed by TruVideo | D14: ='CDK INS not Billed by TV'!J150 -> 148

Sheet May Monthly - non INS Sites
A1: CMF | B1: Customer | C1: Contract Number | D1: CMF Number | E1: CID Number | F1: Item | G1: Base Fee | H1: AI Suite Fee | I1: on March 10 Cancel list? | J1: CDK Asked TV to retain | K1: Comments - CDK Status | L1: Comments - Status Date | M1: Comments - Product | N1: Comments - Others
A2: 05088801 | B2: WINTER CHEVROLET CO. INC. | C2: T-5636 | D2: 5088801 | E2: 2503075 | F2: CDK Reseller - Base Fee | G2: 300 | H2: 200 | I2: =VLOOKUP(D2,'3.10 Cancel List'!$C:$C,1,0) -> #N/A
A3: 05236442 | B3: Smothers European | C3: T-7444 | D3: 5236442 | E3: 3001276 | F3: CDK Reseller - Base Fee | G3: 400 | H3: 200 | I3: =VLOOKUP(D3,'3.10 Cancel List'!$C:$C,1,0) -> #N/A
A4: 08300018 | B4: GRAINGER HONDA | C4: T-13310 | D4: 8300018 | E4: 3000322 | F4: CDK Reseller - Base Fee | G4: 300 | H4: 200 | I4: =VLOOKUP(D4,'3.10 Cancel List'!$C:$C,1,0) -> #N/A
A5: 13093301 | B5: MIKE FINNIN FORD | C5: T-10652 | D5: 13093301 | E5: 2503593 | F5: CDK Reseller - Base Fee | G5: 300 | H5: 200 | I5: =VLOOKUP(D5,'3.10 Cancel List'!$C:$C,1,0) -> #N/A
A6: 25297551 | B6: COLONIAL TOYOTA - CT | C6: T-9268 | D6: 25297551 | E6: 153 | F6: CDK Reseller - Base Fee | G6: 300 | H6: 200 | I6: =VLOOKUP(D6,'3.10 Cancel List'!$C:$C,1,0) -> #N/A
A7: 33049702 | B7: Don Ayres Honda | C7: T-11270 | D7: 33049702 | E7: 2700012 | F7: CDK Reseller - Base Fee | G7: 300 | H7: 200 | I7: =VLOOKUP(D7,'3.10 Cancel List'!$C:$C,1,0) -> #N/A
A8: 37216003 | B8: TC CHEVROLET | C8: T-10901 | D8: 37216003 | E8: 2700001 | F8: CDK Reseller - Base Fee | G8: 300 | H8: 200 | I8: =VLOOKUP(D8,'3.10 Cancel List'!$C:$C,1,0) -> #N/A
A9: 43996001 | B9: PAUL MILLER AUDI | C9: T-4201 | D9: 43996001 | E9: 2502552 | F9: CDK Reseller - Base Fee | G9: 450 | H9: 200 | I9: =VLOOKUP(D9,'3.10 Cancel List'!$C:$C,1,0) -> #N/A
A10: 71062428 | B10: WINTER HONDA | C10: T-5710 | D10: 71062428 | E10: 2503087 | F10: CDK Reseller - Base Fee | G10: 300 | H10: 200 | I10: =VLOOKUP(D10,'3.10 Cancel List'!$C:$C,1,0) -> #N/A
A11: 76001666 | B11: KOEPPEL NISSAN | C11: T-4093 | D11: 76001666 | E11: 2501710 | F11: CDK Reseller - Base Fee | G11: 450 | H11: 200 | I11: =VLOOKUP(D11,'3.10 Cancel List'!$C:$C,1,0) -> 76001666 | J11: Yes | K11: =VLOOKUP(D11,'March Cancel - checking results'!$C:$Q,9,0) -> LSS | L11: =VLOOKUP(D11,'March Cancel - checking results'!$C:$Q,10,0) -> 44682 | M11: =VLOOKUP(D11,'March Cancel - checking results'!$C:$Q,11,0) -> Standalone | N11: =VLOOKUP(D11,'March Cancel - checking results'!$C:$Q,15,0) -> With Inspect, no suite.
A12: 76018447 | B12: CAROLINA HYUNDAI OF HIGH POINT | C12: T-13384 | D12: 76018447 | E12: 2501591 | F12: CDK Reseller - Base Fee | G12: 300 | H12: 200 | I12: =VLOOKUP(D12,'3.10 Cancel List'!$C:$C,1,0) -> #N/A
A13: 76025293 | B13: ATLANTIC AUTO EQUIP CORP DBA ATLANTIC TOYOTA | C13: T-1024 | D13: 76025293 | E13: 2502775 | F13: CDK Reseller - Base Fee | G13: 300 | H13: 200 | I13: =VLOOKUP(D13,'3.10 Cancel List'!$C:$C,1,0) -> #N/A
A14: 76028715 | B14: JOHNSON HYUNDAI OF CARY | C14: T-4067 | D14: 76028715 | E14: 2000422 | F14: CDK Reseller - Base Fee | G14: 450 | H14: 200 | I14: =VLOOKUP(D14,'3.10 Cancel List'!$C:$C,1,0) -> 76028715 | J14: Yes | K14: =VLOOKUP(D14,'March Cancel - checking results'!$C:$M,9,0) -> LSS | L14: =VLOOKUP(D14,'March Cancel - checking results'!$C:$M,10,0) -> 45047 | M14: =VLOOKUP(D14,'March Cancel - checking results'!$C:$M,11,0) -> Standalone | N14: =VLOOKUP(D14,'March Cancel - checking results'!$C:$Q,15,0) -> Conversion LSS
A15: 76043277 | B15: PAUL MILLER HONDA OF WEST CALDWELL | C15: T-4204 | D15: 76043277 | E15: 2502505 | F15: CDK Reseller - Base Fee | G15: 450 | H15: 200 | I15: =VLOOKUP(D15,'3.10 Cancel List'!$C:$C,1,0) -> #N/A
A16: 76051500 | B16: RED BANK VOLVO | C16: T-8026 | D16: 76051500 | E16: 2503331 | F16: CDK Reseller - Base Fee | G16: 300 | H16: 200 | I16: =VLOOKUP(D16,'3.10 Cancel List'!$C:$C,1,0) -> 76051500 | J16: Yes | K16: =VLOOKUP(D16,'March Cancel - checking results'!$C:$M,9,0) -> ANS | L16: =VLOOKUP(D16,'March Cancel - checking results'!$C:$M,10,0) -> 45444 | M16: =VLOOKUP(D16,'March Cancel - checking results'!$C:$M,11,0) -> Suite | N16: =VLOOKUP(D16,'March Cancel - checking results'!$C:$Q,15,0) -> LSS lines converted from a previous ANS
A17: 76057672 | B17: MAZDA OF MILFORD | C17: T-4134 | D17: 76057672 | E17: 2501660 | F17: CDK Reseller - Base Fee | G17: 450 | H17: 200 | I17: =VLOOKUP(D17,'3.10 Cancel List'!$C:$C,1,0) -> #N/A
A18: 76097658 | B18: STATELINE MASERATI ALFA ROMEO | C18: T-14496 | D18: 76097658 | E18: 3000911 | F18: CDK Reseller - Base Fee | G18: 300 | H18: 200 | I18: =VLOOKUP(D18,'3.10 Cancel List'!$C:$C,1,0) -> 76097658 | J18: Yes | K18: =VLOOKUP(D18,'March Cancel - checking results'!$C:$M,9,0) -> LSS | L18: =VLOOKUP(D18,'March Cancel - checking results'!$C:$M,10,0) -> 45992 | M18: =VLOOKUP(D18,'March Cancel - checking results'!$C:$M,11,0) -> Suite | N18: =VLOOKUP(D18,'March Cancel - checking results'!$C:$Q,15,0) -> Whole suite LSS
A19: 76134865 | B19: REINEKE NISSAN | C19: T-13497 | D19: 76134865 | E19: 5113 | F19: CDK Reseller - Base Fee | G19: 300 | H19: 200 | I19: =VLOOKUP(D19,'3.10 Cancel List'!$C:$C,1,0) -> #N/A
A20: 76157327 | B20: MARINA DEL REY TOYOTA SCION | C20: T-4118 | D20: 76157327 | E20: 10190 | F20: CDK Reseller - Base Fee | G20: 300 | H20: 200 | I20: =VLOOKUP(D20,'3.10 Cancel List'!$C:$C,1,0) -> 76157327 | K20: =VLOOKUP(D20,'March Cancel - checking results'!$C:$M,9,0) -> ANS | L20: =VLOOKUP(D20,'March Cancel - checking results'!$C:$M,10,0) -> 45047 | M20: =VLOOKUP(D20,'March Cancel - checking results'!$C:$M,11,0) -> Suite | N20: =VLOOKUP(D20,'March Cancel - checking results'!$C:$Q,15,0) -> CDKS ANS
A21: 76173064 | B21: WEST HOUSTON INFINITI | C21: T-14518 | D21: 76173064 | E21: 3000888 | F21: CDK Reseller - Base Fee | G21: 300 | H21: 200 | I21: =VLOOKUP(D21,'3.10 Cancel List'!$C:$C,1,0) -> #N/A
A22: 76181139 | B22: Mazda of Richmond Hill | C22: T-14525 | D22: 76181139 | E22: 3000966 | F22: CDK Reseller - Base Fee | G22: 300 | H22: 200 | I22: =VLOOKUP(D22,'3.10 Cancel List'!$C:$C,1,0) -> #N/A
A23: 76184938 | B23: TAYLOR FORD LINCOLN | C23: T-14162 | D23: 76184938 | E23: 3000690 | F23: CDK Reseller - Base Fee | G23: 300 | H23: 200 | I23: =VLOOKUP(D23,'3.10 Cancel List'!$C:$C,1,0) -> #N/A
A24: 76194812 | B24: PUTNAM SUBARU BURLINGAME | C24: T-5627 | D24: 76194812 | E24: 0 | F24: CDK Reseller - Base Fee | G24: 400 | H24: 200 | I24: =VLOOKUP(D24,'3.10 Cancel List'!$C:$C,1,0) -> 76194812 | K24: =VLOOKUP(D24,'March Cancel - checking results'!$C:$M,9,0) -> LSS | L24: =VLOOKUP(D24,'March Cancel - checking results'!$C:$M,10,0) -> 45474 | M24: =VLOOKUP(D24,'March Cancel - checking results'!$C:$M,11,0) -> Standalone | N24: =VLOOKUP(D24,'March Cancel - checking results'!$C:$Q,15,0) -> Everything ANS or LSS
A25: 76197109 | B25: LEXUS OF WESLEY CHAPEL | C25: T-5929 | D25: 76197109 | E25: 2503116 | F25: CDK Reseller - Base Fee | G25: 300 | H25: 200 | I25: =VLOOKUP(D25,'3.10 Cancel List'!$C:$C,1,0) -> #N/A
A26: 76201836 | B26: VOLVO CARS WEST HOUSTON | C26: T-14393 | D26: 76201836 | E26: 3000889 | F26: CDK Reseller - Base Fee | G26: 300 | H26: 200 | I26: =VLOOKUP(D26,'3.10 Cancel List'!$C:$C,1,0) -> #N/A
A27: 76202516 | B27: KEN GANLEY TOYOTA | C27: T-6016 | D27: 76202516 | E27: 1500109 | F27: CDK Reseller - Base Fee | G27: 300 | H27: 200 | I27: =VLOOKUP(D27,'3.10 Cancel List'!$C:$C,1,0) -> 76202516 | J27: Yes | K27: =VLOOKUP(D27,'March Cancel - checking results'!$C:$M,9,0) -> LSS | L27: =VLOOKUP(D27,'March Cancel - checking results'!$C:$M,10,0) -> 45689 | M27: =VLOOKUP(D27,'March Cancel - checking results'!$C:$M,11,0) -> Suite | N27: =VLOOKUP(D27,'March Cancel - checking results'!$C:$Q,15,0) -> CDKS - LSS
A28: 76204182 | B28: Saskatoon South Hyundai | C28: T-9598 | D28: 76204182 | E28: 2001776 | F28: CDK Reseller - Base Fee | G28: 300 | H28: 200 | I28: =VLOOKUP(D28,'3.10 Cancel List'!$C:$C,1,0) -> 76204182 | J28: Yes | K28: =VLOOKUP(D28,'March Cancel - checking results'!$C:$M,9,0) -> ANS | L28: =VLOOKUP(D28,'March Cancel - checking results'!$C:$M,10,0) -> 45627 | M28: =VLOOKUP(D28,'March Cancel - checking results'!$C:$M,11,0) -> Suite | N28: =VLOOKUP(D28,'March Cancel - checking results'!$C:$Q,15,0) -> SUITE INS
A29: 76205609 | B29: FRIENDSHIP FORD LENOIR | C29: T-3955 | D29: 76205609 | E29: 2000850 | F29: CDK Reseller - Base Fee | G29: 300 | H29: 200 | I29: =VLOOKUP(D29,'3.10 Cancel List'!$C:$C,1,0) -> #N/A
A30: 76215310 | B30: DON AYRES ACURA | C30: T-10911 | D30: 76215310 | E30: 2700010 | F30: CDK Reseller - Base Fee | G30: 300 | H30: 200 | I30: =VLOOKUP(D30,'3.10 Cancel List'!$C:$C,1,0) -> #N/A
A31: 76215380 | B31: Purdy Mazda | C31: T-3912 | D31: 76215380 | E31: 2000797 | F31: CDK Reseller - Base Fee | G31: 450 | H31: 200 | I31: =VLOOKUP(D31,'3.10 Cancel List'!$C:$C,1,0) -> #N/A
A32: 76217036 | B32: CAROLINA KIA OF HIGH POINT | C32: T-11253 | D32: 76217036 | E32: 2501508 | F32: CDK Reseller - Base Fee | G32: 300 | H32: 200 | I32: =VLOOKUP(D32,'3.10 Cancel List'!$C:$C,1,0) -> #N/A
A33: 76217358 | B33: ROCKY MOUNT TOYOTA | C33: T-4254 | D33: 76217358 | E33: 3000423 | F33: CDK Reseller - Base Fee | G33: 400 | H33: 200 | I33: =VLOOKUP(D33,'3.10 Cancel List'!$C:$C,1,0) -> 76217358 | J33: Yes | K33: =VLOOKUP(D33,'March Cancel - checking results'!$C:$M,9,0) -> LSS | L33: =VLOOKUP(D33,'March Cancel - checking results'!$C:$M,10,0) -> 45383 | M33: =VLOOKUP(D33,'March Cancel - checking results'!$C:$M,11,0) -> Standalone | N33: =VLOOKUP(D33,'March Cancel - checking results'!$C:$Q,15,0) -> CDK CONVERSION - SYS GENERATED
A34: 76220331 | B34: SUBARU SOUTH TAMPA | C34: T-8125 | D34: 76220331 | E34: 2501681 | F34: CDK Reseller - Base Fee | G34: 300 | H34: 200 | I34: =VLOOKUP(D34,'3.10 Cancel List'!$C:$C,1,0) -> #N/A
A35: 76220332 | B35: SUBARU NORTH ORLANDO | C35: T-8094 | D35: 76220332 | E35: 2501684 | F35: CDK Reseller - Base Fee | G35: 300 | H35: 200 | I35: =VLOOKUP(D35,'3.10 Cancel List'!$C:$C,1,0) -> #N/A
A36: 76225712 | B36: HGREG NISSAN BUENA PARK | C36: T-3995 | D36: 76225712 | E36: 2502268 | F36: CDK Reseller - Base Fee | G36: 450 | H36: 200 | I36: =VLOOKUP(D36,'3.10 Cancel List'!$C:$C,1,0) -> 76225712 | J36: Yes | K36: =VLOOKUP(D36,'March Cancel - checking results'!$C:$M,9,0) -> LSS | L36: =VLOOKUP(D36,'March Cancel - checking results'!$C:$M,10,0) -> 45931 | M36: =VLOOKUP(D36,'March Cancel - checking results'!$C:$M,11,0) -> Suite | N36: =VLOOKUP(D36,'March Cancel - checking results'!$C:$Q,15,0) -> CDK CONVERSION - SYS GENERATED
A37: 76227121 | B37: MARTHALER HONDA TOYOTA OF ASHLAND | C37: T-4122 | D37: 76227121 | E37: 2502262 | F37: CDK Reseller - Base Fee | G37: 450 | H37: 200 | I37: =VLOOKUP(D37,'3.10 Cancel List'!$C:$C,1,0) -> 76227121 | K37: =VLOOKUP(D37,'March Cancel - checking results'!$C:$M,9,0) -> LSS | L37: =VLOOKUP(D37,'March Cancel - checking results'!$C:$M,10,0) -> 45566 | M37: =VLOOKUP(D37,'March Cancel - checking results'!$C:$M,11,0) -> Suite | N37: =VLOOKUP(D37,'March Cancel - checking results'!$C:$Q,15,0) -> Price/Value Proposition
A38: 76227134 | B38: INFINITI OF NORTHERN KENTUCKY | C38: T-9119 | D38: 76227134 | E38: 2503481 | F38: CDK Reseller - Base Fee | G38: 300 | H38: 200 | I38: =VLOOKUP(D38,'3.10 Cancel List'!$C:$C,1,0) -> 76227134 | K38: =VLOOKUP(D38,'March Cancel - checking results'!$C:$M,9,0) -> LSS | L38: =VLOOKUP(D38,'March Cancel - checking results'!$C:$M,10,0) -> 45931 | M38: =VLOOKUP(D38,'March Cancel - checking results'!$C:$M,11,0) -> Suite | N38: =VLOOKUP(D38,'March Cancel - checking results'!$C:$Q,15,0) -> Ownership Change / FOS ANS
A39: 76227679 | B39: Express Chevrolet | C39: T-9807 | D39: 76227679 | E39: 2001988 | F39: CDK Reseller - Base Fee | G39: 300 | H39: 200 | I39: =VLOOKUP(D39,'3.10 Cancel List'!$C:$C,1,0) -> 76227679 | K39: =VLOOKUP(D39,'March Cancel - checking results'!$C:$M,9,0) -> LSS | L39: =VLOOKUP(D39,'March Cancel - checking results'!$C:$M,10,0) -> 46381 | M39: =VLOOKUP(D39,'March Cancel - checking results'!$C:$M,11,0) -> Suite | N39: =VLOOKUP(D39,'March Cancel - checking results'!$C:$Q,15,0) -> CDK CONVERSION - SYS GENERATED
A40: 76227757 | B40: Spitzer Ford Dubois | C40: T-5725 | D40: 76227757 | E40: 2502508 | F40: CDK Reseller - Base Fee | G40: 400 | H40: 200 | I40: =VLOOKUP(D40,'3.10 Cancel List'!$C:$C,1,0) -> 76227757 | K40: =VLOOKUP(D40,'March Cancel - checking results'!$C:$M,9,0) -> LSS | L40: =VLOOKUP(D40,'March Cancel - checking results'!$C:$M,10,0) -> 45627 | M40: =VLOOKUP(D40,'March Cancel - checking results'!$C:$M,11,0) -> Standalone | N40: =VLOOKUP(D40,'March Cancel - checking results'!$C:$Q,15,0) -> CDK CONVERSION
A41: 76228229 | B41: INFINITI of Montgomery | C41: T-7174 | D41: 76228229 | E41: 2502240 | F41: CDK Reseller - Base Fee | G41: 300 | H41: 200 | I41: =VLOOKUP(D41,'3.10 Cancel List'!$C:$C,1,0) -> 76228229 | K41: =VLOOKUP(D41,'March Cancel - checking results'!$C:$M,9,0) -> 0 | L41: =VLOOKUP(D41,'March Cancel - checking results'!$C:$M,10,0) -> 0 | M41: =VLOOKUP(D41,'March Cancel - checking results'!$C:$M,11,0) -> 0 | N41: =VLOOKUP(D41,'March Cancel - checking results'!$C:$Q,15,0) -> SV NOT ON CONTRACT
A42: 76228237 | B42: PINE BELT MAZDA - NJ | C42: T-4219 | D42: 76228237 | E42: 2001918 | F42: CDK Reseller - Base Fee | G42: 450 | H42: 200 | I42: =VLOOKUP(D42,'3.10 Cancel List'!$C:$C,1,0) -> 76228237 | K42: =VLOOKUP(D42,'March Cancel - checking results'!$C:$M,9,0) -> LSS | L42: =VLOOKUP(D42,'March Cancel - checking results'!$C:$M,10,0) -> 45474 | M42: =VLOOKUP(D42,'March Cancel - checking results'!$C:$M,11,0) -> Standalone | N42: =VLOOKUP(D42,'March Cancel - checking results'!$C:$Q,15,0) -> Price/Value Proposition
A43: 76228316 | B43: Genesis West Houston | C43: T-7224 | D43: 76228316 | E43: 2001986 | F43: CDK Reseller - Base Fee | G43: 300 | H43: 200 | I43: =VLOOKUP(D43,'3.10 Cancel List'!$C:$C,1,0) -> 76228316 | K43: =VLOOKUP(D43,'March Cancel - checking results'!$C:$M,9,0) -> LSS | L43: =VLOOKUP(D43,'March Cancel - checking results'!$C:$M,10,0) -> 45413 | M43: =VLOOKUP(D43,'March Cancel - checking results'!$C:$M,11,0) -> Suite | N43: =VLOOKUP(D43,'March Cancel - checking results'!$C:$Q,15,0) -> CDK CONVERSION - SYS GENERATED
A44: 76228629 | B44: MIDLANDS TOYOTA | C44: T-4159 | D44: 76228629 | E44: 2001956 | F44: CDK Reseller - Base Fee | G44: 450 | H44: 200 | I44: =VLOOKUP(D44,'3.10 Cancel List'!$C:$C,1,0) -> 76228629 | K44: =VLOOKUP(D44,'March Cancel - checking results'!$C:$M,9,0) -> LSS | L44: =VLOOKUP(D44,'March Cancel - checking results'!$C:$M,10,0) -> 46106 | M44: =VLOOKUP(D44,'March Cancel - checking results'!$C:$M,11,0) -> Suite | N44: =VLOOKUP(D44,'March Cancel - checking results'!$C:$Q,15,0) -> CDK CONVERSION
A45: 76228727 | B45: HAMBLOCK FORD LINCOLN | C45: T-14818 | D45: 76228727 | E45: 8054 | F45: CDK Reseller - Base Fee | G45: 300 | H45: 200 | I45: =VLOOKUP(D45,'3.10 Cancel List'!$C:$C,1,0) -> #N/A
A46: 76229253 | B46: BRAVO NISSAN OF VICTORIA | C46: T-5712 | D46: 76229253 | E46: 2002721 | F46: CDK Reseller - Base Fee | G46: 300 | H46: 200 | I46: =VLOOKUP(D46,'3.10 Cancel List'!$C:$C,1,0) -> 76229253 | K46: =VLOOKUP(D46,'March Cancel - checking results'!$C:$M,9,0) -> LSS | L46: =VLOOKUP(D46,'March Cancel - checking results'!$C:$M,10,0) -> 45778 | M46: =VLOOKUP(D46,'March Cancel - checking results'!$C:$M,11,0) -> Suite | N46: =VLOOKUP(D46,'March Cancel - checking results'!$C:$Q,15,0) -> CDK CONVERSION - SYS GENERATED
A47: 76229684 | B47: UNITY CHEVROLET CADILLAC | C47: T-6185 | D47: 76229684 | E47: 2002036 | F47: CDK Reseller - Base Fee | G47: 400 | H47: 200 | I47: =VLOOKUP(D47,'3.10 Cancel List'!$C:$C,1,0) -> 76229684 | K47: =VLOOKUP(D47,'March Cancel - checking results'!$C:$M,9,0) -> LSS | L47: =VLOOKUP(D47,'March Cancel - checking results'!$C:$M,10,0) -> 45870 | M47: =VLOOKUP(D47,'March Cancel - checking results'!$C:$M,11,0) -> Standalone | N47: =VLOOKUP(D47,'March Cancel - checking results'!$C:$Q,15,0) -> OWNERSHIP CHANGE
A48: 76229942 | B48: KOCH ROUTE 2 TOYOTA | C48: T-4092 | D48: 76229942 | E48: 2502402 | F48: CDK Reseller - Base Fee | G48: 450 | H48: 200 | I48: =VLOOKUP(D48,'3.10 Cancel List'!$C:$C,1,0) -> 76229942 | K48: =VLOOKUP(D48,'March Cancel - checking results'!$C:$M,9,0) -> LSS | L48: =VLOOKUP(D48,'March Cancel - checking results'!$C:$M,10,0) -> 45323 | M48: =VLOOKUP(D48,'March Cancel - checking results'!$C:$M,11,0) -> Suite | N48: =VLOOKUP(D48,'March Cancel - checking results'!$C:$Q,15,0) -> Price/Value Proposition
A49: 76230156 | B49: FIRELANDS CHEVROLET BUICK | C49: T-3933 | D49: 76230156 | E49: 2002068 | F49: CDK Reseller - Base Fee | G49: 450 | H49: 200 | I49: =VLOOKUP(D49,'3.10 Cancel List'!$C:$C,1,0) -> #N/A
A50: 76230427 | B50: PUENTE HILLS TOYOTA | C50: T-6028 | D50: 76230427 | E50: 9005 | F50: CDK Reseller - Base Fee | G50: 300 | H50: 200 | I50: =VLOOKUP(D50,'3.10 Cancel List'!$C:$C,1,0) -> 76230427 | K50: =VLOOKUP(D50,'March Cancel - checking results'!$C:$M,9,0) -> LSS | L50: =VLOOKUP(D50,'March Cancel - checking results'!$C:$M,10,0) -> 45748 | M50: =VLOOKUP(D50,'March Cancel - checking results'!$C:$M,11,0) -> Suite | N50: =VLOOKUP(D50,'March Cancel - checking results'!$C:$Q,15,0) -> CLEANUP
A51: 76231689 | B51: LONG-LEWIS FORD LINCOLN | C51: T-14170 | D51: 76231689 | E51: 2700004 | F51: CDK Reseller - Base Fee | G51: 300 | H51: 200 | I51: =VLOOKUP(D51,'3.10 Cancel List'!$C:$C,1,0) -> #N/A
A52: 76231928 | B52: Spitzer Ford St. Mary's | C52: T-5727 | D52: 76231928 | E52: 2502571 | F52: CDK Reseller - Base Fee | G52: 400 | H52: 200 | I52: =VLOOKUP(D52,'3.10 Cancel List'!$C:$C,1,0) -> 76231928 | K52: =VLOOKUP(D52,'March Cancel - checking results'!$C:$M,9,0) -> LSS | L52: =VLOOKUP(D52,'March Cancel - checking results'!$C:$M,10,0) -> 45170 | M52: =VLOOKUP(D52,'March Cancel - checking results'!$C:$M,11,0) -> Standalone | N52: =VLOOKUP(D52,'March Cancel - checking results'!$C:$Q,15,0) -> CDK CONVERSION
A53: 76232064 | B53: Tucson Subaru | C53: T-4488 | D53: 76232064 | E53: 2502968 | F53: CDK Reseller - Base Fee | G53: 300 | H53: 200 | I53: =VLOOKUP(D53,'3.10 Cancel List'!$C:$C,1,0) -> 76232064 | K53: =VLOOKUP(D53,'March Cancel - checking results'!$C:$M,9,0) -> LSS | L53: =VLOOKUP(D53,'March Cancel - checking results'!$C:$M,10,0) -> 45383 | M53: =VLOOKUP(D53,'March Cancel - checking results'!$C:$M,11,0) -> Suite | N53: =VLOOKUP(D53,'March Cancel - checking results'!$C:$Q,15,0) -> CDK CONVERSION
A54: 76232553 | B54: NISSAN OF THE MAIN LINE | C54: T-7916 | D54: 76232553 | E54: 2502656 | F54: CDK Reseller - Base Fee | G54: 300 | H54: 200 | I54: =VLOOKUP(D54,'3.10 Cancel List'!$C:$C,1,0) -> 76232553 | K54: =VLOOKUP(D54,'March Cancel - checking results'!$C:$M,9,0) -> ANS | L54: =VLOOKUP(D54,'March Cancel - checking results'!$C:$M,10,0) -> 45108 | M54: =VLOOKUP(D54,'March Cancel - checking results'!$C:$M,11,0) -> Suite | N54: =VLOOKUP(D54,'March Cancel - checking results'!$C:$Q,15,0) -> CDKS LSS
A55: 76232596 | B55: MENKE BUICK GMC SCHOFIELD | C55: T-4146 | D55: 76232596 | E55: 2500144 | F55: CDK Reseller - Base Fee | G55: 450 | H55: 200 | I55: =VLOOKUP(D55,'3.10 Cancel List'!$C:$C,1,0) -> 76232596 | K55: =VLOOKUP(D55,'March Cancel - checking results'!$C:$M,9,0) -> LSS | L55: =VLOOKUP(D55,'March Cancel - checking results'!$C:$M,10,0) -> 45566 | M55: =VLOOKUP(D55,'March Cancel - checking results'!$C:$M,11,0) -> Suite | N55: =VLOOKUP(D55,'March Cancel - checking results'!$C:$Q,15,0) -> Price/Value Proposition
A56: 76232815 | B56: Downtown Ford Fleet | C56: T-3914 | D56: 76232815 | E56: 0 | F56: CDK Reseller - Base Fee | G56: 400 | H56: 200 | I56: =VLOOKUP(D56,'3.10 Cancel List'!$C:$C,1,0) -> 76232815 | K56: =VLOOKUP(D56,'March Cancel - checking results'!$C:$M,9,0) -> 0 | L56: =VLOOKUP(D56,'March Cancel - checking results'!$C:$M,10,0) -> 0 | M56: =VLOOKUP(D56,'March Cancel - checking results'!$C:$M,11,0) -> 0 | N56: =VLOOKUP(D56,'March Cancel - checking results'!$C:$Q,15,0) -> SV NOT ON CONTRACT
A57: 76233048 | B57: AUDI KIRKWOOD | C57: T-1025 | D57: 76233048 | E57: 2002132 | F57: CDK Reseller - Base Fee | G57: 450 | H57: 200 | I57: =VLOOKUP(D57,'3.10 Cancel List'!$C:$C,1,0) -> 76233048 | K57: =VLOOKUP(D57,'March Cancel - checking results'!$C:$M,9,0) -> LSS | L57: =VLOOKUP(D57,'March Cancel - checking results'!$C:$M,10,0) -> 45839 | M57: =VLOOKUP(D57,'March Cancel - checking results'!$C:$M,11,0) -> Suite | N57: =VLOOKUP(D57,'March Cancel - checking results'!$C:$Q,15,0) -> cdk conversion
A58: 76233242 | B58: Tonkin Hillsboro Chevrolet | C58: T-4332 | D58: 76233242 | E58: 0 | F58: CDK Reseller - Base Fee | G58: 400 | H58: 200 | I58: =VLOOKUP(D58,'3.10 Cancel List'!$C:$C,1,0) -> 76233242 | K58: =VLOOKUP(D58,'March Cancel - checking results'!$C:$M,9,0) -> LSS | L58: =VLOOKUP(D58,'March Cancel - checking results'!$C:$M,10,0) -> 45261 | M58: =VLOOKUP(D58,'March Cancel - checking results'!$C:$M,11,0) -> Standalone | N58: =VLOOKUP(D58,'March Cancel - checking results'!$C:$Q,15,0) -> Low or No Utilization
A59: 76234206 | B59: EDWARDS CHRYSLER DODGE JEEP RAM NE | C59: T-9008 | D59: 76234206 | E59: 2003022 | F59: CDK Reseller - Base Fee | G59: 300 | H59: 200 | I59: =VLOOKUP(D59,'3.10 Cancel List'!$C:$C,1,0) -> 76234206 | K59: =VLOOKUP(D59,'March Cancel - checking results'!$C:$M,9,0) -> ANS | L59: =VLOOKUP(D59,'March Cancel - checking results'!$C:$M,10,0) -> 45352 | M59: =VLOOKUP(D59,'March Cancel - checking results'!$C:$M,11,0) -> Suite | N59: =VLOOKUP(D59,'March Cancel - checking results'!$C:$Q,15,0) -> suite ANS
A60: 76234275 | B60: PLATTNER'S OCALA VOLVO SUBARU | C60: T-4222 | D60: 76234275 | E60: 0 | F60: CDK Reseller - Base Fee | G60: 400 | H60: 200 | I60: =VLOOKUP(D60,'3.10 Cancel List'!$C:$C,1,0) -> 76234275 | K60: =VLOOKUP(D60,'March Cancel - checking results'!$C:$M,9,0) -> LSS | L60: =VLOOKUP(D60,'March Cancel - checking results'!$C:$M,10,0) -> 45323 | M60: =VLOOKUP(D60,'March Cancel - checking results'!$C:$M,11,0) -> Standalone | N60: =VLOOKUP(D60,'March Cancel - checking results'!$C:$Q,15,0) -> Low or No Utilization
A61: 76235514 | B61: Genesis of North Charleston | C61: T-11265 | D61: 76235514 | E61: 2503145 | F61: CDK Reseller - Base Fee | G61: 300 | H61: 200 | I61: =VLOOKUP(D61,'3.10 Cancel List'!$C:$C,1,0) -> 76235514 | K61: =VLOOKUP(D61,'March Cancel - checking results'!$C:$M,9,0) -> 0 | L61: =VLOOKUP(D61,'March Cancel - checking results'!$C:$M,10,0) -> 0 | M61: =VLOOKUP(D61,'March Cancel - checking results'!$C:$M,11,0) -> 0 | N61: =VLOOKUP(D61,'March Cancel - checking results'!$C:$Q,15,0) -> SV NOT ON CONTRACT
A62: 76236622 | B62: LAND ROVER ALEXANDRIA | C62: T-6019 | D62: 76236622 | E62: 2503117 | F62: CDK Reseller - Base Fee | G62: 300 | H62: 200 | I62: =VLOOKUP(D62,'3.10 Cancel List'!$C:$C,1,0) -> 76236622 | K62: =VLOOKUP(D62,'March Cancel - checking results'!$C:$M,9,0) -> LSS | L62: =VLOOKUP(D62,'March Cancel - checking results'!$C:$M,10,0) -> 45444 | M62: =VLOOKUP(D62,'March Cancel - checking results'!$C:$M,11,0) -> Suite | N62: =VLOOKUP(D62,'March Cancel - checking results'!$C:$Q,15,0) -> Low or No Utilization
A63: 76237142 | B63: PRIORITY TOYOTA CHESAPEAKE | C63: T-5923 | D63: 76237142 | E63: 2002655 | F63: CDK Reseller - Base Fee | G63: 300 | H63: 200 | I63: =VLOOKUP(D63,'3.10 Cancel List'!$C:$C,1,0) -> 76237142 | K63: =VLOOKUP(D63,'March Cancel - checking results'!$C:$M,9,0) -> LSS | L63: =VLOOKUP(D63,'March Cancel - checking results'!$C:$M,10,0) -> 45778 | M63: =VLOOKUP(D63,'March Cancel - checking results'!$C:$M,11,0) -> Suite | N63: =VLOOKUP(D63,'March Cancel - checking results'!$C:$Q,15,0) -> Dealership Operation Changes
... A67: 76238760 | B67: FRED ANDERSON NISSAN OF GREER | C67: T-5893 | D67: 76238760 | E67: 11073 | F67: CDK Reseller - Base Fee | G67: 300 | H67: 200 | I67: =VLOOKUP(D67,'3.10 Cancel List'!$C:$C,1,0) -> 76238760 | K67: =VLOOKUP(D67,'March Cancel - checking results'!$C:$M,9,0) -> LSS | L67: =VLOOKUP(D67,'March Cancel - checking results'!$C:$M,10,0) -> 45505 | M67: =VLOOKUP(D67,'March Cancel - checking results'!$C:$M,11,0) -> Suite | N67: =VLOOKUP(D67,'March Cancel - checking results'!$C:$Q,15,0) -> CDK CONVERSION - SYS GENERATED
A68: 76240142 | B68: NORTHSIDE FORD TRUCK | C68: T-14150 | D68: 76240142 | E68: 2000770 | F68: CDK Reseller - Base Fee | G68: 300 | H68: 200 | I68: =VLOOKUP(D68,'3.10 Cancel List'!$C:$C,1,0) -> #N/A
A69: 76240429 | B69: FRED ANDERSON CHEVROLET | C69: T-5925 | D69: 76240429 | E69: 2002703 | F69: CDK Reseller - Base Fee | G69: 300 | H69: 200 | I69: =VLOOKUP(D69,'3.10 Cancel List'!$C:$C,1,0) -> 76240429 | K69: =VLOOKUP(D69,'March Cancel - checking results'!$C:$M,9,0) -> ANS | L69: =VLOOKUP(D69,'March Cancel - checking results'!$C:$M,10,0) -> 45139 | M69: =VLOOKUP(D69,'March Cancel - checking results'!$C:$M,11,0) -> Standalone | N69: =VLOOKUP(D69,'March Cancel - checking results'!$C:$Q,15,0) -> ENTIRE ANS
A70: 76241005 | B70: SUBARU OF MIDLAND | C70: T-6783 | D70: 76241005 | E70: 2002833 | F70: CDK Reseller - Base Fee | G70: 300 | H70: 200 | I70: =VLOOKUP(D70,'3.10 Cancel List'!$C:$C,1,0) -> 76241005 | K70: =VLOOKUP(D70,'March Cancel - checking results'!$C:$M,9,0) -> LSS | L70: =VLOOKUP(D70,'March Cancel - checking results'!$C:$M,10,0) -> 45870 | M70: =VLOOKUP(D70,'March Cancel - checking results'!$C:$M,11,0) -> Suite | N70: =VLOOKUP(D70,'March Cancel - checking results'!$C:$Q,15,0) -> Price/Value Proposition
A71: 76241171 | B71: MERCEDES BENZ OF RICHMOND | C71: T-13505 | D71: 76241171 | E71: 2002774 | F71: CDK Reseller - Base Fee | G71: 300 | H71: 200 | I71: =VLOOKUP(D71,'3.10 Cancel List'!$C:$C,1,0) -> 76241171 | K71: =VLOOKUP(D71,'March Cancel - checking results'!$C:$M,9,0) -> LSS | L71: =VLOOKUP(D71,'March Cancel - checking results'!$C:$M,10,0) -> 45962 | M71: =VLOOKUP(D71,'March Cancel - checking results'!$C:$M,11,0) -> Standalone | N71: =VLOOKUP(D71,'March Cancel - checking results'!$C:$Q,15,0) -> Price/Value Proposition
A72: 76241172 | B72: MERCEDES BENZ OF MIDLOTHIAN | C72: T-8289 | D72: 76241172 | E72: 2002773 | F72: CDK Reseller - Base Fee | G72: 400 | H72: 200 | I72: =VLOOKUP(D72,'3.10 Cancel List'!$C:$C,1,0) -> 76241172 | K72: =VLOOKUP(D72,'March Cancel - checking results'!$C:$M,9,0) -> LSS | L72: =VLOOKUP(D72,'March Cancel - checking results'!$C:$M,10,0) -> 45962 | M72: =VLOOKUP(D72,'March Cancel - checking results'!$C:$M,11,0) -> Standalone | N72: =VLOOKUP(D72,'March Cancel - checking results'!$C:$Q,15,0) -> Price/Value Proposition
A73: 76241447 | B73: LAND ROVER SHREVEPORT.1 | C73: T-6453 | D73: 76241447 | E73: 2002789 | F73: CDK Reseller - Base Fee | G73: 300 | H73: 200 | I73: =VLOOKUP(D73,'3.10 Cancel List'!$C:$C,1,0) -> 76241447 | K73: =VLOOKUP(D73,'March Cancel - checking results'!$C:$M,9,0) -> LSS | L73: =VLOOKUP(D73,'March Cancel - checking results'!$C:$M,10,0) -> 45717 | M73: =VLOOKUP(D73,'March Cancel - checking results'!$C:$M,11,0) -> Suite | N73: =VLOOKUP(D73,'March Cancel - checking results'!$C:$Q,15,0) -> CDK CONVERSION
A74: 76241522 | B74: SMAIL FORD | C74: T-6458 | D74: 76241522 | E74: 2002804 | F74: CDK Reseller - Base Fee | G74: 300 | H74: 200 | I74: =VLOOKUP(D74,'3.10 Cancel List'!$C:$C,1,0) -> 76241522 | K74: =VLOOKUP(D74,'March Cancel - checking results'!$C:$M,9,0) -> LSS | L74: =VLOOKUP(D74,'March Cancel - checking results'!$C:$M,10,0) -> 46023 | M74: =VLOOKUP(D74,'March Cancel - checking results'!$C:$M,11,0) -> Standalone | N74: =VLOOKUP(D74,'March Cancel - checking results'!$C:$Q,15,0) -> CDK CONVERSION - SYS GENERATED
A75: 76243293 | B75: DAYTONAUTOS LLC DBA MAZDA OF DAYTON | C75: T-8002 | D75: 76243293 | E75: 2503344 | F75: CDK Reseller - Base Fee | G75: 300 | H75: 200 | I75: =VLOOKUP(D75,'3.10 Cancel List'!$C:$C,1,0) -> 76243293 | K75: =VLOOKUP(D75,'March Cancel - checking results'!$C:$M,9,0) -> ANS | L75: =VLOOKUP(D75,'March Cancel - checking results'!$C:$M,10,0) -> 45509 | M75: =VLOOKUP(D75,'March Cancel - checking results'!$C:$M,11,0) -> Suite | N75: =VLOOKUP(D75,'March Cancel - checking results'!$C:$Q,15,0) -> 0
A76: 76244521 | B76: Go Kia West | C76: T-9434 | D76: 76244521 | E76: 2003072 | F76: CDK Reseller - Base Fee | G76: 300 | H76: 200 | I76: =VLOOKUP(D76,'3.10 Cancel List'!$C:$C,1,0) -> 76244521 | K76: =VLOOKUP(D76,'March Cancel - checking results'!$C:$M,9,0) -> 0 | L76: =VLOOKUP(D76,'March Cancel - checking results'!$C:$M,10,0) -> 0 | M76: =VLOOKUP(D76,'March Cancel - checking results'!$C:$M,11,0) -> 0 | N76: =VLOOKUP(D76,'March Cancel - checking results'!$C:$Q,15,0) -> SV NOT ON CONTRACT
A77: 76244781 | B77: FOX VALLEY VOLKSWAGEN OF CRYSTAL LAKE | C77: T-7456 | D77: 76244781 | E77: 2502176 | F77: CDK Reseller - Base Fee | G77: 400 | H77: 200 | I77: =VLOOKUP(D77,'3.10 Cancel List'!$C:$C,1,0) -> 76244781 | K77: =VLOOKUP(D77,'March Cancel - checking results'!$C:$M,9,0) -> LSS | L77: =VLOOKUP(D77,'March Cancel - checking results'!$C:$M,10,0) -> 45385 | M77: =VLOOKUP(D77,'March Cancel - checking results'!$C:$M,11,0) -> Standalone | N77: =VLOOKUP(D77,'March Cancel - checking results'!$C:$Q,15,0) -> Price/Value Proposition
A78: 76245003 | B78: GRUBBS NISSAN | C78: T-8091 | D78: 76245003 | E78: 2002906 | F78: CDK Reseller - Base Fee | G78: 300 | H78: 200 | I78: =VLOOKUP(D78,'3.10 Cancel List'!$C:$C,1,0) -> 76245003 | K78: =VLOOKUP(D78,'March Cancel - checking results'!$C:$M,9,0) -> LSS | L78: =VLOOKUP(D78,'March Cancel - checking results'!$C:$M,10,0) -> 45839 | M78: =VLOOKUP(D78,'March Cancel - checking results'!$C:$M,11,0) -> Suite | N78: =VLOOKUP(D78,'March Cancel - checking results'!$C:$Q,15,0) -> CDK conversion
A79: 76245016 | B79: FOLSOM LAKE CHRYSLER DODGE JEEP RAM | C79: T-7881 | D79: 76245016 | E79: 2002905 | F79: CDK Reseller - Base Fee | G79: 300 | H79: 200 | I79: =VLOOKUP(D79,'3.10 Cancel List'!$C:$C,1,0) -> 76245016 | K79: =VLOOKUP(D79,'March Cancel - checking results'!$C:$M,9,0) -> ANS | L79: =VLOOKUP(D79,'March Cancel - checking results'!$C:$M,10,0) -> 45323 | M79: =VLOOKUP(D79,'March Cancel - checking results'!$C:$M,11,0) -> Suite | N79: =VLOOKUP(D79,'March Cancel - checking results'!$C:$Q,15,0) -> 0
A80: 76245040 | B80: CHIEF TWO LLC DBA CROWN DODGE AND CHRYSLER | C80: T-9614 | D80: 76245040 | E80: 2503548 | F80: CDK Reseller - Base Fee | G80: 300 | H80: 200 | I80: =VLOOKUP(D80,'3.10 Cancel List'!$C:$C,1,0) -> #N/A
A81: 76246888 | B81: Pilson CDJR | C81: T-9433 | D81: 76246888 | E81: 2503531 | F81: CDK Reseller - Base Fee | G81: 300 | H81: 200 | I81: =VLOOKUP(D81,'3.10 Cancel List'!$C:$C,1,0) -> 76246888 | K81: =VLOOKUP(D81,'March Cancel - checking results'!$C:$M,9,0) -> 0 | L81: =VLOOKUP(D81,'March Cancel - checking results'!$C:$M,10,0) -> 0 | M81: =VLOOKUP(D81,'March Cancel - checking results'!$C:$M,11,0) -> 0 | N81: =VLOOKUP(D81,'March Cancel - checking results'!$C:$Q,15,0) -> SV NOT ON CONTRACT
A82: 76250378 | B82: GALEANA CDJR MT. PLEASANT | C82: T-8809 | D82: 76250378 | E82: 2503449 | F82: CDK Reseller - Base Fee | G82: 300 | H82: 200 | I82: =VLOOKUP(D82,'3.10 Cancel List'!$C:$C,1,0) -> 76250378 | K82: =VLOOKUP(D82,'March Cancel - checking results'!$C:$M,9,0) -> LSS | L82: =VLOOKUP(D82,'March Cancel - checking results'!$C:$M,10,0) -> 45719 | M82: =VLOOKUP(D82,'March Cancel - checking results'!$C:$M,11,0) -> Suite | N82: =VLOOKUP(D82,'March Cancel - checking results'!$C:$Q,15,0) -> CDK conversion
A83: 76252046 | B83: ALFA ROMEO OF HAZLET | C83: T-9266 | D83: 76252046 | E83: 2503503 | F83: CDK Reseller - Base Fee | G83: 300 | H83: 200 | I83: =VLOOKUP(D83,'3.10 Cancel List'!$C:$C,1,0) -> 76252046 | K83: =VLOOKUP(D83,'March Cancel - checking results'!$C:$M,9,0) -> LSS | L83: =VLOOKUP(D83,'March Cancel - checking results'!$C:$M,10,0) -> 45712 | M83: =VLOOKUP(D83,'March Cancel - checking results'!$C:$M,11,0) -> Suite | N83: =VLOOKUP(D83,'March Cancel - checking results'!$C:$Q,15,0) -> REASON UNKOWN
A84: 76253766 | B84: MVP MITSUBISHI | C84: T-10869 | D84: 76253766 | E84: 2503580 | F84: CDK Reseller - Base Fee | G84: 300 | H84: 200 | I84: =VLOOKUP(D84,'3.10 Cancel List'!$C:$C,1,0) -> 76253766 | K84: =VLOOKUP(D84,'March Cancel - checking results'!$C:$M,9,0) -> ANS | L84: =VLOOKUP(D84,'March Cancel - checking results'!$C:$M,10,0) -> 45713 | M84: =VLOOKUP(D84,'March Cancel - checking results'!$C:$M,11,0) -> Suite | N84: =VLOOKUP(D84,'March Cancel - checking results'!$C:$Q,15,0) -> DMS ANS
A85: 76253767 | B85: MVP KIA | C85: T-10868 | D85: 76253767 | E85: 2503579 | F85: CDK Reseller - Base Fee | G85: 300 | H85: 200 | I85: =VLOOKUP(D85,'3.10 Cancel List'!$C:$C,1,0) -> 76253767 | K85: =VLOOKUP(D85,'March Cancel - checking results'!$C:$M,9,0) -> ANS | L85: =VLOOKUP(D85,'March Cancel - checking results'!$C:$M,10,0) -> 45689 | M85: =VLOOKUP(D85,'March Cancel - checking results'!$C:$M,11,0) -> Suite | N85: =VLOOKUP(D85,'March Cancel - checking results'!$C:$Q,15,0) -> DMS ANS
A86: 76256562 | B86: McGovern Ford of Beverly | C86: T-13842 | D86: 76256562 | E86: 3000496 | F86: CDK Reseller - Base Fee | G86: 300 | H86: 200 | I86: =VLOOKUP(D86,'3.10 Cancel List'!$C:$C,1,0) -> 76256562 | K86: =VLOOKUP(D86,'March Cancel - checking results'!$C:$M,9,0) -> 0 | L86: =VLOOKUP(D86,'March Cancel - checking results'!$C:$M,10,0) -> 0 | M86: =VLOOKUP(D86,'March Cancel - checking results'!$C:$M,11,0) -> 0 | N86: =VLOOKUP(D86,'March Cancel - checking results'!$C:$Q,15,0) -> SV NOT ON CONTRACT
A87: 76257159 | B87: KIA OF FORT MYERS | C87: T-14803 | D87: 76257159 | E87: 8038 | F87: CDK Reseller - Base Fee | G87: 400 | H87: 200 | I87: =VLOOKUP(D87,'3.10 Cancel List'!$C:$C,1,0) -> #N/A
A88: 76258093 | B88: EUROBAHN MOTORSPORTS | C88: T-14491 | D88: 76258093 | E88: 3000981 | F88: CDK Reseller - Base Fee | G88: 300 | H88: 200 | I88: =VLOOKUP(D88,'3.10 Cancel List'!$C:$C,1,0) -> #N/A
F89: Subtotal Amount | G89: =SUM(G2:G88) -> 29400 | H89: =SUM(H2:H88) -> 17400 | I89: =VLOOKUP(D89,'3.10 Cancel List'!$C:$C,1,0) -> #N/A
F90: total Amount | H90: =G89+H89 -> 46800

Sheet TruVideo May Invoice Gap Sites
A1: CMF | B1: Customer | C1: Contract Number | D1: CMF Number | E1: CID Number | F1: Item | G1: Base Fee | H1: AI Suite Fee | I1: on March 10 Cancel list? | J1: Commentss | K1: Actions | L1: CDK sent Cancellation date | M1: Additional Comments | N1: new CMF
A2: 05088801 | B2: WINTER CHEVROLET CO. INC. | C2: T-5636 | D2: 5088801 | E2: 2503075 | F2: CDK Reseller - Base Fee | G2: 300 | H2: 200 | I2: No | J2: CDK Loss on 3/31/2026 | K2: To Cancel | L2: =VLOOKUP(A2,'CDK Cancel tracking 5.16.26'!$A:$E,5,0) -> #N/A
A3: 05236442 | B3: Smothers European | C3: T-7444 | D3: 5236442 | E3: 3001276 | F3: CDK Reseller - Base Fee | G3: 400 | H3: 200 | I3: No | J3: CDK Loss on 3/31/2026 | K3: To Cancel | L3: =VLOOKUP(A3,'CDK Cancel tracking 5.16.26'!$A:$E,5,0) -> 46143
A4: 08300018 | B4: GRAINGER HONDA | C4: T-13310 | D4: 8300018 | E4: 3000322 | F4: CDK Reseller - Base Fee | G4: 300 | H4: 200 | I4: No | J4: CDK Loss on 3/31/2026 | K4: To Cancel | L4: =VLOOKUP(A4,'CDK Cancel tracking 5.16.26'!$A:$E,5,0) -> 46146
A5: 13093301 | B5: MIKE FINNIN FORD | C5: T-10652 | D5: 13093301 | E5: 2503593 | F5: CDK Reseller - Base Fee | G5: 300 | H5: 200 | I5: No | J5: CDK loss on 4/30/2026 | K5: To Cancel | L5: =VLOOKUP(A5,'CDK Cancel tracking 5.16.26'!$A:$E,5,0) -> #N/A
A6: 25297551 | B6: COLONIAL TOYOTA - CT | C6: T-9268 | D6: 25297551 | E6: 153 | F6: CDK Reseller - Base Fee | G6: 300 | H6: 200 | I6: No | J6: Converted to CMF76234346 in BLG | K6: Retained | L6: =VLOOKUP(A6,'CDK Cancel tracking 5.16.26'!$A:$E,5,0) -> #N/A
A7: 33049702 | B7: Don Ayres Honda | C7: T-11270 | D7: 33049702 | E7: 2700012 | F7: CDK Reseller - Base Fee | G7: 300 | H7: 200 | I7: No | J7: no SV contract for this site found | K7: To Cancel | L7: =VLOOKUP(A7,'CDK Cancel tracking 5.16.26'!$A:$E,5,0) -> #N/A
A8: 37216003 | B8: TC CHEVROLET | C8: T-10901 | D8: 37216003 | E8: 2700001 | F8: CDK Reseller - Base Fee | G8: 300 | H8: 200 | I8: No | J8: CDK Loss on Feb 28, 2026 | K8: To Cancel | L8: =VLOOKUP(A8,'CDK Cancel tracking 5.16.26'!$A:$E,5,0) -> #N/A
A9: 43996001 | B9: PAUL MILLER AUDI | C9: T-4201 | D9: 43996001 | E9: 2502552 | F9: CDK Reseller - Base Fee | G9: 450 | H9: 200 | I9: No | J9: CDK Loss on 3/31/2026 | K9: To Cancel | L9: =VLOOKUP(A9,'CDK Cancel tracking 5.16.26'!$A:$E,5,0) -> #N/A
A10: 71062428 | B10: WINTER HONDA | C10: T-5710 | D10: 71062428 | E10: 2503087 | F10: CDK Reseller - Base Fee | G10: 300 | H10: 200 | I10: No | J10: CDK Loss on 3/31/2026 | K10: To Cancel | L10: =VLOOKUP(A10,'CDK Cancel tracking 5.16.26'!$A:$E,5,0) -> #N/A
A11: 76001666 | B11: KOEPPEL NISSAN | C11: T-4093 | D11: 76001666 | E11: 2501710 | F11: CDK Reseller - Base Fee | G11: 450 | H11: 200 | I11: =VLOOKUP(D11,'3.10 Cancel List'!$C:$C,1,0) -> 76001666 | J11: Buysell to retain - new CMF76257313- Notified TV | K11: Retained
A12: 76018447 | B12: CAROLINA HYUNDAI OF HIGH POINT | C12: T-13384 | D12: 76018447 | E12: 2501591 | F12: CDK Reseller - Base Fee | G12: 300 | H12: 200 | I12: No | J12: CDK Loss on March 15, 2026, | K12: To Cancel | L12: =VLOOKUP(A12,'CDK Cancel tracking 5.16.26'!$A:$E,5,0) -> #N/A
A13: 76025293 | B13: ATLANTIC AUTO EQUIP CORP DBA ATLANTIC TOYOTA | C13: T-1024 | D13: 76025293 | E13: 2502775 | F13: CDK Reseller - Base Fee | G13: 300 | H13: 200 | I13: No | J13: CDK loss on 4/30/2026 | K13: To Cancel | L13: =VLOOKUP(A13,'CDK Cancel tracking 5.16.26'!$A:$E,5,0) -> #N/A
A14: 76028715 | B14: JOHNSON HYUNDAI OF CARY | C14: T-4067 | D14: 76028715 | E14: 2000422 | F14: CDK Reseller - Base Fee | G14: 450 | H14: 200 | I14: =VLOOKUP(D14,'3.10 Cancel List'!$C:$C,1,0) -> 76028715 | J14: Buysell to retain - new CMF 76244599- Notified TV | K14: Retained
A15: 76043277 | B15: PAUL MILLER HONDA OF WEST CALDWELL | C15: T-4204 | D15: 76043277 | E15: 2502505 | F15: CDK Reseller - Base Fee | G15: 450 | H15: 200 | I15: No | J15: CDK Loss on 3/31/2026 | K15: To Cancel | L15: =VLOOKUP(A15,'CDK Cancel tracking 5.16.26'!$A:$E,5,0) -> 46146
A16: 76051500 | B16: RED BANK VOLVO | C16: T-8026 | D16: 76051500 | E16: 2503331 | F16: CDK Reseller - Base Fee | G16: 300 | H16: 200 | I16: =VLOOKUP(D16,'3.10 Cancel List'!$C:$C,1,0) -> 76051500 | J16: Buysell to retain - new CMF 76258384- Notified TV | K16: Retained
A17: 76057672 | B17: MAZDA OF MILFORD | C17: T-4134 | D17: 76057672 | E17: 2501660 | F17: CDK Reseller - Base Fee | G17: 450 | H17: 200 | I17: No | J17: CDK loss on 4/30/2026 | K17: To Cancel | L17: =VLOOKUP(A17,'CDK Cancel tracking 5.16.26'!$A:$E,5,0) -> #N/A
A18: 76097658 | B18: STATELINE MASERATI ALFA ROMEO | C18: T-14496 | D18: 76097658 | E18: 3000911 | F18: CDK Reseller - Base Fee | G18: 300 | H18: 200 | I18: =VLOOKUP(D18,'3.10 Cancel List'!$C:$C,1,0) -> 76097658 | J18: Buysell to retain - new CMF 76257430 - Notified TV | K18: Retained
A19: 76134865 | B19: REINEKE NISSAN | C19: T-13497 | D19: 76134865 | E19: 5113 | F19: CDK Reseller - Base Fee | G19: 300 | H19: 200 | I19: No | J19: CDK Loss on Feb 28, 2026 | K19: To Cancel | L19: =VLOOKUP(A19,'CDK Cancel tracking 5.16.26'!$A:$E,5,0) -> #N/A
A20: 76157327 | B20: MARINA DEL REY TOYOTA SCION | C20: T-4118 | D20: 76157327 | E20: 10190 | F20: CDK Reseller - Base Fee | G20: 300 | H20: 200 | I20: =VLOOKUP(D20,'3.10 Cancel List'!$C:$C,1,0) -> 76157327 | J20: ANS 05/01/2023 Suite CDKS ANS, on TV active usage list, CDK to Review | K20: To Cancel
A21: 76173064 | B21: WEST HOUSTON INFINITI | C21: T-14518 | D21: 76173064 | E21: 3000888 | F21: CDK Reseller - Base Fee | G21: 300 | H21: 200 | I21: No | J21: CDK Loss on 3/31/2026 | K21: To Cancel | L21: =VLOOKUP(A21,'CDK Cancel tracking 5.16.26'!$A:$E,5,0) -> 46146
A22: 76181139 | B22: Mazda of Richmond Hill | C22: T-14525 | D22: 76181139 | E22: 3000966 | F22: CDK Reseller - Base Fee | G22: 300 | H22: 200 | I22: No | J22: CDK Loss on 3/31/2026 | K22: To Cancel | L22: =VLOOKUP(A22,'CDK Cancel tracking 5.16.26'!$A:$E,5,0) -> #N/A
A23: 76184938 | B23: TAYLOR FORD LINCOLN | C23: T-14162 | D23: 76184938 | E23: 3000690 | F23: CDK Reseller - Base Fee | G23: 300 | H23: 200 | I23: No | J23: CDK Loss on Feb 28, 2026 | K23: To Cancel | L23: =VLOOKUP(A23,'CDK Cancel tracking 5.16.26'!$A:$E,5,0) -> #N/A
A24: 76194812 | B24: PUTNAM SUBARU BURLINGAME | C24: T-5627 | D24: 76194812 | E24: 0 | F24: CDK Reseller - Base Fee | G24: 400 | H24: 200 | I24: =VLOOKUP(D24,'3.10 Cancel List'!$C:$C,1,0) -> 76194812 | J24: LSS 07/01/2024 Standalone Everything ANS or LSS | K24: To Cancel
A25: 76197109 | B25: LEXUS OF WESLEY CHAPEL | C25: T-5929 | D25: 76197109 | E25: 2503116 | F25: CDK Reseller - Base Fee | G25: 300 | H25: 200 | I25: No | J25: CDK Loss on 3/31/2026 | K25: To Cancel | L25: =VLOOKUP(A25,'CDK Cancel tracking 5.16.26'!$A:$E,5,0) -> #N/A
A26: 76201836 | B26: VOLVO CARS WEST HOUSTON | C26: T-14393 | D26: 76201836 | E26: 3000889 | F26: CDK Reseller - Base Fee | G26: 300 | H26: 200 | I26: No | J26: CDK Loss on 3/31/2026 | K26: To Cancel | L26: =VLOOKUP(A26,'CDK Cancel tracking 5.16.26'!$A:$E,5,0) -> 46146
A27: 76202516 | B27: KEN GANLEY TOYOTA | C27: T-6016 | D27: 76202516 | E27: 1500109 | F27: CDK Reseller - Base Fee | G27: 300 | H27: 200 | I27: =VLOOKUP(D27,'3.10 Cancel List'!$C:$C,1,0) -> 76202516 | J27: CDK asked to retain | K27: Retained
A28: 76204182 | B28: Saskatoon South Hyundai | C28: T-9598 | D28: 76204182 | E28: 2001776 | F28: CDK Reseller - Base Fee | G28: 300 | H28: 200 | I28: =VLOOKUP(D28,'3.10 Cancel List'!$C:$C,1,0) -> 76204182 | J28: CDK asked to retain | K28: Retained
A29: 76205609 | B29: FRIENDSHIP FORD LENOIR | C29: T-3955 | D29: 76205609 | E29: 2000850 | F29: CDK Reseller - Base Fee | G29: 300 | H29: 200 | I29: No | J29: CDK loss on 4/30/2026 | K29: To Cancel | L29: =VLOOKUP(A29,'CDK Cancel tracking 5.16.26'!$A:$E,5,0) -> #N/A
A30: 76215310 | B30: DON AYRES ACURA | C30: T-10911 | D30: 76215310 | E30: 2700010 | F30: CDK Reseller - Base Fee | G30: 300 | H30: 200 | I30: No | J30: CDK loss on 4/30/2026 | K30: To Cancel | L30: =VLOOKUP(A30,'CDK Cancel tracking 5.16.26'!$A:$E,5,0) -> #N/A
A31: 76215380 | B31: Purdy Mazda | C31: T-3912 | D31: 76215380 | E31: 2000797 | F31: CDK Reseller - Base Fee | G31: 450 | H31: 200 | I31: No | J31: CDK Loss on Feb 28, 2026, | K31: To Cancel | L31: =VLOOKUP(A31,'CDK Cancel tracking 5.16.26'!$A:$E,5,0) -> #N/A
A32: 76217036 | B32: CAROLINA KIA OF HIGH POINT | C32: T-11253 | D32: 76217036 | E32: 2501508 | F32: CDK Reseller - Base Fee | G32: 300 | H32: 200 | I32: No | J32: CDK Loss on March 15, 2026 | K32: To Cancel | L32: =VLOOKUP(A32,'CDK Cancel tracking 5.16.26'!$A:$E,5,0) -> #N/A
A33: 76217358 | B33: ROCKY MOUNT TOYOTA | C33: T-4254 | D33: 76217358 | E33: 3000423 | F33: CDK Reseller - Base Fee | G33: 400 | H33: 200 | I33: =VLOOKUP(D33,'3.10 Cancel List'!$C:$C,1,0) -> 76217358 | J33: Buysell to retain - new CMF 76244595 - Notified TV | K33: Retained
A34: 76220331 | B34: SUBARU SOUTH TAMPA | C34: T-8125 | D34: 76220331 | E34: 2501681 | F34: CDK Reseller - Base Fee | G34: 300 | H34: 200 | I34: No | J34: CDK loss on 4/30/2026 | K34: To Cancel | L34: =VLOOKUP(A34,'CDK Cancel tracking 5.16.26'!$A:$E,5,0) -> #N/A
A35: 76220332 | B35: SUBARU NORTH ORLANDO | C35: T-8094 | D35: 76220332 | E35: 2501684 | F35: CDK Reseller - Base Fee | G35: 300 | H35: 200 | I35: No | J35: CDK loss on 4/30/2026 | K35: To Cancel | L35: =VLOOKUP(A35,'CDK Cancel tracking 5.16.26'!$A:$E,5,0) -> #N/A
A36: 76225712 | B36: HGREG NISSAN BUENA PARK | C36: T-3995 | D36: 76225712 | E36: 2502268 | F36: CDK Reseller - Base Fee | G36: 450 | H36: 200 | I36: =VLOOKUP(D36,'3.10 Cancel List'!$C:$C,1,0) -> 76225712 | J36: Buysell to retain - new CMF 76257313 - notified TV | K36: Retained
A37: 76227121 | B37: MARTHALER HONDA TOYOTA OF ASHLAND | C37: T-4122 | D37: 76227121 | E37: 2502262 | F37: CDK Reseller - Base Fee | G37: 450 | H37: 200 | I37: =VLOOKUP(D37,'3.10 Cancel List'!$C:$C,1,0) -> 76227121 | J37: LSS 10/01/2024 Suite Price/Value Proposition | K37: To Cancel
A38: 76227134 | B38: INFINITI OF NORTHERN KENTUCKY | C38: T-9119 | D38: 76227134 | E38: 2503481 | F38: CDK Reseller - Base Fee | G38: 300 | H38: 200 | I38: =VLOOKUP(D38,'3.10 Cancel List'!$C:$C,1,0) -> 76227134 | J38: LSS 10/01/2025 Suite Ownership Change / FOS ANS | K38: To Cancel
A39: 76227679 | B39: Express Chevrolet | C39: T-9807 | D39: 76227679 | E39: 2001988 | F39: CDK Reseller - Base Fee | G39: 300 | H39: 200 | I39: =VLOOKUP(D39,'3.10 Cancel List'!$C:$C,1,0) -> 76227679 | J39: LSS 12/25/2026 Suite CDK CONVERSION - SYS GENERATED | K39: To Retain | M39: Buy/sell new CMF | N39: 76257614
A40: 76227757 | B40: Spitzer Ford Dubois | C40: T-5725 | D40: 76227757 | E40: 2502508 | F40: CDK Reseller - Base Fee | G40: 400 | H40: 200 | I40: =VLOOKUP(D40,'3.10 Cancel List'!$C:$C,1,0) -> 76227757 | J40: LSS 12/01/2024 Standalone CDK CONVERSION | K40: To Cancel | M40: No CDK client billing
A41: 76228229 | B41: INFINITI of Montgomery | C41: T-7174 | D41: 76228229 | E41: 2502240 | F41: CDK Reseller - Base Fee | G41: 300 | H41: 200 | I41: =VLOOKUP(D41,'3.10 Cancel List'!$C:$C,1,0) -> 76228229 | J41: 0 01/00/1900 0 SV NOT ON CONTRACT | K41: To Cancel
A42: 76228237 | B42: PINE BELT MAZDA - NJ | C42: T-4219 | D42: 76228237 | E42: 2001918 | F42: CDK Reseller - Base Fee | G42: 450 | H42: 200 | I42: =VLOOKUP(D42,'3.10 Cancel List'!$C:$C,1,0) -> 76228237 | J42: LSS 07/01/2024 Standalone Price/Value Proposition | K42: To Cancel
A43: 76228316 | B43: Genesis West Houston | C43: T-7224 | D43: 76228316 | E43: 2001986 | F43: CDK Reseller - Base Fee | G43: 300 | H43: 200 | I43: =VLOOKUP(D43,'3.10 Cancel List'!$C:$C,1,0) -> 76228316 | J43: LSS 05/01/2024 Suite CDK CONVERSION - SYS GENERATED | K43: To Retain | M43: Shows CDK client billing under | N43: 76245067
A44: 76228629 | B44: MIDLANDS TOYOTA | C44: T-4159 | D44: 76228629 | E44: 2001956 | F44: CDK Reseller - Base Fee | G44: 450 | H44: 200 | I44: =VLOOKUP(D44,'3.10 Cancel List'!$C:$C,1,0) -> 76228629 | J44: LSS 03/25/2026 Suite CDK CONVERSION | K44: To Cancel | M44: No CDK client Package billing
A45: 76228727 | B45: HAMBLOCK FORD LINCOLN | C45: T-14818 | D45: 76228727 | E45: 8054 | F45: CDK Reseller - Base Fee | G45: 300 | H45: 200 | I45: No | J45: CDK loss on 4/30/2026 | K45: To Cancel | L45: =VLOOKUP(A45,'CDK Cancel tracking 5.16.26'!$A:$E,5,0) -> #N/A
A46: 76229253 | B46: BRAVO NISSAN OF VICTORIA | C46: T-5712 | D46: 76229253 | E46: 2002721 | F46: CDK Reseller - Base Fee | G46: 300 | H46: 200 | I46: =VLOOKUP(D46,'3.10 Cancel List'!$C:$C,1,0) -> 76229253 | J46: LSS 05/01/2025 Suite CDK CONVERSION - SYS GENERATED | K46: To Retain | M46: Ownership change new cmf | N46: 76254533
A47: 76229684 | B47: UNITY CHEVROLET CADILLAC | C47: T-6185 | D47: 76229684 | E47: 2002036 | F47: CDK Reseller - Base Fee | G47: 400 | H47: 200 | I47: =VLOOKUP(D47,'3.10 Cancel List'!$C:$C,1,0) -> 76229684 | J47: LSS 08/01/2025 Standalone OWNERSHIP CHANGE | K47: To Cancel
A48: 76229942 | B48: KOCH ROUTE 2 TOYOTA | C48: T-4092 | D48: 76229942 | E48: 2502402 | F48: CDK Reseller - Base Fee | G48: 450 | H48: 200 | I48: =VLOOKUP(D48,'3.10 Cancel List'!$C:$C,1,0) -> 76229942 | J48: LSS 02/01/2024 Suite Price/Value Proposition | K48: To Cancel
A49: 76230156 | B49: FIRELANDS CHEVROLET BUICK | C49: T-3933 | D49: 76230156 | E49: 2002068 | F49: CDK Reseller - Base Fee | G49: 450 | H49: 200 | I49: No | J49: CDK Loss on March 26, 2026 | K49: To Cancel | L49: =VLOOKUP(A49,'CDK Cancel tracking 5.16.26'!$A:$E,5,0) -> #N/A
A50: 76230427 | B50: PUENTE HILLS TOYOTA | C50: T-6028 | D50: 76230427 | E50: 9005 | F50: CDK Reseller - Base Fee | G50: 300 | H50: 200 | I50: =VLOOKUP(D50,'3.10 Cancel List'!$C:$C,1,0) -> 76230427 | J50: LSS 04/01/2025 Suite CLEANUP | K50: To Cancel
A51: 76231689 | B51: LONG-LEWIS FORD LINCOLN | C51: T-14170 | D51: 76231689 | E51: 2700004 | F51: CDK Reseller - Base Fee | G51: 300 | H51: 200 | I51: No | J51: CDK Loss on 3/31/2026 | K51: To Cancel | L51: =VLOOKUP(A51,'CDK Cancel tracking 5.16.26'!$A:$E,5,0) -> #N/A
A52: 76231928 | B52: Spitzer Ford St. Mary's | C52: T-5727 | D52: 76231928 | E52: 2502571 | F52: CDK Reseller - Base Fee | G52: 400 | H52: 200 | I52: =VLOOKUP(D52,'3.10 Cancel List'!$C:$C,1,0) -> 76231928 | J52: LSS 09/01/2023 Standalone CDK CONVERSION | K52: To Cancel | M52: No CDK client Package billing
A53: 76232064 | B53: Tucson Subaru | C53: T-4488 | D53: 76232064 | E53: 2502968 | F53: CDK Reseller - Base Fee | G53: 300 | H53: 200 | I53: =VLOOKUP(D53,'3.10 Cancel List'!$C:$C,1,0) -> 76232064 | J53: LSS 04/01/2024 Suite CDK CONVERSION | K53: To Cancel | M53: No CDK client Package billing
A54: 76232553 | B54: NISSAN OF THE MAIN LINE | C54: T-7916 | D54: 76232553 | E54: 2502656 | F54: CDK Reseller - Base Fee | G54: 300 | H54: 200 | I54: =VLOOKUP(D54,'3.10 Cancel List'!$C:$C,1,0) -> 76232553 | J54: ANS 07/01/2023 Suite CDKS LSS | K54: To Cancel
A55: 76232596 | B55: MENKE BUICK GMC SCHOFIELD | C55: T-4146 | D55: 76232596 | E55: 2500144 | F55: CDK Reseller - Base Fee | G55: 450 | H55: 200 | I55: =VLOOKUP(D55,'3.10 Cancel List'!$C:$C,1,0) -> 76232596 | J55: LSS 10/01/2024 Suite Price/Value Proposition | K55: To Cancel
A56: 76232815 | B56: Downtown Ford Fleet | C56: T-3914 | D56: 76232815 | E56: 0 | F56: CDK Reseller - Base Fee | G56: 400 | H56: 200 | I56: =VLOOKUP(D56,'3.10 Cancel List'!$C:$C,1,0) -> 76232815 | J56: 0 01/00/1900 0 SV NOT ON CONTRACT | K56: To Cancel
A57: 76233048 | B57: AUDI KIRKWOOD | C57: T-1025 | D57: 76233048 | E57: 2002132 | F57: CDK Reseller - Base Fee | G57: 450 | H57: 200 | I57: =VLOOKUP(D57,'3.10 Cancel List'!$C:$C,1,0) -> 76233048 | J57: LSS 07/01/2025 Suite cdk conversion | K57: To Cancel | M57: No CDK client Package billing
A58: 76233242 | B58: Tonkin Hillsboro Chevrolet | C58: T-4332 | D58: 76233242 | E58: 0 | F58: CDK Reseller - Base Fee | G58: 400 | H58: 200 | I58: =VLOOKUP(D58,'3.10 Cancel List'!$C:$C,1,0) -> 76233242 | J58: LSS 12/01/2023 Standalone Low or No Utilization | K58: To Cancel
A59: 76234206 | B59: EDWARDS CHRYSLER DODGE JEEP RAM NE | C59: T-9008 | D59: 76234206 | E59: 2003022 | F59: CDK Reseller - Base Fee | G59: 300 | H59: 200 | I59: =VLOOKUP(D59,'3.10 Cancel List'!$C:$C,1,0) -> 76234206 | J59: ANS 03/01/2024 Suite suite ANS | K59: To Cancel
A60: 76234275 | B60: PLATTNER'S OCALA VOLVO SUBARU | C60: T-4222 | D60: 76234275 | E60: 0 | F60: CDK Reseller - Base Fee | G60: 400 | H60: 200 | I60: =VLOOKUP(D60,'3.10 Cancel List'!$C:$C,1,0) -> 76234275 | J60: LSS 02/01/2024 Standalone Low or No Utilization | K60: To Cancel
A61: 76235514 | B61: Genesis of North Charleston | C61: T-11265 | D61: 76235514 | E61: 2503145 | F61: CDK Reseller - Base Fee | G61: 300 | H61: 200 | I61: =VLOOKUP(D61,'3.10 Cancel List'!$C:$C,1,0) -> 76235514 | J61: 0 01/00/1900 0 SV NOT ON CONTRACT | K61: To Cancel
A62: 76236622 | B62: LAND ROVER ALEXANDRIA | C62: T-6019 | D62: 76236622 | E62: 2503117 | F62: CDK Reseller - Base Fee | G62: 300 | H62: 200 | I62: =VLOOKUP(D62,'3.10 Cancel List'!$C:$C,1,0) -> 76236622 | J62: LSS 06/01/2024 Suite Low or No Utilization | K62: To Cancel
A63: 76237142 | B63: PRIORITY TOYOTA CHESAPEAKE | C63: T-5923 | D63: 76237142 | E63: 2002655 | F63: CDK Reseller - Base Fee | G63: 300 | H63: 200 | I63: =VLOOKUP(D63,'3.10 Cancel List'!$C:$C,1,0) -> 76237142 | J63: LSS 05/01/2025 Suite Dealership Operation Changes | K63: To Cancel
A64: 76237167 | B64: PRIORITY TOYOTA SPRINGFIELD | C64: T-6487 | D64: 76237167 | E64: 2002821 | F64: CDK Reseller - Base Fee | G64: 300 | H64: 200 | I64: =VLOOKUP(D64,'3.10 Cancel List'!$C:$C,1,0) -> 76237167 | J64: LSS 04/01/2025 Suite Cleanup | K64: To Cancel
A65: 76237170 | B65: PRIORITY HONDA HAMPTON | C65: T-6161 | D65: 76237170 | E65: 2000380 | F65: CDK Reseller - Base Fee | G65: 300 | H65: 200 | I65: =VLOOKUP(D65,'3.10 Cancel List'!$C:$C,1,0) -> 76237170 | J65: LSS 05/01/2025 Suite Dealership Operation Changes | K65: To Cancel
A66: 76238669 | B66: Wallace Volkswagen of Kingsport | C66: T-6769 | D66: 76238669 | E66: 2503205 | F66: CDK Reseller - Base Fee | G66: 300 | H66: 200 | I66: =VLOOKUP(D66,'3.10 Cancel List'!$C:$C,1,0) -> 76238669 | J66: 0 01/00/1900 0 SV NOT ON CONTRACT | K66: To Cancel
A67: 76238760 | B67: FRED ANDERSON NISSAN OF GREER | C67: T-5893 | D67: 76238760 | E67: 11073 | F67: CDK Reseller - Base Fee | G67: 300 | H67: 200 | I67: =VLOOKUP(D67,'3.10 Cancel List'!$C:$C,1,0) -> 76238760 | J67: LSS 08/01/2024 Suite CDK CONVERSION - SYS GENERATED | K67: To retain | M67: billing under new CMF | N67: 76250570
A68: 76240142 | B68: NORTHSIDE FORD TRUCK | C68: T-14150 | D68: 76240142 | E68: 2000770 | F68: CDK Reseller - Base Fee | G68: 300 | H68: 200 | I68: No | J68: CDK loss on 4/30/2026 | K68: To Cancel | L68: =VLOOKUP(A68,'CDK Cancel tracking 5.16.26'!$A:$E,5,0) -> #N/A
A69: 76240429 | B69: FRED ANDERSON CHEVROLET | C69: T-5925 | D69: 76240429 | E69: 2002703 | F69: CDK Reseller - Base Fee | G69: 300 | H69: 200 | I69: =VLOOKUP(D69,'3.10 Cancel List'!$C:$C,1,0) -> 76240429 | J69: ANS 08/01/2023 Standalone ENTIRE ANS | K69: To Cancel
A70: 76241005 | B70: SUBARU OF MIDLAND | C70: T-6783 | D70: 76241005 | E70: 2002833 | F70: CDK Reseller - Base Fee | G70: 300 | H70: 200 | I70: =VLOOKUP(D70,'3.10 Cancel List'!$C:$C,1,0) -> 76241005 | J70: LSS 08/01/2025 Suite Price/Value Proposition | K70: To Cancel
A71: 76241171 | B71: MERCEDES BENZ OF RICHMOND | C71: T-13505 | D71: 76241171 | E71: 2002774 | F71: CDK Reseller - Base Fee | G71: 300 | H71: 200 | I71: =VLOOKUP(D71,'3.10 Cancel List'!$C:$C,1,0) -> 76241171 | J71: LSS 11/01/2025 Standalone Price/Value Proposition | K71: To Cancel
A72: 76241172 | B72: MERCEDES BENZ OF MIDLOTHIAN | C72: T-8289 | D72: 76241172 | E72: 2002773 | F72: CDK Reseller - Base Fee | G72: 400 | H72: 200 | I72: =VLOOKUP(D72,'3.10 Cancel List'!$C:$C,1,0) -> 76241172 | J72: LSS 11/01/2025 Standalone Price/Value Proposition | K72: To Cancel
A73: 76241447 | B73: LAND ROVER SHREVEPORT.1 | C73: T-6453 | D73: 76241447 | E73: 2002789 | F73: CDK Reseller - Base Fee | G73: 300 | H73: 200 | I73: =VLOOKUP(D73,'3.10 Cancel List'!$C:$C,1,0) -> 76241447 | J73: LSS 03/01/2025 Suite CDK CONVERSION | K73: To Retain | M73: billing under new CMF | N73: 76241446
A74: 76241522 | B74: SMAIL FORD | C74: T-6458 | D74: 76241522 | E74: 2002804 | F74: CDK Reseller - Base Fee | G74: 300 | H74: 200 | I74: =VLOOKUP(D74,'3.10 Cancel List'!$C:$C,1,0) -> 76241522 | J74: LSS 01/01/2026 Standalone CDK CONVERSION - SYS GENERATED | K74: To Retain | M74: billing under new CMF | N74: 71057123
A75: 76243293 | B75: DAYTONAUTOS LLC DBA MAZDA OF DAYTON | C75: T-8002 | D75: 76243293 | E75: 2503344 | F75: CDK Reseller - Base Fee | G75: 300 | H75: 200 | I75: =VLOOKUP(D75,'3.10 Cancel List'!$C:$C,1,0) -> 76243293 | J75: ANS 08/05/2024 Suite 0 | K75: To Cancel
A76: 76244521 | B76: Go Kia West | C76: T-9434 | D76: 76244521 | E76: 2003072 | F76: CDK Reseller - Base Fee | G76: 300 | H76: 200 | I76: =VLOOKUP(D76,'3.10 Cancel List'!$C:$C,1,0) -> 76244521 | J76: 0 01/00/1900 0 SV NOT ON CONTRACT | K76: To Cancel
A77: 76244781 | B77: FOX VALLEY VOLKSWAGEN OF CRYSTAL LAKE | C77: T-7456 | D77: 76244781 | E77: 2502176 | F77: CDK Reseller - Base Fee | G77: 400 | H77: 200 | I77: =VLOOKUP(D77,'3.10 Cancel List'!$C:$C,1,0) -> 76244781 | J77: LSS 04/03/2024 Standalone Price/Value Proposition | K77: To Cancel
A78: 76245003 | B78: GRUBBS NISSAN | C78: T-8091 | D78: 76245003 | E78: 2002906 | F78: CDK Reseller - Base Fee | G78: 300 | H78: 200 | I78: =VLOOKUP(D78,'3.10 Cancel List'!$C:$C,1,0) -> 76245003 | J78: LSS 07/01/2025 Suite CDK conversion | K78: To Retain | M78: billing under new CMF | N78: 76255685
A79: 76245016 | B79: FOLSOM LAKE CHRYSLER DODGE JEEP RAM | C79: T-7881 | D79: 76245016 | E79: 2002905 | F79: CDK Reseller - Base Fee | G79: 300 | H79: 200 | I79: =VLOOKUP(D79,'3.10 Cancel List'!$C:$C,1,0) -> 76245016 | J79: ANS 02/01/2024 Suite 0 | K79: To Cancel
A80: 76245040 | B80: CHIEF TWO LLC DBA CROWN DODGE AND CHRYSLER | C80: T-9614 | D80: 76245040 | E80: 2503548 | F80: CDK Reseller - Base Fee | G80: 300 | H80: 200 | I80: No | J80: CDK Loss on 3/31/2026 | K80: To Cancel | L80: =VLOOKUP(A80,'CDK Cancel tracking 5.16.26'!$A:$E,5,0) -> 46146
A81: 76246888 | B81: Pilson CDJR | C81: T-9433 | D81: 76246888 | E81: 2503531 | F81: CDK Reseller - Base Fee | G81: 300 | H81: 200 | I81: =VLOOKUP(D81,'3.10 Cancel List'!$C:$C,1,0) -> 76246888 | J81: 0 01/00/1900 0 SV NOT ON CONTRACT | K81: To Cancel
A82: 76250378 | B82: GALEANA CDJR MT. PLEASANT | C82: T-8809 | D82: 76250378 | E82: 2503449 | F82: CDK Reseller - Base Fee | G82: 300 | H82: 200 | I82: =VLOOKUP(D82,'3.10 Cancel List'!$C:$C,1,0) -> 76250378 | J82: LSS 03/03/2025 Suite CDK conversion | K82: To Retain | M82: billing under new CMF | N82: 76255914
A83: 76252046 | B83: ALFA ROMEO OF HAZLET | C83: T-9266 | D83: 76252046 | E83: 2503503 | F83: CDK Reseller - Base Fee | G83: 300 | H83: 200 | I83: =VLOOKUP(D83,'3.10 Cancel List'!$C:$C,1,0) -> 76252046 | J83: LSS 02/24/2025 Suite REASON UNKOWN | K83: To Cancel
A84: 76253766 | B84: MVP MITSUBISHI | C84: T-10869 | D84: 76253766 | E84: 2503580 | F84: CDK Reseller - Base Fee | G84: 300 | H84: 200 | I84: =VLOOKUP(D84,'3.10 Cancel List'!$C:$C,1,0) -> 76253766 | J84: ANS 02/25/2025 Suite DMS ANS | K84: To Cancel
A85: 76253767 | B85: MVP KIA | C85: T-10868 | D85: 76253767 | E85: 2503579 | F85: CDK Reseller - Base Fee | G85: 300 | H85: 200 | I85: =VLOOKUP(D85,'3.10 Cancel List'!$C:$C,1,0) -> 76253767 | J85: ANS 02/01/2025 Suite DMS ANS | K85: To Cancel
A86: 76256562 | B86: McGovern Ford of Beverly | C86: T-13842 | D86: 76256562 | E86: 3000496 | F86: CDK Reseller - Base Fee | G86: 300 | H86: 200 | I86: =VLOOKUP(D86,'3.10 Cancel List'!$C:$C,1,0) -> 76256562 | J86: 0 01/00/1900 0 SV NOT ON CONTRACT | K86: To Cancel
A87: 76257159 | B87: KIA OF FORT MYERS | C87: T-14803 | D87: 76257159 | E87: 8038 | F87: CDK Reseller - Base Fee | G87: 400 | H87: 200 | I87: No | J87: CDK Loss on Jan 23, 2026 | K87: To Cancel | L87: =VLOOKUP(A87,'CDK Cancel tracking 5.16.26'!$A:$E,5,0) -> #N/A
A88: 76258093 | B88: EUROBAHN MOTORSPORTS | C88: T-14491 | D88: 76258093 | E88: 3000981 | F88: CDK Reseller - Base Fee | G88: 300 | H88: 200 | I88: No | J88: CDK Loss on 3/31/2026 | K88: To Cancel | L88: =VLOOKUP(A88,'CDK Cancel tracking 5.16.26'!$A:$E,5,0) -> 46143
F89: Subtotal Amount | G89: =SUM(G2:G88) -> 29400 | H89: =SUM(H2:H88) -> 17400 | I89: =VLOOKUP(D89,'3.10 Cancel List'!$C:$C,1,0) -> #N/A
F90: total Amount | H90: =G89+H89 -> 46800

Sheet May Monthly Invoice- BLG Sites
A1: CMF | B1: Customer | C1: Contract Number | D1: CMF Number | E1: CID Number | F1: Item | G1: Local Amount | H1: AI fee | I1: Total Amount
A2: 01012201 | B2: Lynn Layton Chevrolet | C2: T-16228 | D2: 1012201 | E2: 3001502 | F2: CDK Reseller - Base Fee | G2: 300 | H2: 200 | I2: =G2+H2 -> 500
A3: 01012202 | B3: LYNN LAYTON CADILLAC NISSAN | C3: T-16227 | D3: 1012202 | E3: 3001510 | F3: CDK Reseller - Base Fee | G3: 300 | H3: 200 | I3: =G3+H3 -> 500
A4: 01013501 | B4: AL PACKER FORD INC | C4: T-15480 | D4: 1013501 | E4: 10027 | F4: CDK Reseller - Base Fee | G4: 300 | H4: 200 | I4: =G4+H4 -> 500
A5: 01013502 | B5: AL PACKER FORD ROYAL PALM BEACH | C5: T-15479 | D5: 1013502 | E5: 10028 | F5: CDK Reseller - Base Fee | G5: 300 | H5: 200 | I5: =G5+H5 -> 500
A6: 01029501 | B6: HAMPTON CHEVROLET - VA | C6: T-15096 | D6: 1029501 | E6: 2001100 | F6: CDK Reseller - Base Fee | G6: 300 | H6: 200 | I6: =G6+H6 -> 500
A7: 01325739 | B7: SOUTHTOWNE MOTORS OF NEWNAN | C7: T-13815 | D7: 1325739 | E7: 2000912 | F7: CDK Reseller - Base Fee | G7: 300 | H7: 200 | I7: =G7+H7 -> 500
A8: 01326145 | B8: Honda de San Juan | C8: T-16178 | D8: 1326145 | E8: 2500576 | F8: CDK Reseller - Base Fee | G8: 300 | H8: 200 | I8: =G8+H8 -> 500
A9: 08320081 | B9: BAHAMAS BUS & TRUCK CO | C9: T-10870 | D9: 8320081 | E9: 2002071 | F9: CDK Reseller - Base Fee | G9: 300 | H9: 200 | I9: =G9+H9 -> 500
A10: 09025902 | B10: BRANTFORD NISSAN | C10: T-16213 | D10: 9025902 | E10: 2002697 | F10: CDK Reseller - Base Fee | G10: 300 | H10: 200 | I10: =G10+H10 -> 500
A11: 13498058 | B11: PAT MILLIKEN FORD | C11: T-16176 | D11: 13498058 | E11: 3365 | F11: CDK Reseller - Base Fee | G11: 300 | H11: 200 | I11: =G11+H11 -> 500
A12: 17237901 | B12: WESTSIDE CHEVROLET INC. | C12: T-4374 | D12: 17237901 | E12: 2501985 | F12: CDK Reseller - Base Fee | G12: 300 | H12: 200 | I12: =G12+H12 -> 500
A13: 25111201 | B13: RYE SUBARU | C13: T-15509 | D13: 25111201 | E13: 2502986 | F13: CDK Reseller - Base Fee | G13: 300 | H13: 200 | I13: =G13+H13 -> 500
... A20: 71034933 | B20: AL PACKER FORD WHITE MARSH | C20: T-15475 | D20: 71034933 | E20: 10038 | F20: CDK Reseller - Base Fee | G20: 300 | H20: 200 | I20: =G20+H20 -> 500
A21: 71046210 | B21: PETERBILT OF UTAH, INC. | C21: T-6822 | D21: 71046210 | E21: N/A | F21: CDK Reseller - Base Fee | G21: 300 | H21: 200 | I21: =G21+H21 -> 500
A22: 71047545 | B22: FIRST TEAM HONDA | C22: T-15095 | D22: 71047545 | E22: 2001103 | F22: CDK Reseller - Base Fee | G22: 300 | H22: 200 | I22: =G22+H22 -> 500
A23: 71052261 | B23: JAY WOLFE ACURA | C23: T-15484 | D23: 71052261 | E23: 3002167 | F23: CDK Reseller - Base Fee | G23: 300 | H23: 200 | I23: =G23+H23 -> 500
A24: 71059338 | B24: FIRST TEAM TOYOTA SCION | C24: T-15094 | D24: 71059338 | E24: 2001096 | F24: CDK Reseller - Base Fee | G24: 300 | H24: 200 | I24: =G24+H24 -> 500
A25: 71061453 | B25: BURLINGTON KIA | C25: T-16233 | D25: 71061453 | E25: 3002947 | F25: CDK Reseller - Base Fee | G25: 300 | H25: 200 | I25: =G25+H25 -> 500
A26: 71064116 | B26: MERCEDES BENZ OF SOUTH ORLANDO | C26: T-14827 | D26: 71064116 | E26: 8076 | F26: CDK Reseller - Base Fee | G26: 300 | H26: 200 | I26: =G26+H26 -> 500
A27: 71064158 | B27: CASTLE CHEVROLET NORTH | C27: T-13597 | D27: 71064158 | E27: 2501853 | F27: CDK Reseller - Base Fee | G27: 300 | H27: 200 | I27: =G27+H27 -> 500
A28: 76003334 | B28: FRIENDLY FORD | C28: T-14786 | D28: 76003334 | E28: 8061 | F28: CDK Reseller - Base Fee | G28: 300 | H28: 200 | I28: =G28+H28 -> 500
A29: 76031206 | B29: MARSHALL FORD - TX | C29: T-15478 | D29: 76031206 | E29: 903072 | F29: CDK Reseller - Base Fee | G29: 300 | H29: 200 | I29: =G29+H29 -> 500
A30: 76032748 | B30: KERRY MAZDA | C30: T-16222 | D30: 76032748 | E30: 3002949 | F30: CDK Reseller - Base Fee | G30: 300 | H30: 200 | I30: =G30+H30 -> 500
A31: 76036137 | B31: SHAW GMC CHEVROLET BUICK | C31: T-16221 | D31: 76036137 | E31: 2501825 | F31: CDK Reseller - Base Fee | G31: 300 | H31: 200 | I31: =G31+H31 -> 500
A32: 76036160 | B32: GREENWOOD CHEVY OF AUSTINTOWN | C32: T-16169 | D32: 76036160 | E32: 9014 | F32: CDK Reseller - Base Fee | G32: 300 | H32: 200 | I32: =G32+H32 -> 500
A33: 76037591 | B33: LB SMITH FORD LINCOLN | C33: T-16203 | D33: 76037591 | E33: 6091 | F33: CDK Reseller - Base Fee | G33: 300 | H33: 200 | I33: =G33+H33 -> 500
A34: 76038422 | B34: ROUTE 60 HYUNDAI | C34: T-16167 | D34: 76038422 | E34: 2500295 | F34: CDK Reseller - Base Fee | G34: 300 | H34: 200 | I34: =G34+H34 -> 500
A35: 76041535 | B35: JEROME PETERBILT, INC. | C35: T-5708 | D35: 76041535 | E35: N/A | F35: CDK Reseller - Base Fee | G35: 300 | H35: 200 | I35: =G35+H35 -> 500
A36: 76043449 | B36: FELDMAN CHEVROLET OF NEW HUDSON | C36: T-15506 | D36: 76043449 | E36: 123018 | F36: CDK Reseller - Base Fee | G36: 300 | H36: 200 | I36: =G36+H36 -> 500
A37: 76043451 | B37: FELDMAN CHEVROLET OF HIGHLAND | C37: T-15505 | D37: 76043451 | E37: 123019 | F37: CDK Reseller - Base Fee | G37: 300 | H37: 200 | I37: =G37+H37 -> 500
A38: 76043453 | B38: FELDMAN HYUNDAI OF NEW HUDSON | C38: T-15085 | D38: 76043453 | E38: 0 | F38: CDK Reseller - Base Fee | G38: 300 | H38: 200 | I38: =G38+H38 -> 500
A39: 76043455 | B39: FELDMAN CHEVROLET OF NOVI | C39: T-15504 | D39: 76043455 | E39: 123021 | F39: CDK Reseller - Base Fee | G39: 300 | H39: 200 | I39: =G39+H39 -> 500
A40: 76043468 | B40: MIKE TOLER CHRYSLER DODGE JEEP | C40: T-16172 | D40: 76043468 | E40: 2001550 | F40: CDK Reseller - Base Fee | G40: 300 | H40: 200 | I40: =G40+H40 -> 500
A41: 76044062 | B41: TOYOTA SCION OF WEST COUNTY | C41: T-15483 | D41: 76044062 | E41: 2503554 | F41: CDK Reseller - Base Fee | G41: 300 | H41: 200 | I41: =G41+H41 -> 500
A42: 76072064 | B42: BMW OF SOUTHAMPTON | C42: T-16199 | D42: 76072064 | E42: 2503103 | F42: CDK Reseller - Base Fee | G42: 300 | H42: 200 | I42: =G42+H42 -> 500
A43: 76073131 | B43: SIMMONS ROCKWELL FORD - NY | C43: T-16214 | D43: 76073131 | E43: 143062 | F43: CDK Reseller - Base Fee | G43: 300 | H43: 200 | I43: =G43+H43 -> 500
A44: 76074237 | B44: FELDMAN 1800 PRE-OWNED SUPERCENTER | C44: T-15084 | D44: 76074237 | E44: 2503477 | F44: CDK Reseller - Base Fee | G44: 300 | H44: 200 | I44: =G44+H44 -> 500
A45: 76074791 | B45: ACADEMY FORD SALES | C45: T-16219 | D45: 76074791 | E45: 3002489 | F45: CDK Reseller - Base Fee | G45: 300 | H45: 200 | I45: =G45+H45 -> 500
A46: 76124458 | B46: Pepe Cadillac | C46: T-13331 | D46: 76124458 | E46: 3000121 | F46: CDK Reseller - Base Fee | G46: 300 | H46: 200 | I46: =G46+H46 -> 500
A47: 76135790 | B47: GENE LANGLEY FORD | C47: T-16217 | D47: 76135790 | E47: 2503496 | F47: CDK Reseller - Base Fee | G47: 300 | H47: 200 | I47: =G47+H47 -> 500
... A57: 76169148 | B57: FIRST TEAM SUBARU | C57: T-15080 | D57: 76169148 | E57: 2001102 | F57: CDK Reseller - Base Fee | G57: 300 | H57: 200 | I57: =G57+H57 -> 500
A58: 76170921 | B58: OGDEN PETERBILT, INC. | C58: T-6189 | D58: 76170921 | E58: N/A | F58: CDK Reseller - Base Fee | G58: 300 | H58: 200 | I58: =G58+H58 -> 500
A59: 76171400 | B59: EASTSIDE DODGE CHRYSLER JEEP RAM | C59: T-13752 | D59: 76171400 | E59: 2002889 | F59: CDK Reseller - Base Fee | G59: 300 | H59: 200 | I59: =G59+H59 -> 500
A60: 76171640 | B60: DUPAGE DODGE CHRYSLER JEEP | C60: T-15106 | D60: 76171640 | E60: 3001065 | F60: CDK Reseller - Base Fee | G60: 300 | H60: 200 | I60: =G60+H60 -> 500
A61: 76174651 | B61: LAMBORGHINI PALM BEACH | C61: T-14498 | D61: 76174651 | E61: 3000945 | F61: CDK Reseller - Base Fee | G61: 300 | H61: 200 | I61: =G61+H61 -> 500
A62: 76180102 | B62: HONDA OF PRINCETON | C62: T-16198 | D62: 76180102 | E62: 2502528 | F62: CDK Reseller - Base Fee | G62: 300 | H62: 200 | I62: =G62+H62 -> 500
A63: 76181398 | B63: GRIMSBY HYUNDAI | C63: T-15489 | D63: 76181398 | E63: 3002455 | F63: CDK Reseller - Base Fee | G63: 300 | H63: 200 | I63: =G63+H63 -> 500
A64: 76181513 | B64: TRANSWEST CHRYSLER DODGE JEEP RAM | C64: T-16204 | D64: 76181513 | E64: 3001083 | F64: CDK Reseller - Base Fee | G64: 300 | H64: 200 | I64: =G64+H64 -> 500
A65: 76187537 | B65: MT. ORAB FORD | C65: T-16174 | D65: 76187537 | E65: 10143 | F65: CDK Reseller - Base Fee | G65: 300 | H65: 200 | I65: =G65+H65 -> 500
A66: 76188296 | B66: TRANSWEST CHEVROLET BUICK -STERLING | C66: T-16205 | D66: 76188296 | E66: 3001076 | F66: CDK Reseller - Base Fee | G66: 300 | H66: 200 | I66: =G66+H66 -> 500
A67: 76204394 | B67: SIMMONS ROCKWELL NISSAN OF HORNELL | C67: T-16207 | D67: 76204394 | E67: 2503164 | F67: CDK Reseller - Base Fee | G67: 300 | H67: 200 | I67: =G67+H67 -> 500
A68: 76204610 | B68: Mark Wahlberg Chevrolet of Columbus | C68: T-15501 | D68: 76204610 | E68: 2500558 | F68: CDK Reseller - Base Fee | G68: 300 | H68: 200 | I68: =G68+H68 -> 500
A69: 76206543 | B69: AUDI NYACK - NY | C69: T-13584 | D69: 76206543 | E69: 3000651 | F69: CDK Reseller - Base Fee | G69: 300 | H69: 200 | I69: =G69+H69 -> 500
A70: 76209301 | B70: FIRST TEAM SUBARU NORFOLK | C70: T-14798 | D70: 76209301 | E70: 8113 | F70: CDK Reseller - Base Fee | G70: 300 | H70: 200 | I70: =G70+H70 -> 500
... A81: 76219675 | B81: CALIFORNIA CHRYSLER DODGE JEEP RAM | C81: T-9858 | D81: 76219675 | E81: 210272 | F81: CDK Reseller - Base Fee | G81: 400 | H81: 200 | I81: =G81+H81 -> 600
A82: 76220871 | B82: GRAND JUNCTION PETERBILT, INC. | C82: T-9471 | D82: 76220871 | E82: N/A | F82: CDK Reseller - Base Fee | G82: 300 | H82: 200 | I82: =G82+H82 -> 500
A83: 76220871 | B83: JACKSON GROUP PETERBILT MISSOULA | C83: T-6014 | D83: 76220871 | E83: N/A | F83: CDK Reseller - Base Fee | G83: 300 | H83: 200 | I83: =G83+H83 -> 500
A84: 76220873 | B84: JACKSON GROUP PETERBILT BILLINGS | C84: T-5638 | D84: 76220873 | E84: N/A | F84: CDK Reseller - Base Fee | G84: 300 | H84: 200 | I84: =G84+H84 -> 500
A85: 76221156 | B85: JIM ELLIS FORD OF SANDY SPRINGS | C85: T-10639 | D85: 76221156 | E85: 2001555 | F85: CDK Reseller - Base Fee | G85: 300 | H85: 200 | I85: =G85+H85 -> 500
A86: 76222063 | B86: FELDMAN CHRYSLER DODGE JEEP RAM OF CLARKSTON | C86: T-15497 | D86: 76222063 | E86: 2501755 | F86: CDK Reseller - Base Fee | G86: 300 | H86: 200 | I86: =G86+H86 -> 500
A87: 76222545 | B87: UNION CITY CHRYSLER DODGE JEEP | C87: T-10623 | D87: 76222545 | E87: 0 | F87: CDK Reseller - Base Fee | G87: 300 | H87: 200 | I87: =G87+H87 -> 500
A88: 76223425 | B88: PORTLAND PETERBILT, INC. | C88: T-5709 | D88: 76223425 | E88: N/A | F88: CDK Reseller - Base Fee | G88: 300 | H88: 200 | I88: =G88+H88 -> 500
A89: 76225720 | B89: KARL MALONE TOYOTA CHEVROLET | C89: T-13504 | D89: 76225720 | E89: 2502191 | F89: CDK Reseller - Base Fee | G89: 300 | H89: 200 | I89: =G89+H89 -> 500
A90: 76225949 | B90: Mark Wahlberg Chevrolet of Worthington | C90: T-15496 | D90: 76225949 | E90: 2502146 | F90: CDK Reseller - Base Fee | G90: 300 | H90: 200 | I90: =G90+H90 -> 500
A91: 76227697 | B91: UTAH VALLEY PETERBILT | C91: T-6190 | D91: 76227697 | E91: N/A | F91: CDK Reseller - Base Fee | G91: 300 | H91: 200 | I91: =G91+H91 -> 500
A92: 76229011 | B92: HELLO SUBARU OF VALENCIA | C92: T-3993 | D92: 76229011 | E92: 0 | F92: CDK Reseller - Base Fee | G92: 450 | H92: 200 | I92: =G92+H92 -> 650
A93: 76229318 | B93: CASTLE VOLKSWAGEN SCHAUMBURG | C93: T-13600 | D93: 76229318 | E93: 2502328 | F93: CDK Reseller - Base Fee | G93: 300 | H93: 200 | I93: =G93+H93 -> 500
A94: 76230520 | B94: LAURENTIAN CHRYSLER | C94: T-13583 | D94: 76230520 | E94: 2503257 | F94: CDK Reseller - Base Fee | G94: 300 | H94: 200 | I94: =G94+H94 -> 500
A95: 76231277 | B95: MAZDA OF BEDFORD - OH | C95: T-15467 | D95: 76231277 | E95: 2502635 | F95: CDK Reseller - Base Fee | G95: 300 | H95: 200 | I95: =G95+H95 -> 500
A96: 76231546 | B96: JERRY V HONOLULU HYUNDAI | C96: T-15495 | D96: 76231546 | E96: 2002201 | F96: CDK Reseller - Base Fee | G96: 300 | H96: 200 | I96: =G96+H96 -> 500
A97: 76232074 | B97: NORTH HILLS TOYOTA SERVICE CENTER | C97: T-14466 | D97: 76232074 | E97: 2500696 | F97: CDK Reseller - Base Fee | G97: 300 | H97: 200 | I97: =G97+H97 -> 500
A98: 76233198 | B98: BURLINGTON HYUNDAI - NJ | C98: T-16232 | D98: 76233198 | E98: 3002958 | F98: CDK Reseller - Base Fee | G98: 300 | H98: 200 | I98: =G98+H98 -> 500
A99: 76233833 | B99: WINDWARD DODGE CHRYSLER JEEP | C99: T-15494 | D99: 76233833 | E99: 2002292 | F99: CDK Reseller - Base Fee | G99: 300 | H99: 200 | I99: =G99+H99 -> 500
A100: 76234346 | B100: Crabtree Toyota | C100: T-14452 | D100: 76234346 | E100: 2002231 | F100: CDK Reseller - Base Fee | G100: 300 | H100: 200 | I100: =G100+H100 -> 500
A101: 76236503 | B101: WINSLOW FORD | C101: T-16210 | D101: 76236503 | E101: 3002961 | F101: CDK Reseller - Base Fee | G101: 300 | H101: 200 | I101: =G101+H101 -> 500
A102: 76240343 | B102: HAPPY CHRYSLER DODGE JEEP RAM OF ROCHESTER | C102: T-15107 | D102: 76240343 | E102: 3000814 | F102: CDK Reseller - Base Fee | G102: 300 | H102: 200 | I102: =G102+H102 -> 500
A103: 76241159 | B103: LEGENDARY FORD | C103: T-16209 | D103: 76241159 | E103: 3001147 | F103: CDK Reseller - Base Fee | G103: 300 | H103: 200 | I103: =G103+H103 -> 500
... A118: 97000001 | B118: KERRY INFINITI OF NORTHERN KENTUCKY - KERRY NISSAN | C118: T-16229 | D118: 97000001 | E118: 2500664 | F118: CDK Reseller - Base Fee | G118: 300 | H118: 200 | I118: =G118+H118 -> 500
F119: Total Amount | G119: =SUM(G2:G118) -> 35450 | H119: =SUM(H2:H118) -> 23400 | I119: =SUM(I2:I118) -> 58850

Sheet April Prorated Invoice-BLG Site
A1: CMF | B1: Customer | C1: CMF Number | D1: CID Number | E1: Item | F1: Local Amount | G1: CDK asked to retain
A2: =TRIM("0"&C2) -> 01012201 | B2: Lynn Layton Chevrolet | C2: 1012201 | D2: 3001502 | E2: CDK Reseller - Base Fee | F2: 40
A3: =TRIM("0"&C3) -> 01012202 | B3: LYNN LAYTON CADILLAC NISSAN | C3: 1012202 | D3: 3001510 | E3: CDK Reseller - Base Fee | F3: 100
A4: =TRIM("0"&C4) -> 01326145 | B4: Honda de San Juan | C4: 1326145 | D4: 2500576 | E4: CDK Reseller - Base Fee | F4: 290
A5: =TRIM("0"&C5) -> 09025902 | B5: BRANTFORD NISSAN | C5: 9025902 | D5: 2002697 | E5: CDK Reseller - Base Fee | F5: 160
A6: =TRIM(C6) -> 13498058 | B6: PAT MILLIKEN FORD | C6: 13498058 | D6: 3365 | E6: CDK Reseller - Base Fee | F6: 210
A7: =TRIM(C7) -> 25212501 | B7: WAYNE FORD | C7: 25212501 | D7: 6024 | E7: CDK Reseller - Base Fee | F7: 170
A8: =TRIM(C8) -> 25300610 | B8: SIMMONS ROCKWELL CHEVROLET GMC | C8: 25300610 | D8: 3002945 | E8: CDK Reseller - Base Fee | F8: 40
A9: =TRIM(C9) -> 44780001 | B9: BEECHMONT FORD | C9: 44780001 | D9: 2502046 | E9: CDK Reseller - Base Fee | F9: 90
A10: =TRIM(C10) -> 45602701 | B10: CMP CHEVY CADILLAC BUICK GMC | C10: 45602701 | D10: 2501852 | E10: CDK Reseller - Base Fee | F10: 30
A11: =TRIM(C11) -> 71061453 | B11: BURLINGTON KIA | C11: 71061453 | D11: 3002947 | E11: CDK Reseller - Base Fee | F11: 110
A12: =TRIM(C12) -> 76032748 | B12: KERRY MAZDA | C12: 76032748 | D12: 3002949 | E12: CDK Reseller - Base Fee | F12: 30
A13: =TRIM(C13) -> 76036137 | B13: SHAW GMC CHEVROLET BUICK | C13: 76036137 | D13: 2501825 | E13: CDK Reseller - Base Fee | F13: 90
A14: =TRIM(C14) -> 76036160 | B14: GREENWOOD CHEVY OF AUSTINTOWN | C14: 76036160 | D14: 9014 | E14: CDK Reseller - Base Fee | F14: 170
A15: =TRIM(C15) -> 76037591 | B15: LB SMITH FORD LINCOLN | C15: 76037591 | D15: 6091 | E15: CDK Reseller - Base Fee | F15: 160
A16: =TRIM(C16) -> 76038422 | B16: ROUTE 60 HYUNDAI | C16: 76038422 | D16: 2500295 | E16: CDK Reseller - Base Fee | F16: 300
A17: =TRIM(C17) -> 76043468 | B17: MIKE TOLER CHRYSLER DODGE JEEP | C17: 76043468 | D17: 2001550 | E17: CDK Reseller - Base Fee | F17: 280
... A88: =TRIM(C88) -> 76236503 | B88: WINSLOW FORD | C88: 76236503 | D88: 3002961 | E88: TruVideo AI Suite | F88: 20
E89: total amount | F89: =SUM(F2:F88) -> 9100.03

Sheet CDK INS not Billed by TV
A1: CMF | B1: CMF Number | C1: CDF ID | D1: Ship-To Name | E1: Catalog Number | F1: CDF Status (w/ATN) | G1: Catalog Description | H1: Consolidation Name | I1: Roll Call Date | J1: Total
A2: 05400042 | B2: 05400042 | C2: 62188525SW04 | D2: BEAVERTON KIA | E2: 4508714 | F2: INS | G2: CDK SERVICEVIEW (IN FIXED OPS PKG) | H2: LANPHERE | I2: 45638 | J2: 1
A3: 05400043 | B3: 05400043 | C3: 62188525SW11 | D3: BEAVERTON INFINITI 1 | E3: 4508714 | F3: INS | G3: CDK SERVICEVIEW (IN FIXED OPS PKG) | H3: LANPHERE | I3: 45638 | J3: 1
A4: 13115402 | B4: 13115402 | C4: 64238276SW87 | D4: BILLION HYUNDAI | E4: 4508714 | F4: INS | G4: CDK SERVICEVIEW (IN FIXED OPS PKG) | H4: BILLION | I4: 45747 | J4: 1
A5: 13115403 | B5: 13115403 | C5: 64238279SW74 | D5: BILLION DODGE CHRYSLER JEEP | E5: 4508714 | F5: INS | G5: CDK SERVICEVIEW (IN FIXED OPS PKG) | H5: BILLION | I5: 45747 | J5: 1
A6: 13497880 | B6: 13497880 | C6: 64238409SW64 | D6: WARD CHRYSLER CENTER | E6: 4508714 | F6: INS | G6: CDK SERVICEVIEW (IN FIXED OPS PKG) | H6: WARD | I6: 45748 | J6: 1
A7: 14600646 | B7: 14600646 | C7: 68233042SW04 | D7: FLOW MOTORS OF WINSTON-SALEM, LLC | E7: 4508714 | F7: INS | G7: CDK SERVICEVIEW (IN FIXED OPS PKG) | H7: FLOW COMPANIES - GROUP | I7: 45622 | J7: 1
A8: 17042101 | B8: 17042101 | C8: 64234862SW04 | D8: KNIPPELMIER CHEV INC | E8: 4508714 | F8: INS | G8: CDK SERVICEVIEW (IN FIXED OPS PKG) | H8: KNIPPELMIER CHEVROLET INC. | I8: 45639 | J8: 1
A9: 17150701 | B9: 17150701 | C9: 62188549SW04 | D9: MAC HAIK CHEV | E9: 4508714 | F9: INS | G9: CDK SERVICEVIEW (IN FIXED OPS PKG) | H9: MAC HAIK AUTO GROUP | I9: 45638 | J9: 1
A10: 25298834 | B10: 25298834 | C10: 68243943SW69 | D10: RUGE'S CHRYSLER DODGE JEEP RAM | E10: 4508714 | F10: INS | G10: CDK SERVICEVIEW (IN FIXED OPS PKG) | H10: RUGE | I10: 45930 | J10: 1
A11: 25300234 | B11: 25300234 | C11: 68245295SW83 | D11: SIMMONS ROCKWELL BUICK GMC OF ELMIRA | E11: 4508714 | F11: INS | G11: CDK SERVICEVIEW (IN FIXED OPS PKG) | H11: SIMMONS ROCKWELL | I11: 45967 | J11: 1
A12: 29012602 | B12: 29012602 | C12: 01354704SW50 | D12: MORREY NISSAN | E12: 4408593 | F12: INS | G12: CDK SERVICEVIEW IN PKG (CHILD CATALOG NUMBER FOR CDK SERVICE BUNDLE) | H12: MORREY | I12: 45721 | J12: 1
A13: 33118201 | B13: 33118201 | C13: 68233615SW08 | D13: LINDSAY HONDA | E13: 4408593 | F13: INS | G13: CDK SERVICEVIEW IN PKG (CHILD CATALOG NUMBER FOR CDK SERVICE BUNDLE) | H13: LINDSAY AUTOMOTIVE | I13: 45636 | J13: 1
A14: 33118203 | B14: 33118203 | C14: 68233615SW13 | D14: LINDSAY ACURA | E14: 4408593 | F14: INS | G14: CDK SERVICEVIEW IN PKG (CHILD CATALOG NUMBER FOR CDK SERVICE BUNDLE) | H14: LINDSAY AUTOMOTIVE | I14: 45636 | J14: 1
A15: 37119401 | B15: 37119401 | C15: 62188525SW18 | D15: BEAVERTON HONDA | E15: 4508714 | F15: INS | G15: CDK SERVICEVIEW (IN FIXED OPS PKG) | H15: LANPHERE | I15: 45638 | J15: 1
... A49: 76127638 | B49: 76127638 | C49: 68233042SW75 | D49: FLOW AUTOBAHN, LLC | E49: 4508714 | F49: INS | G49: CDK SERVICEVIEW (IN FIXED OPS PKG) | H49: FLOW COMPANIES - GROUP | I49: 45622 | J49: 1
A50: 76127639 | B50: 76127639 | C50: 68233047SW04 | D50: FLOW AUTOMOTIVE CENTER OF WINSTON-SALEM, LLC | E50: 4508714 | F50: INS | G50: CDK SERVICEVIEW (IN FIXED OPS PKG) | H50: FLOW COMPANIES - GROUP | I50: 45622 | J50: Saskatoon North Hyundai Genesis
A51: 76127658 | B51: 76127658 | C51: 68233047SW11 | D51: FLOW AUDI VOLKSWAGEN OF GREENSBORO | E51: 4508714 | F51: INS | G51: CDK SERVICEVIEW (IN FIXED OPS PKG) | H51: FLOW COMPANIES - GROUP | I51: 45622 | J51: 1
A52: 76127658 | B52: 76127658 | C52: 68233047SW18 | D52: FLOW AUDI VOLKSWAGEN OF GREENSBORO | E52: 4508714 | F52: INS | G52: CDK SERVICEVIEW (IN FIXED OPS PKG) | H52: FLOW COMPANIES - GROUP | I52: 45622 | J52: 1
A53: 76127659 | B53: 76127659 | C53: 68233047SW67 | D53: FLOW AUTO OF FAYETTEVILLE | E53: 4508714 | F53: INS | G53: CDK SERVICEVIEW (IN FIXED OPS PKG) | H53: FLOW COMPANIES - GROUP | I53: 45622 | J53: 1
A54: 76127679 | B54: 76127679 | C54: 68233047SW74 | D54: FLOW BUICK GMC LAND ROVER MAZDA OF GREENSBORO | E54: 4508714 | F54: INS | G54: CDK SERVICEVIEW (IN FIXED OPS PKG) | H54: FLOW COMPANIES - GROUP | I54: 45622 | J54: 1
A55: 76127679 | B55: 76127679 | C55: 68233047SW81 | D55: FLOW BUICK GMC LAND ROVER MAZDA OF GREENSBORO | E55: 4508714 | F55: INS | G55: CDK SERVICEVIEW (IN FIXED OPS PKG) | H55: FLOW COMPANIES - GROUP | I55: 45622 | J55: 1
A56: 76139117 | B56: 76139117 | C56: 68233048SW04 | D56: FLOW LEAN SERVICE, LLC | E56: 4508714 | F56: INS | G56: CDK SERVICEVIEW (IN FIXED OPS PKG) | H56: FLOW COMPANIES - GROUP | I56: 45622 | J56: 1
A57: 76150784 | B57: 76150784 | C57: 62198326SW58 | D57: JAGUAR LAND ROVER SAN JUAN | E57: 4508714 | F57: INS | G57: CDK SERVICEVIEW (IN FIXED OPS PKG) | H57: HELLER-BIRD AUTO GROUP | I57: 46085 | J57: 1
A58: 76155716 | B58: 76155716 | C58: 68233047SW25 | D58: FLOW HONDA OF STATESVILLE | E58: 4508714 | F58: INS | G58: CDK SERVICEVIEW (IN FIXED OPS PKG) | H58: FLOW COMPANIES - GROUP | I58: 45622 | J58: 1
A59: 76159995 | B59: 76159995 | C59: 68233047SW32 | D59: FLOW VOLKSWAGEN OF BURLINGTON | E59: 4508714 | F59: INS | G59: CDK SERVICEVIEW (IN FIXED OPS PKG) | H59: FLOW COMPANIES - GROUP | I59: 45622 | J59: 1
A60: 76160175 | B60: 76160175 | C60: 62190591SW87 | D60: ACURA OF PORTLAND | E60: 4508714 | F60: INS | G60: CDK SERVICEVIEW (IN FIXED OPS PKG) | H60: DICK HANNAH | I60: 45726 | J60: 1
A61: 76160177 | B61: 76160177 | C61: 62190592SW43 | D61: DICK HANNAH TOYOTA | E61: 4508714 | F61: INS | G61: CDK SERVICEVIEW (IN FIXED OPS PKG) | H61: DICK HANNAH | I61: 45726 | J61: 1
A62: 76160178 | B62: 76160178 | C62: 62190593SW04 | D62: DICK HANNAH VOLKSWAGEN | E62: 4508714 | F62: INS | G62: CDK SERVICEVIEW (IN FIXED OPS PKG) | H62: DICK HANNAH | I62: 45726 | J62: 1
... A149: 76259847 | B149: 76259847 | C149: 68250022SW85 | D149: VANN YORK KIA | E149: 4508714 | F149: INS | G149: CDK SERVICEVIEW (IN FIXED OPS PKG) | H149: VANN YORK | I149: 46101 | J149: 1
J150: =SUM(J2:J149) -> 148

Sheet CDK asked to retain list
A1: Store Name | B1: Comments | C1: CMF | D1: Exclude for May non INS gap list | E1: Exclude from May BLG gap list | H1: CMF # | I1: CMF | J1: Store Name
A2: Ken Ganley Toyota | B2: not installed on TV invoice | C2: 76202516 | D2: yes | H2: =TRIM(I2) -> 25149301 | I2: 25149301 | J2: WESTBROOK HONDA
A3: MODERN INFINITI OF GREENSBORO | B3: moved to Installed, and matched | C3: 71043922 | H3: =TRIM(I3) -> 25149306 | I3: 25149306 | J3: TOYOTA OF WESTBROOK
A4: HONDA OF WATERTOWN | B4: moved to Installed, and matched | C4: 71042332 | H4: =TRIM(I4) -> 71042332 | I4: 71042332 | J4: HONDA OF WATERTOWN
A5: Saskatoon North Hyundai Genesis | B5: moved to Installed, and matched | C5: 76204181 | H5: =TRIM(I5) -> 71043922 | I5: 71043922 | J5: MODERN INFINITI OF GREENSBORO
A6: Saskatoon South Hyundai | B6: not installed on TV invoice | C6: 76204182 | D6: yes | H6: =TRIM(I6) -> 76001666 | I6: 76001666 | J6: KOEPPEL NISSAN
A7: TOYOTA OF WESTBROOK | B7: moved to BLG in CDK | C7: 25149306 | E7: yes | H7: =TRIM(I7) -> 76028715 | I7: 76028715 | J7: JOHNSON HYUNDAI OF CARY
A8: WESTBROOK HONDA | B8: moved to BLG in CDK | C8: 25149301 | E8: yes | H8: =TRIM(I8) -> 76051500 | I8: 76051500 | J8: RED BANK VOLVO
A9: HGREG NISSAN BUENA PARK | B9: not installed on TV invoice | C9: 76225712 | D9: Yes | H9: =TRIM(I9) -> 76074807 | I9: 76074807 | J9: SUPERIOR CHEVROLET
A10: JOHNSON HYUNDAI OF CARY | B10: not installed on TV invoice | C10: 76028715 | D10: Yes | H10: =TRIM(I10) -> 76097658 | I10: 76097658 | J10: STATELINE MASERATI ALFA ROMEO
A11: KOEPPEL NISSAN | B11: not installed on TV invoice | C11: 76001666 | D11: Yes | H11: =TRIM(I11) -> 76202516 | I11: 76202516 | J11: Ken Ganley Toyota
A12: ROCKY MOUNT TOYOTA | B12: not installed on TV invoice | C12: 76217358 | D12: Yes | H12: =TRIM(I12) -> 76204181 | I12: 76204181 | J12: Saskatoon North Hyundai Genesis
A13: STATELINE MASERATI ALFA ROMEO | B13: not installed on TV invoice | C13: 76097658 | D13: Yes | H13: =TRIM(I13) -> 76204182 | I13: 76204182 | J13: Saskatoon South Hyundai
A14: SUPERIOR CHEVROLET | B14: not on TV invoice, CDK shows LSS | C14: 76074807 | H14: =TRIM(I14) -> 76209246 | I14: 76209246 | J14: Scenic Chevrolet GMC Subaru
A15: RED BANK VOLVO | B15: not installed on TV invoice | C15: 76051500 | D15: Yes | H15: =TRIM(I15) -> 76217358 | I15: 76217358 | J15: ROCKY MOUNT TOYOTA
A16: Scenic Chevrolet GMC Subaru | B16: moved to BLG in CDK | C16: 76209246 | E16: Yes | H16: =TRIM(I16) -> 76225712 | I16: 76225712 | J16: HGREG NISSAN BUENA PARK
H17: =TRIM(I17) -> 76227679 | I17: 76227679 | J17: Express Chevrolet
H18: =TRIM(I18) -> 76228316 | I18: 76228316 | J18: Genesis West Houston
H19: =TRIM(I19) -> 76229253 | I19: 76229253 | J19: BRAVO NISSAN OF VICTORIA
A20: additional to ratain sites found on May 19 | H20: =TRIM(I20) -> 76238760 | I20: 76238760 | J20: FRED ANDERSON NISSAN OF GREER
A21: 76227679 | B21: Express Chevrolet | H21: =TRIM(I21) -> 76241447 | I21: 76241447 | J21: LAND ROVER SHREVEPORT.1
A22: 76228316 | B22: Genesis West Houston | H22: =TRIM(I22) -> 76241522 | I22: 76241522 | J22: SMAIL FORD
A23: 76229253 | B23: BRAVO NISSAN OF VICTORIA | H23: =TRIM(I23) -> 76245003 | I23: 76245003 | J23: GRUBBS NISSAN
A24: 76238760 | B24: FRED ANDERSON NISSAN OF GREER | H24: =TRIM(I24) -> 76250378 | I24: 76250378 | J24: GALEANA CDJR MT. PLEASANT
A25: 76241447 | B25: LAND ROVER SHREVEPORT.1
A26: 76241522 | B26: SMAIL FORD
A27: 76245003 | B27: GRUBBS NISSAN
A28: 76250378 | B28: GALEANA CDJR MT. PLEASANT

Sheet TV active sites in March Cancel
A1: CMF | B1: Customer | C1: Partner ID# | D1: Contract Number | E1: Customer Number | F1: TV ID | G1: MOST_RECENT_VIDEO | H1: Asked by CDK to retain | I1: BuySell New CMF | J1: Billed in May? | K1: Comments
A2: =TRIM(C2) -> 08310080 | B2: C. Harper Ford KIA | C2: 08310080 | D2: T-8969 | E2: T-8209 | F2: 6240 | G2: 46121.657 | H2: =VLOOKUP(C2,'CDK asked to retain list'!$C$2:$C$16,1,0) -> #N/A | J2: No
A3: =TRIM(C3) -> 13345702 | B3: RUSS DARROW CHRYSLER DODGE JEEP WEST BEND | C3: 13345702 | D3: T-4258 | E3: T-3236 | F3: 3102 | G3: 46121.664 | H3: =VLOOKUP(C3,'CDK asked to retain list'!$C$2:$C$16,1,0) -> #N/A | J3: No
A4: =TRIM(C4) -> 25149301 | B4: WESTBROOK HONDA | C4: 25149301 | D4: T-14524 | E4: T-12723 | F4: 6567 | G4: 46121.664 | H4: Yes | J4: =VLOOKUP(C4,'TV May Monthly Billing Sites'!$D:$F,1,0) -> 25149301
A5: =TRIM(C5) -> 25149302 | B5: HONDA OF WATERTOWN | C5: 25149302 | D5: T-9440 | E5: T-8576 | F5: 6623 | G5: 46121.653 | H5: =VLOOKUP(C5,'CDK asked to retain list'!$C$2:$C$16,1,0) -> #N/A | J5: =VLOOKUP(C5,'TV May Monthly Billing Sites'!$D:$F,1,0) -> 25149302 | K5: CDK in BLG
A6: =TRIM(C6) -> 25149303 | B6: ACURA OF AVON | C6: 25149303 | D6: T-9439 | E6: T-8575 | F6: 6565 | G6: 46121.624 | H6: =VLOOKUP(C6,'CDK asked to retain list'!$C$2:$C$16,1,0) -> #N/A | J6: No
A7: =TRIM(C7) -> 25149306 | B7: TOYOTA OF WESTBROOK | C7: 25149306 | D7: T-9607 | E7: T-8705 | F7: 6712 | G7: 46113.746 | H7: Yes | J7: =VLOOKUP(C7,'TV May Monthly Billing Sites'!$D:$F,1,0) -> 25149306
A8: =TRIM(C8) -> 71043922 | B8: MODERN INFINITI OF GREENSBORO | C8: 71043922 | D8: T-7482 | E8: T-6426 | F8: 5152 | G8: 46121.662 | H8: Yes | J8: =VLOOKUP(C8,'TV May Monthly Billing Sites'!$D:$F,1,0) -> 71043922
A9: =TRIM(C9) -> 71046175 | B9: Myers Auto Group | C9: 71046175 | D9: T-8089 | E9: T-6921 | F9: 5679 | G9: 46121.551 | H9: =VLOOKUP(C9,'CDK asked to retain list'!$C$2:$C$16,1,0) -> #N/A | J9: No
A10: =TRIM(C10) -> 71048561 | B10: CAR PROS KIA | C10: 71048561 | D10: T-8975 | E10: T-8215 | F10: 6258 | G10: 46121.654 | H10: =VLOOKUP(C10,'CDK asked to retain list'!$C$2:$C$16,1,0) -> #N/A | J10: No
A11: =TRIM(C11) -> 76001666 | B11: KOEPPEL NISSAN | C11: 76001666 | D11: T-4093 | E11: T-7811 | F11: 2297 | G11: 46120.754 | H11: Yes | I11: 76254215 | J11: =VLOOKUP(C11,'TV May Monthly Billing Sites'!$D:$F,1,0) -> 76001666
A12: =TRIM(C12) -> 76028715 | B12: JOHNSON HYUNDAI OF CARY | C12: 76028715 | D12: T-4067 | E12: T-2669 | F12: 2728 | G12: 46121.652 | H12: Yes | I12: 76244599 | J12: =VLOOKUP(C12,'TV May Monthly Billing Sites'!$D:$F,1,0) -> 76028715
A13: =TRIM(C13) -> 76051500 | B13: RED BANK VOLVO | C13: 76051500 | D13: T-8026 | E13: T-6865 | F13: 5632 | G13: 46121.656 | H13: Yes | I13: 76258384 | J13: =VLOOKUP(C13,'TV May Monthly Billing Sites'!$D:$F,1,0) -> 76051500
A14: =TRIM(C14) -> 76064391 | B14: FINDLAY VOLKSWAGEN OF ST GEORGE | C14: 76064391 | D14: T-4460 | E14: T-4087 | F14: 3380 | G14: 46121.634 | H14: =VLOOKUP(C14,'CDK asked to retain list'!$C$2:$C$16,1,0) -> #N/A | J14: No
A15: =TRIM(C15) -> 76074807 | B15: SUPERIOR CHEVROLET | C15: 76074807 | D15: T-9144 | E15: T-2227 | F15: 2155 | G15: 46121.591 | H15: Yes | I15: 76252069 | J15: No
A16: =TRIM(C16) -> 76074807 | B16: SUPERIOR CHEVROLET | C16: 76074807 | D16: T-4308 | E16: T-2227 | F16: 2155 | G16: 46121.591 | H16: Yes | J16: No
A17: =TRIM(C17) -> 76082339 | B17: Ford Lincoln Fairfield | C17: 76082339 | D17: T-3941 | E17: T-3219 | F17: 3096 | G17: 46121.639 | H17: =VLOOKUP(C17,'CDK asked to retain list'!$C$2:$C$16,1,0) -> #N/A | J17: No
A18: =TRIM(C18) -> 76097658 | B18: STATELINE MASERATI ALFA ROMEO | C18: 76097658 | D18: T-14496 | E18: T-12699 | F18: 7901 | G18: 46120.765 | H18: Yes | I18: 76257430 | J18: =VLOOKUP(C18,'TV May Monthly Billing Sites'!$D:$F,1,0) -> 76097658
A19: =TRIM(C19) -> 76141529 | B19: Al Spitzer Ford Cuyahoga Falls | C19: 76141529 | D19: T-5724 | E19: T-4774 | F19: 3779 | G19: 46121.662 | H19: =VLOOKUP(C19,'CDK asked to retain list'!$C$2:$C$16,1,0) -> #N/A | J19: No
A20: =TRIM(C20) -> 76141532 | B20: Spitzer Ford Hartville | C20: 76141532 | D20: T-5733 | E20: T-4783 | F20: 3655 | G20: 46121.619 | H20: =VLOOKUP(C20,'CDK asked to retain list'!$C$2:$C$16,1,0) -> #N/A | J20: No
A21: =TRIM(C21) -> 76153399 | B21: CAR PROS RENTON HYUNDAI | C21: 76153399 | D21: T-8976 | E21: T-8216 | F21: 6259 | G21: 46121.644 | H21: =VLOOKUP(C21,'CDK asked to retain list'!$C$2:$C$16,1,0) -> #N/A | J21: No
A22: =TRIM(C22) -> 76157327 | B22: MARINA DEL REY TOYOTA SCION | C22: 76157327 | D22: T-4118 | E22: T-2728 | F22: 2804 | G22: 46120.804 | H22: =VLOOKUP(C22,'CDK asked to retain list'!$C$2:$C$16,1,0) -> #N/A | J22: =VLOOKUP(C22,'TV May Monthly Billing Sites'!$D:$F,1,0) -> 76157327 | K22: ANS toyota inspect package, INS non SV inspect bundle. Inactive customer for SV
A23: =TRIM(C23) -> 76166159 | B23: ELYRIA HYUNDAI | C23: 76166159 | D23: T-8302 | E23: T-7618 | F23: 5917 | G23: 46115.706 | H23: =VLOOKUP(C23,'CDK asked to retain list'!$C$2:$C$16,1,0) -> #N/A | J23: No | K23: will be rekeyed to have SV.
A24: =TRIM(C24) -> 76174859 | B24: SIMMONS-ROCKWELL SUBARU MITSUBISHI | C24: 76174859 | D24: T-8790 | E24: T-8068 | F24: 6100 | G24: 46121.648 | H24: =VLOOKUP(C24,'CDK asked to retain list'!$C$2:$C$16,1,0) -> #N/A | J24: No
A25: =TRIM(C25) -> 76180664 | B25: CAR PROS KIA RENTON | C25: 76180664 | D25: T-8977 | E25: T-8217 | F25: 6257 | G25: 46121.603 | H25: =VLOOKUP(C25,'CDK asked to retain list'!$C$2:$C$16,1,0) -> #N/A | I25: 76256639 | J25: No | K25: new CMF 76256639/ Go Kai Renton
A26: =TRIM(C26) -> 76202516 | B26: KEN GANLEY TOYOTA | C26: 76202516 | D26: T-6016 | E26: T-5095 | F26: 3929 | G26: 46121.639 | H26: Yes | J26: =VLOOKUP(C26,'TV May Monthly Billing Sites'!$D:$F,1,0) -> 76202516
A27: =TRIM(C27) -> 76204181 | B27: Saskatoon North Hyundai Genesis | C27: 76204181 | D27: T-9599 | E27: T-3488 | F27: 3075 | G27: 46121.619 | H27: Yes | J27: =VLOOKUP(C27,'TV May Monthly Billing Sites'!$D:$F,1,0) -> 76204181
A28: =TRIM(C28) -> 76204182 | B28: Saskatoon South Hyundai | C28: 76204182 | D28: T-9598 | E28: T-3124 | F28: 3074 | G28: 46121.664 | H28: Yes | J28: =VLOOKUP(C28,'TV May Monthly Billing Sites'!$D:$F,1,0) -> 76204182
A29: =TRIM(C29) -> 76204947 | B29: GRIECO HYUNDAI | C29: 76204947 | D29: T-6776 | E29: T-5812 | F29: 4803 | G29: 46121.511 | H29: =VLOOKUP(C29,'CDK asked to retain list'!$C$2:$C$16,1,0) -> #N/A | J29: No
A30: =TRIM(C30) -> 76207079 | B30: Gengras Volkswagen of Plainville | C30: 76207079 | D30: T-6765 | E30: T-5801 | F30: 4544 | G30: 46121.628 | H30: =VLOOKUP(C30,'CDK asked to retain list'!$C$2:$C$16,1,0) -> #N/A | J30: No
A31: =TRIM(C31) -> 76209246 | B31: Scenic Chevrolet GMC Subaru | C31: 76209246 | D31: T-9822 | E31: T-8876 | F31: 6937 | G31: 46121.654 | H31: Yes | J31: already billed under new CMF
A32: =TRIM(C32) -> 76217358 | B32: ROCKY MOUNT TOYOTA | C32: 76217358 | D32: T-4254 | E32: T-2717 | F32: 2784 | G32: 46121.647 | H32: Yes | I32: 76244695 | J32: =VLOOKUP(C32,'TV May Monthly Billing Sites'!$D:$F,1,0) -> 76217358
A33: =TRIM(C33) -> 76219463 | B33: PREMIER CAPE COD | C33: 76219463 | D33: T-4228 | E33: T-2380 | F33: 2375 | G33: 46121.664 | H33: =VLOOKUP(C33,'CDK asked to retain list'!$C$2:$C$16,1,0) -> #N/A | J33: No
A34: =TRIM(C34) -> 76225712 | B34: HGREG NISSAN BUENA PARK | C34: 76225712 | D34: T-3995 | E34: T-2706 | F34: 2749 | G34: 46121.662 | H34: Yes | I34: 76257313 | J34: =VLOOKUP(C34,'TV May Monthly Billing Sites'!$D:$F,1,0) -> 76225712

Sheet CDK Cancel tracking 5.16.26
A1: CMF | B1: Dealer Name | C1: CMF # | D1: Service/Dealer Code | E1: Date Loss Requested | F1: Cancel Reason | G1: On Lei List | H1: Notes
A2: ="0"&TRIM(C2) -> 01196701 | B2: Coastal Hyundai | C2: 1196701 | D2: 845834 | E2: 46092 | H2: Recent
A3: ="0"&TRIM(C3) -> 01325978 | B3: Maxie Price Chevrolet | C3: 1325978 | D3: 512350 | E3: 46091 | F3: Low Utilization | H3: Recent
A4: ="0"&TRIM(C4) -> 05139104 | B4: Maita Chevrolet | C4: 5139104 | D4: 466845 | E4: 46091 | F4: DMS Provider Change | H4: Recent
A5: ="0"&TRIM(C5) -> 05236442 | B5: Smothers European | C5: 5236442 | D5: 62045 | E5: 46143 | F5: Changed DMS Provider
A6: ="0"&TRIM(C6) -> 07615206 | B6: Toyota Del Rio | C6: 7615206 | D6: 024996 | E6: 46093 | H6: Recent
A7: ="0"&TRIM(C7) -> 07621134 | B7: Anderson Ford | C7: 7621134 | D7: 544664 | E7: 46091 | F7: Low Utilization | H7: Recent
A8: ="0"&TRIM(C8) -> 07624170 | B8: Ford of Spartanburg | C8: 7624170 | D8: 768457 | E8: 46092 | H8: Recent
A9: ="0"&TRIM(C9) -> 08300018 | B9: Grainger Honda | C9: 8300018 | D9: 282414 | E9: 46146 | F9: No Comment
A10: ="0"&TRIM(C10) -> 08300127 | B10: Prestige Imports | C10: 8300127 | D10: 188030 | E10: 46059 | F10: Low Utilization | G10: No
A11: ="0"&TRIM(C11) -> 09800035 | B11: Van Buren Buick GMC - DealerID 6554 | C11: 9800035 | D11: 6554 | E11: 46027 | G11: Yes
A12: =TRIM(C12) -> 17314868 | B12: Sames Ford Laredo | C12: 17314868 | D12: 305057 | E12: 46042 | F12: DMS Provider Change | G12: Yes | H12: On Loss list from Lei SAMES MOTOR COMPANY Same CMF
A13: =TRIM(C13) -> 17315776 | B13: Sames Honda | C13: 17315776 | D13: 163617 | E13: 46093 | F13: Low Utilization | H13: Recent
A14: =TRIM(C14) -> 37002901 | B14: Len Lyall Chevrolet | C14: 37002901 | D14: 664881 | E14: 46093 | H14: Recent
A15: =TRIM(C15) -> 37011801 | B15: Jerry Seiner Chevrolet Cadillac Kia Salt Lake | C15: 37011801 | D15: 305755 | E15: 46090 | G15: Yes | H15: Recent
A16: =TRIM(C16) -> 37011804 | B16: Jerry Seiner Buick GMS North Salt Lake | C16: 37011804 | D16: 526414 | E16: 46090 | F16: Low Utilization | G16: Yes | H16: Recent
A17: =TRIM(C17) -> 43996001 | B17: Paul MIller Audi | C17: 43996001 | D17: 451374 | E17: 46146 | F17: Changed provider
A18: =TRIM(C18) -> 71038202 | B18: Aiport Chevrolet | C18: 71038202 | D18: 560288 | E18: 46141 | F18: Cancelled
A19: =TRIM(C19) -> 71046604 | B19: The Chevrolet Exchange | C19: 71046604 | D19: 526554 | E19: 46093 | H19: Recent
A20: =TRIM(C20) -> 71052821 | B20: Schicker Ford St. Louis - Dealer ID 3000872 | C20: 71052821 | D20: 513030 | E20: 46119 | F20: incompatible
A21: =TRIM(C21) -> 71052902 | B21: Caldwell Toyota | C21: 71052902 | D21: 358008 | E21: 46093 | F21: Changed Vendors | H21: Recent
A22: =TRIM(C22) -> 71065039 | B22: Toyota Tacoma | C22: 71065039 | D22: 308822 | E22: 46142 | F22: DmS Provider Change
A23: =TRIM(C23) -> 76002916 | B23: Bentley Paramus - DealerID 2139 | C23: 76002916 | D23: 2139 | E23: 46031 | G23: No
A24: =TRIM(C24) -> 76012651 | B24: Findlay Honda Henderson | C24: 76012651 | D24: 350208 | E24: 46093 | F24: Low Utilization | H24: Recent
A25: =TRIM(C25) -> 76024029 | B25: Damerow Ford | C25: 76024029 | D25: 385244 | E25: 46142
A26: =TRIM(C26) -> 76024700 | B26: Cannon Chevrolet Buick Cadillac | C26: 76024700 | D26: 506664 | E26: 46093 | F26: Low Utilization | H26: Recent
A27: =TRIM(C27) -> 76027610 | B27: Valley Hi Honda | C27: 76027610 | D27: 580262 | E27: 46142 | F27: Changed vendors
A28: =TRIM(C28) -> 76038829 | B28: Sames Bastrop Ford | C28: 76038829 | D28: 822458 | E28: 46042 | F28: DMS Provider Change | H28: On Loss list from Lei SAMES MOTOR COMPANY Different CMF
A29: =TRIM(C29) -> 76039933 | B29: Chaparral Buick GMC | C29: 76039933 | D29: 214382 | E29: 46092 | H29: Recent
A30: =TRIM(C30) -> 76042015 | B30: Mag Volvo Cars Dublin | C30: 76042015 | D30: 304806 | E30: 46093 | F30: Changed DMS Provider | H30: Recent
A31: =TRIM(C31) -> 76043277 | B31: Paul Miller Honda West Caldwell | C31: 76043277 | D31: 545776 | E31: 46146 | F31: Changed provider
A32: =TRIM(C32) -> 76043322 | B32: Rancho Grand Motors Buick GMC | C32: 76043322 | D32: 647815 | E32: 46091 | F32: Changed Vendors | H32: Recent
A33: =TRIM(C33) -> 76054901 | B33: Midwestern Auto Group | C33: 76054901 | D33: 72400 | E33: 46093 | F33: Changed DMS Provider | H33: Recent
A34: =TRIM(C34) -> 76057761 | B34: Jeff Schmitt Mazda | C34: 76057761 | D34: 803007 | E34: 46128 | F34: Changed providers
A35: =TRIM(C35) -> 76062180 | B35: Volvo Car Pioneer Valley | C35: 76062180 | D35: 31421 | E35: 46134 | F35: Dealer closed
A36: =TRIM(C36) -> 76066680 | B36: Speedway Chevrolet | C36: 76066680 | D36: 41080 | E36: 46090 | F36: Low Utilization | G36: Yes | H36: Recent- Reinstated 4/8/26 per Ryan Reed
A37: =TRIM(C37) -> 76072111 | B37: Gebhardt BMW | C37: 76072111 | D37: 865628 | E37: 46093 | H37: Recent
A38: =TRIM(C38) -> 76073768 | B38: Lexington Toyota | C38: 76073768 | D38: 418053 | E38: 46093 | F38: Low Utilization | H38: Recent
A39: =TRIM(C39) -> 76080698 | B39: Hyundai Inland Empire | C39: 76080698 | D39: 608705 | E39: 46091 | F39: Low Utilization | H39: Recent
A40: =TRIM(C40) -> 76140116 | B40: Roseburg Honda | C40: 76140116 | D40: 138421 | E40: 46092 | H40: Recent
A41: =TRIM(C41) -> 76140762 | B41: Sames Kia | C41: 76140762 | D41: 268346 | E41: 46093 | F41: Low Utilization | H41: Recent
A42: =TRIM(C42) -> 76150784 | B42: Jaguar Land Rover San Juan | C42: 76150784 | D42: 656278 | E42: 46142 | F42: Changed Vendors
A43: =TRIM(C43) -> 76162825 | B43: Johnson City Ford | C43: 76162825 | D43: 525525 | E43: 46092 | H43: Recent 4/14/26 asked to have onboarding sent and SV reinstalled 4/16/26 reconnected
A44: =TRIM(C44) -> 76169426 | B44: Lithia Nissan Clovis | C44: 76169426 | D44: 29456 | E44: 46093 | F44: Low Utilization | H44: Recent
A45: =TRIM(C45) -> 76171302 | B45: Hawk VW of Joliet | C45: 76171302 | D45: 7196 | E45: 46044 | G45: No
A46: =TRIM(C46) -> 76171893 | B46: Paul Miller Porsche - DealerID 2143 | C46: 76171893 | D46: 2143 | E46: 46031 | G46: Yes
A47: =TRIM(C47) -> 76173064 | B47: Infiniti West Houston | C47: 76173064 | D47: 524662 | E47: 46146 | F47: incompatible
A48: =TRIM(C48) -> 76174379 | B48: Hawk Chevrolet of Joliet | C48: 76174379 | D48: 6815 | E48: 46044 | G48: No | H48: On Loss list from Lei as HAWK CHEVROLET CADILLAC OF JOLIET 76174379
A49: =TRIM(C49) -> 76175175 | B49: Audi Tacoma | C49: 76175175 | D49: 740077 | E49: 46142 | F49: DMS Provider Change
A50: =TRIM(C50) -> 76181637 | B50: Magna Motors Dealership (ServiceView Plus for Truck) | C50: 76181637 | E50: 46091 | H50: Recent: There is no as this Dealer is no ServiceView however they do appear on our invoice
A51: =TRIM(C51) -> 76195666 | B51: Four Start Toyota | C51: 76195666 | D51: 341726 | E51: 46091 | F51: Low Utilization | H51: Recent
A52: =TRIM(C52) -> 76195919 | B52: Interstate Ford | C52: 76195919 | D52: 644558 | E52: 46028 | F52: Changed Vendors | G52: No
A53: =TRIM(C53) -> 76197109 | B53: Lexus of Wesley Chapel | C53: 76197109 | D53: 520422 | E53: 46143 | F53: Changed DMS Provider
A54: =TRIM(C54) -> 76201836 | B54: Volvo Cars West Houston | C54: 76201836 | D54: 814547 | E54: 46146 | F54: incompatible
A55: =TRIM(C55) -> 76202065 | B55: Johnson City Toyota | C55: 76202065 | D55: 105473 | E55: 46092 | H55: Recent
A56: =TRIM(C56) -> 76203882 | B56: Reliance Chevrolet Buick GMC | C56: 76203882 | D56: 432400 | E56: 46090 | F56: Low Utilization | G56: Yes | H56: Recent
A57: =TRIM(C57) -> 76205088 | B57: Lebanon Ford | C57: 76205088 | D57: 716374 | E57: 46028 | F57: Changed Vendors | G57: Yes
A58: =TRIM(C58) -> 76206328 | B58: Toyota of Berkeley | C58: 76206328 | D58: 261150 | E58: 46093 | F58: Low Utilization | H58: Recent
A59: =TRIM(C59) -> 76208069 | B59: Mercedez Benz of Cincinnati | C59: 76208069 | D59: 812855 | E59: 46092 | H59: Recent
A60: =TRIM(C60) -> 76209123 | B60: Ciocca Toyota of Williamsport | C60: 76209123 | D60: 355724 | E60: 46029 | G60: yes
A61: =TRIM(C61) -> 76211326 | B61: New Century Honda | C61: 76211326 | D61: 818818 | E61: 46142 | F61: Changed DMS Provider
A62: =TRIM(C62) -> 76211612 | B62: Honda of Kingsport | C62: 76211612 | D62: 704100 | E62: 46092 | H62: Recent
A63: =TRIM(C63) -> 76211737 | B63: Asheville Ford Lincoln | C63: 76211737 | D63: 55041 | E63: 46091 | F63: Low Utilization | H63: Recent
A64: =TRIM(C64) -> 76212091 | B64: Huntersviille Ford | C64: 76212091 | D64: 318737 | E64: 46091 | F64: Low Utilization | H64: Recent
A65: =TRIM(C65) -> 76214618 | B65: Acura of Fremont | C65: 76214618 | D65: 85167 | E65: 46091 | F65: Low Utilization | H65: Recent 4/14/26 asked to have onboarding sent and SV reinstalled -4/16/26 reconnected
A66: =TRIM(C66) -> 76215823 | B66: Lia Infiniti Latham | C66: 76215823 | D66: 260582 | E66: 46093 | H66: Recent
A67: =TRIM(C67) -> 76218326 | B67: StoneCrest Honda | C67: 76218326 | D67: 545638 | E67: 46092 | H67: Recent
A68: =TRIM(C68) -> 76218622 | B68: Cleveland Ford | C68: 76218622 | D68: 651677 | E68: 46092 | H68: Recent
A69: =TRIM(C69) -> 76220778 | B69: Hyundai or Cumming | C69: 76220778 | D69: 785637 | E69: 46091 | F69: Low Utilization | H69: Recent
A70: =TRIM(C70) -> 76220929 | B70: Beaman Buick | C70: 76220929 | D70: 483846 | E70: 46092 | H70: Recent
A71: =TRIM(C71) -> 76220930 | B71: Beaman Toyota | C71: 76220930 | D71: 412605 | E71: 46092 | H71: Recent
A72: =TRIM(C72) -> 76221166 | B72: Lexus of Greenville | C72: 76221166 | D72: 338516 | E72: 46092 | H72: Recent- 4/13/26 asked to have them reinstated as loss was from 9/2025 and they recontracted 11/25 4/16/26 reconnected
A73: =TRIM(C73) -> 76223745 | B73: Forest Lane CDJR | C73: 76223745 | E73: 46093 | F73: Low Utilization | H73: - I do not see them setup in ServiceView- Please verify that we are not being billed for this store
A74: =TRIM(C74) -> 76224033 | B74: Morristown Chevrolet | C74: 76224033 | D74: 103784 | E74: 46092 | H74: Recent
A75: =TRIM(C75) -> 76224072 | B75: Mazda of Amarillo | C75: 76224072 | D75: 134285 | E75: 46093 | H75: Recent
A76: =TRIM(C76) -> 76227448 | B76: Mercedes Benz West Chester | C76: 76227448 | D76: 7441770 | E76: 46092 | H76: Recent
A77: =TRIM(C77) -> 76227701 | B77: Corpus Christi Mitsubishi | C77: 76227701 | D77: 217301 | E77: 46093 | F77: Changed Vendors | H77: Recent
A78: =TRIM(C78) -> 76227703 | B78: Mazda Corus Christi | C78: 76227703 | D78: 83583 | E78: 46093 | H78: Recent
A79: =TRIM(C79) -> 76230499 | B79: Jerry Seiner Buick GMC | C79: 76230499 | D79: 431473 | E79: 46090 | G79: Yes | H79: Jerry Seiner Buick GMC South Jordan 76230499 Same CMF
A80: =TRIM(C80) -> 76231547 | B80: Rock Hill Ford | C80: 76231547 | D80: 451775 | E80: 46091 | F80: Low Utilization | H80: Recent
A81: =TRIM(C81) -> 76234979 | B81: Confidence Chevrolet | C81: 76234979 | D81: 883308 | E81: 46090 | G81: Yes | H81: Recent
A82: =TRIM(C82) -> 76234982 | B82: Confidence Buick GMC- Changed Vendor | C82: 76234982 | D82: 801215 | E82: 46090 | G82: Yes | H82: Recent
A83: =TRIM(C83) -> 76235392 | B83: Hyundai of North Charleston | C83: 76235392 | D83: 312505 | E83: 46091 | F83: Low Utilization | H83: Recent
A84: =TRIM(C84) -> 76235642 | B84: Hyundai of Charleston | C84: 76235642 | D84: 805601 | E84: 46091 | F84: Low Utilization | H84: Recent
A85: =TRIM(C85) -> 76236423 | B85: Young Mazda Idaho Falls | C85: 76236423 | D85: 972035 | E85: 46142 | F85: Changing provider
A86: =TRIM(C86) -> 76237278 | B86: Hyundai of Gainsville (Gainsville Hyundai) | C86: 76237278 | D86: 347281 | E86: 46091 | F86: Low Utilization | H86: Recent
A87: =TRIM(C87) -> 76237579 | B87: Gensis of Greensboro | C87: 76237579 | D87: 325873 | E87: 46091 | F87: Out of Business | H87: Recent
A88: =TRIM(C88) -> 76238024 | B88: Infiniti City of Queens - DealerID 5321 | C88: 76238024 | D88: 5321 | E88: 46031 | G88: Yes
A89: =TRIM(C89) -> 76241969 | B89: Porsche Service Center East Hanover - DealerID 4363 | C89: 76241969 | D89: 4363 | E89: 46031 | G89: No
A90: =TRIM(C90) -> 76244657 | B90: Fort Myers Genesis | C90: 76244657 | D90: 41784 | E90: 46091 | F90: Low Utilization | H90: Recent
A91: =TRIM(C91) -> 76245040 | B91: Crown Dodge Chrysler | C91: 76245040 | D91: 680015 | E91: 46146 | F91: Dealer Sold
A92: =TRIM(C92) -> 76245731 | B92: Bravo Nissan of Baytown | C92: 76245731 | D92: 243570 | E92: 46059 | F92: Incompatible | G92: No
A93: =TRIM(C93) -> 76245931 | B93: Vaden Hyundai of Statesboro - DealerID 5702 | C93: 76245931 | D93: 5702 | E93: 46027 | H93: On Loss list from Lei VADEN NISSAN OF STATESBORO 76245931
A94: =TRIM(C94) -> 76246309 | B94: Lexus of Huntsville | C94: 76246309 | D94: 188030 | E94: 46063 | H94: On Loss list from Lei LEXUS OF HUNTSVILLE 01327159 Different CMF
A95: =TRIM(C95) -> 76254419 | B95: Mercedes Benz of Collierville - DealerID 6082 | C95: 76254419 | D95: 6082 | E95: 46031 | G95: Yes
A96: =TRIM(C96) -> 76254420 | B96: Mercedes Benz of Jackson - DealerID 6083 | C96: 76254420 | D96: 6083 | E96: 46031 | G96: Yes
A97: =TRIM(C97) -> 76258093 | B97: Eurobahn Motorsport | C97: 76258093 | D97: 31503 | E97: 46143 | F97: Changed DMS Provider
A98: =TRIM(C98) -> 76231813 or 37011802 | B98: Jerry Seiner Kia South Jordan | C98: 76231813 or 37011802 | D98: 280076 | E98: 46090 | H98: On Loss list from Lei as Jerry Seiner Chevrolet Casa Grande 76219556 Different CMF

Sheet TV May Monthly Billing Sites
A1: CMF | B1: Customer | C1: Contract Number | D1: CMF Number | E1: CID Number | F1: Item | G1: Local Amount | H1: Found in CDK INS by CMF | I1: Found in CDK INS by Name | J1: Found in CDK BLG by CMF | K1: Found in CDK BLG by Name | L1: New Sites in April | M1: To Retain List
A2: ="0"&TRIM(D2) -> 01012201 | B2: Lynn Layton Chevrolet | C2: T-16228 | D2: 1012201 | E2: 3001502 | F2: CDK Reseller - Base Fee | G2: 300 | H2: =VLOOKUP(A2,'SV Child INS Apr'!$A:$H,1,0) -> #N/A | I2: =VLOOKUP(B2,'SV Child INS Apr'!$D:$F,1,0) -> #N/A | J2: =VLOOKUP(A2,'SV Child BLG Apr'!$A:$J,1,0) -> 01012201 | L2: =VLOOKUP(A2,'TV Apr Prorated Billing Sites'!$A:$I,1,0) -> 01012201 | M2: =VLOOKUP(A2,'CDK asked to retain list'!$H$1:$J$24,1,0) -> #N/A
A3: ="0"&TRIM(D3) -> 01012202 | B3: LYNN LAYTON CADILLAC NISSAN | C3: T-16227 | D3: 1012202 | E3: 3001510 | F3: CDK Reseller - Base Fee | G3: 300 | H3: =VLOOKUP(A3,'SV Child INS Apr'!$A:$H,1,0) -> #N/A | I3: =VLOOKUP(B3,'SV Child INS Apr'!$D:$F,1,0) -> #N/A | J3: =VLOOKUP(A3,'SV Child BLG Apr'!$A:$J,1,0) -> 01012202 | L3: =VLOOKUP(A3,'TV Apr Prorated Billing Sites'!$A:$I,1,0) -> 01012202 | M3: =VLOOKUP(A3,'CDK asked to retain list'!$H$1:$J$24,1,0) -> #N/A
A4: ="0"&TRIM(D4) -> 01012401 | B4: Solomon Chevrolet Cadillac | C4: T-11243 | D4: 1012401 | E4: 2500033 | F4: CDK Reseller - Base Fee | G4: 300 | H4: =VLOOKUP(A4,'SV Child INS Apr'!$A:$H,1,0) -> 01012401 | L4: =VLOOKUP(A4,'TV Apr Prorated Billing Sites'!$A:$I,1,0) -> #N/A
A5: ="0"&TRIM(D5) -> 01013001 | B5: Tameron Honda | C5: T-10927 | D5: 1013001 | E5: 2503657 | F5: CDK Reseller - Base Fee | G5: 300 | H5: =VLOOKUP(A5,'SV Child INS Apr'!$A:$H,1,0) -> 01013001 | L5: =VLOOKUP(A5,'TV Apr Prorated Billing Sites'!$A:$I,1,0) -> #N/A
A6: ="0"&TRIM(D6) -> 01013501 | B6: AL PACKER FORD INC | C6: T-15480 | D6: 1013501 | E6: 10027 | F6: CDK Reseller - Base Fee | G6: 300 | H6: =VLOOKUP(A6,'SV Child INS Apr'!$A:$H,1,0) -> #N/A | I6: =VLOOKUP(B6,'SV Child INS Apr'!$D:$F,1,0) -> #N/A | J6: =VLOOKUP(A6,'SV Child BLG Apr'!$A:$J,1,0) -> 01013501 | L6: =VLOOKUP(A6,'TV Apr Prorated Billing Sites'!$A:$I,1,0) -> #N/A | M6: =VLOOKUP(A6,'CDK asked to retain list'!$H$1:$J$24,1,0) -> #N/A
A7: ="0"&TRIM(D7) -> 01013502 | B7: AL PACKER FORD ROYAL PALM BEACH | C7: T-15479 | D7: 1013502 | E7: 10028 | F7: CDK Reseller - Base Fee | G7: 300 | H7: =VLOOKUP(A7,'SV Child INS Apr'!$A:$H,1,0) -> #N/A | I7: =VLOOKUP(B7,'SV Child INS Apr'!$D:$F,1,0) -> #N/A | J7: =VLOOKUP(A7,'SV Child BLG Apr'!$A:$J,1,0) -> 01013502 | L7: =VLOOKUP(A7,'TV Apr Prorated Billing Sites'!$A:$I,1,0) -> #N/A | M7: =VLOOKUP(A7,'CDK asked to retain list'!$H$1:$J$24,1,0) -> #N/A
A8: ="0"&TRIM(D8) -> 01017901 | B8: JOHN THORNTON CHEVROLET | C8: T-14157 | D8: 1017901 | E8: 123013 | F8: CDK Reseller - Base Fee | G8: 300 | H8: =VLOOKUP(A8,'SV Child INS Apr'!$A:$H,1,0) -> 01017901 | L8: =VLOOKUP(A8,'TV Apr Prorated Billing Sites'!$A:$I,1,0) -> #N/A
A9: ="0"&TRIM(D9) -> 01023201 | B9: Dick Smith Nissan of Columbia | C9: T-6802 | D9: 1023201 | E9: 1500194 | F9: CDK Reseller - Base Fee | G9: 300 | H9: =VLOOKUP(A9,'SV Child INS Apr'!$A:$H,1,0) -> 01023201 | L9: =VLOOKUP(A9,'TV Apr Prorated Billing Sites'!$A:$I,1,0) -> #N/A
A10: ="0"&TRIM(D10) -> 01027202 | B10: CMA's Colonial Honda | C10: T-6786 | D10: 1027202 | E10: 2500877 | F10: CDK Reseller - Base Fee | G10: 300 | H10: =VLOOKUP(A10,'SV Child INS Apr'!$A:$H,1,0) -> 01027202 | L10: =VLOOKUP(A10,'TV Apr Prorated Billing Sites'!$A:$I,1,0) -> #N/A
A11: ="0"&TRIM(D11) -> 01027210 | B11: CMA's Colonial Auto Center | C11: T-7442 | D11: 1027210 | E11: 2500896 | F11: CDK Reseller - Base Fee | G11: 300 | H11: =VLOOKUP(A11,'SV Child INS Apr'!$A:$H,1,0) -> 01027210 | L11: =VLOOKUP(A11,'TV Apr Prorated Billing Sites'!$A:$I,1,0) -> #N/A
A12: ="0"&TRIM(D12) -> 01028106 | B12: BERGLUND FORD MAZDA | C12: T-3836 | D12: 1028106 | E12: 3378 | F12: CDK Reseller - Base Fee | G12: 450 | H12: =VLOOKUP(A12,'SV Child INS Apr'!$A:$H,1,0) -> 01028106 | L12: =VLOOKUP(A12,'TV Apr Prorated Billing Sites'!$A:$I,1,0) -> #N/A
A13: ="0"&TRIM(D13) -> 01029201 | B13: MORGAN MCCLURE CHEVY BUICK CADILLAC | C13: T-14159 | D13: 1029201 | E13: 3000869 | F13: CDK Reseller - Base Fee | G13: 300 | H13: =VLOOKUP(A13,'SV Child INS Apr'!$A:$H,1,0) -> 01029201 | L13: =VLOOKUP(A13,'TV Apr Prorated Billing Sites'!$A:$I,1,0) -> #N/A
A14: ="0"&TRIM(D14) -> 01029202 | B14: MORGAN-MCCLURE CHEVROLET | C14: T-14158 | D14: 1029202 | E14: 3000870 | F14: CDK Reseller - Base Fee | G14: 300 | H14: =VLOOKUP(A14,'SV Child INS Apr'!$A:$H,1,0) -> 01029202 | L14: =VLOOKUP(A14,'TV Apr Prorated Billing Sites'!$A:$I,1,0) -> #N/A
A15: ="0"&TRIM(D15) -> 01029501 | B15: HAMPTON CHEVROLET - VA | C15: T-15096 | D15: 1029501 | E15: 2001100 | F15: CDK Reseller - Base Fee | G15: 300 | H15: =VLOOKUP(A15,'SV Child INS Apr'!$A:$H,1,0) -> #N/A | I15: =VLOOKUP(B15,'SV Child INS Apr'!$D:$F,1,0) -> #N/A | J15: =VLOOKUP(A15,'SV Child BLG Apr'!$A:$J,1,0) -> 01029501 | L15: =VLOOKUP(A15,'TV Apr Prorated Billing Sites'!$A:$I,1,0) -> #N/A | M15: =VLOOKUP(A15,'CDK asked to retain list'!$H$1:$J$24,1,0) -> #N/A
A16: ="0"&TRIM(D16) -> 01029901 | B16: WEST BROAD HONDA | C16: T-4370 | D16: 1029901 | E16: 13134 | F16: CDK Reseller - Base Fee | G16: 450 | H16: =VLOOKUP(A16,'SV Child INS Apr'!$A:$H,1,0) -> 01029901 | L16: =VLOOKUP(A16,'TV Apr Prorated Billing Sites'!$A:$I,1,0) -> #N/A
A17: ="0"&TRIM(D17) -> 01029905 | B17: MECHANICSVILLE HONDA | C17: T-9118 | D17: 1029905 | E17: 2500591 | F17: CDK Reseller - Base Fee | G17: 300 | H17: =VLOOKUP(A17,'SV Child INS Apr'!$A:$H,1,0) -> 01029905 | L17: =VLOOKUP(A17,'TV Apr Prorated Billing Sites'!$A:$I,1,0) -> #N/A
A18: ="0"&TRIM(D18) -> 01029906 | B18: WEST BROAD HYUNDAI | C18: T-4371 | D18: 1029906 | E18: 13139 | F18: CDK Reseller - Base Fee | G18: 450 | H18: =VLOOKUP(A18,'SV Child INS Apr'!$A:$H,1,0) -> 01029906 | L18: =VLOOKUP(A18,'TV Apr Prorated Billing Sites'!$A:$I,1,0) -> #N/A
A19: ="0"&TRIM(D19) -> 01046402 | B19: Howard Bentley Buick GMC | C19: T-9655 | D19: 1046402 | E19: 2003102 | F19: CDK Reseller - Base Fee | G19: 300 | H19: =VLOOKUP(A19,'SV Child INS Apr'!$A:$H,1,0) -> 01046402 | L19: =VLOOKUP(A19,'TV Apr Prorated Billing Sites'!$A:$I,1,0) -> #N/A
A20: ="0"&TRIM(D20) -> 01046701 | B20: Tri-State Nissan | C20: T-9251 | D20: 1046701 | E20: 2503537 | F20: CDK Reseller - Base Fee | G20: 300 | H20: =VLOOKUP(A20,'SV Child INS Apr'!$A:$H,1,0) -> 01046701 | L20: =VLOOKUP(A20,'TV Apr Prorated Billing Sites'!$A:$I,1,0) -> #N/A
A21: ="0"&TRIM(D21) -> 01071601 | B21: R.E. Yrausquin & Sons N.V. | C21: T-9789 | D21: 1071601 | E21: 2502506 | F21: CDK Reseller - Base Fee | G21: 300 | H21: =VLOOKUP(A21,'SV Child INS Apr'!$A:$H,1,0) -> 01071601 | L21: =VLOOKUP(A21,'TV Apr Prorated Billing Sites'!$A:$I,1,0) -> #N/A
A22: ="0"&TRIM(D22) -> 01154301 | B22: JIM ARMSTRONG SUBARU | C22: T-14147 | D22: 1154301 | E22: 3000851 | F22: CDK Reseller - Base Fee | G22: 300 | H22: =VLOOKUP(A22,'SV Child INS Apr'!$A:$H,1,0) -> 01154301 | L22: =VLOOKUP(A22,'TV Apr Prorated Billing Sites'!$A:$I,1,0) -> #N/A
A23: ="0"&TRIM(D23) -> 01188402 | B23: WARREN HENRY AUTO MALL | C23: T-9464 | D23: 1188402 | E23: 2500234 | F23: CDK Reseller - Base Fee | G23: 300 | H23: =VLOOKUP(A23,'SV Child INS Apr'!$A:$H,1,0) -> 01188402 | L23: =VLOOKUP(A23,'TV Apr Prorated Billing Sites'!$A:$I,1,0) -> #N/A
A24: ="0"&TRIM(D24) -> 01214101 | B24: Autos Vega Group | C24: T-5998 | D24: 1214101 | E24: 2500137 | F24: CDK Reseller - Base Fee | G24: 300 | H24: =VLOOKUP(A24,'SV Child INS Apr'!$A:$H,1,0) -> 01214101 | L24: =VLOOKUP(A24,'TV Apr Prorated Billing Sites'!$A:$I,1,0) -> #N/A
A25: ="0"&TRIM(D25) -> 01214106 | B25: Volkswagen Kennedy | C25: T-6147 | D25: 1214106 | E25: 2500760 | F25: CDK Reseller - Base Fee | G25: 300 | H25: =VLOOKUP(A25,'SV Child INS Apr'!$A:$H,1,0) -> 01214106 | L25: =VLOOKUP(A25,'TV Apr Prorated Billing Sites'!$A:$I,1,0) -> #N/A
A26: ="0"&TRIM(D26) -> 01247501 | B26: Rice Buick GMC | C26: T-6764 | D26: 1247501 | E26: 2002829 | F26: CDK Reseller - Base Fee | G26: 300 | H26: =VLOOKUP(A26,'SV Child INS Apr'!$A:$H,1,0) -> 01247501 | L26: =VLOOKUP(A26,'TV Apr Prorated Billing Sites'!$A:$I,1,0) -> #N/A
A27: ="0"&TRIM(D27) -> 01262401 | B27: HEADQUARTER TOYOTA | C27: T-13339 | D27: 1262401 | E27: 2000706 | F27: CDK Reseller - Base Fee | G27: 300 | H27: =VLOOKUP(A27,'SV Child INS Apr'!$A:$H,1,0) -> 01262401 | L27: =VLOOKUP(A27,'TV Apr Prorated Billing Sites'!$A:$I,1,0) -> #N/A
... A32: ="0"&TRIM(D32) -> 01325667 | B32: KEVIN WHITAKER CHEVROLET CADILLAC | C32: T-4081 | D32: 1325667 | E32: 13103 | F32: CDK Reseller - Base Fee | G32: 450 | H32: =VLOOKUP(A32,'SV Child INS Apr'!$A:$H,1,0) -> 01325667 | L32: =VLOOKUP(A32,'TV Apr Prorated Billing Sites'!$A:$I,1,0) -> #N/A
A33: ="0"&TRIM(D33) -> 01325739 | B33: SOUTHTOWNE MOTORS OF NEWNAN | C33: T-13815 | D33: 1325739 | E33: 2000912 | F33: CDK Reseller - Base Fee | G33: 300 | H33: =VLOOKUP(A33,'SV Child INS Apr'!$A:$H,1,0) -> #N/A | I33: =VLOOKUP(B33,'SV Child INS Apr'!$D:$F,1,0) -> #N/A | J33: =VLOOKUP(A33,'SV Child BLG Apr'!$A:$J,1,0) -> 01325739 | L33: =VLOOKUP(A33,'TV Apr Prorated Billing Sites'!$A:$I,1,0) -> #N/A | M33: =VLOOKUP(A33,'CDK asked to retain list'!$H$1:$J$24,1,0) -> #N/A
A34: ="0"&TRIM(D34) -> 01326145 | B34: Honda de San Juan | C34: T-16178 | D34: 1326145 | E34: 2500576 | F34: CDK Reseller - Base Fee | G34: 300 | H34: =VLOOKUP(A34,'SV Child INS Apr'!$A:$H,1,0) -> #N/A | I34: =VLOOKUP(B34,'SV Child INS Apr'!$D:$F,1,0) -> #N/A | J34: =VLOOKUP(A34,'SV Child BLG Apr'!$A:$J,1,0) -> 01326145 | L34: =VLOOKUP(A34,'TV Apr Prorated Billing Sites'!$A:$I,1,0) -> 01326145 | M34: =VLOOKUP(A34,'CDK asked to retain list'!$H$1:$J$24,1,0) -> #N/A
A35: ="0"&TRIM(D35) -> 01326209 | B35: MECHANICSVILLE TOYOTA | C35: T-4144 | D35: 1326209 | E35: 2500593 | F35: CDK Reseller - Base Fee | G35: 300 | H35: =VLOOKUP(A35,'SV Child INS Apr'!$A:$H,1,0) -> 01326209 | L35: =VLOOKUP(A35,'TV Apr Prorated Billing Sites'!$A:$I,1,0) -> #N/A
A36: ="0"&TRIM(D36) -> 01326302 | B36: Dick Smith Nissan of Lexington | C36: T-6805 | D36: 1326302 | E36: 1500193 | F36: CDK Reseller - Base Fee | G36: 300 | H36: =VLOOKUP(A36,'SV Child INS Apr'!$A:$H,1,0) -> 01326302 | L36: =VLOOKUP(A36,'TV Apr Prorated Billing Sites'!$A:$I,1,0) -> #N/A
A37: ="0"&TRIM(D37) -> 01326328 | B37: Dick Smith Nissan of St Andrews | C37: T-6804 | D37: 1326328 | E37: 1500195 | F37: CDK Reseller - Base Fee | G37: 300 | H37: =VLOOKUP(A37,'SV Child INS Apr'!$A:$H,1,0) -> 01326328 | L37: =VLOOKUP(A37,'TV Apr Prorated Billing Sites'!$A:$I,1,0) -> #N/A
A38: ="0"&TRIM(D38) -> 01326343 | B38: MIDWAY FORD | C38: T-15078 | D38: 1326343 | E38: 3100 | F38: CDK Reseller - Base Fee | G38: 300 | H38: =VLOOKUP(A38,'SV Child INS Apr'!$A:$H,1,0) -> 01326343 | L38: =VLOOKUP(A38,'TV Apr Prorated Billing Sites'!$A:$I,1,0) -> #N/A
A39: ="0"&TRIM(D39) -> 01326417 | B39: Motor Mile Hyundai | C39: T-9437 | D39: 1326417 | E39: 2002977 | F39: CDK Reseller - Base Fee | G39: 300 | H39: =VLOOKUP(A39,'SV Child INS Apr'!$A:$H,1,0) -> #N/A | I39: =VLOOKUP(B39,'SV Child INS Apr'!$D:$F,1,0) -> MOTOR MILE HYUNDAI | L39: =VLOOKUP(A39,'TV Apr Prorated Billing Sites'!$A:$I,1,0) -> #N/A
A40: ="0"&TRIM(D40) -> 01326450 | B40: PIEDMONT FORD TRUCK SALES | C40: T-4218 | D40: 1326450 | E40: N/A | F40: CDK Reseller - Base Fee | G40: 300 | H40: =VLOOKUP(A40,'SV Child INS Apr'!$A:$H,1,0) -> 01326450 | L40: =VLOOKUP(A40,'TV Apr Prorated Billing Sites'!$A:$I,1,0) -> #N/A
A41: ="0"&TRIM(D41) -> 01326689 | B41: VILLAGE CADILLAC TOYOTA OF HOMASASSA | C41: T-4357 | D41: 1326689 | E41: 2501221 | F41: CDK Reseller - Base Fee | G41: 300 | H41: =VLOOKUP(A41,'SV Child INS Apr'!$A:$H,1,0) -> 01326689 | L41: =VLOOKUP(A41,'TV Apr Prorated Billing Sites'!$A:$I,1,0) -> #N/A
A42: ="0"&TRIM(D42) -> 01326804 | B42: SCENIC MOTORS INC. | C42: T-14828 | D42: 1326804 | E42: 4138 | F42: CDK Reseller - Base Fee | G42: 300 | H42: =VLOOKUP(A42,'SV Child INS Apr'!$A:$H,1,0) -> 01326804 | L42: =VLOOKUP(A42,'TV Apr Prorated Billing Sites'!$A:$I,1,0) -> #N/A
A43: ="0"&TRIM(D43) -> 01326917 | B43: JAGUAR LAND ROVER NORTH DADE | C43: T-9463 | D43: 1326917 | E43: 2500240 | F43: CDK Reseller - Base Fee | G43: 300 | H43: =VLOOKUP(A43,'SV Child INS Apr'!$A:$H,1,0) -> 01326917 | L43: =VLOOKUP(A43,'TV Apr Prorated Billing Sites'!$A:$I,1,0) -> #N/A
A44: ="0"&TRIM(D44) -> 01327435 | B44: Bella Acura de Guaynabo | C44: T-15461 | D44: 1327435 | E44: 2500588 | F44: CDK Reseller - Base Fee | G44: 300 | H44: =VLOOKUP(A44,'SV Child INS Apr'!$A:$H,1,0) -> 01327435 | L44: =VLOOKUP(A44,'TV Apr Prorated Billing Sites'!$A:$I,1,0) -> #N/A
A45: ="0"&TRIM(D45) -> 01327499 | B45: Harry's Buick GMC | C45: T-10631 | D45: 1327499 | E45: 2001702 | F45: CDK Reseller - Base Fee | G45: 300 | H45: =VLOOKUP(A45,'SV Child INS Apr'!$A:$H,1,0) -> 01327499 | L45: =VLOOKUP(A45,'TV Apr Prorated Billing Sites'!$A:$I,1,0) -> #N/A
A46: ="0"&TRIM(D46) -> 04508714 | B46: ROPER KIA | C46: T-8516 | D46: 4508714 | E46: 2503385 | F46: CDK Reseller - Base Fee | G46: 300 | H46: =VLOOKUP(A46,'SV Child INS Apr'!$A:$H,1,0) -> #N/A | I46: =VLOOKUP(B46,'SV Child INS Apr'!$D:$F,1,0) -> ROPER KIA | L46: =VLOOKUP(A46,'TV Apr Prorated Billing Sites'!$A:$I,1,0) -> #N/A
A47: ="0"&TRIM(D47) -> 05021101 | B47: ROYAL MOTOR SALES | C47: T-4257 | D47: 5021101 | E47: 2502087 | F47: CDK Reseller - Base Fee | G47: 450 | H47: =VLOOKUP(A47,'SV Child INS Apr'!$A:$H,1,0) -> 05021101 | L47: =VLOOKUP(A47,'TV Apr Prorated Billing Sites'!$A:$I,1,0) -> #N/A
A48: ="0"&TRIM(D48) -> 05088801 | B48: WINTER CHEVROLET CO. INC. | C48: T-5636 | D48: 5088801 | E48: 2503075 | F48: CDK Reseller - Base Fee | G48: 300 | H48: =VLOOKUP(A48,'SV Child INS Apr'!$A:$H,1,0) -> #N/A | I48: =VLOOKUP(B48,'SV Child INS Apr'!$D:$F,1,0) -> #N/A | J48: =VLOOKUP(A48,'SV Child BLG Apr'!$A:$J,1,0) -> #N/A | K48: =VLOOKUP(B48,'SV Child BLG Apr'!$D:$I,1,0) -> #N/A | L48: =VLOOKUP(A48,'TV Apr Prorated Billing Sites'!$A:$I,1,0) -> #N/A
A49: ="0"&TRIM(D49) -> 05120806 | B49: ACURA OF STOCKTON | C49: T-1020 | D49: 5120806 | E49: 2002171 | F49: CDK Reseller - Base Fee | G49: 450 | H49: =VLOOKUP(A49,'SV Child INS Apr'!$A:$H,1,0) -> 05120806 | L49: =VLOOKUP(A49,'TV Apr Prorated Billing Sites'!$A:$I,1,0) -> #N/A
A50: ="0"&TRIM(D50) -> 05157307 | B50: FREMONT TOYOTA | C50: T-3952 | D50: 5157307 | E50: 2002175 | F50: CDK Reseller - Base Fee | G50: 450 | H50: =VLOOKUP(A50,'SV Child INS Apr'!$A:$H,1,0) -> 05157307 | L50: =VLOOKUP(A50,'TV Apr Prorated Billing Sites'!$A:$I,1,0) -> #N/A
A51: ="0"&TRIM(D51) -> 05163201 | B51: MANLY HYUNDAI | C51: T-5699 | D51: 5163201 | E51: 2001236 | F51: CDK Reseller - Base Fee | G51: 300 | H51: =VLOOKUP(A51,'SV Child INS Apr'!$A:$H,1,0) -> 05163201 | L51: =VLOOKUP(A51,'TV Apr Prorated Billing Sites'!$A:$I,1,0) -> #N/A
A52: ="0"&TRIM(D52) -> 05163202 | B52: MANLY HONDA | C52: T-5698 | D52: 5163202 | E52: 2001237 | F52: CDK Reseller - Base Fee | G52: 300 | H52: =VLOOKUP(A52,'SV Child INS Apr'!$A:$H,1,0) -> 05163202 | L52: =VLOOKUP(A52,'TV Apr Prorated Billing Sites'!$A:$I,1,0) -> #N/A
A53: ="0"&TRIM(D53) -> 05172601 | B53: TEAM VW OF HAYWARD | C53: T-4320 | D53: 5172601 | E53: 2502511 | F53: CDK Reseller - Base Fee | G53: 450 | H53: =VLOOKUP(A53,'SV Child INS Apr'!$A:$H,1,0) -> 05172601 | L53: =VLOOKUP(A53,'TV Apr Prorated Billing Sites'!$A:$I,1,0) -> #N/A
A54: ="0"&TRIM(D54) -> 05172603 | B54: SERRAMONTE VOLKSWAGEN | C54: T-4287 | D54: 5172603 | E54: 2502464 | F54: CDK Reseller - Base Fee | G54: 450 | H54: =VLOOKUP(A54,'SV Child INS Apr'!$A:$H,1,0) -> 05172603 | L54: =VLOOKUP(A54,'TV Apr Prorated Billing Sites'!$A:$I,1,0) -> #N/A
A55: ="0"&TRIM(D55) -> 05228101 | B55: CYPRESS COAST SUBARU | C55: T-3899 | D55: 5228101 | E55: 2000341 | F55: CDK Reseller - Base Fee | G55: 450 | H55: =VLOOKUP(A55,'SV Child INS Apr'!$A:$H,1,0) -> 05228101 | L55: =VLOOKUP(A55,'TV Apr Prorated Billing Sites'!$A:$I,1,0) -> #N/A
A56: ="0"&TRIM(D56) -> 05228102 | B56: CYPRESS COAST FORD | C56: T-3898 | D56: 5228102 | E56: 3136 | F56: CDK Reseller - Base Fee | G56: 450 | H56: =VLOOKUP(A56,'SV Child INS Apr'!$A:$H,1,0) -> 05228102 | L56: =VLOOKUP(A56,'TV Apr Prorated Billing Sites'!$A:$I,1,0) -> #N/A
A57: ="0"&TRIM(D57) -> 05228501 | B57: CHASE CHEVROLET | C57: T-8996 | D57: 5228501 | E57: 2003012 | F57: CDK Reseller - Base Fee | G57: 300 | H57: =VLOOKUP(A57,'SV Child INS Apr'!$A:$H,1,0) -> 05228501 | L57: =VLOOKUP(A57,'TV Apr Prorated Billing Sites'!$A:$I,1,0) -> #N/A
A58: ="0"&TRIM(D58) -> 05236216 | B58: MERCED HONDA | C58: T-8092 | D58: 5236216 | E58: 2000368 | F58: CDK Reseller - Base Fee | G58: 300 | H58: =VLOOKUP(A58,'SV Child INS Apr'!$A:$H,1,0) -> 05236216 | L58: =VLOOKUP(A58,'TV Apr Prorated Billing Sites'!$A:$I,1,0) -> #N/A
A59: ="0"&TRIM(D59) -> 05236425 | B59: CRESTVIEW CADILLAC OF WEST COVINA | C59: T-10607 | D59: 5236425 | E59: 2503601 | F59: CDK Reseller - Base Fee | G59: 300 | H59: =VLOOKUP(A59,'SV Child INS Apr'!$A:$H,1,0) -> 05236425 | L59: =VLOOKUP(A59,'TV Apr Prorated Billing Sites'!$A:$I,1,0) -> #N/A
A60: ="0"&TRIM(D60) -> 05236442 | B60: Smothers European | C60: T-7444 | D60: 5236442 | E60: 3001276 | F60: CDK Reseller - Base Fee | G60: 400 | H60: =VLOOKUP(A60,'SV Child INS Apr'!$A:$H,1,0) -> #N/A | I60: =VLOOKUP(B60,'SV Child INS Apr'!$D:$F,1,0) -> #N/A | J60: =VLOOKUP(A60,'SV Child BLG Apr'!$A:$J,1,0) -> #N/A | K60: =VLOOKUP(B60,'SV Child BLG Apr'!$D:$I,1,0) -> #N/A | L60: =VLOOKUP(A60,'TV Apr Prorated Billing Sites'!$A:$I,1,0) -> #N/A
A61: ="0"&TRIM(D61) -> 05236492 | B61: LODI HONDA | C61: T-4109 | D61: 5236492 | E61: 2002178 | F61: CDK Reseller - Base Fee | G61: 450 | H61: =VLOOKUP(A61,'SV Child INS Apr'!$A:$H,1,0) -> 05236492 | L61: =VLOOKUP(A61,'TV Apr Prorated Billing Sites'!$A:$I,1,0) -> #N/A
A62: ="0"&TRIM(D62) -> 05236645 | B62: VAL STROUGH HONDA | C62: T-4354 | D62: 5236645 | E62: 2000417 | F62: CDK Reseller - Base Fee | G62: 450 | H62: =VLOOKUP(A62,'SV Child INS Apr'!$A:$H,1,0) -> 05236645 | L62: =VLOOKUP(A62,'TV Apr Prorated Billing Sites'!$A:$I,1,0) -> #N/A
A63: ="0"&TRIM(D63) -> 05236759 | B63: WALNUT CREEK FORD | C63: T-14800 | D63: 5236759 | E63: 8096 | F63: CDK Reseller - Base Fee | G63: 300 | H63: =VLOOKUP(A63,'SV Child INS Apr'!$A:$H,1,0) -> 05236759 | L63: =VLOOKUP(A63,'TV Apr Prorated Billing Sites'!$A:$I,1,0) -> #N/A
A64: ="0"&TRIM(D64) -> 05236822 | B64: ELK GROVE HONDA | C64: T-14160 | D64: 5236822 | E64: 5031 | F64: CDK Reseller - Base Fee | G64: 300 | H64: =VLOOKUP(A64,'SV Child INS Apr'!$A:$H,1,0) -> 05236822 | L64: =VLOOKUP(A64,'TV Apr Prorated Billing Sites'!$A:$I,1,0) -> #N/A
A65: ="0"&TRIM(D65) -> 05237164 | B65: BONANDER BUICK GMC | C65: T-13576 | D65: 5237164 | E65: 2001818 | F65: CDK Reseller - Base Fee | G65: 300 | H65: =VLOOKUP(A65,'SV Child INS Apr'!$A:$H,1,0) -> 05237164 | L65: =VLOOKUP(A65,'TV Apr Prorated Billing Sites'!$A:$I,1,0) -> #N/A
A66: ="0"&TRIM(D66) -> 05237677 | B66: CHAMPION CHEVROLET - NV | C66: T-9802 | D66: 5237677 | E66: 2002983 | F66: CDK Reseller - Base Fee | G66: 300 | H66: =VLOOKUP(A66,'SV Child INS Apr'!$A:$H,1,0) -> 05237677 | L66: =VLOOKUP(A66,'TV Apr Prorated Billing Sites'!$A:$I,1,0) -> #N/A
A67: ="0"&TRIM(D67) -> 05400118 | B67: COURTESY BUICK GMC - LA | C67: T-9430 | D67: 5400118 | E67: 2501669 | F67: CDK Reseller - Base Fee | G67: 300 | H67: =VLOOKUP(A67,'SV Child INS Apr'!$A:$H,1,0) -> 05400118 | L67: =VLOOKUP(A67,'TV Apr Prorated Billing Sites'!$A:$I,1,0) -> #N/A
A68: ="0"&TRIM(D68) -> 05400192 | B68: Walker Volkswagen | C68: T-6767 | D68: 5400192 | E68: 2500551 | F68: CDK Reseller - Base Fee | G68: 300 | H68: =VLOOKUP(A68,'SV Child INS Apr'!$A:$H,1,0) -> 05400192 | L68: =VLOOKUP(A68,'TV Apr Prorated Billing Sites'!$A:$I,1,0) -> #N/A
A69: ="0"&TRIM(D69) -> 05700077 | B69: Carlsen Subaru | C69: T-7214 | D69: 5700077 | E69: 2500687 | F69: CDK Reseller - Base Fee | G69: 300 | H69: =VLOOKUP(A69,'SV Child INS Apr'!$A:$H,1,0) -> 05700077 | L69: =VLOOKUP(A69,'TV Apr Prorated Billing Sites'!$A:$I,1,0) -> #N/A
A70: ="0"&TRIM(D70) -> 05700078 | B70: RALPH SELLERS CHRYSLER DODGE JEEP HYUNDAI | C70: T-8657 | D70: 5700078 | E70: 2500495 | F70: CDK Reseller - Base Fee | G70: 300 | H70: =VLOOKUP(A70,'SV Child INS Apr'!$A:$H,1,0) -> 05700078 | L70: =VLOOKUP(A70,'TV Apr Prorated Billing Sites'!$A:$I,1,0) -> #N/A
A71: ="0"&TRIM(D71) -> 05700175 | B71: Rio Motor Co. | C71: T-6787 | D71: 5700175 | E71: 9018 | F71: CDK Reseller - Base Fee | G71: 300 | H71: =VLOOKUP(A71,'SV Child INS Apr'!$A:$H,1,0) -> 05700175 | L71: =VLOOKUP(A71,'TV Apr Prorated Billing Sites'!$A:$I,1,0) -> #N/A
A72: ="0"&TRIM(D72) -> 05710031 | B72: TYLER FORD | C72: T-9793 | D72: 5710031 | E72: 212 | F72: CDK Reseller - Base Fee | G72: 300 | H72: =VLOOKUP(A72,'SV Child INS Apr'!$A:$H,1,0) -> 05710031 | L72: =VLOOKUP(A72,'TV Apr Prorated Billing Sites'!$A:$I,1,0) -> #N/A
... A81: ="0"&TRIM(D81) -> 08300016 | B81: MONTGOMERYVILLE ACURA | C81: T-4166 | D81: 8300016 | E81: 2000549 | F81: CDK Reseller - Base Fee | G81: 450 | H81: =VLOOKUP(A81,'SV Child INS Apr'!$A:$H,1,0) -> 08300016 | L81: =VLOOKUP(A81,'TV Apr Prorated Billing Sites'!$A:$I,1,0) -> #N/A
A82: ="0"&TRIM(D82) -> 08300018 | B82: GRAINGER HONDA | C82: T-13310 | D82: 8300018 | E82: 3000322 | F82: CDK Reseller - Base Fee | G82: 300 | H82: =VLOOKUP(A82,'SV Child INS Apr'!$A:$H,1,0) -> #N/A | I82: =VLOOKUP(B82,'SV Child INS Apr'!$D:$F,1,0) -> #N/A | J82: =VLOOKUP(A82,'SV Child BLG Apr'!$A:$J,1,0) -> #N/A | K82: =VLOOKUP(B82,'SV Child BLG Apr'!$D:$I,1,0) -> #N/A | L82: =VLOOKUP(A82,'TV Apr Prorated Billing Sites'!$A:$I,1,0) -> #N/A
A83: ="0"&TRIM(D83) -> 08300034 | B83: ALL AMERICAN FORD | C83: T-15482 | D83: 8300034 | E83: 6136 | F83: CDK Reseller - Base Fee | G83: 300 | H83: =VLOOKUP(A83,'SV Child INS Apr'!$A:$H,1,0) -> 08300034 | L83: =VLOOKUP(A83,'TV Apr Prorated Billing Sites'!$A:$I,1,0) -> #N/A
A84: ="0"&TRIM(D84) -> 08300046 | B84: TASCA FORD MAZDA | C84: T-4315 | D84: 8300046 | E84: 2501241 | F84: CDK Reseller - Base Fee | G84: 450 | H84: =VLOOKUP(A84,'SV Child INS Apr'!$A:$H,1,0) -> 08300046 | L84: =VLOOKUP(A84,'TV Apr Prorated Billing Sites'!$A:$I,1,0) -> #N/A
A85: ="0"&TRIM(D85) -> 08300105 | B85: Toyota World of Lakewood | C85: T-7989 | D85: 8300105 | E85: 2001705 | F85: CDK Reseller - Base Fee | G85: 400 | H85: =VLOOKUP(A85,'SV Child INS Apr'!$A:$H,1,0) -> 08300105 | L85: =VLOOKUP(A85,'TV Apr Prorated Billing Sites'!$A:$I,1,0) -> #N/A
A86: ="0"&TRIM(D86) -> 08300163 | B86: SPRINGFIELD BUICK GMC CADILLAC | C86: T-5647 | D86: 8300163 | E86: 2500596 | F86: CDK Reseller - Base Fee | G86: 400 | H86: =VLOOKUP(A86,'SV Child INS Apr'!$A:$H,1,0) -> 08300163 | L86: =VLOOKUP(A86,'TV Apr Prorated Billing Sites'!$A:$I,1,0) -> #N/A
A87: ="0"&TRIM(D87) -> 08300287 | B87: Freehold Dodge | C87: T-8005 | D87: 8300287 | E87: 2000180 | F87: CDK Reseller - Base Fee | G87: 300 | H87: =VLOOKUP(A87,'SV Child INS Apr'!$A:$H,1,0) -> 08300287 | L87: =VLOOKUP(A87,'TV Apr Prorated Billing Sites'!$A:$I,1,0) -> #N/A
A88: ="0"&TRIM(D88) -> 08300299 | B88: PRESTON CDJR TOYOTA | C88: T-4232 | D88: 8300299 | E88: 2502776 | F88: CDK Reseller - Base Fee | G88: 300 | H88: =VLOOKUP(A88,'SV Child INS Apr'!$A:$H,1,0) -> 08300299 | L88: =VLOOKUP(A88,'TV Apr Prorated Billing Sites'!$A:$I,1,0) -> #N/A
A89: ="0"&TRIM(D89) -> 08300299 | B89: PRESTON CHRYSLER DODGE JEEP RAM TOYOTA | C89: T-4234 | D89: 8300299 | E89: 2502776 | F89: CDK Reseller - Base Fee | G89: 300 | H89: =VLOOKUP(A89,'SV Child INS Apr'!$A:$H,1,0) -> 08300299 | L89: =VLOOKUP(A89,'TV Apr Prorated Billing Sites'!$A:$I,1,0) -> #N/A
A90: ="0"&TRIM(D90) -> 08310011 | B90: CHRYSLER JEEP DODGE OF PARAMUS | C90: T-14814 | D90: 8310011 | E90: 3001014 | F90: CDK Reseller - Base Fee | G90: 300 | H90: =VLOOKUP(A90,'SV Child INS Apr'!$A:$H,1,0) -> 08310011 | L90: =VLOOKUP(A90,'TV Apr Prorated Billing Sites'!$A:$I,1,0) -> #N/A
A91: ="0"&TRIM(D91) -> 08310108 | B91: Audi of Mendham | C91: T-7893 | D91: 8310108 | E91: 2001531 | F91: CDK Reseller - Base Fee | G91: 300 | H91: =VLOOKUP(A91,'SV Child INS Apr'!$A:$H,1,0) -> 08310108 | L91: =VLOOKUP(A91,'TV Apr Prorated Billing Sites'!$A:$I,1,0) -> #N/A
A92: ="0"&TRIM(D92) -> 08310123 | B92: Jaguar Land Rover Freeport | C92: T-15114 | D92: 8310123 | E92: 2500745 | F92: CDK Reseller - Base Fee | G92: 300 | H92: =VLOOKUP(A92,'SV Child INS Apr'!$A:$H,1,0) -> 08310123 | L92: =VLOOKUP(A92,'TV Apr Prorated Billing Sites'!$A:$I,1,0) -> #N/A
A93: ="0"&TRIM(D93) -> 08320047 | B93: CELLA FORD | C93: T-14508 | D93: 8320047 | E93: 3000907 | F93: CDK Reseller - Base Fee | G93: 300 | H93: =VLOOKUP(A93,'SV Child INS Apr'!$A:$H,1,0) -> 08320047 | L93: =VLOOKUP(A93,'TV Apr Prorated Billing Sites'!$A:$I,1,0) -> #N/A
A94: ="0"&TRIM(D94) -> 08320062 | B94: VAMPT MOTORS | C94: T-7908 | D94: 8320062 | E94: 2503320 | F94: CDK Reseller - Base Fee | G94: 300 | H94: =VLOOKUP(A94,'SV Child INS Apr'!$A:$H,1,0) -> 08320062 | L94: =VLOOKUP(A94,'TV Apr Prorated Billing Sites'!$A:$I,1,0) -> #N/A
A95: ="0"&TRIM(D95) -> 08320081 | B95: BAHAMAS BUS & TRUCK CO | C95: T-10870 | D95: 8320081 | E95: 2002071 | F95: CDK Reseller - Base Fee | G95: 300 | H95: =VLOOKUP(A95,'SV Child INS Apr'!$A:$H,1,0) -> #N/A | I95: =VLOOKUP(B95,'SV Child INS Apr'!$D:$F,1,0) -> #N/A | J95: =VLOOKUP(A95,'SV Child BLG Apr'!$A:$J,1,0) -> 08320081 | L95: =VLOOKUP(A95,'TV Apr Prorated Billing Sites'!$A:$I,1,0) -> #N/A | M95: =VLOOKUP(A95,'CDK asked to retain list'!$H$1:$J$24,1,0) -> #N/A
A96: ="0"&TRIM(D96) -> 08320151 | B96: LAND ROVER SOUTH DADE | C96: T-9458 | D96: 8320151 | E96: 2500259 | F96: CDK Reseller - Base Fee | G96: 300 | H96: =VLOOKUP(A96,'SV Child INS Apr'!$A:$H,1,0) -> 08320151 | L96: =VLOOKUP(A96,'TV Apr Prorated Billing Sites'!$A:$I,1,0) -> #N/A
A97: ="0"&TRIM(D97) -> 09014501 | B97: HICKMAN MOTORS LTD. | C97: T-14514 | D97: 9014501 | E97: 3000950 | F97: CDK Reseller - Base Fee | G97: 300 | H97: =VLOOKUP(A97,'SV Child INS Apr'!$A:$H,1,0) -> 09014501 | L97: =VLOOKUP(A97,'TV Apr Prorated Billing Sites'!$A:$I,1,0) -> #N/A
A98: ="0"&TRIM(D98) -> 09025902 | B98: BRANTFORD NISSAN | C98: T-16213 | D98: 9025902 | E98: 2002697 | F98: CDK Reseller - Base Fee | G98: 300 | H98: =VLOOKUP(A98,'SV Child INS Apr'!$A:$H,1,0) -> #N/A | I98: =VLOOKUP(B98,'SV Child INS Apr'!$D:$F,1,0) -> #N/A | J98: =VLOOKUP(A98,'SV Child BLG Apr'!$A:$J,1,0) -> 09025902 | L98: =VLOOKUP(A98,'TV Apr Prorated Billing Sites'!$A:$I,1,0) -> 09025902 | M98: =VLOOKUP(A98,'CDK asked to retain list'!$H$1:$J$24,1,0) -> #N/A
A99: ="0"&TRIM(D99) -> 09082601 | B99: MACDONALD BUICK GMC CADILLAC LTD | C99: T-14132 | D99: 9082601 | E99: 3000737 | F99: CDK Reseller - Base Fee | G99: 300 | H99: =VLOOKUP(A99,'SV Child INS Apr'!$A:$H,1,0) -> 09082601 | L99: =VLOOKUP(A99,'TV Apr Prorated Billing Sites'!$A:$I,1,0) -> #N/A
A100: ="0"&TRIM(D100) -> 09086501 | B100: DECARIE MOTORS INC. | C100: T-13382 | D100: 9086501 | E100: 143038 | F100: CDK Reseller - Base Fee | G100: 300 | H100: =VLOOKUP(A100,'SV Child INS Apr'!$A:$H,1,0) -> 09086501 | L100: =VLOOKUP(A100,'TV Apr Prorated Billing Sites'!$A:$I,1,0) -> #N/A
A101: ="0"&TRIM(D101) -> 09187704 | B101: OAKVILLE TOYOTA LTD | C101: T-8024 | D101: 9187704 | E101: 2502362 | F101: CDK Reseller - Base Fee | G101: 300 | H101: =VLOOKUP(A101,'SV Child INS Apr'!$A:$H,1,0) -> 09187704 | L101: =VLOOKUP(A101,'TV Apr Prorated Billing Sites'!$A:$I,1,0) -> #N/A
A102: ="0"&TRIM(D102) -> 09700114 | B102: COCONUT CREEK AUTOMALL | C102: T-9263 | D102: 9700114 | E102: 2000594 | F102: CDK Reseller - Base Fee | G102: 300 | H102: =VLOOKUP(A102,'SV Child INS Apr'!$A:$H,1,0) -> 09700114 | L102: =VLOOKUP(A102,'TV Apr Prorated Billing Sites'!$A:$I,1,0) -> #N/A
A103: ="0"&TRIM(D103) -> 09700250 | B103: Ganley Chevrolet | C103: T-10670 | D103: 9700250 | E103: 2503594 | F103: CDK Reseller - Base Fee | G103: 300 | H103: =VLOOKUP(A103,'SV Child INS Apr'!$A:$H,1,0) -> 09700250 | L103: =VLOOKUP(A103,'TV Apr Prorated Billing Sites'!$A:$I,1,0) -> #N/A
A104: ="0"&TRIM(D104) -> 09800181 | B104: RIHM KENWORTH DULUTH/SUPERIOR | C104: T-6030 | D104: 9800181 | E104: N/A | F104: CDK Reseller - Base Fee | G104: 600 | H104: =VLOOKUP(A104,'SV Child INS Apr'!$A:$H,1,0) -> 09800181 | L104: =VLOOKUP(A104,'TV Apr Prorated Billing Sites'!$A:$I,1,0) -> #N/A
A105: =TRIM(D105) -> 10027564 | B105: PARKS MOTOR SALES INC | C105: T-15492 | D105: 10027564 | E105: 3001858 | F105: CDK Reseller - Base Fee | G105: 300 | H105: =VLOOKUP(A105,'SV Child INS Apr'!$A:$H,1,0) -> 10027564 | L105: =VLOOKUP(A105,'TV Apr Prorated Billing Sites'!$A:$I,1,0) -> #N/A
A106: =TRIM(D106) -> 13059104 | B106: Valley Imports | C106: T-15076 | D106: 13059104 | E106: 12088 | F106: CDK Reseller - Base Fee | G106: 300 | H106: =VLOOKUP(A106,'SV Child INS Apr'!$A:$H,1,0) -> 13059104 | L106: =VLOOKUP(A106,'TV Apr Prorated Billing Sites'!$A:$I,1,0) -> #N/A
A107: =TRIM(D107) -> 13093301 | B107: MIKE FINNIN FORD | C107: T-10652 | D107: 13093301 | E107: 2503593 | F107: CDK Reseller - Base Fee | G107: 300 | H107: =VLOOKUP(A107,'SV Child INS Apr'!$A:$H,1,0) -> #N/A | I107: =VLOOKUP(B107,'SV Child INS Apr'!$D:$F,1,0) -> #N/A | J107: =VLOOKUP(A107,'SV Child BLG Apr'!$A:$J,1,0) -> #N/A | K107: =VLOOKUP(B107,'SV Child BLG Apr'!$D:$I,1,0) -> #N/A | L107: =VLOOKUP(A107,'TV Apr Prorated Billing Sites'!$A:$I,1,0) -> #N/A
A108: =TRIM(D108) -> 13104901 | B108: ALAN BROWNE CHEVROLET | C108: T-10863 | D108: 13104901 | E108: 1500085 | F108: CDK Reseller - Base Fee | G108: 300 | H108: =VLOOKUP(A108,'SV Child INS Apr'!$A:$H,1,0) -> 13104901 | L108: =VLOOKUP(A108,'TV Apr Prorated Billing Sites'!$A:$I,1,0) -> #N/A
A109: =TRIM(D109) -> 13115401 | B109: BILLION BUICK GMC, INC. | C109: T-10601 | D109: 13115401 | E109: 2500146 | F109: CDK Reseller - Base Fee | G109: 300 | H109: =VLOOKUP(A109,'SV Child INS Apr'!$A:$H,1,0) -> 13115401 | L109: =VLOOKUP(A109,'TV Apr Prorated Billing Sites'!$A:$I,1,0) -> #N/A
A110: =TRIM(D110) -> 13221101 | B110: MINNESOTA MOTOR CO | C110: T-15086 | D110: 13221101 | E110: 2500334 | F110: CDK Reseller - Base Fee | G110: 300 | H110: =VLOOKUP(A110,'SV Child INS Apr'!$A:$H,1,0) -> 13221101 | L110: =VLOOKUP(A110,'TV Apr Prorated Billing Sites'!$A:$I,1,0) -> #N/A
A111: =TRIM(D111) -> 13323802 | B111: CONTINENTAL TOYOTA | C111: T-4534 | D111: 13323802 | E111: 2500252 | F111: CDK Reseller - Base Fee | G111: 300 | H111: =VLOOKUP(A111,'SV Child INS Apr'!$A:$H,1,0) -> 13323802 | L111: =VLOOKUP(A111,'TV Apr Prorated Billing Sites'!$A:$I,1,0) -> #N/A
A112: =TRIM(D112) -> 13326501 | B112: JOHN AMATO HYUNDAI | C112: T-14139 | D112: 13326501 | E112: 2001367 | F112: CDK Reseller - Base Fee | G112: 300 | H112: =VLOOKUP(A112,'SV Child INS Apr'!$A:$H,1,0) -> 13326501 | L112: =VLOOKUP(A112,'TV Apr Prorated Billing Sites'!$A:$I,1,0) -> #N/A
...

Sheet TV Apr Prorated Billing Sites
A1: CMF | B1: Customer | C1: CMF Number | D1: CID Number | E1: Item | F1: Local Amount | G1: Found in CDK INS by CMF | H1: Found in CDK INS by Name | I1: Found in CDK BLG by CMF | J1: Found in CDK BLG by Name | K1: To Retain List
A2: =TRIM("0"&C2) -> 01012201 | B2: Lynn Layton Chevrolet | C2: 1012201 | D2: 3001502 | E2: CDK Reseller - Base Fee | F2: 40 | G2: =VLOOKUP(A2,'SV Child INS Apr'!$A:$J,1,0) -> #N/A | H2: =VLOOKUP(B2,'SV Child INS Apr'!$D:$J,1,0) -> #N/A | I2: =VLOOKUP(A2,'SV Child BLG Apr'!A:J,1,0) -> 01012201 | K2: =VLOOKUP(A2,'CDK asked to retain list'!H2:$K$25,1,0) -> #N/A
A3: =TRIM("0"&C3) -> 01012202 | B3: LYNN LAYTON CADILLAC NISSAN | C3: 1012202 | D3: 3001510 | E3: CDK Reseller - Base Fee | F3: 100 | G3: =VLOOKUP(A3,'SV Child INS Apr'!$A:$J,1,0) -> #N/A | H3: =VLOOKUP(B3,'SV Child INS Apr'!$D:$J,1,0) -> #N/A | I3: =VLOOKUP(A3,'SV Child BLG Apr'!A:J,1,0) -> 01012202 | K3: =VLOOKUP(A3,'CDK asked to retain list'!H3:$K$25,1,0) -> #N/A
A4: =TRIM("0"&C4) -> 01326145 | B4: Honda de San Juan | C4: 1326145 | D4: 2500576 | E4: CDK Reseller - Base Fee | F4: 290 | G4: =VLOOKUP(A4,'SV Child INS Apr'!$A:$J,1,0) -> #N/A | H4: =VLOOKUP(B4,'SV Child INS Apr'!$D:$J,1,0) -> #N/A | I4: =VLOOKUP(A4,'SV Child BLG Apr'!A:J,1,0) -> 01326145 | K4: =VLOOKUP(A4,'CDK asked to retain list'!H4:$K$25,1,0) -> #N/A
A5: =TRIM("0"&C5) -> 09025902 | B5: BRANTFORD NISSAN | C5: 9025902 | D5: 2002697 | E5: CDK Reseller - Base Fee | F5: 160 | G5: =VLOOKUP(A5,'SV Child INS Apr'!$A:$J,1,0) -> #N/A | H5: =VLOOKUP(B5,'SV Child INS Apr'!$D:$J,1,0) -> #N/A | I5: =VLOOKUP(A5,'SV Child BLG Apr'!A:J,1,0) -> 09025902 | K5: =VLOOKUP(A5,'CDK asked to retain list'!H5:$K$25,1,0) -> #N/A
A6: =TRIM(C6) -> 13498058 | B6: PAT MILLIKEN FORD | C6: 13498058 | D6: 3365 | E6: CDK Reseller - Base Fee | F6: 210 | G6: =VLOOKUP(A6,'SV Child INS Apr'!$A:$J,1,0) -> #N/A | H6: =VLOOKUP(B6,'SV Child INS Apr'!$D:$J,1,0) -> #N/A | I6: =VLOOKUP(A6,'SV Child BLG Apr'!A:J,1,0) -> 13498058 | K6: =VLOOKUP(A6,'CDK asked to retain list'!H6:$K$25,1,0) -> #N/A
A7: =TRIM(C7) -> 25212501 | B7: WAYNE FORD | C7: 25212501 | D7: 6024 | E7: CDK Reseller - Base Fee | F7: 170 | G7: =VLOOKUP(A7,'SV Child INS Apr'!$A:$J,1,0) -> #N/A | H7: =VLOOKUP(B7,'SV Child INS Apr'!$D:$J,1,0) -> #N/A | I7: =VLOOKUP(A7,'SV Child BLG Apr'!A:J,1,0) -> 25212501 | K7: =VLOOKUP(A7,'CDK asked to retain list'!H7:$K$25,1,0) -> #N/A
A8: =TRIM(C8) -> 25300610 | B8: SIMMONS ROCKWELL CHEVROLET GMC | C8: 25300610 | D8: 3002945 | E8: CDK Reseller - Base Fee | F8: 40 | G8: =VLOOKUP(A8,'SV Child INS Apr'!$A:$J,1,0) -> #N/A | H8: =VLOOKUP(B8,'SV Child INS Apr'!$D:$J,1,0) -> #N/A | I8: =VLOOKUP(A8,'SV Child BLG Apr'!A:J,1,0) -> 25300610 | K8: =VLOOKUP(A8,'CDK asked to retain list'!H8:$K$25,1,0) -> #N/A
A9: =TRIM(C9) -> 44780001 | B9: BEECHMONT FORD | C9: 44780001 | D9: 2502046 | E9: CDK Reseller - Base Fee | F9: 90 | G9: =VLOOKUP(A9,'SV Child INS Apr'!$A:$J,1,0) -> #N/A | H9: =VLOOKUP(B9,'SV Child INS Apr'!$D:$J,1,0) -> #N/A | I9: =VLOOKUP(A9,'SV Child BLG Apr'!A:J,1,0) -> 44780001 | K9: =VLOOKUP(A9,'CDK asked to retain list'!H9:$K$25,1,0) -> #N/A
A10: =TRIM(C10) -> 45602701 | B10: CMP CHEVY CADILLAC BUICK GMC | C10: 45602701 | D10: 2501852 | E10: CDK Reseller - Base Fee | F10: 30 | G10: =VLOOKUP(A10,'SV Child INS Apr'!$A:$J,1,0) -> #N/A | H10: =VLOOKUP(B10,'SV Child INS Apr'!$D:$J,1,0) -> #N/A | I10: =VLOOKUP(A10,'SV Child BLG Apr'!A:J,1,0) -> 45602701 | K10: =VLOOKUP(A10,'CDK asked to retain list'!H10:$K$25,1,0) -> #N/A
A11: =TRIM(C11) -> 71040312 | B11: MULLINAX FORD OF CENTRAL FLORIDA | C11: 71040312 | D11: 4150 | E11: CDK Reseller - Base Fee | F11: 180 | G11: =VLOOKUP(A11,'SV Child INS Apr'!$A:$J,1,0) -> 71040312 | K11: =VLOOKUP(A11,'CDK asked to retain list'!H11:$K$25,1,0) -> #N/A
A12: =TRIM(C12) -> 71048539 | B12: JAY WOLFE HONDA | C12: 71048539 | D12: 3001338 | E12: CDK Reseller - Base Fee | F12: 290 | G12: =VLOOKUP(A12,'SV Child INS Apr'!$A:$J,1,0) -> 71048539 | K12: =VLOOKUP(A12,'CDK asked to retain list'!H12:$K$25,1,0) -> #N/A
A13: =TRIM(C13) -> 71052266 | B13: JAY WOLFE TOYOTA SCION | C13: 71052266 | D13: 2503552 | E13: CDK Reseller - Base Fee | F13: 290 | G13: =VLOOKUP(A13,'SV Child INS Apr'!$A:$J,1,0) -> 71052266 | K13: =VLOOKUP(A13,'CDK asked to retain list'!H13:$K$25,1,0) -> #N/A
A14: =TRIM(C14) -> 71061453 | B14: BURLINGTON KIA | C14: 71061453 | D14: 3002947 | E14: CDK Reseller - Base Fee | F14: 110 | G14: =VLOOKUP(A14,'SV Child INS Apr'!$A:$J,1,0) -> #N/A | H14: =VLOOKUP(B14,'SV Child INS Apr'!$D:$J,1,0) -> #N/A | I14: =VLOOKUP(A14,'SV Child BLG Apr'!A:J,1,0) -> 71061453 | K14: =VLOOKUP(A14,'CDK asked to retain list'!H14:$K$25,1,0) -> #N/A
A15: =TRIM(C15) -> 76023577 | B15: PORSCHE OF COLORADO SPRINGS | C15: 76023577 | D15: 3001713 | E15: CDK Reseller - Base Fee | F15: 170 | G15: =VLOOKUP(A15,'SV Child INS Apr'!$A:$J,1,0) -> 76023577 | K15: =VLOOKUP(A15,'CDK asked to retain list'!H15:$K$25,1,0) -> #N/A
A16: =TRIM(C16) -> 76026176 | B16: ALL AMERICAN FORD OF PARAMUS | C16: 76026176 | D16: 10011 | E16: CDK Reseller - Base Fee | F16: 280 | G16: =VLOOKUP(A16,'SV Child INS Apr'!$A:$J,1,0) -> 76026176 | K16: =VLOOKUP(A16,'CDK asked to retain list'!H16:$K$25,1,0) -> #N/A
A17: =TRIM(C17) -> 76032748 | B17: KERRY MAZDA | C17: 76032748 | D17: 3002949 | E17: CDK Reseller - Base Fee | F17: 30 | G17: =VLOOKUP(A17,'SV Child INS Apr'!$A:$J,1,0) -> #N/A | H17: =VLOOKUP(B17,'SV Child INS Apr'!$D:$J,1,0) -> #N/A | I17: =VLOOKUP(A17,'SV Child BLG Apr'!A:J,1,0) -> 76032748 | K17: =VLOOKUP(A17,'CDK asked to retain list'!H17:$K$25,1,0) -> #N/A
A18: =TRIM(C18) -> 76034396 | B18: DALE EARNHARDT CHEVROLET | C18: 76034396 | D18: 2503573 | E18: CDK Reseller - Base Fee | F18: 100 | G18: =VLOOKUP(A18,'SV Child INS Apr'!$A:$J,1,0) -> 76034396 | K18: =VLOOKUP(A18,'CDK asked to retain list'!H18:$K$25,1,0) -> #N/A
A19: =TRIM(C19) -> 76036137 | B19: SHAW GMC CHEVROLET BUICK | C19: 76036137 | D19: 2501825 | E19: CDK Reseller - Base Fee | F19: 90 | G19: =VLOOKUP(A19,'SV Child INS Apr'!$A:$J,1,0) -> #N/A | H19: =VLOOKUP(B19,'SV Child INS Apr'!$D:$J,1,0) -> #N/A | I19: =VLOOKUP(A19,'SV Child BLG Apr'!A:J,1,0) -> 76036137 | K19: =VLOOKUP(A19,'CDK asked to retain list'!H19:$K$25,1,0) -> #N/A
A20: =TRIM(C20) -> 76036160 | B20: GREENWOOD CHEVY OF AUSTINTOWN | C20: 76036160 | D20: 9014 | E20: CDK Reseller - Base Fee | F20: 170 | G20: =VLOOKUP(A20,'SV Child INS Apr'!$A:$J,1,0) -> #N/A | H20: =VLOOKUP(B20,'SV Child INS Apr'!$D:$J,1,0) -> #N/A | I20: =VLOOKUP(A20,'SV Child BLG Apr'!A:J,1,0) -> 76036160 | K20: =VLOOKUP(A20,'CDK asked to retain list'!H20:$K$25,1,0) -> #N/A
A21: =TRIM(C21) -> 76037591 | B21: LB SMITH FORD LINCOLN | C21: 76037591 | D21: 6091 | E21: CDK Reseller - Base Fee | F21: 160 | G21: =VLOOKUP(A21,'SV Child INS Apr'!$A:$J,1,0) -> #N/A | H21: =VLOOKUP(B21,'SV Child INS Apr'!$D:$J,1,0) -> #N/A | I21: =VLOOKUP(A21,'SV Child BLG Apr'!A:J,1,0) -> 76037591 | K21: =VLOOKUP(A21,'CDK asked to retain list'!H21:$K$25,1,0) -> #N/A
A22: =TRIM(C22) -> 76038422 | B22: ROUTE 60 HYUNDAI | C22: 76038422 | D22: 2500295 | E22: CDK Reseller - Base Fee | F22: 300 | G22: =VLOOKUP(A22,'SV Child INS Apr'!$A:$J,1,0) -> #N/A | H22: =VLOOKUP(B22,'SV Child INS Apr'!$D:$J,1,0) -> #N/A | I22: =VLOOKUP(A22,'SV Child BLG Apr'!A:J,1,0) -> 76038422 | K22: =VLOOKUP(A22,'CDK asked to retain list'!H22:$K$25,1,0) -> #N/A
A23: =TRIM(C23) -> 76043468 | B23: MIKE TOLER CHRYSLER DODGE JEEP | C23: 76043468 | D23: 2001550 | E23: CDK Reseller - Base Fee | F23: 280 | G23: =VLOOKUP(A23,'SV Child INS Apr'!$A:$J,1,0) -> #N/A | H23: =VLOOKUP(B23,'SV Child INS Apr'!$D:$J,1,0) -> #N/A | I23: =VLOOKUP(A23,'SV Child BLG Apr'!A:J,1,0) -> 76043468 | K23: =VLOOKUP(A23,'CDK asked to retain list'!H23:$K$25,1,0) -> #N/A
A24: =TRIM(C24) -> 76055894 | B24: WHITE'S QUEEN CITY MOTORS | C24: 76055894 | D24: 2502435 | E24: CDK Reseller - Base Fee | F24: 210 | G24: =VLOOKUP(A24,'SV Child INS Apr'!$A:$J,1,0) -> 76055894 | K24: =VLOOKUP(A24,'CDK asked to retain list'!H24:$K$25,1,0) -> #N/A
A25: =TRIM(C25) -> 76061499 | B25: Landers Mclarty Chevrolet | C25: 76061499 | D25: 12028 | E25: CDK Reseller - Base Fee | F25: 300 | G25: =VLOOKUP(A25,'SV Child INS Apr'!$A:$J,1,0) -> 76061499 | K25: =VLOOKUP(A25,'CDK asked to retain list'!H25:$K$25,1,0) -> #N/A
A26: =TRIM(C26) -> 76063135 | B26: GERMAIN FORD | C26: 76063135 | D26: 2001667 | E26: CDK Reseller - Base Fee | F26: 300 | G26: =VLOOKUP(A26,'SV Child INS Apr'!$A:$J,1,0) -> 76063135 | K26: =VLOOKUP(A26,'CDK asked to retain list'!H$25:$K26,1,0) -> #N/A
A27: =TRIM(C27) -> 76066680 | B27: SPEEDWAY CHEVROLET LLC | C27: 76066680 | D27: 2503609 | E27: CDK Reseller - Base Fee | F27: 230 | G27: =VLOOKUP(A27,'SV Child INS Apr'!$A:$J,1,0) -> 76066680 | K27: =VLOOKUP(A27,'CDK asked to retain list'!H$25:$K27,1,0) -> #N/A
A28: =TRIM(C28) -> 76072064 | B28: BMW OF SOUTHAMPTON | C28: 76072064 | D28: 2503103 | E28: CDK Reseller - Base Fee | F28: 110 | G28: =VLOOKUP(A28,'SV Child INS Apr'!$A:$J,1,0) -> #N/A | H28: =VLOOKUP(B28,'SV Child INS Apr'!$D:$J,1,0) -> #N/A | I28: =VLOOKUP(A28,'SV Child BLG Apr'!A:J,1,0) -> 76072064 | K28: =VLOOKUP(A28,'CDK asked to retain list'!H$25:$K28,1,0) -> #N/A
A29: =TRIM(C29) -> 76072230 | B29: TRANSWEST GMC TRUCK | C29: 76072230 | D29: 2000509 | E29: CDK Reseller - Base Fee | F29: 210 | G29: =VLOOKUP(A29,'SV Child INS Apr'!$A:$J,1,0) -> 76072230 | K29: =VLOOKUP(A29,'CDK asked to retain list'!H$25:$K29,1,0) -> #N/A
A30: =TRIM(C30) -> 76073131 | B30: SIMMONS ROCKWELL FORD - NY | C30: 76073131 | D30: 143062 | E30: CDK Reseller - Base Fee | F30: 160 | G30: =VLOOKUP(A30,'SV Child INS Apr'!$A:$J,1,0) -> #N/A | H30: =VLOOKUP(B30,'SV Child INS Apr'!$D:$J,1,0) -> #N/A | I30: =VLOOKUP(A30,'SV Child BLG Apr'!A:J,1,0) -> 76073131 | K30: =VLOOKUP(A30,'CDK asked to retain list'!H$25:$K30,1,0) -> #N/A
A31: =TRIM(C31) -> 76074791 | B31: ACADEMY FORD SALES | C31: 76074791 | D31: 3002489 | E31: CDK Reseller - Base Fee | F31: 300 | G31: =VLOOKUP(A31,'SV Child INS Apr'!$A:$J,1,0) -> #N/A | H31: =VLOOKUP(B31,'SV Child INS Apr'!$D:$J,1,0) -> #N/A | I31: =VLOOKUP(A31,'SV Child BLG Apr'!A:J,1,0) -> 76074791 | K31: =VLOOKUP(A31,'CDK asked to retain list'!H$25:$K31,1,0) -> #N/A
A32: =TRIM(C32) -> 76075567 | B32: FIRST CHOICE FORD | C32: 76075567 | D32: 3131 | E32: CDK Reseller - Base Fee | F32: 300 | G32: =VLOOKUP(A32,'SV Child INS Apr'!$A:$J,1,0) -> 76075567 | K32: =VLOOKUP(A32,'CDK asked to retain list'!H$25:$K32,1,0) -> #N/A
A33: =TRIM(C33) -> 76076543 | B33: TOYOTA OF BERKELEY ALBANY SERVICE CENTER & USED CARS | C33: 76076543 | D33: 1500222 | E33: CDK Reseller - Base Fee | F33: 30 | G33: =VLOOKUP(A33,'SV Child INS Apr'!$A:$J,1,0) -> 76076543 | K33: =VLOOKUP(A33,'CDK asked to retain list'!H$25:$K33,1,0) -> #N/A
A34: =TRIM(C34) -> 76078918 | B34: COURTESY FORD BREAUX BRIDGE | C34: 76078918 | D34: 2500456 | E34: CDK Reseller - Base Fee | F34: 300 | G34: =VLOOKUP(A34,'SV Child INS Apr'!$A:$J,1,0) -> 76078918 | K34: =VLOOKUP(A34,'CDK asked to retain list'!H$25:$K34,1,0) -> #N/A
A35: =TRIM(C35) -> 76135790 | B35: GENE LANGLEY FORD | C35: 76135790 | D35: 2503496 | E35: CDK Reseller - Base Fee | F35: 100 | G35: =VLOOKUP(A35,'SV Child INS Apr'!$A:$J,1,0) -> #N/A | H35: =VLOOKUP(B35,'SV Child INS Apr'!$D:$J,1,0) -> #N/A | I35: =VLOOKUP(A35,'SV Child BLG Apr'!A:J,1,0) -> 76135790 | K35: =VLOOKUP(A35,'CDK asked to retain list'!H$25:$K35,1,0) -> #N/A
A36: =TRIM(C36) -> 76143376 | B36: MILNES CHEVROLET | C36: 76143376 | D36: 3001863 | E36: CDK Reseller - Base Fee | F36: 280 | G36: =VLOOKUP(A36,'SV Child INS Apr'!$A:$J,1,0) -> #N/A | H36: =VLOOKUP(B36,'SV Child INS Apr'!$D:$J,1,0) -> #N/A | I36: =VLOOKUP(A36,'SV Child BLG Apr'!A:J,1,0) -> 76143376 | K36: =VLOOKUP(A36,'CDK asked to retain list'!H$25:$K36,1,0) -> #N/A
A37: =TRIM(C37) -> 76144136 | B37: GENE LATTA FORD | C37: 76144136 | D37: 3002895 | E37: CDK Reseller - Base Fee | F37: 150 | G37: =VLOOKUP(A37,'SV Child INS Apr'!$A:$J,1,0) -> #N/A | H37: =VLOOKUP(B37,'SV Child INS Apr'!$D:$J,1,0) -> #N/A | I37: =VLOOKUP(A37,'SV Child BLG Apr'!A:J,1,0) -> 76144136 | K37: =VLOOKUP(A37,'CDK asked to retain list'!H$25:$K37,1,0) -> #N/A
A38: =TRIM(C38) -> 76159225 | B38: TREND MOTORS VOLKSWAGEN | C38: 76159225 | D38: 2502115 | E38: CDK Reseller - Base Fee | F38: 90 | G38: =VLOOKUP(A38,'SV Child INS Apr'!$A:$J,1,0) -> #N/A | H38: =VLOOKUP(B38,'SV Child INS Apr'!$D:$J,1,0) -> #N/A | I38: =VLOOKUP(A38,'SV Child BLG Apr'!A:J,1,0) -> 76159225 | K38: =VLOOKUP(A38,'CDK asked to retain list'!H$25:$K38,1,0) -> #N/A
A39: =TRIM(C39) -> 76159913 | B39: Honda de Caguas | C39: 76159913 | D39: 2500592 | E39: CDK Reseller - Base Fee | F39: 100 | G39: =VLOOKUP(A39,'SV Child INS Apr'!$A:$J,1,0) -> #N/A | H39: =VLOOKUP(B39,'SV Child INS Apr'!$D:$J,1,0) -> #N/A | I39: =VLOOKUP(A39,'SV Child BLG Apr'!A:J,1,0) -> 76159913 | K39: =VLOOKUP(A39,'CDK asked to retain list'!H$25:$K39,1,0) -> #N/A
A40: =TRIM(C40) -> 76162825 | B40: JOHNSON CITY FORD | C40: 76162825 | D40: 2002165 | E40: CDK Reseller - Base Fee | F40: 150 | G40: =VLOOKUP(A40,'SV Child INS Apr'!$A:$J,1,0) -> 76162825 | K40: =VLOOKUP(A40,'CDK asked to retain list'!H$25:$K40,1,0) -> #N/A
A41: =TRIM(C41) -> 76164480 | B41: THOROUGHBRED FORD OF PLATTE CITY | C41: 76164480 | D41: 2000978 | E41: CDK Reseller - Base Fee | F41: 210 | G41: =VLOOKUP(A41,'SV Child INS Apr'!$A:$J,1,0) -> #N/A | H41: =VLOOKUP(B41,'SV Child INS Apr'!$D:$J,1,0) -> #N/A | I41: =VLOOKUP(A41,'SV Child BLG Apr'!A:J,1,0) -> 76164480 | K41: =VLOOKUP(A41,'CDK asked to retain list'!H$25:$K41,1,0) -> #N/A
A42: =TRIM(C42) -> 76171174 | B42: Sam Pack's Five Star Chevrolet | C42: 76171174 | D42: 2000092 | E42: CDK Reseller - Base Fee | F42: 160 | G42: =VLOOKUP(A42,'SV Child INS Apr'!$A:$J,1,0) -> 76171174 | K42: =VLOOKUP(A42,'CDK asked to retain list'!H$25:$K42,1,0) -> #N/A
A43: =TRIM(C43) -> 76172751 | B43: WALSH HONDA | C43: 76172751 | D43: 3000979 | E43: CDK Reseller - Base Fee | F43: 280 | G43: =VLOOKUP(A43,'SV Child INS Apr'!$A:$J,1,0) -> 76172751 | K43: =VLOOKUP(A43,'CDK asked to retain list'!H$25:$K43,1,0) -> #N/A
A44: =TRIM(C44) -> 76180102 | B44: HONDA OF PRINCETON | C44: 76180102 | D44: 2502528 | E44: CDK Reseller - Base Fee | F44: 110 | G44: =VLOOKUP(A44,'SV Child INS Apr'!$A:$J,1,0) -> #N/A | H44: =VLOOKUP(B44,'SV Child INS Apr'!$D:$J,1,0) -> #N/A | I44: =VLOOKUP(A44,'SV Child BLG Apr'!A:J,1,0) -> 76180102 | K44: =VLOOKUP(A44,'CDK asked to retain list'!H$25:$K44,1,0) -> #N/A
A45: =TRIM(C45) -> 76181513 | B45: TRANSWEST CHRYSLER DODGE JEEP RAM | C45: 76181513 | D45: 3001083 | E45: CDK Reseller - Base Fee | F45: 40 | G45: =VLOOKUP(A45,'SV Child INS Apr'!$A:$J,1,0) -> #N/A | H45: =VLOOKUP(B45,'SV Child INS Apr'!$D:$J,1,0) -> #N/A | I45: =VLOOKUP(A45,'SV Child BLG Apr'!A:J,1,0) -> 76181513 | K45: =VLOOKUP(A45,'CDK asked to retain list'!H$25:$K45,1,0) -> #N/A
A46: =TRIM(C46) -> 76187537 | B46: MT. ORAB FORD | C46: 76187537 | D46: 10143 | E46: CDK Reseller - Base Fee | F46: 280 | G46: =VLOOKUP(A46,'SV Child INS Apr'!$A:$J,1,0) -> #N/A | H46: =VLOOKUP(B46,'SV Child INS Apr'!$D:$J,1,0) -> #N/A | I46: =VLOOKUP(A46,'SV Child BLG Apr'!A:J,1,0) -> 76187537 | K46: =VLOOKUP(A46,'CDK asked to retain list'!H$25:$K46,1,0) -> #N/A
A47: =TRIM(C47) -> 76188296 | B47: TRANSWEST CHEVROLET BUICK -STERLING | C47: 76188296 | D47: 3001076 | E47: CDK Reseller - Base Fee | F47: 170 | G47: =VLOOKUP(A47,'SV Child INS Apr'!$A:$J,1,0) -> #N/A | H47: =VLOOKUP(B47,'SV Child INS Apr'!$D:$J,1,0) -> #N/A | I47: =VLOOKUP(A47,'SV Child BLG Apr'!A:J,1,0) -> 76188296 | K47: =VLOOKUP(A47,'CDK asked to retain list'!H$25:$K47,1,0) -> #N/A
A48: =TRIM(C48) -> 76204394 | B48: SIMMONS ROCKWELL NISSAN OF HORNELL | C48: 76204394 | D48: 2503164 | E48: CDK Reseller - Base Fee | F48: 160 | G48: =VLOOKUP(A48,'SV Child INS Apr'!$A:$J,1,0) -> #N/A | H48: =VLOOKUP(B48,'SV Child INS Apr'!$D:$J,1,0) -> #N/A | I48: =VLOOKUP(A48,'SV Child BLG Apr'!A:J,1,0) -> 76204394 | K48: =VLOOKUP(A48,'CDK asked to retain list'!H$25:$K48,1,0) -> #N/A
A49: =TRIM(C49) -> 76206439 | B49: ANCIRA VOLKSWAGEN | C49: 76206439 | D49: 2000748 | E49: CDK Reseller - Base Fee | F49: 160 | G49: =VLOOKUP(A49,'SV Child INS Apr'!$A:$J,1,0) -> 76206439 | K49: =VLOOKUP(A49,'CDK asked to retain list'!H$25:$K49,1,0) -> #N/A
A50: =TRIM(C50) -> 76206447 | B50: ANCIRA VW OF LERADO | C50: 76206447 | D50: 2000755 | E50: CDK Reseller - Base Fee | F50: 160 | G50: =VLOOKUP(A50,'SV Child INS Apr'!$A:$J,1,0) -> 76206447 | K50: =VLOOKUP(A50,'CDK asked to retain list'!H$25:$K50,1,0) -> #N/A
A51: =TRIM(C51) -> 76209808 | B51: COFFMAN GMC - AURORA | C51: 76209808 | D51: 2503569 | E51: CDK Reseller - Base Fee | F51: 240 | G51: =VLOOKUP(A51,'SV Child INS Apr'!$A:$J,1,0) -> 76209808 | K51: =VLOOKUP(A51,'CDK asked to retain list'!H$25:$K51,1,0) -> #N/A
A52: =TRIM(C52) -> 76210834 | B52: JAY WOLFE ACURA OF OVERLAND PARK | C52: 76210834 | D52: 3002830 | E52: CDK Reseller - Base Fee | F52: 240 | G52: =VLOOKUP(A52,'SV Child INS Apr'!$A:$J,1,0) -> #N/A | H52: =VLOOKUP(B52,'SV Child INS Apr'!$D:$J,1,0) -> #N/A | I52: =VLOOKUP(A52,'SV Child BLG Apr'!A:J,1,0) -> 76210834 | K52: =VLOOKUP(A52,'CDK asked to retain list'!H$25:$K52,1,0) -> #N/A
A53: =TRIM(C53) -> 76211772 | B53: RED RIVER FORD | C53: 76211772 | D53: 3002899 | E53: CDK Reseller - Base Fee | F53: 30 | G53: =VLOOKUP(A53,'SV Child INS Apr'!$A:$J,1,0) -> #N/A | H53: =VLOOKUP(B53,'SV Child INS Apr'!$D:$J,1,0) -> #N/A | I53: =VLOOKUP(A53,'SV Child BLG Apr'!A:J,1,0) -> 76211772 | K53: =VLOOKUP(A53,'CDK asked to retain list'!H$25:$K53,1,0) -> #N/A
A54: =TRIM(C54) -> 76216633 | B54: CHRYSLER DODGE JEEP RAM OF SOUTHAMPTON | C54: 76216633 | D54: 2503124 | E54: CDK Reseller - Base Fee | F54: 90 | G54: =VLOOKUP(A54,'SV Child INS Apr'!$A:$J,1,0) -> #N/A | H54: =VLOOKUP(B54,'SV Child INS Apr'!$D:$J,1,0) -> #N/A | I54: =VLOOKUP(A54,'SV Child BLG Apr'!A:J,1,0) -> 76216633 | K54: =VLOOKUP(A54,'CDK asked to retain list'!H$25:$K54,1,0) -> #N/A
A55: =TRIM(C55) -> 76217262 | B55: Flagship Mazda De Ponce | C55: 76217262 | D55: 2501434 | E55: CDK Reseller - Base Fee | F55: 100 | G55: =VLOOKUP(A55,'SV Child INS Apr'!$A:$J,1,0) -> #N/A | H55: =VLOOKUP(B55,'SV Child INS Apr'!$D:$J,1,0) -> #N/A | I55: =VLOOKUP(A55,'SV Child BLG Apr'!A:J,1,0) -> 76217262 | K55: =VLOOKUP(A55,'CDK asked to retain list'!H$25:$K55,1,0) -> #N/A
A56: =TRIM(C56) -> 76221166 | B56: LEXUS OF GREENVILLE | C56: 76221166 | D56: 2002176 | E56: CDK Reseller - Base Fee | F56: 150 | G56: =VLOOKUP(A56,'SV Child INS Apr'!$A:$J,1,0) -> 76221166 | K56: =VLOOKUP(A56,'CDK asked to retain list'!H$25:$K56,1,0) -> #N/A
A57: =TRIM(C57) -> 76226228 | B57: JENKINS FORD LINCOLN OF CRYSTAL RIVER | C57: 76226228 | D57: 2001934 | E57: CDK Reseller - Base Fee | F57: 220 | G57: =VLOOKUP(A57,'SV Child INS Apr'!$A:$J,1,0) -> 76226228 | K57: =VLOOKUP(A57,'CDK asked to retain list'!H$25:$K57,1,0) -> #N/A
A58: =TRIM(C58) -> 76232056 | B58: Forest Lake Chevrolet | C58: 76232056 | D58: 2502589 | E58: CDK Reseller - Base Fee | F58: 180 | G58: =VLOOKUP(A58,'SV Child INS Apr'!$A:$J,1,0) -> 76232056 | K58: =VLOOKUP(A58,'CDK asked to retain list'!H$25:$K58,1,0) -> #N/A
A59: =TRIM(C59) -> 76233198 | B59: BURLINGTON HYUNDAI - NJ | C59: 76233198 | D59: 3002958 | E59: CDK Reseller - Base Fee | F59: 40 | G59: =VLOOKUP(A59,'SV Child INS Apr'!$A:$J,1,0) -> #N/A | H59: =VLOOKUP(B59,'SV Child INS Apr'!$D:$J,1,0) -> #N/A | I59: =VLOOKUP(A59,'SV Child BLG Apr'!A:J,1,0) -> 76233198 | K59: =VLOOKUP(A59,'CDK asked to retain list'!H$25:$K59,1,0) -> #N/A
A60: =TRIM(C60) -> 76233199 | B60: BURLINGTON CHRYSLER DODGE JEEP RAM - NJ | C60: 76233199 | D60: 3002934 | E60: CDK Reseller - Base Fee | F60: 100 | G60: =VLOOKUP(A60,'SV Child INS Apr'!$A:$J,1,0) -> 76233199 | K60: =VLOOKUP(A60,'CDK asked to retain list'!H$25:$K60,1,0) -> #N/A
A61: =TRIM(C61) -> 76235265 | B61: HUNTER FORD | C61: 76235265 | D61: 2002561 | E61: CDK Reseller - Base Fee | F61: 230 | G61: =VLOOKUP(A61,'SV Child INS Apr'!$A:$J,1,0) -> 76235265 | K61: =VLOOKUP(A61,'CDK asked to retain list'!H$25:$K61,1,0) -> #N/A
A62: =TRIM(C62) -> 76236503 | B62: WINSLOW FORD | C62: 76236503 | D62: 3002961 | E62: CDK Reseller - Base Fee | F62: 30 | G62: =VLOOKUP(A62,'SV Child INS Apr'!$A:$J,1,0) -> #N/A | H62: =VLOOKUP(B62,'SV Child INS Apr'!$D:$J,1,0) -> #N/A | I62: =VLOOKUP(A62,'SV Child BLG Apr'!A:J,1,0) -> 76236503 | K62: =VLOOKUP(A62,'CDK asked to retain list'!H$25:$K62,1,0) -> #N/A
A63: =TRIM(C63) -> 76241159 | B63: LEGENDARY FORD | C63: 76241159 | D63: 3001147 | E63: CDK Reseller - Base Fee | F63: 100 | G63: =VLOOKUP(A63,'SV Child INS Apr'!$A:$J,1,0) -> #N/A | H63: =VLOOKUP(B63,'SV Child INS Apr'!$D:$J,1,0) -> #N/A | I63: =VLOOKUP(A63,'SV Child BLG Apr'!A:J,1,0) -> 76241159 | K63: =VLOOKUP(A63,'CDK asked to retain list'!H$25:$K63,1,0) -> #N/A
A64: =TRIM(C64) -> 76241605 | B64: QUEEN CITY FORD | C64: 76241605 | D64: 2001100 | E64: CDK Reseller - Base Fee | F64: 90 | G64: =VLOOKUP(A64,'SV Child INS Apr'!$A:$J,1,0) -> #N/A | H64: =VLOOKUP(B64,'SV Child INS Apr'!$D:$J,1,0) -> #N/A | I64: =VLOOKUP(A64,'SV Child BLG Apr'!A:J,1,0) -> 76241605 | K64: =VLOOKUP(A64,'CDK asked to retain list'!H$25:$K64,1,0) -> #N/A
A65: =TRIM(C65) -> 76251423 | B65: Norm Reeves Dallas Toyota | C65: 76251423 | D65: 3002946 | E65: CDK Reseller - Base Fee | F65: 30 | G65: =VLOOKUP(A65,'SV Child INS Apr'!$A:$J,1,0) -> #N/A | H65: =VLOOKUP(B65,'SV Child INS Apr'!$D:$J,1,0) -> #N/A | I65: =VLOOKUP(A65,'SV Child BLG Apr'!A:J,1,0) -> 76251423 | K65: =VLOOKUP(A65,'CDK asked to retain list'!H$25:$K65,1,0) -> #N/A
A66: =TRIM(C66) -> 76252738 | B66: NORM REEVES HONDA SUPERSTORE NORTH RICHLAND HILLS | C66: 76252738 | D66: 3002944 | E66: CDK Reseller - Base Fee | F66: 90 | G66: =VLOOKUP(A66,'SV Child INS Apr'!$A:$J,1,0) -> #N/A | H66: =VLOOKUP(B66,'SV Child INS Apr'!$D:$J,1,0) -> #N/A | I66: =VLOOKUP(A66,'SV Child BLG Apr'!A:J,1,0) -> 76252738 | K66: =VLOOKUP(A66,'CDK asked to retain list'!H$25:$K66,1,0) -> #N/A
A67: =TRIM(C67) -> 76252740 | B67: NORM REEVES SUBARU ROCKWALL | C67: 76252740 | D67: 3002948 | E67: CDK Reseller - Base Fee | F67: 30 | G67: =VLOOKUP(A67,'SV Child INS Apr'!$A:$J,1,0) -> #N/A | H67: =VLOOKUP(B67,'SV Child INS Apr'!$D:$J,1,0) -> #N/A | I67: =VLOOKUP(A67,'SV Child BLG Apr'!A:J,1,0) -> 76252740 | K67: =VLOOKUP(A67,'CDK asked to retain list'!H$25:$K67,1,0) -> #N/A
A68: =TRIM(C68) -> 76257049 | B68: Acura of Fremont | C68: 76257049 | D68: 2002855 | E68: CDK Reseller - Base Fee | F68: 150 | G68: =VLOOKUP(A68,'SV Child INS Apr'!$A:$J,1,0) -> 76257049 | K68: =VLOOKUP(A68,'CDK asked to retain list'!H$25:$K68,1,0) -> #N/A
A69: =TRIM(C69) -> 76257108 | B69: KERRY INFINITI N. KENTUCKY - KERRY NISSAN | C69: 76257108 | D69: 3000642 | E69: CDK Reseller - Base Fee | F69: 30 | G69: =VLOOKUP(A69,'SV Child INS Apr'!$A:$J,1,0) -> #N/A | H69: =VLOOKUP(B69,'SV Child INS Apr'!$D:$J,1,0) -> #N/A | I69: =VLOOKUP(A69,'SV Child BLG Apr'!A:J,1,0) -> 76257108 | K69: =VLOOKUP(A69,'CDK asked to retain list'!H$25:$K69,1,0) -> #N/A
A70: =TRIM(C70) -> 97000001 | B70: KERRY INFINITI OF NORTHERN KENTUCKY - KERRY NISSAN | C70: 97000001 | D70: 2500664 | E70: CDK Reseller - Base Fee | F70: 30 | G70: =VLOOKUP(A70,'SV Child INS Apr'!$A:$J,1,0) -> #N/A | H70: =VLOOKUP(B70,'SV Child INS Apr'!$D:$J,1,0) -> #N/A | I70: =VLOOKUP(A70,'SV Child BLG Apr'!A:J,1,0) -> 97000001 | K70: =VLOOKUP(A70,'CDK asked to retain list'!H$25:$K70,1,0) -> #N/A

Sheet TV Apr Prorated Invoice
A1: Customer | B1: CMF Number | C1: CID Number | D1: Item | E1: Local Amount | F1: Notes | G1: BLG
A2: ACADEMY FORD SALES | B2: 76074791 | C2: 3002489 | D2: CDK Reseller - Set Up Fee | E2: 499
A3: Acura of Fremont | B3: 76257049 | C3: 2002855 | D3: CDK Reseller - Set Up Fee | E3: 499
A4: ALL AMERICAN FORD OF PARAMUS | B4: 76026176 | C4: 10011 | D4: CDK Reseller - Set Up Fee | E4: 499
A5: ANCIRA VOLKSWAGEN | B5: 76206439 | C5: 2000748 | D5: CDK Reseller - Set Up Fee | E5: 499
A6: ANCIRA VW OF LERADO | B6: 76206447 | C6: 2000755 | D6: CDK Reseller - Set Up Fee | E6: 499
A7: BEECHMONT FORD | B7: 44780001 | C7: 2502046 | D7: CDK Reseller - Set Up Fee | E7: 499
A8: BMW OF SOUTHAMPTON | B8: 76072064 | C8: 2503103 | D8: CDK Reseller - Set Up Fee | E8: 499
A9: BRANTFORD NISSAN | B9: 9025902 | C9: 2002697 | D9: CDK Reseller - Set Up Fee | E9: 499
A10: BURLINGTON CHRYSLER DODGE JEEP RAM - NJ | B10: 76233199 | C10: 3002934 | D10: CDK Reseller - Set Up Fee | E10: 499
A11: BURLINGTON HYUNDAI - NJ | B11: 76233198 | C11: 3002958 | D11: CDK Reseller - Set Up Fee | E11: 499
A12: BURLINGTON KIA | B12: 71061453 | C12: 3002947 | D12: CDK Reseller - Set Up Fee | E12: 499
A13: CHRYSLER DODGE JEEP RAM OF SOUTHAMPTON | B13: 76216633 | C13: 2503124 | D13: CDK Reseller - Set Up Fee | E13: 499
... A70: WINSLOW FORD | B70: 76236503 | C70: 3002961 | D70: CDK Reseller - Set Up Fee | E70: 499
E71: =SUM(E2:E70) -> 34431
A73: ACADEMY FORD SALES | B73: 76074791 | C73: 3002489 | D73: CDK Reseller - Base Fee | E73: 300
A74: Acura of Fremont | B74: 76257049 | C74: 2002855 | D74: CDK Reseller - Base Fee | E74: 150
A75: ALL AMERICAN FORD OF PARAMUS | B75: 76026176 | C75: 10011 | D75: CDK Reseller - Base Fee | E75: 280
A76: ANCIRA VOLKSWAGEN | B76: 76206439 | C76: 2000748 | D76: CDK Reseller - Base Fee | E76: 160
A77: ANCIRA VW OF LERADO | B77: 76206447 | C77: 2000755 | D77: CDK Reseller - Base Fee | E77: 160
A78: BEECHMONT FORD | B78: 44780001 | C78: 2502046 | D78: CDK Reseller - Base Fee | E78: 90
A79: BMW OF SOUTHAMPTON | B79: 76072064 | C79: 2503103 | D79: CDK Reseller - Base Fee | E79: 110
A80: BRANTFORD NISSAN | B80: 9025902 | C80: 2002697 | D80: CDK Reseller - Base Fee | E80: 160
A81: BURLINGTON CHRYSLER DODGE JEEP RAM - NJ | B81: 76233199 | C81: 3002934 | D81: CDK Reseller - Base Fee | E81: 100
A82: BURLINGTON HYUNDAI - NJ | B82: 76233198 | C82: 3002958 | D82: CDK Reseller - Base Fee | E82: 40
A83: BURLINGTON KIA | B83: 71061453 | C83: 3002947 | D83: CDK Reseller - Base Fee | E83: 110
A84: CHRYSLER DODGE JEEP RAM OF SOUTHAMPTON | B84: 76216633 | C84: 2503124 | D84: CDK Reseller - Base Fee | E84: 90
... A141: WINSLOW FORD | B141: 76236503 | C141: 3002961 | D141: CDK Reseller - Base Fee | E141: 30
E142: =SUM(E73:E141) -> 10830
A144: ACADEMY FORD SALES | B144: 76074791 | C144: 3002489 | D144: TruVideo AI Suite | E144: 200 | G144: =VLOOKUP(B144,'April Prorated Invoice-BLG Site'!$C:$F,1,0) -> 76074791
A145: Acura of Fremont | B145: 76257049 | C145: 2002855 | D145: TruVideo AI Suite | E145: 100 | G145: =VLOOKUP(B145,'April Prorated Invoice-BLG Site'!$C:$F,1,0) -> #N/A
A146: ALL AMERICAN FORD OF PARAMUS | B146: 76026176 | C146: 10011 | D146: TruVideo AI Suite | E146: 186.67 | G146: =VLOOKUP(B146,'April Prorated Invoice-BLG Site'!$C:$F,1,0) -> #N/A
A147: ANCIRA VOLKSWAGEN | B147: 76206439 | C147: 2000748 | D147: TruVideo AI Suite | E147: 106.67 | G147: =VLOOKUP(B147,'April Prorated Invoice-BLG Site'!$C:$F,1,0) -> #N/A
A148: ANCIRA VW OF LERADO | B148: 76206447 | C148: 2000755 | D148: TruVideo AI Suite | E148: 106.67 | G148: =VLOOKUP(B148,'April Prorated Invoice-BLG Site'!$C:$F,1,0) -> #N/A
A149: BEECHMONT FORD | B149: 44780001 | C149: 2502046 | D149: TruVideo AI Suite | E149: 60 | G149: =VLOOKUP(B149,'April Prorated Invoice-BLG Site'!$C:$F,1,0) -> 44780001
A150: BMW OF SOUTHAMPTON | B150: 76072064 | C150: 2503103 | D150: TruVideo AI Suite | E150: 73.33 | G150: =VLOOKUP(B150,'April Prorated Invoice-BLG Site'!$C:$F,1,0) -> 76072064
A151: BRANTFORD NISSAN | B151: 9025902 | C151: 2002697 | D151: TruVideo AI Suite | E151: 106.67 | G151: =VLOOKUP(B151,'April Prorated Invoice-BLG Site'!$C:$F,1,0) -> 9025902
A152: BURLINGTON CHRYSLER DODGE JEEP RAM - NJ | B152: 76233199 | C152: 3002934 | D152: TruVideo AI Suite | E152: 66.67 | G152: =VLOOKUP(B152,'April Prorated Invoice-BLG Site'!$C:$F,1,0) -> #N/A
A153: BURLINGTON HYUNDAI - NJ | B153: 76233198 | C153: 3002958 | D153: TruVideo AI Suite | E153: 26.67 | G153: =VLOOKUP(B153,'April Prorated Invoice-BLG Site'!$C:$F,1,0) -> 76233198
A154: BURLINGTON KIA | B154: 71061453 | C154: 3002947 | D154: TruVideo AI Suite | E154: 73.33 | G154: =VLOOKUP(B154,'April Prorated Invoice-BLG Site'!$C:$F,1,0) -> 71061453
A155: CHRYSLER DODGE JEEP RAM OF SOUTHAMPTON | B155: 76216633 | C155: 2503124 | D155: TruVideo AI Suite | E155: 60 | G155: =VLOOKUP(B155,'April Prorated Invoice-BLG Site'!$C:$F,1,0) -> 76216633
... A212: WINSLOW FORD | B212: 76236503 | C212: 3002961 | D212: TruVideo AI Suite | E212: 20 | G212: =VLOOKUP(B212,'April Prorated Invoice-BLG Site'!$C:$F,1,0) -> 76236503
E213: =SUM(E144:E212) -> 7220.04
A215: Total - 69 New Customers | E215: =E71+E142+E213 -> 52481.04

Sheet TV May Monthly Invoice
A1: Customer | B1: Contract Number | C1: CMF Number | D1: CID Number | E1: Item | F1: Local Amount
A2: #1 COCHRAN HONDA SOUTH HILLS | B2: T-13571 | C2: 76237899 | D2: 2503083 | E2: CDK Reseller - Base Fee | F2: 400
A3: #1 COCHRAN HONDA SOUTH HILLS | B3: T-13571 | C3: 76237899 | D3: 2503083 | E3: TruVideo AI Suite | F3: 200
A4: 427 QEW KIA | B4: T-15093 | C4: 76012107 | D4: 2502638 | E4: CDK Reseller - Base Fee | F4: 300
A5: 427 QEW KIA | B5: T-15093 | C5: 76012107 | D5: 2502638 | E5: TruVideo AI Suite | F5: 200
A6: ABERDEEN CHRYSLER CENTER | B6: T-13829 | C6: 13494907 | D6: 3000753 | E6: CDK Reseller - Base Fee | F6: 300
A7: ABERDEEN CHRYSLER CENTER | B7: T-13829 | C7: 13494907 | D7: 3000753 | E7: TruVideo AI Suite | F7: 200
A8: ACADEMY FORD SALES | B8: T-16219 | C8: 76074791 | D8: 3002489 | E8: CDK Reseller - Base Fee | F8: 300
A9: ACADEMY FORD SALES | B9: T-16219 | C9: 76074791 | D9: 3002489 | E9: TruVideo AI Suite | F9: 200
A10: ACADIANA DODGE, INC. | B10: T-13758 | C10: 76074827 | D10: 3000599 | E10: CDK Reseller - Base Fee | F10: 300
A11: ACADIANA DODGE, INC. | B11: T-13758 | C11: 76074827 | D11: 3000599 | E11: TruVideo AI Suite | F11: 200
A12: ACKERMAN TOYOTA | B12: T-1018 | C12: 13337904 | D12: 2502347 | E12: CDK Reseller - Base Fee | F12: 450
A13: ACKERMAN TOYOTA | B13: T-1018 | C13: 13337904 | D13: 2502347 | E13: TruVideo AI Suite | F13: 200
... A35: AIRPORT MARINA HONDA | B35: T-3804 | C35: 76157326 | D35: 10189 | E35: TruVideo AI Suite | F35: 200
A36: AIRSTREAM INLAND EMPIRE | B36: T-5995 | C36: 76190250 | D36: N/A | E36: CDK Reseller - Base Fee | F36: 400
A37: AIRSTREAM INLAND EMPIRE | B37: T-5995 | C37: 76190250 | D37: N/A | E37: TruVideo AI Suite | F37: 200
A38: AIRSTREAM LAS VEGAS | B38: T-5996 | C38: 76195274 | D38: N/A | E38: CDK Reseller - Base Fee | F38: 400
A39: AIRSTREAM LAS VEGAS | B39: T-5996 | C39: 76195274 | D39: N/A | E39: TruVideo AI Suite | F39: 200
A40: AIRSTREAM LOS ANGELES | B40: T-5997 | C40: 76157682 | D40: N/A | E40: CDK Reseller - Base Fee | F40: 400
A41: AIRSTREAM LOS ANGELES | B41: T-5997 | C41: 76157682 | D41: N/A | E41: TruVideo AI Suite | F41: 200
A42: AIRSTREAM ORANGE COUNTY | B42: T-6180 | C42: 76159809 | D42: N/A | E42: CDK Reseller - Base Fee | F42: 400
A43: AIRSTREAM ORANGE COUNTY | B43: T-6180 | C43: 76159809 | D43: N/A | E43: TruVideo AI Suite | F43: 200
A44: Ajax Mazda | B44: T-9272 | C44: 76208845 | D44: 2500855 | E44: CDK Reseller - Base Fee | F44: 300
A45: Ajax Mazda | B45: T-9272 | C45: 76208845 | D45: 2500855 | E45: TruVideo AI Suite | F45: 200
A46: AL PACKER FORD INC | B46: T-15480 | C46: 1013501 | D46: 10027 | E46: CDK Reseller - Base Fee | F46: 300
A47: AL PACKER FORD INC | B47: T-15480 | C47: 1013501 | D47: 10027 | E47: TruVideo AI Suite | F47: 200
A48: AL PACKER FORD ROYAL PALM BEACH | B48: T-15479 | C48: 1013502 | D48: 10028 | E48: CDK Reseller - Base Fee | F48: 300
A49: AL PACKER FORD ROYAL PALM BEACH | B49: T-15479 | C49: 1013502 | D49: 10028 | E49: TruVideo AI Suite | F49: 200
A50: AL PACKER FORD WHITE MARSH | B50: T-15475 | C50: 71034933 | D50: 10038 | E50: CDK Reseller - Base Fee | F50: 300
A51: AL PACKER FORD WHITE MARSH | B51: T-15475 | C51: 71034933 | D51: 10038 | E51: TruVideo AI Suite | F51: 200
A52: ALAN BROWNE CHEVROLET | B52: T-10863 | C52: 13104901 | D52: 1500085 | E52: CDK Reseller - Base Fee | F52: 300
A53: ALAN BROWNE CHEVROLET | B53: T-10863 | C53: 13104901 | D53: 1500085 | E53: TruVideo AI Suite | F53: 200
A54: ALAN JAY CHEVROLET BUICK GMC CADILLAC | B54: T-13591 | C54: 1325654 | D54: 3000691 | E54: CDK Reseller - Base Fee | F54: 300
A55: ALAN JAY CHEVROLET BUICK GMC CADILLAC | B55: T-13591 | C55: 1325654 | D55: 3000691 | E55: TruVideo AI Suite | F55: 200
... A1273: GRAINGER HONDA | B1273: T-13310 | C1273: 8300018 | D1273: 3000322 | E1273: TruVideo AI Suite | F1273: 200
A1274: GRAND JUNCTION PETERBILT, INC. | B1274: T-9471 | C1274: 76220871 | D1274: N/A | E1274: CDK Reseller - Base Fee | F1274: 300
A1275: GRAND JUNCTION PETERBILT, INC. | B1275: T-9471 | C1275: 76220871 | D1275: N/A | E1275: TruVideo AI Suite | F1275: 200
A1276: GRANGER CHEVROLET | B1276: T-14795 | C1276: 71039781 | D1276: 8072 | E1276: CDK Reseller - Base Fee | F1276: 300
A1277: GRANGER CHEVROLET | B1277: T-14795 | C1277: 71039781 | D1277: 8072 | E1277: TruVideo AI Suite | F1277: 200
A1278: GRAPPONE FORD | B1278: T-3982 | C1278: 76021673 | D1278: 2000073 | E1278: CDK Reseller - Base Fee | F1278: 400
A1279: GRAPPONE FORD | B1279: T-3982 | C1279: 76021673 | D1279: 2000073 | E1279: TruVideo AI Suite | F1279: 200
A1280: Grappone Honda | B1280: T-3983 | C1280: 76021665 | D1280: 2000071 | E1280: CDK Reseller - Base Fee | F1280: 450
A1281: Grappone Honda | B1281: T-3983 | C1281: 76021665 | D1281: 2000071 | E1281: TruVideo AI Suite | F1281: 200
A1282: Grappone Mazda | B1282: T-7227 | C1282: 76021674 | D1282: 2002854 | E1282: CDK Reseller - Base Fee | F1282: 300
A1283: Grappone Mazda | B1283: T-7227 | C1283: 76021674 | D1283: 2002854 | E1283: TruVideo AI Suite | F1283: 200
A1284: GREAT LAKES HYUNDAI | B1284: T-10899 | C1284: 76022907 | D1284: 2600001 | E1284: CDK Reseller - Base Fee | F1284: 300
A1285: GREAT LAKES HYUNDAI | B1285: T-10899 | C1285: 76022907 | D1285: 2600001 | E1285: TruVideo AI Suite | F1285: 200
A1286: GREAT LAKES PETERBILT | B1286: T-6752 | C1286: 76170714 | D1286: N/A | E1286: CDK Reseller - Base Fee | F1286: 300
A1287: GREAT LAKES PETERBILT | B1287: T-6752 | C1287: 76170714 | D1287: N/A | E1287: TruVideo AI Suite | F1287: 200
A1288: GREEN BUICK GMC | B1288: T-9257 | C1288: 76066702 | D1288: 13043 | E1288: CDK Reseller - Base Fee | F1288: 300
A1289: GREEN BUICK GMC | B1289: T-9257 | C1289: 76066702 | D1289: 13043 | E1289: TruVideo AI Suite | F1289: 200
A1290: GREEN CHEVROLET | B1290: T-9253 | C1290: 76066716 | D1290: 13042 | E1290: CDK Reseller - Base Fee | F1290: 300
A1291: GREEN CHEVROLET | B1291: T-9253 | C1291: 76066716 | D1291: 13042 | E1291: TruVideo AI Suite | F1291: 200
A1292: GREEN FAMILY HYUNDAI | B1292: T-9252 | C1292: 76153879 | D1292: 2001283 | E1292: CDK Reseller - Base Fee | F1292: 300
A1293: GREEN FAMILY HYUNDAI | B1293: T-9252 | C1293: 76153879 | D1293: 2001283 | E1293: TruVideo AI Suite | F1293: 200
A1294: Greencastle Chevrolet | B1294: T-9658 | C1294: 76243311 | D1294: 2503254 | E1294: CDK Reseller - Base Fee | F1294: 300
A1295: Greencastle Chevrolet | B1295: T-9658 | C1295: 76243311 | D1295: 2503254 | E1295: TruVideo AI Suite | F1295: 200
A1296: GREENS TOYOTA OF LEXINGTON | B1296: T-3986 | C1296: 76149136 | D1296: 2501441 | E1296: CDK Reseller - Base Fee | F1296: 450
A1297: GREENS TOYOTA OF LEXINGTON | B1297: T-3986 | C1297: 76149136 | D1297: 2501441 | E1297: TruVideo AI Suite | F1297: 200
A1298: GREENVILLE CHRYSLER | B1298: T-15066 | C1298: 76228473 | D1298: 3001181 | E1298: CDK Reseller - Base Fee | F1298: 300
A1299: GREENVILLE CHRYSLER | B1299: T-15066 | C1299: 76228473 | D1299: 3001181 | E1299: TruVideo AI Suite | F1299: 200
... A1549: JACKIE COOPER PORSCHE | B1549: T-15464 | C1549: 76259370 | D1549: 3002017 | E1549: TruVideo AI Suite | F1549: 200
A1550: JACKSON GROUP PETERBILT BILLINGS | B1550: T-5638 | C1550: 76220873 | D1550: N/A | E1550: CDK Reseller - Base Fee | F1550: 300
A1551: JACKSON GROUP PETERBILT BILLINGS | B1551: T-5638 | C1551: 76220873 | D1551: N/A | E1551: TruVideo AI Suite | F1551: 200
A1552: JACKSON GROUP PETERBILT MISSOULA | B1552: T-6014 | C1552: 76220871 | D1552: N/A | E1552: CDK Reseller - Base Fee | F1552: 300
A1553: JACKSON GROUP PETERBILT MISSOULA | B1553: T-6014 | C1553: 76220871 | D1553: N/A | E1553: TruVideo AI Suite | F1553: 200
A1554: JAGUAR LAND ROVER CHESTERFIELD | B1554: T-9797 | C1554: 76224904 | D1554: 2001885 | E1554: CDK Reseller - Base Fee | F1554: 300
A1555: JAGUAR LAND ROVER CHESTERFIELD | B1555: T-9797 | C1555: 76224904 | D1555: 2001885 | E1555: TruVideo AI Suite | F1555: 200
A1556: JAGUAR LAND ROVER CINCINNATI | B1556: T-4463 | C1556: 76063223 | D1556: 2502969 | E1556: CDK Reseller - Base Fee | F1556: 300
A1557: JAGUAR LAND ROVER CINCINNATI | B1557: T-4463 | C1557: 76063223 | D1557: 2502969 | E1557: TruVideo AI Suite | F1557: 200
A1558: JAGUAR LAND ROVER CORAL GABLES | B1558: T-6457 | C1558: 76232569 | D1558: 2002206 | E1558: CDK Reseller - Base Fee | F1558: 400
A1559: JAGUAR LAND ROVER CORAL GABLES | B1559: T-6457 | C1559: 76232569 | D1559: 2002206 | E1559: TruVideo AI Suite | F1559: 200
A1560: JAGUAR LAND ROVER FORT WAYNE | B1560: T-4023 | C1560: 76220316 | D1560: 2502461 | E1560: CDK Reseller - Base Fee | F1560: 450
A1561: JAGUAR LAND ROVER FORT WAYNE | B1561: T-4023 | C1561: 76220316 | D1561: 2502461 | E1561: TruVideo AI Suite | F1561: 200
A1562: Jaguar Land Rover Freeport | B1562: T-15114 | C1562: 8310123 | D1562: 2500745 | E1562: CDK Reseller - Base Fee | F1562: 300
A1563: Jaguar Land Rover Freeport | B1563: T-15114 | C1563: 8310123 | D1563: 2500745 | E1563: TruVideo AI Suite | F1563: 200
A1564: JAGUAR LAND ROVER GLEN COVE | B1564: T-6466 | C1564: 76172298 | D1564: 2500778 | E1564: CDK Reseller - Base Fee | F1564: 300
A1565: JAGUAR LAND ROVER GLEN COVE | B1565: T-6466 | C1565: 76172298 | D1565: 2500778 | E1565: TruVideo AI Suite | F1565: 200
... A1603: JENNINGS VOLKSWAGEN | B1603: T-8097 | C1603: 76211393 | D1603: 2501116 | E1603: TruVideo AI Suite | F1603: 200
A1604: JEROME PETERBILT, INC. | B1604: T-5708 | C1604: 76041535 | D1604: N/A | E1604: CDK Reseller - Base Fee | F1604: 300
A1605: JEROME PETERBILT, INC. | B1605: T-5708 | C1605: 76041535 | D1605: N/A | E1605: TruVideo AI Suite | F1605: 200
A1606: JERRY V HONOLULU HYUNDAI | B1606: T-15495 | C1606: 76231546 | D1606: 2002201 | E1606: CDK Reseller - Base Fee | F1606: 300
A1607: JERRY V HONOLULU HYUNDAI | B1607: T-15495 | C1607: 76231546 | D1607: 2002201 | E1607: TruVideo AI Suite | F1607: 200
A1608: Jerry's Chevrolet Buick GMC | B1608: T-9657 | C1608: 76169223 | D1608: 2000229 | E1608: CDK Reseller - Base Fee | F1608: 300
A1609: Jerry's Chevrolet Buick GMC | B1609: T-9657 | C1609: 76169223 | D1609: 2000229 | E1609: TruVideo AI Suite | F1609: 200
A1610: JERRY'S CHEVROLET OF BERESFORD | B1610: T-9615 | C1610: 76169221 | D1610: 2000227 | E1610: CDK Reseller - Base Fee | F1610: 300
A1611: JERRY'S CHEVROLET OF BERESFORD | B1611: T-9615 | C1611: 76169221 | D1611: 2000227 | E1611: TruVideo AI Suite | F1611: 200
A1612: JERSEY CITY KIA | B1612: T-4064 | C1612: 76232990 | D1612: 2502714 | E1612: CDK Reseller - Base Fee | F1612: 300
A1613: JERSEY CITY KIA | B1613: T-4064 | C1613: 76232990 | D1613: 2502714 | E1613: TruVideo AI Suite | F1613: 200
A1614: JIM ARMSTRONG SUBARU | B1614: T-14147 | C1614: 1154301 | D1614: 3000851 | E1614: CDK Reseller - Base Fee | F1614: 300
A1615: JIM ARMSTRONG SUBARU | B1615: T-14147 | C1615: 1154301 | D1615: 3000851 | E1615: TruVideo AI Suite | F1615: 200
A1616: JIM BONE KIA OF SANTA ROSA | B1616: T-10606 | C1616: 76135482 | D1616: 2003140 | E1616: CDK Reseller - Base Fee | F1616: 300
A1617: JIM BONE KIA OF SANTA ROSA | B1617: T-10606 | C1617: 76135482 | D1617: 2003140 | E1617: TruVideo AI Suite | F1617: 200
... A2397: O'Daniel Motor Sales CDJR | B2397: T-14154 | C2397: 45226301 | D2397: 3000247 | E2397: TruVideo AI Suite | F2397: 200
A2398: OGDEN PETERBILT, INC. | B2398: T-6189 | C2398: 76170921 | D2398: N/A | E2398: CDK Reseller - Base Fee | F2398: 300
A2399: OGDEN PETERBILT, INC. | B2399: T-6189 | C2399: 76170921 | D2399: N/A | E2399: TruVideo AI Suite | F2399: 200
A2400: O'NEIL BUICK GMC | B2400: T-4196 | C2400: 25090101 | D2400: 1500076 | E2400: CDK Reseller - Base Fee | F2400: 450
A2401: O'NEIL BUICK GMC | B2401: T-4196 | C2401: 25090101 | D2401: 1500076 | E2401: TruVideo AI Suite | F2401: 200
A2402: ONTARIO PETERBILT, INC. | B2402: T-9466 | C2402: 76211206 | D2402: N/A | E2402: CDK Reseller - Base Fee | F2402: 400
A2403: ONTARIO PETERBILT, INC. | B2403: T-9466 | C2403: 76211206 | D2403: N/A | E2403: TruVideo AI Suite | F2403: 200
...

Sheet SV Child INS Apr
A1: CMF | B1: CMF Number | C1: CDF ID | D1: Ship-To Name | E1: Catalog Number | F1: CDF Status (w/ATN) | G1: Catalog Description | H1: Consolidation Name | I1: Roll Call Date | J1: Total | K1: Billed by TV by CMF | L1: Billed by TV by Name
A2: =TRIM(B2) -> 01012401 | B2: 01012401 | C2: 64239719SW03 | D2: SOLOMON CHEVROLET CADILLAC | E2: 4408593 | F2: INS | G2: CDK SERVICEVIEW IN PKG (CHILD CATALOG NUMBER FOR CDK SERVICE BUNDLE) | H2: SOLOMON CHEVROLET CADILLAC | I2: 45793 | J2: 1 | K2: =VLOOKUP(A2,'TV May Monthly Billing Sites'!$A:$L,1,0) -> 01012401
A3: =TRIM(B3) -> 01013001 | B3: 01013001 | C3: 64237387SW59 | D3: TAMERON HONDA | E3: 4508714 | F3: INS | G3: CDK SERVICEVIEW (IN FIXED OPS PKG) | H3: TAMERON | I3: 45719 | J3: 1 | K3: =VLOOKUP(A3,'TV May Monthly Billing Sites'!$A:$L,1,0) -> 01013001
A4: =TRIM(B4) -> 01017901 | B4: 01017901 | C4: 68242168SW04 | D4: JOHN THORNTON CHEVROLET | E4: 4508714 | F4: INS | G4: CDK SERVICEVIEW (IN FIXED OPS PKG) | H4: JOHN THORNTON | I4: 45870 | J4: 1 | K4: =VLOOKUP(A4,'TV May Monthly Billing Sites'!$A:$L,1,0) -> 01017901
A5: =TRIM(B5) -> 01023201 | B5: 01023201 | C5: 68233291SW04 | D5: DICK SMITH NISSAN OF COLUMBIA | E5: 4508714 | F5: INS | G5: CDK SERVICEVIEW (IN FIXED OPS PKG) | H5: DICK SMITH | I5: 45629 | J5: 1 | K5: =VLOOKUP(A5,'TV May Monthly Billing Sites'!$A:$L,1,0) -> 01023201
A6: =TRIM(B6) -> 01027202 | B6: 01027202 | C6: 68233069SW13 | D6: CMA'S COLONIAL HONDA | E6: 4508714 | F6: INS | G6: CDK SERVICEVIEW (IN FIXED OPS PKG) | H6: CARTER MYERS GROUP | I6: 45622 | J6: 1 | K6: =VLOOKUP(A6,'TV May Monthly Billing Sites'!$A:$L,1,0) -> 01027202
A7: =TRIM(B7) -> 01027210 | B7: 01027210 | C7: 68233075SW04 | D7: CMA'S COLONIAL AUTO CENTER | E7: 4508714 | F7: INS | G7: CDK SERVICEVIEW (IN FIXED OPS PKG) | H7: CARTER MYERS GROUP | I7: 45622 | J7: 1 | K7: =VLOOKUP(A7,'TV May Monthly Billing Sites'!$A:$L,1,0) -> 01027210
A8: =TRIM(B8) -> 01028106 | B8: 01028106 | C8: 68193827SW74 | D8: BERGLUND FORD MAZDA | E8: 4408594 | F8: INS | G8: CDK SERVICEVIEW (AUDI & MAZDA DEALERS ONLY) | H8: BERGLUND | I8: 44708 | J8: 1 | K8: =VLOOKUP(A8,'TV May Monthly Billing Sites'!$A:$L,1,0) -> 01028106
A9: =TRIM(B9) -> 01029201 | B9: 01029201 | C9: 68240865SW60 | D9: MORGAN-MCCLURE CHEVROLET BUICK CADILLAC, INC. | E9: 4508714 | F9: INS | G9: CDK SERVICEVIEW (IN FIXED OPS PKG) | H9: MORGAN-MCCLURE | I9: 45847 | J9: 1 | K9: =VLOOKUP(A9,'TV May Monthly Billing Sites'!$A:$L,1,0) -> 01029201
A10: =TRIM(B10) -> 01029202 | B10: 01029202 | C10: 68240865SW82 | D10: MORGAN-MCCLURE CHEVROLET GMC INC. | E10: 4508714 | F10: INS | G10: CDK SERVICEVIEW (IN FIXED OPS PKG) | H10: MORGAN-MCCLURE | I10: 45847 | J10: 1 | K10: =VLOOKUP(A10,'TV May Monthly Billing Sites'!$A:$L,1,0) -> 01029202
A11: =TRIM(B11) -> 01029901 | B11: 01029901 | C11: 68232269SW54 | D11: WEST BROAD HONDA | E11: 4508714 | F11: INS | G11: CDK SERVICEVIEW (IN FIXED OPS PKG) | H11: THE PAGE AUTO GROUP | I11: 45597 | J11: 1 | K11: =VLOOKUP(A11,'TV May Monthly Billing Sites'!$A:$L,1,0) -> 01029901
A12: =TRIM(B12) -> 01029905 | B12: 01029905 | C12: 68232269SW72 | D12: MECHANICSVILLE HONDA | E12: 4508714 | F12: INS | G12: CDK SERVICEVIEW (IN FIXED OPS PKG) | H12: THE PAGE AUTO GROUP | I12: 45597 | J12: 1 | K12: =VLOOKUP(A12,'TV May Monthly Billing Sites'!$A:$L,1,0) -> 01029905
A13: =TRIM(B13) -> 01029906 | B13: 01029906 | C13: 68232269SW90 | D13: WEST BROAD HYUNDAI | E13: 4508714 | F13: INS | G13: CDK SERVICEVIEW (IN FIXED OPS PKG) | H13: THE PAGE AUTO GROUP | I13: 45597 | J13: 1 | K13: =VLOOKUP(A13,'TV May Monthly Billing Sites'!$A:$L,1,0) -> 01029906
... A58: =TRIM(B58) -> 05237677 | B58: 05237677 | C58: 62188358SW51 | D58: CHAMPION CHEVROLET | E58: 4508714 | F58: INS | G58: CDK SERVICEVIEW (IN FIXED OPS PKG) | H58: CHAMPION CHEVROLET | I58: 45625 | J58: 1 | K58: =VLOOKUP(A58,'TV May Monthly Billing Sites'!$A:$L,1,0) -> 05237677
A59: =TRIM(B59) -> 05400042 | B59: 05400042 | C59: 62188525SW04 | D59: BEAVERTON KIA | E59: 4508714 | F59: INS | G59: CDK SERVICEVIEW (IN FIXED OPS PKG) | H59: LANPHERE | I59: 45638 | J59: 1 | K59: =VLOOKUP(A59,'TV May Monthly Billing Sites'!$A:$L,1,0) -> #N/A | L59: =VLOOKUP(D59,'TV May Monthly Billing Sites'!$B:$L,1,0) -> #N/A
A60: =TRIM(B60) -> 05400043 | B60: 05400043 | C60: 62188525SW11 | D60: BEAVERTON INFINITI 1 | E60: 4508714 | F60: INS | G60: CDK SERVICEVIEW (IN FIXED OPS PKG) | H60: LANPHERE | I60: 45638 | J60: 1 | K60: =VLOOKUP(A60,'TV May Monthly Billing Sites'!$A:$L,1,0) -> #N/A | L60: =VLOOKUP(D60,'TV May Monthly Billing Sites'!$B:$L,1,0) -> #N/A
A61: =TRIM(B61) -> 05400118 | B61: 05400118 | C61: 64236678SW01 | D61: COURTESY BUICK GMC | E61: 4408592 | F61: INS | G61: CDK SERVICEVIEW (REQUIRES CDK SERVICE INSPECT) | H61: COURTESY AUTOMOTIVE GROUP - LA | I61: 45694 | J61: 1 | K61: =VLOOKUP(A61,'TV May Monthly Billing Sites'!$A:$L,1,0) -> 05400118
A62: =TRIM(B62) -> 05400192 | B62: 05400192 | C62: 64235049SW18 | D62: WALKER VOLKSWAGEN | E62: 4508714 | F62: INS | G62: CDK SERVICEVIEW (IN FIXED OPS PKG) | H62: WALKER - NEW ORLEANS | I62: 45642 | J62: 1 | K62: =VLOOKUP(A62,'TV May Monthly Billing Sites'!$A:$L,1,0) -> 05400192
A63: =TRIM(B63) -> 05700077 | B63: 05700077 | C63: 62188269SW04 | D63: CARLSEN SUBARU | E63: 4508714 | F63: INS | G63: CDK SERVICEVIEW (IN FIXED OPS PKG) | H63: CARLSEN | I63: 45622 | J63: 1 | K63: =VLOOKUP(A63,'TV May Monthly Billing Sites'!$A:$L,1,0) -> 05700077
A64: =TRIM(B64) -> 05700078 | B64: 05700078 | C64: 64234453SW04 | D64: RALPH SELLERS CHRYSLER | E64: 4508714 | F64: INS | G64: CDK SERVICEVIEW (IN FIXED OPS PKG) | H64: RALPH SELLERS | I64: 45625 | J64: 1 | K64: =VLOOKUP(A64,'TV May Monthly Billing Sites'!$A:$L,1,0) -> 05700078
A65: =TRIM(B65) -> 05700175 | B65: 05700175 | C65: 62188275SW04 | D65: RIO MOTOR COMPANY | E65: 4508714 | F65: INS | G65: CDK SERVICEVIEW (IN FIXED OPS PKG) | H65: RIO MOTOR COMPANY INC. | I65: 45622 | J65: 1 | K65: =VLOOKUP(A65,'TV May Monthly Billing Sites'!$A:$L,1,0) -> 05700175
A66: =TRIM(B66) -> 05710031 | B66: 05710031 | C66: 62190444SW03 | D66: TYLER FORD | E66: 4508714 | F66: INS | G66: CDK SERVICEVIEW (IN FIXED OPS PKG) | H66: TYLER FORD | I66: 45715 | J66: 1 | K66: =VLOOKUP(A66,'TV May Monthly Billing Sites'!$A:$L,1,0) -> 05710031
A67: =TRIM(B67) -> 05710042 | B67: 05710042 | C67: 62197095SW63 | D67: RELIABLE BUICK GMC CADILLAC | E67: 4508714 | F67: INS | G67: CDK SERVICEVIEW (IN FIXED OPS PKG) | H67: RELIABLE BUICK GMC CADILLAC | I67: 46024 | J67: 1 | K67: =VLOOKUP(A67,'TV May Monthly Billing Sites'!$A:$L,1,0) -> 05710042
A68: =TRIM(B68) -> 05710177 | B68: 05710177 | C68: 62191005SW03 | D68: WHEELER AUTO CENTER | E68: 4408593 | F68: INS | G68: CDK SERVICEVIEW IN PKG (CHILD CATALOG NUMBER FOR CDK SERVICE BUNDLE) | H68: WHEELER AUTO CENTER | I68: 45739 | J68: 1 | K68: =VLOOKUP(A68,'TV May Monthly Billing Sites'!$A:$L,1,0) -> 05710177
A69: =TRIM(B69) -> 05720026 | B69: 05720026 | C69: 64242674SW58 | D69: DAVIS-MOORE CHEVROLET | E69: 4508714 | F69: INS | G69: CDK SERVICEVIEW (IN FIXED OPS PKG) | H69: DAVIS MOORE | I69: 45902 | J69: 1 | K69: =VLOOKUP(A69,'TV May Monthly Billing Sites'!$A:$L,1,0) -> 05720026
A70: =TRIM(B70) -> 05720064 | B70: 05720064 | C70: 62162229SW03 | D70: STOCKTON HONDA | E70: 4408592 | F70: INS | G70: CDK SERVICEVIEW (REQUIRES CDK SERVICE INSPECT) | H70: ZAMORA AUTOMOTIVE GROUP | I70: 44712 | J70: 1 | K70: =VLOOKUP(A70,'TV May Monthly Billing Sites'!$A:$L,1,0) -> 05720064
A71: =TRIM(B71) -> 06600066 | B71: 06600066 | C71: 64207972SW52 | D71: CAROUSEL MOTORS | E71: 4408592 | F71: INS | G71: CDK SERVICEVIEW (REQUIRES CDK SERVICE INSPECT) | H71: CAROUSEL | I71: 45047 | J71: 1 | K71: =VLOOKUP(A71,'TV May Monthly Billing Sites'!$A:$L,1,0) -> 06600066
A72: =TRIM(B72) -> 06600309 | B72: 06600309 | C72: 64229043SW21 | D72: O'DANIEL AUTOMART INC | E72: 4508675 | F72: INS | G72: CDK SERVICEVIEW (STANDALONE WITHOUT CDK SERVICE) | H72: O'DANIEL | I72: 45435 | J72: 1 | K72: =VLOOKUP(A72,'TV May Monthly Billing Sites'!$A:$L,1,0) -> 06600309
... A95: =TRIM(B95) -> 09800181 | B95: 09800181 | C95: 98052321SW81 | D95: RIHM KENWORTH DULUTH/SUPERIOR | E95: 4508684 | F95: INS | G95: CDK SERVICEVIEW PLUS FOR TRUCK (STANDALONE WITHOUT CDK SERVICE) | H95: RIHM | I95: 45891 | J95: 1 | K95: =VLOOKUP(A95,'TV May Monthly Billing Sites'!$A:$L,1,0) -> 09800181
A96: =TRIM(B96) -> 10027564 | B96: 10027564 | C96: 64246559SW03 | D96: PARKS MOTOR SALES, INC. | E96: 4408593 | F96: INS | G96: CDK SERVICEVIEW IN PKG (CHILD CATALOG NUMBER FOR CDK SERVICE BUNDLE) | H96: PARKS MOTOR - TN | I96: 46042 | J96: 1 | K96: =VLOOKUP(A96,'TV May Monthly Billing Sites'!$A:$L,1,0) -> 10027564
A97: =TRIM(B97) -> 13059104 | B97: 13059104 | C97: 64246119SW19 | D97: VALLEY IMPORTS | E97: 4508714 | F97: INS | G97: CDK SERVICEVIEW (IN FIXED OPS PKG) | H97: VALLEY IMPORTS | I97: 46024 | J97: 1 | K97: =VLOOKUP(A97,'TV May Monthly Billing Sites'!$A:$L,1,0) -> 13059104
A98: =TRIM(B98) -> 13104901 | B98: 13104901 | C98: 64238619SW51 | D98: ALAN BROWNE CHEVROLET | E98: 4508714 | F98: INS | G98: CDK SERVICEVIEW (IN FIXED OPS PKG) | H98: ALAN BROWNE CHEVROLET | I98: 45755 | J98: 1 | K98: =VLOOKUP(A98,'TV May Monthly Billing Sites'!$A:$L,1,0) -> 13104901
A99: =TRIM(B99) -> 13115401 | B99: 13115401 | C99: 64238276SW51 | D99: BILLION BUICK GMC INC | E99: 4508714 | F99: INS | G99: CDK SERVICEVIEW (IN FIXED OPS PKG) | H99: BILLION | I99: 45747 | J99: 1 | K99: =VLOOKUP(A99,'TV May Monthly Billing Sites'!$A:$L,1,0) -> 13115401
A100: =TRIM(B100) -> 13115402 | B100: 13115402 | C100: 64238276SW87 | D100: BILLION HYUNDAI | E100: 4508714 | F100: INS | G100: CDK SERVICEVIEW (IN FIXED OPS PKG) | H100: BILLION | I100: 45747 | J100: 1 | K100: =VLOOKUP(A100,'TV May Monthly Billing Sites'!$A:$L,1,0) -> #N/A | L100: =VLOOKUP(D100,'TV May Monthly Billing Sites'!$B:$L,1,0) -> #N/A
A101: =TRIM(B101) -> 13115403 | B101: 13115403 | C101: 64238279SW74 | D101: BILLION DODGE CHRYSLER JEEP | E101: 4508714 | F101: INS | G101: CDK SERVICEVIEW (IN FIXED OPS PKG) | H101: BILLION | I101: 45747 | J101: 1 | K101: =VLOOKUP(A101,'TV May Monthly Billing Sites'!$A:$L,1,0) -> #N/A | L101: =VLOOKUP(D101,'TV May Monthly Billing Sites'!$B:$L,1,0) -> #N/A
A102: =TRIM(B102) -> 13221101 | B102: 13221101 | C102: 64246175SW60 | D102: MINNESOTA MOTOR COMPANY | E102: 4508714 | F102: INS | G102: CDK SERVICEVIEW (IN FIXED OPS PKG) | H102: MINNESOTA MOTOR CO | I102: 46024 | J102: 1 | K102: =VLOOKUP(A102,'TV May Monthly Billing Sites'!$A:$L,1,0) -> 13221101
A103: =TRIM(B103) -> 13323802 | B103: 13323802 | C103: 64209510SW01 | D103: CONTINENTAL TOYOTA | E103: 4408592 | F103: INS | G103: CDK SERVICEVIEW (REQUIRES CDK SERVICE INSPECT) | H103: CONTINENTAL GROUP AKA J&J PARTNERSHIP | I103: 45072 | J103: 1 | K103: =VLOOKUP(A103,'TV May Monthly Billing Sites'!$A:$L,1,0) -> 13323802
A104: =TRIM(B104) -> 13326501 | B104: 13326501 | C104: 64243749SW04 | D104: JOHN AMATO HYUNDAI MENOMONEE FALLS | E104: 4508714 | F104: INS | G104: CDK SERVICEVIEW (IN FIXED OPS PKG) | H104: AMATO | I104: 45939 | J104: 1 | K104: =VLOOKUP(A104,'TV May Monthly Billing Sites'!$A:$L,1,0) -> 13326501
A105: =TRIM(B105) -> 13337904 | B105: 13337904 | C105: 64243233SW08 | D105: JERRY ACKERMAN TOYOTA INC. | E105: 4508714 | F105: INS | G105: CDK SERVICEVIEW (IN FIXED OPS PKG) | H105: ACKERMAN TOYOTA | I105: 45925 | J105: 1 | K105: =VLOOKUP(A105,'TV May Monthly Billing Sites'!$A:$L,1,0) -> 13337904
A106: =TRIM(B106) -> 13344301 | B106: 13344301 | C106: 64240259SW03 | D106: VAESSEN BROS. | E106: 4408593 | F106: INS | G106: CDK SERVICEVIEW IN PKG (CHILD CATALOG NUMBER FOR CDK SERVICE BUNDLE) | H106: VAESSEN BROTHERS | I106: 45812 | J106: 1 | K106: =VLOOKUP(A106,'TV May Monthly Billing Sites'!$A:$L,1,0) -> 13344301
A107: =TRIM(B107) -> 13345704 | B107: 13345704 | C107: 64234828SW53 | D107: RUSS DARROW KIA OF WAUKESHA | E107: 4508714 | F107: INS | G107: CDK SERVICEVIEW (IN FIXED OPS PKG) | H107: RUSS DARROW GROUP | I107: 45636 | J107: 1 | K107: =VLOOKUP(A107,'TV May Monthly Billing Sites'!$A:$L,1,0) -> 13345704
A108: =TRIM(B108) -> 13345705 | B108: 13345705 | C108: 64234828SW32 | D108: RUSS DARROW KIA OF MADISON | E108: 4508714 | F108: INS | G108: CDK SERVICEVIEW (IN FIXED OPS PKG) | H108: RUSS DARROW GROUP | I108: 45636 | J108: 1 | K108: =VLOOKUP(A108,'TV May Monthly Billing Sites'!$A:$L,1,0) -> 13345705
A109: =TRIM(B109) -> 13345710 | B109: 13345710 | C109: 64234834SW03 | D109: RUSS DARROW TOYOTA-W.BEND | E109: 4408593 | F109: INS | G109: CDK SERVICEVIEW IN PKG (CHILD CATALOG NUMBER FOR CDK SERVICE BUNDLE) | H109: RUSS DARROW GROUP | I109: 45636 | J109: 1 | K109: =VLOOKUP(A109,'TV May Monthly Billing Sites'!$A:$L,1,0) -> 13345710
A110: =TRIM(B110) -> 13376401 | B110: 13376401 | C110: 64234882SW04 | D110: RIVER FRONT CHRYSLER JEEP | E110: 4508714 | F110: INS | G110: CDK SERVICEVIEW (IN FIXED OPS PKG) | H110: RIVER FRONT GROUP | I110: 45637 | J110: 1 | K110: =VLOOKUP(A110,'TV May Monthly Billing Sites'!$A:$L,1,0) -> 13376401
A111: =TRIM(B111) -> 13387401 | B111: 13387401 | C111: 64214619SW67 | D111: GORDIE BOUCHER LINCOLN | E111: 4408592 | F111: INS | G111: CDK SERVICEVIEW (REQUIRES CDK SERVICE INSPECT) | H111: BOUCHER INC | I111: 45146 | J111: 1 | K111: =VLOOKUP(A111,'TV May Monthly Billing Sites'!$A:$L,1,0) -> 13387401
A112: =TRIM(B112) -> 13387403 | B112: 13387403 | C112: 64234816SW18 | D112: GORDIE BOUCHER CHEVROLET | E112: 4508714 | F112: INS | G112: CDK SERVICEVIEW (IN FIXED OPS PKG) | H112: BOUCHER INC | I112: 45638 | J112: 1 | K112: =VLOOKUP(A112,'TV May Monthly Billing Sites'!$A:$L,1,0) -> 13387403
A113: =TRIM(B113) -> 13387405 | B113: 13387405 | C113: 64234836SW32 | D113: FRANK BOUCHER CHEVROLET INC. | E113: 4508714 | F113: INS | G113: CDK SERVICEVIEW (IN FIXED OPS PKG) | H113: BOUCHER INC | I113: 45636 | J113: 1 | K113: =VLOOKUP(A113,'TV May Monthly Billing Sites'!$A:$L,1,0) -> 13387405
... A129: =TRIM(B129) -> 13497591 | B129: 13497591 | C129: 64227078SW83 | D129: ERIC VON SCHLEDORN FORD | E129: 4408592 | F129: INS | G129: CDK SERVICEVIEW (REQUIRES CDK SERVICE INSPECT) | H129: ERIC VON SCHLEDORN | I129: 45380 | J129: 1 | K129: =VLOOKUP(A129,'TV May Monthly Billing Sites'!$A:$L,1,0) -> 13497591
A130: =TRIM(B130) -> 13497880 | B130: 13497880 | C130: 64238409SW64 | D130: WARD CHRYSLER CENTER | E130: 4508714 | F130: INS | G130: CDK SERVICEVIEW (IN FIXED OPS PKG) | H130: WARD | I130: 45748 | J130: 1 | K130: =VLOOKUP(A130,'TV May Monthly Billing Sites'!$A:$L,1,0) -> #N/A | L130: =VLOOKUP(D130,'TV May Monthly Billing Sites'!$B:$L,1,0) -> #N/A
A131: =TRIM(B131) -> 13498091 | B131: 13498091 | C131: 68226976SW01 | D131: WARRENSBURG CHRYSLER DODGE JEEP | E131: 4508675 | F131: INS | G131: CDK SERVICEVIEW (STANDALONE WITHOUT CDK SERVICE) | H131: CLIFF HARRIS AUTO GROUP | I131: 45457 | J131: 1 | K131: =VLOOKUP(A131,'TV May Monthly Billing Sites'!$A:$L,1,0) -> 13498091
A132: =TRIM(B132) -> 14090096 | B132: 14090096 | C132: 68230210SW56 | D132: PRESTON CHEVROLET KIA | E132: 4508714 | F132: INS | G132: CDK SERVICEVIEW (IN FIXED OPS PKG) | H132: PRESTON - OH | I132: 45569 | J132: 1 | K132: =VLOOKUP(A132,'TV May Monthly Billing Sites'!$A:$L,1,0) -> 14090096
A133: =TRIM(B133) -> 14090150 | B133: 14090150 | C133: 68233671SW04 | D133: VALLEY AUTOWORLD, INC | E133: 4508714 | F133: INS | G133: CDK SERVICEVIEW (IN FIXED OPS PKG) | H133: JW WYATT | I133: 45638 | J133: 1 | K133: =VLOOKUP(A133,'TV May Monthly Billing Sites'!$A:$L,1,0) -> 14090150
A134: =TRIM(B134) -> 14600646 | B134: 14600646 | C134: 68233042SW04 | D134: FLOW MOTORS OF WINSTON-SALEM, LLC | E134: 4508714 | F134: INS | G134: CDK SERVICEVIEW (IN FIXED OPS PKG) | H134: FLOW COMPANIES - GROUP | I134: 45622 | J134: 1 | K134: =VLOOKUP(A134,'TV May Monthly Billing Sites'!$A:$L,1,0) -> #N/A | L134: =VLOOKUP(D134,'TV May Monthly Billing Sites'!$B:$L,1,0) -> #N/A
A135: =TRIM(B135) -> 14610284 | B135: 14610284 | C135: 03175603SW01 | D135: MCKINSTRY LTD | E135: 4508675 | F135: INS | G135: CDK SERVICEVIEW (STANDALONE WITHOUT CDK SERVICE) | H135: MCKINSTRY CHRYSLER | I135: 45950 | J135: 1 | K135: =VLOOKUP(A135,'TV May Monthly Billing Sites'!$A:$L,1,0) -> 14610284
A136: =TRIM(B136) -> 14610612 | B136: 14610612 | C136: 03175114SW04 | D136: HYUNDAI AMOS | E136: 4408592 | F136: INS | G136: CDK SERVICEVIEW (REQUIRES CDK SERVICE INSPECT) | H136: HYUNDAI AMOS | I136: 45834 | J136: 1 | K136: =VLOOKUP(A136,'TV May Monthly Billing Sites'!$A:$L,1,0) -> 14610612
A137: =TRIM(B137) -> 17003601 | B137: 17003601 | C137: 64245754SW03 | D137: TERREBONNE FORD | E137: 4508714 | F137: INS | G137: CDK SERVICEVIEW (IN FIXED OPS PKG) | H137: BARKER | I137: 46008 | J137: 1 | K137: =VLOOKUP(A137,'TV May Monthly Billing Sites'!$A:$L,1,0) -> 17003601
A138: =TRIM(B138) -> 17003603 | B138: 17003603 | C138: 64234845SW04 | D138: BARKER KIA | E138: 4508714 | F138: INS | G138: CDK SERVICEVIEW (IN FIXED OPS PKG) | H138: BARKER | I138: 45636 | J138: 1 | K138: =VLOOKUP(A138,'TV May Monthly Billing Sites'!$A:$L,1,0) -> 17003603
A139: =TRIM(B139) -> 17003901 | B139: 17003901 | C139: 64234343SW02 | D139: SERVICE CHEVROLET | E139: 4408592 | F139: INS | G139: CDK SERVICEVIEW (REQUIRES CDK SERVICE INSPECT) | H139: SERVICE CHEVROLET CADILLAC | I139: 45618 | J139: 1 | K139: =VLOOKUP(A139,'TV May Monthly Billing Sites'!$A:$L,1,0) -> 17003901
A140: =TRIM(B140) -> 17042101 | B140: 17042101 | C140: 64234862SW04 | D140: KNIPPELMIER CHEV INC | E140: 4508714 | F140: INS | G140: CDK SERVICEVIEW (IN FIXED OPS PKG) | H140: KNIPPELMIER CHEVROLET INC. | I140: 45639 | J140: 1 | K140: =VLOOKUP(A140,'TV May Monthly Billing Sites'!$A:$L,1,0) -> #N/A | L140: =VLOOKUP(D140,'TV May Monthly Billing Sites'!$B:$L,1,0) -> #N/A
A141: =TRIM(B141) -> 17093401 | B141: 17093401 | C141: 64244094SW52 | D141: ROYAL NISSAN LLC. | E141: 4508714 | F141: INS | G141: CDK SERVICEVIEW (IN FIXED OPS PKG) | H141: ROYAL ATLANTIC CORPORATION | I141: 45959 | J141: 1 | K141: =VLOOKUP(A141,'TV May Monthly Billing Sites'!$A:$L,1,0) -> 17093401
A142: =TRIM(B142) -> 17117601 | B142: 17117601 | C142: 62191682SW01 | D142: TIPOTEX CHEVROLET | E142: 4408592 | F142: INS | G142: CDK SERVICEVIEW (REQUIRES CDK SERVICE INSPECT) | H142: TIPOTEX CHEVROLET | I142: 45771 | J142: 1 | K142: =VLOOKUP(A142,'TV May Monthly Billing Sites'!$A:$L,1,0) -> 17117601
A143: =TRIM(B143) -> 17121105 | B143: 17121105 | C143: 64235049SW04 | D143: WALKER ACURA | E143: 4508714 | F143: INS | G143: CDK SERVICEVIEW (IN FIXED OPS PKG) | H143: WALKER - NEW ORLEANS | I143: 45642 | J143: 1 | K143: =VLOOKUP(A143,'TV May Monthly Billing Sites'!$A:$L,1,0) -> 17121105
A144: =TRIM(B144) -> 17136501 | B144: 17136501 | C144: 64199129SW01 | D144: BATES NISSAN INC | E144: 4408592 | F144: INS | G144: CDK SERVICEVIEW (REQUIRES CDK SERVICE INSPECT) | H144: BATES NISSAN INC. | I144: 44755 | J144: 1 | K144: =VLOOKUP(A144,'TV May Monthly Billing Sites'!$A:$L,1,0) -> 17136501
A145: =TRIM(B145) -> 17150701 | B145: 17150701 | C145: 62188549SW04 | D145: MAC HAIK CHEV | E145: 4508714 | F145: INS | G145: CDK SERVICEVIEW (IN FIXED OPS PKG) | H145: MAC HAIK AUTO GROUP | I145: 45638 | J145: 1 | K145: =VLOOKUP(A145,'TV May Monthly Billing Sites'!$A:$L,1,0) -> #N/A | L145: =VLOOKUP(D145,'TV May Monthly Billing Sites'!$B:$L,1,0) -> #N/A
A146: =TRIM(B146) -> 17215201 | B146: 17215201 | C146: 64245641SW86 | D146: BANNER CHEVROLET | E146: 4408592 | F146: INS | G146: CDK SERVICEVIEW (REQUIRES CDK SERVICE INSPECT) | H146: BANNER AUTOMOTIVE GROUP | I146: 46003 | J146: 1 | K146: =VLOOKUP(A146,'TV May Monthly Billing Sites'!$A:$L,1,0) -> 17215201
A147: =TRIM(B147) -> 17251301 | B147: 17251301 | C147: 62196652SW04 | D147: DAVIS CHEVROLET INC. | E147: 4508714 | F147: INS | G147: CDK SERVICEVIEW (IN FIXED OPS PKG) | H147: DAVIS CHEVROLET | I147: 46008 | J147: 1 | K147: =VLOOKUP(A147,'TV May Monthly Billing Sites'!$A:$L,1,0) -> 17251301
A148: =TRIM(B148) -> 17253201 | B148: 17253201 | C148: 64194759SW01 | D148: LAKESIDE TOYOTA | E148: 4508679 | F148: INS | G148: CDK SERVICEVIEW PLUS (SMALL DEALER) | H148: TONY GULLO AUTO GROUP | I148: 44614 | J148: 1 | K148: =VLOOKUP(A148,'TV May Monthly Billing Sites'!$A:$L,1,0) -> 17253201
A149: =TRIM(B149) -> 17298301 | B149: 17298301 | C149: 64239833SW03 | D149: DIFFEE FORD LINCOLN | E149: 4508714 | F149: INS | G149: CDK SERVICEVIEW (IN FIXED OPS PKG) | H149: DIFFEE FORD LINCOLN | I149: 45799 | J149: 1 | K149: =VLOOKUP(A149,'TV May Monthly Billing Sites'!$A:$L,1,0) -> 17298301
A150: =TRIM(B150) -> 17315021 | B150: 17315021 | C150: 62178545SW52 | D150: ROGER BEASLEY MAZDA SOUTH | E150: 4508714 | F150: INS | G150: CDK SERVICEVIEW (IN FIXED OPS PKG) | H150: ROGER BEASLEY AUTO GROUP | I150: 45293 | J150: 1 | K150: =VLOOKUP(A150,'TV May Monthly Billing Sites'!$A:$L,1,0) -> 17315021
A151: =TRIM(B151) -> 17315987 | B151: 17315987 | C151: 64241671SW78 | D151: PEAKE BMW | E151: 4408592 | F151: INS | G151: CDK SERVICEVIEW (REQUIRES CDK SERVICE INSPECT) | H151: PEAKE | I151: 45863 | J151: 1 | K151: =VLOOKUP(A151,'TV May Monthly Billing Sites'!$A:$L,1,0) -> 17315987
A152: =TRIM(B152) -> 17316041 | B152: 17316041 | C152: 64205945SW01 | D152: FREEMAN TOYOTA | E152: 4408592 | F152: INS | G152: CDK SERVICEVIEW (REQUIRES CDK SERVICE INSPECT) | H152: FREEMAN/HILEY | I152: 44985 | J152: 1 | K152: =VLOOKUP(A152,'TV May Monthly Billing Sites'!$A:$L,1,0) -> 17316041
A153: =TRIM(B153) -> 21004601 | B153: 21004601 | C153: 98049594SW88 | D153: BROADWAY FORD TRUCK SALES | E153: 4508684 | F153: INS | G153: CDK SERVICEVIEW PLUS FOR TRUCK (STANDALONE WITHOUT CDK SERVICE) | H153: BROADWAY FORD TRUCK SALES | I153: 45289 | J153: 1 | K153: =VLOOKUP(A153,'TV May Monthly Billing Sites'!$A:$L,1,0) -> 21004601
A154: =TRIM(B154) -> 25002601 | B154: 25002601 | C154: 68198360SW02 | D154: MONACO & SONS MOTOR SALES, INC. | E154: 4408592 | F154: INS | G154: CDK SERVICEVIEW (REQUIRES CDK SERVICE INSPECT) | H154: MONACO AUTO GROUP | I154: 44846 | J154: 1 | K154: =VLOOKUP(A154,'TV May Monthly Billing Sites'!$A:$L,1,0) -> 25002601
